Workbook

Sheet Parámetros
B2: Ajuste por Conversión – Diferencia de Cambio USD
B3: Southern Copper Argentina S.R.L. — Período 06/2026 (PROTOTIPO)
B5: Fecha de cierre | C5: 46203
B6: T.C. COMPRA (aplica al ACTIVO) | C6: 1473
B7: T.C. VENTA (aplica al PASIVO) | C7: 1482
B8: Concepto del asiento | C8: Ajuste por Conversión
B9: Número de asiento | C9: 1
B10: Cuenta de balanceo (resultado) | C10: 423050000
B11: Umbral materialidad (USD) | C11: 0.005
B14: Celdas amarillas = editá el tipo de cambio y todo el modelo recalcula.

Sheet Resumen y notas
B2: Resumen del asiento — 06/2026
B4: Líneas que publican (cuentas) | C4: =COUNTIF(Cálculo!J3:J91,"SÍ")-1 -> 88
B5: Ajuste a Diferencia de Cambio USD (423050000) | C5: =Cálculo!I91 -> 58374.9
B6: Control de cierre (debe ser 0) | C6: =Cálculo!I93 -> 0
B7: Cuentas marcadas para revisar | C7: =COUNTIF(Cálculo!K3:K91,"REVISAR") -> 0
B12: Cómo se arma (resumen):
B13: • Cuentas MONETARIAS del ACTIVO/PASIVO. No monetarias excluidas: bienes de uso (1240xx),
B14: depreciaciones, cargos diferidos (1250xx), y puntuales 114010016 / 114050005 / 211050000.
B15: • ACTIVO usa T.C. COMPRA; PASIVO usa T.C. VENTA (celdas en Parámetros).
B16: • USD teórico = pesos/TC (proveedores sin redondear; resto REDONDEAR a 2).
B17: • Ajuste = USD teórico − USD en libros. Publica si |ajuste| ≥ 0,01.
B18: • Contrapartida por el neto → 423050000 Diferencia de Cambio USD. El asiento cierra en 0.
B20: Salvaguarda (columna ¿Revisar? en Cálculo):
B21: • Marca una cuenta si el ajuste es > 30% del saldo USD Y > 500 USD (perfil de una no monetaria
B22: mal clasificada). Con la data real de junio no salta ninguna (config correcta).
B24: Nota: los saldos en pesos y USD provienen del SyS 06/2026. Editá los TC (amarillo) para recalcular.

Sheet Cálculo
A1: HOJA DE CÁLCULO — cada USD se deriva por fórmula desde el saldo en pesos y el TC de cierre
A2: Código | B2: Denominación | C2: Sección | D2: Tipo | E2: Saldo Pesos ($) | F2: Saldo USD Libros | G2: T.C. Aplicado | H2: USD Teórico (pesos/TC) | I2: Ajuste USD | J2: ¿Publica? | K2: ¿Revisar?
A3: 111010001 | B3: Caja | C3: ACTIVO | D3: General | E3: 0 | F3: 24.51 | G3: =IF(C3="ACTIVO",Parámetros!$C$6,Parámetros!$C$7) -> 1473 | H3: =IF(D3="Proveedor",E3/G3,ROUND(E3/G3,2)) -> 0 | I3: =ROUND(H3-F3,2) -> -24.51 | J3: =IF(ABS(I3)>=Parámetros!$C$11,"SÍ","no") -> SÍ | K3: =IF(AND(ABS(F3)>0,ABS(I3)>0.3*ABS(F3),ABS(I3)>500),"REVISAR","")
A4: 111020001 | B4: ICBC S.A. c/c | C4: ACTIVO | D4: General | E4: 10663404 | F4: 7627.43 | G4: =IF(C4="ACTIVO",Parámetros!$C$6,Parámetros!$C$7) -> 1473 | H4: =IF(D4="Proveedor",E4/G4,ROUND(E4/G4,2)) -> 7239.24 | I4: =ROUND(H4-F4,2) -> -388.19 | J4: =IF(ABS(I4)>=Parámetros!$C$11,"SÍ","no") -> SÍ | K4: =IF(AND(ABS(F4)>0,ABS(I4)>0.3*ABS(F4),ABS(I4)>500),"REVISAR","")
A5: 111020005 | B5: Banco Macro Pesos | C5: ACTIVO | D5: General | E5: -23141.31 | F5: 24.1 | G5: =IF(C5="ACTIVO",Parámetros!$C$6,Parámetros!$C$7) -> 1473 | H5: =IF(D5="Proveedor",E5/G5,ROUND(E5/G5,2)) -> -15.71 | I5: =ROUND(H5-F5,2) -> -39.81 | J5: =IF(ABS(I5)>=Parámetros!$C$11,"SÍ","no") -> SÍ | K5: =IF(AND(ABS(F5)>0,ABS(I5)>0.3*ABS(F5),ABS(I5)>500),"REVISAR","")
A6: 111020006 | B6: Banco Galicia c/c | C6: ACTIVO | D6: General | E6: 3926.88 | F6: 4.62 | G6: =IF(C6="ACTIVO",Parámetros!$C$6,Parámetros!$C$7) -> 1473 | H6: =IF(D6="Proveedor",E6/G6,ROUND(E6/G6,2)) -> 2.67 | I6: =ROUND(H6-F6,2) -> -1.95 | J6: =IF(ABS(I6)>=Parámetros!$C$11,"SÍ","no") -> SÍ | K6: =IF(AND(ABS(F6)>0,ABS(I6)>0.3*ABS(F6),ABS(I6)>500),"REVISAR","")
A7: 114010001 | B7: IVA Crédito Fiscal | C7: ACTIVO | D7: General | E7: 0 | F7: 179.93 | G7: =IF(C7="ACTIVO",Parámetros!$C$6,Parámetros!$C$7) -> 1473 | H7: =IF(D7="Proveedor",E7/G7,ROUND(E7/G7,2)) -> 0 | I7: =ROUND(H7-F7,2) -> -179.93 | J7: =IF(ABS(I7)>=Parámetros!$C$11,"SÍ","no") -> SÍ | K7: =IF(AND(ABS(F7)>0,ABS(I7)>0.3*ABS(F7),ABS(I7)>500),"REVISAR","")
A8: 114010002 | B8: IVA saldo a favor | C8: ACTIVO | D8: General | E8: 1.6679594e+09 | F8: 1191982.6 | G8: =IF(C8="ACTIVO",Parámetros!$C$6,Parámetros!$C$7) -> 1473 | H8: =IF(D8="Proveedor",E8/G8,ROUND(E8/G8,2)) -> 1132355.3 | I8: =ROUND(H8-F8,2) -> -59627.3 | J8: =IF(ABS(I8)>=Parámetros!$C$11,"SÍ","no") -> SÍ | K8: =IF(AND(ABS(F8)>0,ABS(I8)>0.3*ABS(F8),ABS(I8)>500),"REVISAR","")
A9: 114010003 | B9: Ret. y Perc. IVA | C9: ACTIVO | D9: General | E9: 0 | F9: 1.01 | G9: =IF(C9="ACTIVO",Parámetros!$C$6,Parámetros!$C$7) -> 1473 | H9: =IF(D9="Proveedor",E9/G9,ROUND(E9/G9,2)) -> 0 | I9: =ROUND(H9-F9,2) -> -1.01 | J9: =IF(ABS(I9)>=Parámetros!$C$11,"SÍ","no") -> SÍ | K9: =IF(AND(ABS(F9)>0,ABS(I9)>0.3*ABS(F9),ABS(I9)>500),"REVISAR","")
A10: 114010004 | B10: Ret. y Perc. IIBB | C10: ACTIVO | D10: General | E10: 0 | F10: 0.34 | G10: =IF(C10="ACTIVO",Parámetros!$C$6,Parámetros!$C$7) -> 1473 | H10: =IF(D10="Proveedor",E10/G10,ROUND(E10/G10,2)) -> 0 | I10: =ROUND(H10-F10,2) -> -0.34 | J10: =IF(ABS(I10)>=Parámetros!$C$11,"SÍ","no") -> SÍ | K10: =IF(AND(ABS(F10)>0,ABS(I10)>0.3*ABS(F10),ABS(I10)>500),"REVISAR","")
A11: 114010005 | B11: IIBB saldo a favor | C11: ACTIVO | D11: General | E11: 7866857.1 | F11: 5622.41 | G11: =IF(C11="ACTIVO",Parámetros!$C$6,Parámetros!$C$7) -> 1473 | H11: =IF(D11="Proveedor",E11/G11,ROUND(E11/G11,2)) -> 5340.7 | I11: =ROUND(H11-F11,2) -> -281.71 | J11: =IF(ABS(I11)>=Parámetros!$C$11,"SÍ","no") -> SÍ | K11: =IF(AND(ABS(F11)>0,ABS(I11)>0.3*ABS(F11),ABS(I11)>500),"REVISAR","")
A12: 114010006 | B12: Crédito Imp. L.25413 | C12: ACTIVO | D12: General | E12: 52018352 | F12: 37182.36 | G12: =IF(C12="ACTIVO",Parámetros!$C$6,Parámetros!$C$7) -> 1473 | H12: =IF(D12="Proveedor",E12/G12,ROUND(E12/G12,2)) -> 35314.56 | I12: =ROUND(H12-F12,2) -> -1867.8 | J12: =IF(ABS(I12)>=Parámetros!$C$11,"SÍ","no") -> SÍ | K12: =IF(AND(ABS(F12)>0,ABS(I12)>0.3*ABS(F12),ABS(I12)>500),"REVISAR","")
A13: 114010010 | B13: Imp. Gcia. Min. Presunta | C13: ACTIVO | D13: General | E13: 528747.09 | F13: 377.95 | G13: =IF(C13="ACTIVO",Parámetros!$C$6,Parámetros!$C$7) -> 1473 | H13: =IF(D13="Proveedor",E13/G13,ROUND(E13/G13,2)) -> 358.96 | I13: =ROUND(H13-F13,2) -> -18.99 | J13: =IF(ABS(I13)>=Parámetros!$C$11,"SÍ","no") -> SÍ | K13: =IF(AND(ABS(F13)>0,ABS(I13)>0.3*ABS(F13),ABS(I13)>500),"REVISAR","")
A14: 114010013 | B14: GMP saldo a favor | C14: ACTIVO | D14: General | E14: 243686.59 | F14: 174.19 | G14: =IF(C14="ACTIVO",Parámetros!$C$6,Parámetros!$C$7) -> 1473 | H14: =IF(D14="Proveedor",E14/G14,ROUND(E14/G14,2)) -> 165.44 | I14: =ROUND(H14-F14,2) -> -8.75 | J14: =IF(ABS(I14)>=Parámetros!$C$11,"SÍ","no") -> SÍ | K14: =IF(AND(ABS(F14)>0,ABS(I14)>0.3*ABS(F14),ABS(I14)>500),"REVISAR","")
... A90: 213010007 | B90: Tasa Seguridad e Higiene a pagar | C90: PASIVO | D90: General | E90: -19744 | F90: -14.02 | G90: =IF(C90="ACTIVO",Parámetros!$C$6,Parámetros!$C$7) -> 1482 | H90: =IF(D90="Proveedor",E90/G90,ROUND(E90/G90,2)) -> -13.32 | I90: =ROUND(H90-F90,2) -> 0.7 | J90: =IF(ABS(I90)>=Parámetros!$C$11,"SÍ","no") -> SÍ | K90: =IF(AND(ABS(F90)>0,ABS(I90)>0.3*ABS(F90),ABS(I90)>500),"REVISAR","")
A91: 423050000 | B91: Diferencia de Cambio USD | C91: RESULTADOS | D91: Balanceo | I91: =ROUND(-SUM(I3:I90),2) -> 58374.9 | J91: SÍ
H93: CONTROL — el asiento debe cerrar en 0: | I93: =ROUND(SUM(I3:I91),2) -> 0 | J93: =IF(ABS(I93)<0.005,"OK ✓","ERROR") -> OK ✓

Sheet Importador
A1: ARCHIVO IMPORTADOR — formato Onvio "Asientos" (idéntico a 0.xls). Pesos=0, USD firmado (+ Debe MEP / - Haber MEP).
A2: Número de asiento | B2: Número de Pase | C2: Fecha | D2: Concepto | E2: Código de cuenta | F2: Importe en moneda local | G2: Importe en moneda ext.present. | H2: Leyenda | I2: Código de centro de costos | J2: Porcentaje de distribución | K2: Imp.mon.local dist.C.Costos | L2: Imp.mon.present.dist.C.Costos
A3: =Parámetros!$C$9 -> 1 | B3: 1 | C3: =Parámetros!$C$5 -> 46203 | D3: =Parámetros!$C$8 -> Ajuste por Conversión | E3: =Cálculo!A3 -> 111010001 | F3: 0 | G3: =Cálculo!I3 -> -24.51
A4: =Parámetros!$C$9 -> 1 | B4: 2 | C4: =Parámetros!$C$5 -> 46203 | D4: =Parámetros!$C$8 -> Ajuste por Conversión | E4: =Cálculo!A4 -> 111020001 | F4: 0 | G4: =Cálculo!I4 -> -388.19
A5: =Parámetros!$C$9 -> 1 | B5: 3 | C5: =Parámetros!$C$5 -> 46203 | D5: =Parámetros!$C$8 -> Ajuste por Conversión | E5: =Cálculo!A5 -> 111020005 | F5: 0 | G5: =Cálculo!I5 -> -39.81
A6: =Parámetros!$C$9 -> 1 | B6: 4 | C6: =Parámetros!$C$5 -> 46203 | D6: =Parámetros!$C$8 -> Ajuste por Conversión | E6: =Cálculo!A6 -> 111020006 | F6: 0 | G6: =Cálculo!I6 -> -1.95
A7: =Parámetros!$C$9 -> 1 | B7: 5 | C7: =Parámetros!$C$5 -> 46203 | D7: =Parámetros!$C$8 -> Ajuste por Conversión | E7: =Cálculo!A7 -> 114010001 | F7: 0 | G7: =Cálculo!I7 -> -179.93
A8: =Parámetros!$C$9 -> 1 | B8: 6 | C8: =Parámetros!$C$5 -> 46203 | D8: =Parámetros!$C$8 -> Ajuste por Conversión | E8: =Cálculo!A8 -> 114010002 | F8: 0 | G8: =Cálculo!I8 -> -59627.3
A9: =Parámetros!$C$9 -> 1 | B9: 7 | C9: =Parámetros!$C$5 -> 46203 | D9: =Parámetros!$C$8 -> Ajuste por Conversión | E9: =Cálculo!A9 -> 114010003 | F9: 0 | G9: =Cálculo!I9 -> -1.01
A10: =Parámetros!$C$9 -> 1 | B10: 8 | C10: =Parámetros!$C$5 -> 46203 | D10: =Parámetros!$C$8 -> Ajuste por Conversión | E10: =Cálculo!A10 -> 114010004 | F10: 0 | G10: =Cálculo!I10 -> -0.34
A11: =Parámetros!$C$9 -> 1 | B11: 9 | C11: =Parámetros!$C$5 -> 46203 | D11: =Parámetros!$C$8 -> Ajuste por Conversión | E11: =Cálculo!A11 -> 114010005 | F11: 0 | G11: =Cálculo!I11 -> -281.71
A12: =Parámetros!$C$9 -> 1 | B12: 10 | C12: =Parámetros!$C$5 -> 46203 | D12: =Parámetros!$C$8 -> Ajuste por Conversión | E12: =Cálculo!A12 -> 114010006 | F12: 0 | G12: =Cálculo!I12 -> -1867.8
A13: =Parámetros!$C$9 -> 1 | B13: 11 | C13: =Parámetros!$C$5 -> 46203 | D13: =Parámetros!$C$8 -> Ajuste por Conversión | E13: =Cálculo!A13 -> 114010010 | F13: 0 | G13: =Cálculo!I13 -> -18.99
A14: =Parámetros!$C$9 -> 1 | B14: 12 | C14: =Parámetros!$C$5 -> 46203 | D14: =Parámetros!$C$8 -> Ajuste por Conversión | E14: =Cálculo!A14 -> 114010013 | F14: 0 | G14: =Cálculo!I14 -> -8.75
... A91: =Parámetros!$C$9 -> 1 | B91: 89 | C91: =Parámetros!$C$5 -> 46203 | D91: =Parámetros!$C$8 -> Ajuste por Conversión | E91: =Cálculo!A91 -> 423050000 | F91: 0 | G91: =Cálculo!I91 -> 58374.9
F92: Σ = | G92: =ROUND(SUM(G3:G91),2) -> 0 | H92: =IF(ABS(G92)<0.005,"cierra en 0 ✓","ERROR") -> cierra en 0 ✓
