Workbook

Sheet SyS
A1: Cuenta - Denominación | B1: Clave (CC_Cuenta) | K1: 0 | M1: 0 | P1: 0
A2: 1 - Oficina General
A3: 421030000 - IVA crédito fiscal no computable | B3: 1_421030000 | K3: 1238.25 | M3: 0 | P3: 1238.25
A4: 421050000 - Sueldos Adm. | B4: 1_421050000 | K4: 8810.54 | M4: 0 | P4: 8810.54
A5: 421060000 - Cargas sociales Adm. | B5: 1_421060000 | K5: 2558.21 | M5: 0 | P5: 2558.21
A6: 424500000 - Cargas sociales Campo | B6: 1_424500000 | K6: 0 | M6: 0 | P6: 0
A7: 425110000 - Refrigerios Adm Gral. | B7: 1_425110000 | K7: 0 | M7: 0 | P7: 0
A8: 425170000 - Mensajeria Adm. Gral. | B8: 1_425170000 | K8: 0 | M8: 0 | P8: 0
A9: 425190000 - Honorarios Profesionales Adm. Gral. | B9: 1_425190000 | K9: 6000 | M9: 0 | P9: 6000
A10: 425220000 - Gastos y Comisiones Bancarias Adm. Gral | B10: 1_425220000 | K10: 176.08 | M10: 0 | P10: 176.08
A11: 425230000 - Imp. a los Débitos y Créditos Bancarios Ad. Gral. | B11: 1_425230000 | K11: 427.8 | M11: 0 | P11: 427.8
A12: 425250000 - Amortizaciones Adm. Gral. | B12: 1_425250000 | K12: 3918.01 | M12: 0 | P12: 3918.01
A13: 425300000 - Gst Varios Oficina Adm. Gral. | B13: 1_425300000 | K13: 0 | M13: 0 | P13: 0
A14: 425310000 - Vacaciones Adm Gral. | B14: 1_425310000 | K14: 395.49 | M14: 0 | P14: 395.49
... A19: 433030000 - Honorarios Profesionales Adm. Gral. USD | B19: 1_433030000 | K19: 0 | M19: 0 | P19: 0
A21: 2 - Exploración Regional
A22: 421070000 - Movilidad y viáticos Adm. | B22: 2_421070000 | K22: 0 | M22: 0 | P22: 0
A23: 424220000 - Comida | B23: 2_424220000 | K23: 0 | M23: 0 | P23: 0
A24: 425110000 - Refrigerios Adm Gral. | B24: 2_425110000 | K24: 634.65 | M24: 0 | P24: 634.65
A25: 425120000 - Movilidad y Viáticos Adm. Gral. | B25: 2_425120000 | K25: 123.47 | M25: 0 | P25: 123.47
A26: 425150000 - Alquiler Inmueble Adm. Gral. | B26: 2_425150000 | K26: 1181.74 | M26: 0 | P26: 1181.74
A27: 425180000 - Comunicaciones Adm. Gral | B27: 2_425180000 | K27: 0 | M27: 0 | P27: 0
A28: 425200000 - Combustible Adm Gral. | B28: 2_425200000 | K28: 142.21 | M28: 0 | P28: 142.21
A29: 425300000 - Gst Varios Oficina Adm. Gral. | B29: 2_425300000 | K29: 130.94 | M29: 0 | P29: 130.94
A30: 425400000 - Servicios Informáticos Adm. Gral. | B30: 2_425400000 | K30: 0 | M30: 0 | P30: 0
A31: 425500000 - Servicios Públicos Adm. Gral. | B31: 2_425500000 | K31: 0 | M31: 0 | P31: 0
A32: 425600000 - Gst Mantenimiento Adm. Gral. | B32: 2_425600000 | K32: 0 | M32: 0 | P32: 0
A33: 425700000 - Alojamiento Adm. Gral. | B33: 2_425700000 | K33: 64.7 | M33: 0 | P33: 64.7
... A66: 426960000 - Análisis de Muestras Gs de Campo | B66: 2_426960000 | K66: 818.52 | M66: 0 | P66: 818.52
A68: 13 - Cerro Abanico
A69: 426150000 - Servicios Públicos Gs Campo | B69: 13_426150000 | K69: 0 | M69: 0 | P69: 0
A71: 14 - Cerro La Mina
A72: 426150000 - Servicios Públicos Gs Campo | B72: 14_426150000 | K72: 0 | M72: 0 | P72: 0
A73: 426800000 - Análisis Geoquimicos - Gtos Laboratorio Gs Campo | B73: 14_426800000 | K73: 0 | M73: 0 | P73: 0
A75: 15 - Cañadon del Moro
A76: 424400000 - Sueldos Campo | B76: 15_424400000 | K76: 10334.79 | M76: 0 | P76: 10334.79
A77: 424500000 - Cargas sociales Campo | B77: 15_424500000 | K77: 2716.28 | M77: 0 | P77: 2716.28
A78: 425150000 - Alquiler Inmueble Adm. Gral. | B78: 15_425150000 | K78: 1235.4 | M78: 0 | P78: 1235.4
A79: 426220000 - Alquiler Inmueble Gst Campo | B79: 15_426220000 | K79: 0 | M79: 0 | P79: 0
A81: 16 - Los Menucos
A82: 421410000 - Combustible Gs de campo Catamarca | B82: 16_421410000 | K82: 0 | M82: 0 | P82: 0
A83: 425110000 - Refrigerios Adm Gral. | B83: 16_425110000 | K83: 0 | M83: 0 | P83: 0
A84: 426110000 - Refrigerios Gs Campo | B84: 16_426110000 | K84: 0 | M84: 0 | P84: 0
A85: 426190000 - Gst Varios Oficina Gst Campo | B85: 16_426190000 | K85: 0 | M85: 0 | P85: 0
A86: 426200000 - Combustible Gst Campo | B86: 16_426200000 | K86: 0 | M86: 0 | P86: 0
A87: 426260000 - Alojamiento Gst de Campo | B87: 16_426260000 | K87: 0 | M87: 0 | P87: 0
A88: 426590000 - Alquiler de vehículos Gs Campo | B88: 16_426590000 | K88: 0 | M88: 0 | P88: 0
A89: 426970000 - Encomienda Gs Campo | B89: 16_426970000 | K89: 0 | M89: 0 | P89: 0
A90: 433070000 - Gst de Vehículos Gst de Campo USD | B90: 16_433070000 | K90: 0 | M90: 0 | P90: 0
A91: 426270000 - Gst Varios Campo Gst Campo | B91: 16_426270000 | K91: 0 | M91: 0 | P91: 0
A93: 17 - Esperanza
A94: 421490000 - Alquiler Inmueble Gs. de campo Catamarca | B94: 17_421490000 | K94: 0 | M94: 0 | P94: 0
A95: 424400000 - Sueldos Campo | B95: 17_424400000 | K95: 7812.34 | M95: 0 | P95: 7812.34
A96: 424460000 - Gastos de Perforación | B96: 17_424460000 | K96: 0 | M96: 0 | P96: 0
A97: 424500000 - Cargas sociales Campo | B97: 17_424500000 | K97: 2552.94 | M97: 0 | P97: 2552.94
A98: 425110000 - Refrigerios Adm Gral. | B98: 17_425110000 | K98: 0 | M98: 0 | P98: 0
A99: 425150000 - Alquiler Inmueble Adm. Gral. | B99: 17_425150000 | K99: 0 | M99: 0 | P99: 0
A100: 425200000 - Combustible Adm Gral. | B100: 17_425200000 | K100: 0 | M100: 0 | P100: 0
A101: 425920000 - Libreria y papeleria Adm Gral. | B101: 17_425920000 | K101: 0 | M101: 0 | P101: 0
A102: 426110000 - Refrigerios Gs Campo | B102: 17_426110000 | K102: 1238.03 | M102: 0 | P102: 1238.03
A103: 426120000 - Movilidad y Viaticos Gs Campo | B103: 17_426120000 | K103: 110.95 | M103: 0 | P103: 110.95
A104: 426130000 - Gastos de Limpieza Gs Campo | B104: 17_426130000 | K104: 62.26 | M104: 0 | P104: 62.26
A105: 426150000 - Servicios Públicos Gs Campo | B105: 17_426150000 | K105: 0 | M105: 0 | P105: 0
... A126: 427120000 - Refrigerios Rel. comunitarias | B126: 17_427120000 | K126: 0 | M126: 0 | P126: 0
A128: 19 - Proyecto Lonco Vaca- Palenque
A129: 426800000 - Análisis Geoquimicos - Gtos Laboratorio Gs Campo | B129: 19_426800000 | K129: 0 | M129: 0 | P129: 0
A131: 23 - Gastos Generales
A132: 426110000 - Refrigerios Gs Campo | B132: 23_426110000 | K132: 0 | M132: 0 | P132: 0
A133: 426200000 - Combustible Gst Campo | B133: 23_426200000 | K133: 0 | M133: 0 | P133: 0
A134: 426250000 - Gst de Mantenimiento Gst Campo | B134: 23_426250000 | K134: 0 | M134: 0 | P134: 0
A135: 426260000 - Alojamiento Gst de Campo | B135: 23_426260000 | K135: 0 | M135: 0 | P135: 0
A136: 426450000 - Gs Ferretería Gs Campo | B136: 23_426450000 | K136: 0 | M136: 0 | P136: 0
A137: 426470000 - Librería y Papelería Gs Campo | B137: 23_426470000 | K137: 0 | M137: 0 | P137: 0
A138: 426490000 - Remediación Ambiental Gs de Campo | B138: 23_426490000 | K138: 0 | M138: 0 | P138: 0
A139: 426970000 - Encomienda Gs Campo | B139: 23_426970000 | K139: 0 | M139: 0 | P139: 0
A140: 433070000 - Gst de Vehículos Gst de Campo USD | B140: 23_433070000 | K140: 0 | M140: 0 | P140: 0
A141: 433110000 - Gastos bancarios Adm general (u$s) | B141: 1_433110000 | K141: 18 | M141: 0 | P141: 18

Sheet Sumas y Saldos
A1: SOUTHERN COPPER ARGENTINA S.R.L.
A2: 46113
A3: En Dólares
C4: OFICINA GENERAL | F4: EXPLORACIÓN REGIONAL | I4: TANQUE NEGRO | L4: SAMENTA | O4: CERRO LA MINA | R4: CAÑADON DEL MORO | V4: LOS MENUCOS | X4: CERRO ABANICO | AA4: CENTRO ESPERANZA | AD4: PROYECTO LOS MORTERITOS | AG4: LONCO VACA - PELENQUE | AJ4: PROYECTO SOL | AM4: GASTOS GENERALES | AP4: TRES CONOS | AS4: LA CHILENA | AV4: SOL | AY4: LOS MORTERITOS | BB4: LAS SANTAS | BE4: SHEYLA | BH4: SHEYLA I | BK4: LA HOYADA | BN4: REGIONAL CATAMARCA | BQ4: TOTALES
C5: DEBE | D5: HABER | E5: SALDO | F5: DEBE | G5: HABER | H5: SALDO | I5: DEBE | J5: HABER | K5: SALDO | L5: DEBE | M5: HABER | N5: SALDO | O5: DEBE | P5: HABER | Q5: SALDO | R5: DEBE | S5: HABER | T5: SALDO | U5: DEBE | V5: HABER | W5: SALDO | X5: DEBE | Y5: HABER | Z5: SALDO | AA5: DEBE | AB5: HABER | AC5: SALDO | AD5: DEBE | AE5: HABER | AF5: SALDO | AG5: DEBE | AH5: HABER | AI5: SALDO | AJ5: DEBE | AK5: HABER | AL5: SALDO | AM5: DEBE | AN5: HABER | AO5: SALDO | AP5: DEBE | AQ5: HABER | AR5: SALDO | AS5: DEBE | AT5: HABER | AU5: SALDO | AV5: DEBE | AW5: HABER | AX5: SALDO | AY5: DEBE | AZ5: HABER | BA5: SALDO | BB5: DEBE | BC5: HABER | BD5: SALDO | BE5: DEBE | BF5: HABER | BG5: SALDO | BH5: DEBE | BI5: HABER | BJ5: SALDO | BK5: DEBE | BL5: HABER | BM5: SALDO | BN5: DEBE | BO5: HABER | BP5: SALDO | BQ5: SALDOS
K6: 0
A7: 40000000 | B7: RESULTADOS | C7: =IFERROR(VLOOKUP("1_"&A7,SyS!$B:$P,10,FALSE()),0) -> 0 | D7: =IFERROR(VLOOKUP("1_"&A7,SyS!$B:$P,12,FALSE()),0) -> 0 | E7: =+C7-D7 -> 0 | F7: =IFERROR(VLOOKUP("2_"&A7,SyS!$B:$P,10,FALSE()),0) -> 0 | G7: =IFERROR(VLOOKUP("2_"&A7,SyS!$B:$P,12,FALSE()),0) -> 0 | H7: =+F7-G7 -> 0 | O7: =IFERROR(VLOOKUP("14_"&A7,SyS!$B:$P,10,FALSE()),0) -> 0 | P7: =IFERROR(VLOOKUP("14_"&A7,SyS!$B:$P,12,FALSE()),0) -> 0 | Q7: =+O7-P7 -> 0 | R7: =IFERROR(VLOOKUP("15_"&A7,SyS!$B:$P,10,FALSE()),0) -> 0 | S7: =IFERROR(VLOOKUP("15_"&A7,SyS!$B:$P,12,FALSE()),0) -> 0 | T7: =+R7-S7 -> 0 | U7: =IFERROR(VLOOKUP("16_"&A7,SyS!$B:$P,10,FALSE()),0) -> 0 | V7: =IFERROR(VLOOKUP("16_"&A7,SyS!$B:$P,12,FALSE()),0) -> 0 | W7: =+U7-V7 -> 0 | X7: =IFERROR(VLOOKUP("13_"&A7,SyS!$B:$P,10,FALSE()),0) -> 0 | Y7: =IFERROR(VLOOKUP("13_"&A7,SyS!$B:$P,12,FALSE()),0) -> 0 | Z7: =+X7-Y7 -> 0 | AA7: =IFERROR(VLOOKUP("17_"&A7,SyS!$B:$P,10,FALSE()),0) -> 0 | AB7: =IFERROR(VLOOKUP("17_"&A7,SyS!$B:$P,12,FALSE()),0) -> 0 | AC7: =+AA7-AB7 -> 0 | AG7: =IFERROR(VLOOKUP("19_"&A7,SyS!$B:$P,10,FALSE()),0) -> 0 | AH7: =IFERROR(VLOOKUP("19_"&A7,SyS!$B:$P,12,FALSE()),0) -> 0 | AI7: =+AG7-AH7 -> 0 | AM7: =IFERROR(VLOOKUP("23_"&A7,SyS!$B:$P,10,FALSE()),0) -> 0 | AN7: =IFERROR(VLOOKUP("23_"&A7,SyS!$B:$P,12,FALSE()),0) -> 0 | AO7: =+AM7-AN7 -> 0 | BK7: =IFERROR(VLOOKUP("29_"&A7,SyS!$B:$P,10,FALSE()),0) -> 0 | BL7: =IFERROR(VLOOKUP("29_"&A7,SyS!$B:$P,12,FALSE()),0) -> 0 | BM7: =+BK7-BL7 -> 0 | BN7: =IFERROR(VLOOKUP("30_"&A7,SyS!$B:$P,10,FALSE()),0) -> 0 | BO7: =IFERROR(VLOOKUP("30_"&A7,SyS!$B:$P,12,FALSE()),0) -> 0 | BP7: =+BN7-BO7 -> 0 | BQ7: =+E7+H7+K7+Q7+T7+W7+Z7+AC7+AF7+AI7+AL7+AO7+AR7+AU7+AX7+BA7+BD7+BG7+BJ7+BM7+BP7 -> 0
A8: 41000000 | B8: INGRESOS | C8: =IFERROR(VLOOKUP("1_"&A8,SyS!$B:$P,10,FALSE()),0) -> 0 | D8: =IFERROR(VLOOKUP("1_"&A8,SyS!$B:$P,12,FALSE()),0) -> 0 | E8: =+C8-D8 -> 0 | F8: =IFERROR(VLOOKUP("2_"&A8,SyS!$B:$P,10,FALSE()),0) -> 0 | G8: =IFERROR(VLOOKUP("2_"&A8,SyS!$B:$P,12,FALSE()),0) -> 0 | H8: =+F8-G8 -> 0 | O8: =IFERROR(VLOOKUP("14_"&A8,SyS!$B:$P,10,FALSE()),0) -> 0 | P8: =IFERROR(VLOOKUP("14_"&A8,SyS!$B:$P,12,FALSE()),0) -> 0 | Q8: =+O8-P8 -> 0 | R8: =IFERROR(VLOOKUP("15_"&A8,SyS!$B:$P,10,FALSE()),0) -> 0 | S8: =IFERROR(VLOOKUP("15_"&A8,SyS!$B:$P,12,FALSE()),0) -> 0 | T8: =+R8-S8 -> 0 | U8: =IFERROR(VLOOKUP("16_"&A8,SyS!$B:$P,10,FALSE()),0) -> 0 | V8: =IFERROR(VLOOKUP("16_"&A8,SyS!$B:$P,12,FALSE()),0) -> 0 | W8: =+U8-V8 -> 0 | X8: =IFERROR(VLOOKUP("13_"&A8,SyS!$B:$P,10,FALSE()),0) -> 0 | Y8: =IFERROR(VLOOKUP("13_"&A8,SyS!$B:$P,12,FALSE()),0) -> 0 | Z8: =+X8-Y8 -> 0 | AA8: =IFERROR(VLOOKUP("17_"&A8,SyS!$B:$P,10,FALSE()),0) -> 0 | AB8: =IFERROR(VLOOKUP("17_"&A8,SyS!$B:$P,12,FALSE()),0) -> 0 | AC8: =+AA8-AB8 -> 0 | AG8: =IFERROR(VLOOKUP("19_"&A8,SyS!$B:$P,10,FALSE()),0) -> 0 | AH8: =IFERROR(VLOOKUP("19_"&A8,SyS!$B:$P,12,FALSE()),0) -> 0 | AI8: =+AG8-AH8 -> 0 | AM8: =IFERROR(VLOOKUP("23_"&A8,SyS!$B:$P,10,FALSE()),0) -> 0 | AN8: =IFERROR(VLOOKUP("23_"&A8,SyS!$B:$P,12,FALSE()),0) -> 0 | AO8: =+AM8-AN8 -> 0 | BK8: =IFERROR(VLOOKUP("29_"&A8,SyS!$B:$P,10,FALSE()),0) -> 0 | BL8: =IFERROR(VLOOKUP("29_"&A8,SyS!$B:$P,12,FALSE()),0) -> 0 | BM8: =+BK8-BL8 -> 0 | BN8: =IFERROR(VLOOKUP("30_"&A8,SyS!$B:$P,10,FALSE()),0) -> 0 | BO8: =IFERROR(VLOOKUP("30_"&A8,SyS!$B:$P,12,FALSE()),0) -> 0 | BP8: =+BN8-BO8 -> 0 | BQ8: =+E8+H8+K8+Q8+T8+W8+Z8+AC8+AF8+AI8+AL8+AO8+AR8+AU8+AX8+BA8+BD8+BG8+BJ8+BM8+BP8 -> 0
A9: 41100000 | B9: VENTAS | C9: =IFERROR(VLOOKUP("1_"&A9,SyS!$B:$P,10,FALSE()),0) -> 0 | D9: =IFERROR(VLOOKUP("1_"&A9,SyS!$B:$P,12,FALSE()),0) -> 0 | E9: =+C9-D9 -> 0 | F9: =IFERROR(VLOOKUP("2_"&A9,SyS!$B:$P,10,FALSE()),0) -> 0 | G9: =IFERROR(VLOOKUP("2_"&A9,SyS!$B:$P,12,FALSE()),0) -> 0 | H9: =+F9-G9 -> 0 | O9: =IFERROR(VLOOKUP("14_"&A9,SyS!$B:$P,10,FALSE()),0) -> 0 | P9: =IFERROR(VLOOKUP("14_"&A9,SyS!$B:$P,12,FALSE()),0) -> 0 | Q9: =+O9-P9 -> 0 | R9: =IFERROR(VLOOKUP("15_"&A9,SyS!$B:$P,10,FALSE()),0) -> 0 | S9: =IFERROR(VLOOKUP("15_"&A9,SyS!$B:$P,12,FALSE()),0) -> 0 | T9: =+R9-S9 -> 0 | U9: =IFERROR(VLOOKUP("16_"&A9,SyS!$B:$P,10,FALSE()),0) -> 0 | V9: =IFERROR(VLOOKUP("16_"&A9,SyS!$B:$P,12,FALSE()),0) -> 0 | W9: =+U9-V9 -> 0 | X9: =IFERROR(VLOOKUP("13_"&A9,SyS!$B:$P,10,FALSE()),0) -> 0 | Y9: =IFERROR(VLOOKUP("13_"&A9,SyS!$B:$P,12,FALSE()),0) -> 0 | Z9: =+X9-Y9 -> 0 | AA9: =IFERROR(VLOOKUP("17_"&A9,SyS!$B:$P,10,FALSE()),0) -> 0 | AB9: =IFERROR(VLOOKUP("17_"&A9,SyS!$B:$P,12,FALSE()),0) -> 0 | AC9: =+AA9-AB9 -> 0 | AG9: =IFERROR(VLOOKUP("19_"&A9,SyS!$B:$P,10,FALSE()),0) -> 0 | AH9: =IFERROR(VLOOKUP("19_"&A9,SyS!$B:$P,12,FALSE()),0) -> 0 | AI9: =+AG9-AH9 -> 0 | AM9: =IFERROR(VLOOKUP("23_"&A9,SyS!$B:$P,10,FALSE()),0) -> 0 | AN9: =IFERROR(VLOOKUP("23_"&A9,SyS!$B:$P,12,FALSE()),0) -> 0 | AO9: =+AM9-AN9 -> 0 | BK9: =IFERROR(VLOOKUP("29_"&A9,SyS!$B:$P,10,FALSE()),0) -> 0 | BL9: =IFERROR(VLOOKUP("29_"&A9,SyS!$B:$P,12,FALSE()),0) -> 0 | BM9: =+BK9-BL9 -> 0 | BN9: =IFERROR(VLOOKUP("30_"&A9,SyS!$B:$P,10,FALSE()),0) -> 0 | BO9: =IFERROR(VLOOKUP("30_"&A9,SyS!$B:$P,12,FALSE()),0) -> 0 | BP9: =+BN9-BO9 -> 0 | BQ9: =+E9+H9+K9+Q9+T9+W9+Z9+AC9+AF9+AI9+AL9+AO9+AR9+AU9+AX9+BA9+BD9+BG9+BJ9+BM9+BP9 -> 0
A10: 41200000 | B10: OTROS INGRESOS | C10: =IFERROR(VLOOKUP("1_"&A10,SyS!$B:$P,10,FALSE()),0) -> 0 | D10: =IFERROR(VLOOKUP("1_"&A10,SyS!$B:$P,12,FALSE()),0) -> 0 | E10: =+C10-D10 -> 0 | F10: =IFERROR(VLOOKUP("2_"&A10,SyS!$B:$P,10,FALSE()),0) -> 0 | G10: =IFERROR(VLOOKUP("2_"&A10,SyS!$B:$P,12,FALSE()),0) -> 0 | H10: =+F10-G10 -> 0 | O10: =IFERROR(VLOOKUP("14_"&A10,SyS!$B:$P,10,FALSE()),0) -> 0 | P10: =IFERROR(VLOOKUP("14_"&A10,SyS!$B:$P,12,FALSE()),0) -> 0 | Q10: =+O10-P10 -> 0 | R10: =IFERROR(VLOOKUP("15_"&A10,SyS!$B:$P,10,FALSE()),0) -> 0 | S10: =IFERROR(VLOOKUP("15_"&A10,SyS!$B:$P,12,FALSE()),0) -> 0 | T10: =+R10-S10 -> 0 | U10: =IFERROR(VLOOKUP("16_"&A10,SyS!$B:$P,10,FALSE()),0) -> 0 | V10: =IFERROR(VLOOKUP("16_"&A10,SyS!$B:$P,12,FALSE()),0) -> 0 | W10: =+U10-V10 -> 0 | X10: =IFERROR(VLOOKUP("13_"&A10,SyS!$B:$P,10,FALSE()),0) -> 0 | Y10: =IFERROR(VLOOKUP("13_"&A10,SyS!$B:$P,12,FALSE()),0) -> 0 | Z10: =+X10-Y10 -> 0 | AA10: =IFERROR(VLOOKUP("17_"&A10,SyS!$B:$P,10,FALSE()),0) -> 0 | AB10: =IFERROR(VLOOKUP("17_"&A10,SyS!$B:$P,12,FALSE()),0) -> 0 | AC10: =+AA10-AB10 -> 0 | AG10: =IFERROR(VLOOKUP("19_"&A10,SyS!$B:$P,10,FALSE()),0) -> 0 | AH10: =IFERROR(VLOOKUP("19_"&A10,SyS!$B:$P,12,FALSE()),0) -> 0 | AI10: =+AG10-AH10 -> 0 | AM10: =IFERROR(VLOOKUP("23_"&A10,SyS!$B:$P,10,FALSE()),0) -> 0 | AN10: =IFERROR(VLOOKUP("23_"&A10,SyS!$B:$P,12,FALSE()),0) -> 0 | AO10: =+AM10-AN10 -> 0 | BK10: =IFERROR(VLOOKUP("29_"&A10,SyS!$B:$P,10,FALSE()),0) -> 0 | BL10: =IFERROR(VLOOKUP("29_"&A10,SyS!$B:$P,12,FALSE()),0) -> 0 | BM10: =+BK10-BL10 -> 0 | BN10: =IFERROR(VLOOKUP("30_"&A10,SyS!$B:$P,10,FALSE()),0) -> 0 | BO10: =IFERROR(VLOOKUP("30_"&A10,SyS!$B:$P,12,FALSE()),0) -> 0 | BP10: =+BN10-BO10 -> 0 | BQ10: =+E10+H10+K10+Q10+T10+W10+Z10+AC10+AF10+AI10+AL10+AO10+AR10+AU10+AX10+BA10+BD10+BG10+BJ10+BM10+BP10 -> 0
A11: 41230000 | B11: Envío muestras Chile | C11: =IFERROR(VLOOKUP("1_"&A11,SyS!$B:$P,10,FALSE()),0) -> 0 | D11: =IFERROR(VLOOKUP("1_"&A11,SyS!$B:$P,12,FALSE()),0) -> 0 | E11: =+C11-D11 -> 0 | F11: =IFERROR(VLOOKUP("2_"&A11,SyS!$B:$P,10,FALSE()),0) -> 0 | G11: =IFERROR(VLOOKUP("2_"&A11,SyS!$B:$P,12,FALSE()),0) -> 0 | H11: =+F11-G11 -> 0 | O11: =IFERROR(VLOOKUP("14_"&A11,SyS!$B:$P,10,FALSE()),0) -> 0 | P11: =IFERROR(VLOOKUP("14_"&A11,SyS!$B:$P,12,FALSE()),0) -> 0 | Q11: =+O11-P11 -> 0 | R11: =IFERROR(VLOOKUP("15_"&A11,SyS!$B:$P,10,FALSE()),0) -> 0 | S11: =IFERROR(VLOOKUP("15_"&A11,SyS!$B:$P,12,FALSE()),0) -> 0 | T11: =+R11-S11 -> 0 | U11: =IFERROR(VLOOKUP("16_"&A11,SyS!$B:$P,10,FALSE()),0) -> 0 | V11: =IFERROR(VLOOKUP("16_"&A11,SyS!$B:$P,12,FALSE()),0) -> 0 | W11: =+U11-V11 -> 0 | X11: =IFERROR(VLOOKUP("13_"&A11,SyS!$B:$P,10,FALSE()),0) -> 0 | Y11: =IFERROR(VLOOKUP("13_"&A11,SyS!$B:$P,12,FALSE()),0) -> 0 | Z11: =+X11-Y11 -> 0 | AA11: =IFERROR(VLOOKUP("17_"&A11,SyS!$B:$P,10,FALSE()),0) -> 0 | AB11: =IFERROR(VLOOKUP("17_"&A11,SyS!$B:$P,12,FALSE()),0) -> 0 | AC11: =+AA11-AB11 -> 0 | AG11: =IFERROR(VLOOKUP("19_"&A11,SyS!$B:$P,10,FALSE()),0) -> 0 | AH11: =IFERROR(VLOOKUP("19_"&A11,SyS!$B:$P,12,FALSE()),0) -> 0 | AI11: =+AG11-AH11 -> 0 | AM11: =IFERROR(VLOOKUP("23_"&A11,SyS!$B:$P,10,FALSE()),0) -> 0 | AN11: =IFERROR(VLOOKUP("23_"&A11,SyS!$B:$P,12,FALSE()),0) -> 0 | AO11: =+AM11-AN11 -> 0 | BK11: =IFERROR(VLOOKUP("29_"&A11,SyS!$B:$P,10,FALSE()),0) -> 0 | BL11: =IFERROR(VLOOKUP("29_"&A11,SyS!$B:$P,12,FALSE()),0) -> 0 | BM11: =+BK11-BL11 -> 0 | BN11: =IFERROR(VLOOKUP("30_"&A11,SyS!$B:$P,10,FALSE()),0) -> 0 | BO11: =IFERROR(VLOOKUP("30_"&A11,SyS!$B:$P,12,FALSE()),0) -> 0 | BP11: =+BN11-BO11 -> 0 | BQ11: =+E11+H11+K11+Q11+T11+W11+Z11+AC11+AF11+AI11+AL11+AO11+AR11+AU11+AX11+BA11+BD11+BG11+BJ11+BM11+BP11 -> 0
A12: 41210000 | B12: Baja bien de uso | C12: =IFERROR(VLOOKUP("1_"&A12,SyS!$B:$P,10,FALSE()),0) -> 0 | D12: =IFERROR(VLOOKUP("1_"&A12,SyS!$B:$P,12,FALSE()),0) -> 0 | E12: =+C12-D12 -> 0 | F12: =IFERROR(VLOOKUP("2_"&A12,SyS!$B:$P,10,FALSE()),0) -> 0 | G12: =IFERROR(VLOOKUP("2_"&A12,SyS!$B:$P,12,FALSE()),0) -> 0 | H12: =+F12-G12 -> 0 | O12: =IFERROR(VLOOKUP("14_"&A12,SyS!$B:$P,10,FALSE()),0) -> 0 | P12: =IFERROR(VLOOKUP("14_"&A12,SyS!$B:$P,12,FALSE()),0) -> 0 | Q12: =+O12-P12 -> 0 | R12: =IFERROR(VLOOKUP("15_"&A12,SyS!$B:$P,10,FALSE()),0) -> 0 | S12: =IFERROR(VLOOKUP("15_"&A12,SyS!$B:$P,12,FALSE()),0) -> 0 | T12: =+R12-S12 -> 0 | U12: =IFERROR(VLOOKUP("16_"&A12,SyS!$B:$P,10,FALSE()),0) -> 0 | V12: =IFERROR(VLOOKUP("16_"&A12,SyS!$B:$P,12,FALSE()),0) -> 0 | W12: =+U12-V12 -> 0 | X12: =IFERROR(VLOOKUP("13_"&A12,SyS!$B:$P,10,FALSE()),0) -> 0 | Y12: =IFERROR(VLOOKUP("13_"&A12,SyS!$B:$P,12,FALSE()),0) -> 0 | Z12: =+X12-Y12 -> 0 | AA12: =IFERROR(VLOOKUP("17_"&A12,SyS!$B:$P,10,FALSE()),0) -> 0 | AB12: =IFERROR(VLOOKUP("17_"&A12,SyS!$B:$P,12,FALSE()),0) -> 0 | AC12: =+AA12-AB12 -> 0 | AG12: =IFERROR(VLOOKUP("19_"&A12,SyS!$B:$P,10,FALSE()),0) -> 0 | AH12: =IFERROR(VLOOKUP("19_"&A12,SyS!$B:$P,12,FALSE()),0) -> 0 | AI12: =+AG12-AH12 -> 0 | AM12: =IFERROR(VLOOKUP("23_"&A12,SyS!$B:$P,10,FALSE()),0) -> 0 | AN12: =IFERROR(VLOOKUP("23_"&A12,SyS!$B:$P,12,FALSE()),0) -> 0 | AO12: =+AM12-AN12 -> 0 | BK12: =IFERROR(VLOOKUP("29_"&A12,SyS!$B:$P,10,FALSE()),0) -> 0 | BL12: =IFERROR(VLOOKUP("29_"&A12,SyS!$B:$P,12,FALSE()),0) -> 0 | BM12: =+BK12-BL12 -> 0 | BN12: =IFERROR(VLOOKUP("30_"&A12,SyS!$B:$P,10,FALSE()),0) -> 0 | BO12: =IFERROR(VLOOKUP("30_"&A12,SyS!$B:$P,12,FALSE()),0) -> 0 | BP12: =+BN12-BO12 -> 0 | BQ12: =+E12+H12+K12+Q12+T12+W12+Z12+AC12+AF12+AI12+AL12+AO12+AR12+AU12+AX12+BA12+BD12+BG12+BJ12+BM12+BP12 -> 0
A13: 42000000 | B13: EGRESOS | C13: =IFERROR(VLOOKUP("1_"&A13,SyS!$B:$P,10,FALSE()),0) -> 0 | D13: =IFERROR(VLOOKUP("1_"&A13,SyS!$B:$P,12,FALSE()),0) -> 0 | E13: =+C13-D13 -> 0 | F13: =IFERROR(VLOOKUP("2_"&A13,SyS!$B:$P,10,FALSE()),0) -> 0 | G13: =IFERROR(VLOOKUP("2_"&A13,SyS!$B:$P,12,FALSE()),0) -> 0 | H13: =+F13-G13 -> 0 | O13: =IFERROR(VLOOKUP("14_"&A13,SyS!$B:$P,10,FALSE()),0) -> 0 | P13: =IFERROR(VLOOKUP("14_"&A13,SyS!$B:$P,12,FALSE()),0) -> 0 | Q13: =+O13-P13 -> 0 | R13: =IFERROR(VLOOKUP("15_"&A13,SyS!$B:$P,10,FALSE()),0) -> 0 | S13: =IFERROR(VLOOKUP("15_"&A13,SyS!$B:$P,12,FALSE()),0) -> 0 | T13: =+R13-S13 -> 0 | U13: =IFERROR(VLOOKUP("16_"&A13,SyS!$B:$P,10,FALSE()),0) -> 0 | V13: =IFERROR(VLOOKUP("16_"&A13,SyS!$B:$P,12,FALSE()),0) -> 0 | W13: =+U13-V13 -> 0 | X13: =IFERROR(VLOOKUP("13_"&A13,SyS!$B:$P,10,FALSE()),0) -> 0 | Y13: =IFERROR(VLOOKUP("13_"&A13,SyS!$B:$P,12,FALSE()),0) -> 0 | Z13: =+X13-Y13 -> 0 | AA13: =IFERROR(VLOOKUP("17_"&A13,SyS!$B:$P,10,FALSE()),0) -> 0 | AB13: =IFERROR(VLOOKUP("17_"&A13,SyS!$B:$P,12,FALSE()),0) -> 0 | AC13: =+AA13-AB13 -> 0 | AG13: =IFERROR(VLOOKUP("19_"&A13,SyS!$B:$P,10,FALSE()),0) -> 0 | AH13: =IFERROR(VLOOKUP("19_"&A13,SyS!$B:$P,12,FALSE()),0) -> 0 | AI13: =+AG13-AH13 -> 0 | AM13: =IFERROR(VLOOKUP("23_"&A13,SyS!$B:$P,10,FALSE()),0) -> 0 | AN13: =IFERROR(VLOOKUP("23_"&A13,SyS!$B:$P,12,FALSE()),0) -> 0 | AO13: =+AM13-AN13 -> 0 | BK13: =IFERROR(VLOOKUP("29_"&A13,SyS!$B:$P,10,FALSE()),0) -> 0 | BL13: =IFERROR(VLOOKUP("29_"&A13,SyS!$B:$P,12,FALSE()),0) -> 0 | BM13: =+BK13-BL13 -> 0 | BN13: =IFERROR(VLOOKUP("30_"&A13,SyS!$B:$P,10,FALSE()),0) -> 0 | BO13: =IFERROR(VLOOKUP("30_"&A13,SyS!$B:$P,12,FALSE()),0) -> 0 | BP13: =+BN13-BO13 -> 0 | BQ13: =+E13+H13+K13+Q13+T13+W13+Z13+AC13+AF13+AI13+AL13+AO13+AR13+AU13+AX13+BA13+BD13+BG13+BJ13+BM13+BP13 -> 0
A14: 42100000 | B14: GASTOS DE COMERCIALIZACION | C14: =IFERROR(VLOOKUP("1_"&A14,SyS!$B:$P,10,FALSE()),0) -> 0 | D14: =IFERROR(VLOOKUP("1_"&A14,SyS!$B:$P,12,FALSE()),0) -> 0 | E14: =+C14-D14 -> 0 | F14: =IFERROR(VLOOKUP("2_"&A14,SyS!$B:$P,10,FALSE()),0) -> 0 | G14: =IFERROR(VLOOKUP("2_"&A14,SyS!$B:$P,12,FALSE()),0) -> 0 | H14: =+F14-G14 -> 0 | O14: =IFERROR(VLOOKUP("14_"&A14,SyS!$B:$P,10,FALSE()),0) -> 0 | P14: =IFERROR(VLOOKUP("14_"&A14,SyS!$B:$P,12,FALSE()),0) -> 0 | Q14: =+O14-P14 -> 0 | R14: =IFERROR(VLOOKUP("15_"&A14,SyS!$B:$P,10,FALSE()),0) -> 0 | S14: =IFERROR(VLOOKUP("15_"&A14,SyS!$B:$P,12,FALSE()),0) -> 0 | T14: =+R14-S14 -> 0 | U14: =IFERROR(VLOOKUP("16_"&A14,SyS!$B:$P,10,FALSE()),0) -> 0 | V14: =IFERROR(VLOOKUP("16_"&A14,SyS!$B:$P,12,FALSE()),0) -> 0 | W14: =+U14-V14 -> 0 | X14: =IFERROR(VLOOKUP("13_"&A14,SyS!$B:$P,10,FALSE()),0) -> 0 | Y14: =IFERROR(VLOOKUP("13_"&A14,SyS!$B:$P,12,FALSE()),0) -> 0 | Z14: =+X14-Y14 -> 0 | AA14: =IFERROR(VLOOKUP("17_"&A14,SyS!$B:$P,10,FALSE()),0) -> 0 | AB14: =IFERROR(VLOOKUP("17_"&A14,SyS!$B:$P,12,FALSE()),0) -> 0 | AC14: =+AA14-AB14 -> 0 | AG14: =IFERROR(VLOOKUP("19_"&A14,SyS!$B:$P,10,FALSE()),0) -> 0 | AH14: =IFERROR(VLOOKUP("19_"&A14,SyS!$B:$P,12,FALSE()),0) -> 0 | AI14: =+AG14-AH14 -> 0 | AM14: =IFERROR(VLOOKUP("23_"&A14,SyS!$B:$P,10,FALSE()),0) -> 0 | AN14: =IFERROR(VLOOKUP("23_"&A14,SyS!$B:$P,12,FALSE()),0) -> 0 | AO14: =+AM14-AN14 -> 0 | BK14: =IFERROR(VLOOKUP("29_"&A14,SyS!$B:$P,10,FALSE()),0) -> 0 | BL14: =IFERROR(VLOOKUP("29_"&A14,SyS!$B:$P,12,FALSE()),0) -> 0 | BM14: =+BK14-BL14 -> 0 | BN14: =IFERROR(VLOOKUP("30_"&A14,SyS!$B:$P,10,FALSE()),0) -> 0 | BO14: =IFERROR(VLOOKUP("30_"&A14,SyS!$B:$P,12,FALSE()),0) -> 0 | BP14: =+BN14-BO14 -> 0 | BQ14: =+E14+H14+K14+Q14+T14+W14+Z14+AC14+AF14+AI14+AL14+AO14+AR14+AU14+AX14+BA14+BD14+BG14+BJ14+BM14+BP14 -> 0
A15: 42101000 | B15: Honorarios legales | C15: =IFERROR(VLOOKUP("1_"&A15,SyS!$B:$P,10,FALSE()),0) -> 0 | D15: =IFERROR(VLOOKUP("1_"&A15,SyS!$B:$P,12,FALSE()),0) -> 0 | E15: =+C15-D15 -> 0 | F15: =IFERROR(VLOOKUP("2_"&A15,SyS!$B:$P,10,FALSE()),0) -> 0 | G15: =IFERROR(VLOOKUP("2_"&A15,SyS!$B:$P,12,FALSE()),0) -> 0 | H15: =+F15-G15 -> 0 | O15: =IFERROR(VLOOKUP("14_"&A15,SyS!$B:$P,10,FALSE()),0) -> 0 | P15: =IFERROR(VLOOKUP("14_"&A15,SyS!$B:$P,12,FALSE()),0) -> 0 | Q15: =+O15-P15 -> 0 | R15: =IFERROR(VLOOKUP("15_"&A15,SyS!$B:$P,10,FALSE()),0) -> 0 | S15: =IFERROR(VLOOKUP("15_"&A15,SyS!$B:$P,12,FALSE()),0) -> 0 | T15: =+R15-S15 -> 0 | U15: =IFERROR(VLOOKUP("16_"&A15,SyS!$B:$P,10,FALSE()),0) -> 0 | V15: =IFERROR(VLOOKUP("16_"&A15,SyS!$B:$P,12,FALSE()),0) -> 0 | W15: =+U15-V15 -> 0 | X15: =IFERROR(VLOOKUP("13_"&A15,SyS!$B:$P,10,FALSE()),0) -> 0 | Y15: =IFERROR(VLOOKUP("13_"&A15,SyS!$B:$P,12,FALSE()),0) -> 0 | Z15: =+X15-Y15 -> 0 | AA15: =IFERROR(VLOOKUP("17_"&A15,SyS!$B:$P,10,FALSE()),0) -> 0 | AB15: =IFERROR(VLOOKUP("17_"&A15,SyS!$B:$P,12,FALSE()),0) -> 0 | AC15: =+AA15-AB15 -> 0 | AG15: =IFERROR(VLOOKUP("19_"&A15,SyS!$B:$P,10,FALSE()),0) -> 0 | AH15: =IFERROR(VLOOKUP("19_"&A15,SyS!$B:$P,12,FALSE()),0) -> 0 | AI15: =+AG15-AH15 -> 0 | AM15: =IFERROR(VLOOKUP("23_"&A15,SyS!$B:$P,10,FALSE()),0) -> 0 | AN15: =IFERROR(VLOOKUP("23_"&A15,SyS!$B:$P,12,FALSE()),0) -> 0 | AO15: =+AM15-AN15 -> 0 | BK15: =IFERROR(VLOOKUP("29_"&A15,SyS!$B:$P,10,FALSE()),0) -> 0 | BL15: =IFERROR(VLOOKUP("29_"&A15,SyS!$B:$P,12,FALSE()),0) -> 0 | BM15: =+BK15-BL15 -> 0 | BN15: =IFERROR(VLOOKUP("30_"&A15,SyS!$B:$P,10,FALSE()),0) -> 0 | BO15: =IFERROR(VLOOKUP("30_"&A15,SyS!$B:$P,12,FALSE()),0) -> 0 | BP15: =+BN15-BO15 -> 0 | BQ15: =+E15+H15+K15+Q15+T15+W15+Z15+AC15+AF15+AI15+AL15+AO15+AR15+AU15+AX15+BA15+BD15+BG15+BJ15+BM15+BP15 -> 0
A16: 42102000 | B16: Honorarios profesionales | C16: =IFERROR(VLOOKUP("1_"&A16,SyS!$B:$P,10,FALSE()),0) -> 0 | D16: =IFERROR(VLOOKUP("1_"&A16,SyS!$B:$P,12,FALSE()),0) -> 0 | E16: =+C16-D16 -> 0 | F16: =IFERROR(VLOOKUP("2_"&A16,SyS!$B:$P,10,FALSE()),0) -> 0 | G16: =IFERROR(VLOOKUP("2_"&A16,SyS!$B:$P,12,FALSE()),0) -> 0 | H16: =+F16-G16 -> 0 | O16: =IFERROR(VLOOKUP("14_"&A16,SyS!$B:$P,10,FALSE()),0) -> 0 | P16: =IFERROR(VLOOKUP("14_"&A16,SyS!$B:$P,12,FALSE()),0) -> 0 | Q16: =+O16-P16 -> 0 | R16: =IFERROR(VLOOKUP("15_"&A16,SyS!$B:$P,10,FALSE()),0) -> 0 | S16: =IFERROR(VLOOKUP("15_"&A16,SyS!$B:$P,12,FALSE()),0) -> 0 | T16: =+R16-S16 -> 0 | U16: =IFERROR(VLOOKUP("16_"&A16,SyS!$B:$P,10,FALSE()),0) -> 0 | V16: =IFERROR(VLOOKUP("16_"&A16,SyS!$B:$P,12,FALSE()),0) -> 0 | W16: =+U16-V16 -> 0 | X16: =IFERROR(VLOOKUP("13_"&A16,SyS!$B:$P,10,FALSE()),0) -> 0 | Y16: =IFERROR(VLOOKUP("13_"&A16,SyS!$B:$P,12,FALSE()),0) -> 0 | Z16: =+X16-Y16 -> 0 | AA16: =IFERROR(VLOOKUP("17_"&A16,SyS!$B:$P,10,FALSE()),0) -> 0 | AB16: =IFERROR(VLOOKUP("17_"&A16,SyS!$B:$P,12,FALSE()),0) -> 0 | AC16: =+AA16-AB16 -> 0 | AG16: =IFERROR(VLOOKUP("19_"&A16,SyS!$B:$P,10,FALSE()),0) -> 0 | AH16: =IFERROR(VLOOKUP("19_"&A16,SyS!$B:$P,12,FALSE()),0) -> 0 | AI16: =+AG16-AH16 -> 0 | AM16: =IFERROR(VLOOKUP("23_"&A16,SyS!$B:$P,10,FALSE()),0) -> 0 | AN16: =IFERROR(VLOOKUP("23_"&A16,SyS!$B:$P,12,FALSE()),0) -> 0 | AO16: =+AM16-AN16 -> 0 | BK16: =IFERROR(VLOOKUP("29_"&A16,SyS!$B:$P,10,FALSE()),0) -> 0 | BL16: =IFERROR(VLOOKUP("29_"&A16,SyS!$B:$P,12,FALSE()),0) -> 0 | BM16: =+BK16-BL16 -> 0 | BN16: =IFERROR(VLOOKUP("30_"&A16,SyS!$B:$P,10,FALSE()),0) -> 0 | BO16: =IFERROR(VLOOKUP("30_"&A16,SyS!$B:$P,12,FALSE()),0) -> 0 | BP16: =+BN16-BO16 -> 0 | BQ16: =+E16+H16+K16+Q16+T16+W16+Z16+AC16+AF16+AI16+AL16+AO16+AR16+AU16+AX16+BA16+BD16+BG16+BJ16+BM16+BP16 -> 0
A17: 421030000 | B17: Iva credito fiscal no computable | C17: =IFERROR(VLOOKUP("1_"&A17,SyS!$B:$P,10,FALSE()),0) -> 1238.25 | D17: =IFERROR(VLOOKUP("1_"&A17,SyS!$B:$P,12,FALSE()),0) -> 0 | E17: =+C17-D17 -> 1238.25 | F17: =IFERROR(VLOOKUP("2_"&A17,SyS!$B:$P,10,FALSE()),0) -> 0 | G17: =IFERROR(VLOOKUP("2_"&A17,SyS!$B:$P,12,FALSE()),0) -> 0 | H17: =+F17-G17 -> 0 | O17: =IFERROR(VLOOKUP("14_"&A17,SyS!$B:$P,10,FALSE()),0) -> 0 | P17: =IFERROR(VLOOKUP("14_"&A17,SyS!$B:$P,12,FALSE()),0) -> 0 | Q17: =+O17-P17 -> 0 | R17: =IFERROR(VLOOKUP("15_"&A17,SyS!$B:$P,10,FALSE()),0) -> 0 | S17: =IFERROR(VLOOKUP("15_"&A17,SyS!$B:$P,12,FALSE()),0) -> 0 | T17: =+R17-S17 -> 0 | U17: =IFERROR(VLOOKUP("16_"&A17,SyS!$B:$P,10,FALSE()),0) -> 0 | V17: =IFERROR(VLOOKUP("16_"&A17,SyS!$B:$P,12,FALSE()),0) -> 0 | W17: =+U17-V17 -> 0 | X17: =IFERROR(VLOOKUP("13_"&A17,SyS!$B:$P,10,FALSE()),0) -> 0 | Y17: =IFERROR(VLOOKUP("13_"&A17,SyS!$B:$P,12,FALSE()),0) -> 0 | Z17: =+X17-Y17 -> 0 | AA17: =IFERROR(VLOOKUP("17_"&A17,SyS!$B:$P,10,FALSE()),0) -> 0 | AB17: =IFERROR(VLOOKUP("17_"&A17,SyS!$B:$P,12,FALSE()),0) -> 0 | AC17: =+AA17-AB17 -> 0 | AG17: =IFERROR(VLOOKUP("19_"&A17,SyS!$B:$P,10,FALSE()),0) -> 0 | AH17: =IFERROR(VLOOKUP("19_"&A17,SyS!$B:$P,12,FALSE()),0) -> 0 | AI17: =+AG17-AH17 -> 0 | AM17: =IFERROR(VLOOKUP("23_"&A17,SyS!$B:$P,10,FALSE()),0) -> 0 | AN17: =IFERROR(VLOOKUP("23_"&A17,SyS!$B:$P,12,FALSE()),0) -> 0 | AO17: =+AM17-AN17 -> 0 | BK17: =IFERROR(VLOOKUP("29_"&A17,SyS!$B:$P,10,FALSE()),0) -> 0 | BL17: =IFERROR(VLOOKUP("29_"&A17,SyS!$B:$P,12,FALSE()),0) -> 0 | BM17: =+BK17-BL17 -> 0 | BN17: =IFERROR(VLOOKUP("30_"&A17,SyS!$B:$P,10,FALSE()),0) -> 0 | BO17: =IFERROR(VLOOKUP("30_"&A17,SyS!$B:$P,12,FALSE()),0) -> 0 | BP17: =+BN17-BO17 -> 0 | BQ17: =+E17+H17+K17+Q17+T17+W17+Z17+AC17+AF17+AI17+AL17+AO17+AR17+AU17+AX17+BA17+BD17+BG17+BJ17+BM17+BP17 -> 1238.25
A18: 42104000 | B18: Alquileres | C18: =IFERROR(VLOOKUP("1_"&A18,SyS!$B:$P,10,FALSE()),0) -> 0 | D18: =IFERROR(VLOOKUP("1_"&A18,SyS!$B:$P,12,FALSE()),0) -> 0 | E18: =+C18-D18 -> 0 | F18: =IFERROR(VLOOKUP("2_"&A18,SyS!$B:$P,10,FALSE()),0) -> 0 | G18: =IFERROR(VLOOKUP("2_"&A18,SyS!$B:$P,12,FALSE()),0) -> 0 | H18: =+F18-G18 -> 0 | O18: =IFERROR(VLOOKUP("14_"&A18,SyS!$B:$P,10,FALSE()),0) -> 0 | P18: =IFERROR(VLOOKUP("14_"&A18,SyS!$B:$P,12,FALSE()),0) -> 0 | Q18: =+O18-P18 -> 0 | R18: =IFERROR(VLOOKUP("15_"&A18,SyS!$B:$P,10,FALSE()),0) -> 0 | S18: =IFERROR(VLOOKUP("15_"&A18,SyS!$B:$P,12,FALSE()),0) -> 0 | T18: =+R18-S18 -> 0 | U18: =IFERROR(VLOOKUP("16_"&A18,SyS!$B:$P,10,FALSE()),0) -> 0 | V18: =IFERROR(VLOOKUP("16_"&A18,SyS!$B:$P,12,FALSE()),0) -> 0 | W18: =+U18-V18 -> 0 | X18: =IFERROR(VLOOKUP("13_"&A18,SyS!$B:$P,10,FALSE()),0) -> 0 | Y18: =IFERROR(VLOOKUP("13_"&A18,SyS!$B:$P,12,FALSE()),0) -> 0 | Z18: =+X18-Y18 -> 0 | AA18: =IFERROR(VLOOKUP("17_"&A18,SyS!$B:$P,10,FALSE()),0) -> 0 | AB18: =IFERROR(VLOOKUP("17_"&A18,SyS!$B:$P,12,FALSE()),0) -> 0 | AC18: =+AA18-AB18 -> 0 | AG18: =IFERROR(VLOOKUP("19_"&A18,SyS!$B:$P,10,FALSE()),0) -> 0 | AH18: =IFERROR(VLOOKUP("19_"&A18,SyS!$B:$P,12,FALSE()),0) -> 0 | AI18: =+AG18-AH18 -> 0 | AM18: =IFERROR(VLOOKUP("23_"&A18,SyS!$B:$P,10,FALSE()),0) -> 0 | AN18: =IFERROR(VLOOKUP("23_"&A18,SyS!$B:$P,12,FALSE()),0) -> 0 | AO18: =+AM18-AN18 -> 0 | BK18: =IFERROR(VLOOKUP("29_"&A18,SyS!$B:$P,10,FALSE()),0) -> 0 | BL18: =IFERROR(VLOOKUP("29_"&A18,SyS!$B:$P,12,FALSE()),0) -> 0 | BM18: =+BK18-BL18 -> 0 | BN18: =IFERROR(VLOOKUP("30_"&A18,SyS!$B:$P,10,FALSE()),0) -> 0 | BO18: =IFERROR(VLOOKUP("30_"&A18,SyS!$B:$P,12,FALSE()),0) -> 0 | BP18: =+BN18-BO18 -> 0 | BQ18: =+E18+H18+K18+Q18+T18+W18+Z18+AC18+AF18+AI18+AL18+AO18+AR18+AU18+AX18+BA18+BD18+BG18+BJ18+BM18+BP18 -> 0
... A121: 432010000 | B121: ROBO | C121: =IFERROR(VLOOKUP("1_"&A121,SyS!$B:$P,10,FALSE()),0) -> 0 | D121: =IFERROR(VLOOKUP("1_"&A121,SyS!$B:$P,12,FALSE()),0) -> 0 | E121: =+C121-D121 -> 0 | F121: =IFERROR(VLOOKUP("2_"&A121,SyS!$B:$P,10,FALSE()),0) -> 0 | G121: =IFERROR(VLOOKUP("2_"&A121,SyS!$B:$P,12,FALSE()),0) -> 0 | H121: =+F121-G121 -> 0 | O121: =IFERROR(VLOOKUP("14_"&A121,SyS!$B:$P,10,FALSE()),0) -> 0 | P121: =IFERROR(VLOOKUP("14_"&A121,SyS!$B:$P,12,FALSE()),0) -> 0 | Q121: =+O121-P121 -> 0 | R121: =IFERROR(VLOOKUP("15_"&A121,SyS!$B:$P,10,FALSE()),0) -> 0 | S121: =IFERROR(VLOOKUP("15_"&A121,SyS!$B:$P,12,FALSE()),0) -> 0 | T121: =+R121-S121 -> 0 | U121: =IFERROR(VLOOKUP("16_"&A121,SyS!$B:$P,10,FALSE()),0) -> 0 | V121: =IFERROR(VLOOKUP("16_"&A121,SyS!$B:$P,12,FALSE()),0) -> 0 | W121: =+U121-V121 -> 0 | X121: =IFERROR(VLOOKUP("13_"&A121,SyS!$B:$P,10,FALSE()),0) -> 0 | Y121: =IFERROR(VLOOKUP("13_"&A121,SyS!$B:$P,12,FALSE()),0) -> 0 | Z121: =+X121-Y121 -> 0 | AA121: =IFERROR(VLOOKUP("17_"&A121,SyS!$B:$P,10,FALSE()),0) -> 0 | AB121: =IFERROR(VLOOKUP("17_"&A121,SyS!$B:$P,12,FALSE()),0) -> 0 | AC121: =+AA121-AB121 -> 0 | AG121: =IFERROR(VLOOKUP("19_"&A121,SyS!$B:$P,10,FALSE()),0) -> 0 | AH121: =IFERROR(VLOOKUP("19_"&A121,SyS!$B:$P,12,FALSE()),0) -> 0 | AI121: =+AG121-AH121 -> 0 | AM121: =IFERROR(VLOOKUP("23_"&A121,SyS!$B:$P,10,FALSE()),0) -> 0 | AN121: =IFERROR(VLOOKUP("23_"&A121,SyS!$B:$P,12,FALSE()),0) -> 0 | AO121: =+AM121-AN121 -> 0 | BK121: =IFERROR(VLOOKUP("29_"&A121,SyS!$B:$P,10,FALSE()),0) -> 0 | BL121: =IFERROR(VLOOKUP("29_"&A121,SyS!$B:$P,12,FALSE()),0) -> 0 | BM121: =+BK121-BL121 -> 0 | BN121: =IFERROR(VLOOKUP("30_"&A121,SyS!$B:$P,10,FALSE()),0) -> 0 | BO121: =IFERROR(VLOOKUP("30_"&A121,SyS!$B:$P,12,FALSE()),0) -> 0 | BP121: =+BN121-BO121 -> 0 | BQ121: =+E121+H121+K121+Q121+T121+W121+Z121+AC121+AF121+AI121+AL121+AO121+AR121+AU121+AX121+BA121+BD121+BG121+BJ121+BM121+BP121 -> 0
B122: I - R AMBIENTAL | C122: =IFERROR(VLOOKUP("1_"&A122,SyS!$B:$P,10,FALSE()),0) -> 0 | D122: =IFERROR(VLOOKUP("1_"&A122,SyS!$B:$P,12,FALSE()),0) -> 0 | E122: =+C122-D122 -> 0
A123: 422010000 | B123: TASAS AMBIENTALES I- R. AMBIENTAL | C123: =IFERROR(VLOOKUP("1_"&A123,SyS!$B:$P,10,FALSE()),0) -> 0 | D123: =IFERROR(VLOOKUP("1_"&A123,SyS!$B:$P,12,FALSE()),0) -> 0 | E123: =+C123-D123 -> 0 | F123: =IFERROR(VLOOKUP("2_"&A123,SyS!$B:$P,10,FALSE()),0) -> 0 | G123: =IFERROR(VLOOKUP("2_"&A123,SyS!$B:$P,12,FALSE()),0) -> 0 | H123: =+F123-G123 -> 0 | O123: =IFERROR(VLOOKUP("14_"&A123,SyS!$B:$P,10,FALSE()),0) -> 0 | P123: =IFERROR(VLOOKUP("14_"&A123,SyS!$B:$P,12,FALSE()),0) -> 0 | Q123: =+O123-P123 -> 0 | R123: =IFERROR(VLOOKUP("15_"&A123,SyS!$B:$P,10,FALSE()),0) -> 0 | S123: =IFERROR(VLOOKUP("15_"&A123,SyS!$B:$P,12,FALSE()),0) -> 0 | T123: =+R123-S123 -> 0 | U123: =IFERROR(VLOOKUP("16_"&A123,SyS!$B:$P,10,FALSE()),0) -> 0 | V123: =IFERROR(VLOOKUP("16_"&A123,SyS!$B:$P,12,FALSE()),0) -> 0 | W123: =+U123-V123 -> 0 | X123: =IFERROR(VLOOKUP("13_"&A123,SyS!$B:$P,10,FALSE()),0) -> 0 | Y123: =IFERROR(VLOOKUP("13_"&A123,SyS!$B:$P,12,FALSE()),0) -> 0 | Z123: =+X123-Y123 -> 0 | AA123: =IFERROR(VLOOKUP("17_"&A123,SyS!$B:$P,10,FALSE()),0) -> 0 | AB123: =IFERROR(VLOOKUP("17_"&A123,SyS!$B:$P,12,FALSE()),0) -> 0 | AC123: =+AA123-AB123 -> 0 | AG123: =IFERROR(VLOOKUP("19_"&A123,SyS!$B:$P,10,FALSE()),0) -> 0 | AH123: =IFERROR(VLOOKUP("19_"&A123,SyS!$B:$P,12,FALSE()),0) -> 0 | AI123: =+AG123-AH123 -> 0 | AM123: =IFERROR(VLOOKUP("23_"&A123,SyS!$B:$P,10,FALSE()),0) -> 0 | AN123: =IFERROR(VLOOKUP("23_"&A123,SyS!$B:$P,12,FALSE()),0) -> 0 | AO123: =+AM123-AN123 -> 0 | BK123: =IFERROR(VLOOKUP("29_"&A123,SyS!$B:$P,10,FALSE()),0) -> 0 | BL123: =IFERROR(VLOOKUP("29_"&A123,SyS!$B:$P,12,FALSE()),0) -> 0 | BM123: =+BK123-BL123 -> 0 | BN123: =IFERROR(VLOOKUP("30_"&A123,SyS!$B:$P,10,FALSE()),0) -> 0 | BO123: =IFERROR(VLOOKUP("30_"&A123,SyS!$B:$P,12,FALSE()),0) -> 0 | BP123: =+BN123-BO123 -> 0 | BQ123: =+E123+H123+K123+Q123+T123+W123+Z123+AC123+AF123+AI123+AL123+AO123+AR123+AU123+AX123+BA123+BD123+BG123+BJ123+BM123+BP123 -> 0
A124: 422020000 | B124: Remediación Ambiental I- R. Ambiental | C124: =IFERROR(VLOOKUP("1_"&A124,SyS!$B:$P,10,FALSE()),0) -> 0 | D124: =IFERROR(VLOOKUP("1_"&A124,SyS!$B:$P,12,FALSE()),0) -> 0 | E124: =+C124-D124 -> 0 | F124: =IFERROR(VLOOKUP("2_"&A124,SyS!$B:$P,10,FALSE()),0) -> 0 | G124: =IFERROR(VLOOKUP("2_"&A124,SyS!$B:$P,12,FALSE()),0) -> 0 | H124: =+F124-G124 -> 0 | O124: =IFERROR(VLOOKUP("14_"&A124,SyS!$B:$P,10,FALSE()),0) -> 0 | P124: =IFERROR(VLOOKUP("14_"&A124,SyS!$B:$P,12,FALSE()),0) -> 0 | Q124: =+O124-P124 -> 0 | R124: =IFERROR(VLOOKUP("15_"&A124,SyS!$B:$P,10,FALSE()),0) -> 0 | S124: =IFERROR(VLOOKUP("15_"&A124,SyS!$B:$P,12,FALSE()),0) -> 0 | T124: =+R124-S124 -> 0 | U124: =IFERROR(VLOOKUP("16_"&A124,SyS!$B:$P,10,FALSE()),0) -> 0 | V124: =IFERROR(VLOOKUP("16_"&A124,SyS!$B:$P,12,FALSE()),0) -> 0 | W124: =+U124-V124 -> 0 | X124: =IFERROR(VLOOKUP("13_"&A124,SyS!$B:$P,10,FALSE()),0) -> 0 | Y124: =IFERROR(VLOOKUP("13_"&A124,SyS!$B:$P,12,FALSE()),0) -> 0 | Z124: =+X124-Y124 -> 0 | AA124: =IFERROR(VLOOKUP("17_"&A124,SyS!$B:$P,10,FALSE()),0) -> 0 | AB124: =IFERROR(VLOOKUP("17_"&A124,SyS!$B:$P,12,FALSE()),0) -> 0 | AC124: =+AA124-AB124 -> 0 | AG124: =IFERROR(VLOOKUP("19_"&A124,SyS!$B:$P,10,FALSE()),0) -> 0 | AH124: =IFERROR(VLOOKUP("19_"&A124,SyS!$B:$P,12,FALSE()),0) -> 0 | AI124: =+AG124-AH124 -> 0 | AM124: =IFERROR(VLOOKUP("23_"&A124,SyS!$B:$P,10,FALSE()),0) -> 0 | AN124: =IFERROR(VLOOKUP("23_"&A124,SyS!$B:$P,12,FALSE()),0) -> 0 | AO124: =+AM124-AN124 -> 0 | BK124: =IFERROR(VLOOKUP("29_"&A124,SyS!$B:$P,10,FALSE()),0) -> 0 | BL124: =IFERROR(VLOOKUP("29_"&A124,SyS!$B:$P,12,FALSE()),0) -> 0 | BM124: =+BK124-BL124 -> 0 | BN124: =IFERROR(VLOOKUP("30_"&A124,SyS!$B:$P,10,FALSE()),0) -> 0 | BO124: =IFERROR(VLOOKUP("30_"&A124,SyS!$B:$P,12,FALSE()),0) -> 0 | BP124: =+BN124-BO124 -> 0 | BQ124: =+E124+H124+K124+Q124+T124+W124+Z124+AC124+AF124+AI124+AL124+AO124+AR124+AU124+AX124+BA124+BD124+BG124+BJ124+BM124+BP124 -> 0
A125: 422080000 | B125: Gastos Ferretería I -R.Ambiental | C125: =IFERROR(VLOOKUP("1_"&A125,SyS!$B:$P,10,FALSE()),0) -> 0 | D125: =IFERROR(VLOOKUP("1_"&A125,SyS!$B:$P,12,FALSE()),0) -> 0 | E125: =+C125-D125 -> 0 | F125: =IFERROR(VLOOKUP("2_"&A125,SyS!$B:$P,10,FALSE()),0) -> 0 | G125: =IFERROR(VLOOKUP("2_"&A125,SyS!$B:$P,12,FALSE()),0) -> 0 | H125: =+F125-G125 -> 0 | O125: =IFERROR(VLOOKUP("14_"&A125,SyS!$B:$P,10,FALSE()),0) -> 0 | P125: =IFERROR(VLOOKUP("14_"&A125,SyS!$B:$P,12,FALSE()),0) -> 0 | Q125: =+O125-P125 -> 0 | R125: =IFERROR(VLOOKUP("15_"&A125,SyS!$B:$P,10,FALSE()),0) -> 0 | S125: =IFERROR(VLOOKUP("15_"&A125,SyS!$B:$P,12,FALSE()),0) -> 0 | T125: =+R125-S125 -> 0 | U125: =IFERROR(VLOOKUP("16_"&A125,SyS!$B:$P,10,FALSE()),0) -> 0 | V125: =IFERROR(VLOOKUP("16_"&A125,SyS!$B:$P,12,FALSE()),0) -> 0 | W125: =+U125-V125 -> 0 | X125: =IFERROR(VLOOKUP("13_"&A125,SyS!$B:$P,10,FALSE()),0) -> 0 | Y125: =IFERROR(VLOOKUP("13_"&A125,SyS!$B:$P,12,FALSE()),0) -> 0 | Z125: =+X125-Y125 -> 0 | AA125: =IFERROR(VLOOKUP("17_"&A125,SyS!$B:$P,10,FALSE()),0) -> 0 | AB125: =IFERROR(VLOOKUP("17_"&A125,SyS!$B:$P,12,FALSE()),0) -> 0 | AC125: =+AA125-AB125 -> 0 | AG125: =IFERROR(VLOOKUP("19_"&A125,SyS!$B:$P,10,FALSE()),0) -> 0 | AH125: =IFERROR(VLOOKUP("19_"&A125,SyS!$B:$P,12,FALSE()),0) -> 0 | AI125: =+AG125-AH125 -> 0 | AM125: =IFERROR(VLOOKUP("23_"&A125,SyS!$B:$P,10,FALSE()),0) -> 0 | AN125: =IFERROR(VLOOKUP("23_"&A125,SyS!$B:$P,12,FALSE()),0) -> 0 | AO125: =+AM125-AN125 -> 0 | BK125: =IFERROR(VLOOKUP("29_"&A125,SyS!$B:$P,10,FALSE()),0) -> 0 | BL125: =IFERROR(VLOOKUP("29_"&A125,SyS!$B:$P,12,FALSE()),0) -> 0 | BM125: =+BK125-BL125 -> 0 | BN125: =IFERROR(VLOOKUP("30_"&A125,SyS!$B:$P,10,FALSE()),0) -> 0 | BO125: =IFERROR(VLOOKUP("30_"&A125,SyS!$B:$P,12,FALSE()),0) -> 0 | BP125: =+BN125-BO125 -> 0 | BQ125: =+E125+H125+K125+Q125+T125+W125+Z125+AC125+AF125+AI125+AL125+AO125+AR125+AU125+AX125+BA125+BD125+BG125+BJ125+BM125+BP125 -> 0
A126: 422220000 | B126: Análisis Muestras -R. Ambiental | C126: =IFERROR(VLOOKUP("1_"&A126,SyS!$B:$P,10,FALSE()),0) -> 0 | D126: =IFERROR(VLOOKUP("1_"&A126,SyS!$B:$P,12,FALSE()),0) -> 0 | E126: =+C126-D126 -> 0 | F126: =IFERROR(VLOOKUP("2_"&A126,SyS!$B:$P,10,FALSE()),0) -> 0 | G126: =IFERROR(VLOOKUP("2_"&A126,SyS!$B:$P,12,FALSE()),0) -> 0 | H126: =+F126-G126 -> 0 | O126: =IFERROR(VLOOKUP("14_"&A126,SyS!$B:$P,10,FALSE()),0) -> 0 | P126: =IFERROR(VLOOKUP("14_"&A126,SyS!$B:$P,12,FALSE()),0) -> 0 | Q126: =+O126-P126 -> 0 | R126: =IFERROR(VLOOKUP("15_"&A126,SyS!$B:$P,10,FALSE()),0) -> 0 | S126: =IFERROR(VLOOKUP("15_"&A126,SyS!$B:$P,12,FALSE()),0) -> 0 | T126: =+R126-S126 -> 0 | U126: =IFERROR(VLOOKUP("16_"&A126,SyS!$B:$P,10,FALSE()),0) -> 0 | V126: =IFERROR(VLOOKUP("16_"&A126,SyS!$B:$P,12,FALSE()),0) -> 0 | W126: =+U126-V126 -> 0 | X126: =IFERROR(VLOOKUP("13_"&A126,SyS!$B:$P,10,FALSE()),0) -> 0 | Y126: =IFERROR(VLOOKUP("13_"&A126,SyS!$B:$P,12,FALSE()),0) -> 0 | Z126: =+X126-Y126 -> 0 | AA126: =IFERROR(VLOOKUP("17_"&A126,SyS!$B:$P,10,FALSE()),0) -> 0 | AB126: =IFERROR(VLOOKUP("17_"&A126,SyS!$B:$P,12,FALSE()),0) -> 0 | AC126: =+AA126-AB126 -> 0 | AG126: =IFERROR(VLOOKUP("19_"&A126,SyS!$B:$P,10,FALSE()),0) -> 0 | AH126: =IFERROR(VLOOKUP("19_"&A126,SyS!$B:$P,12,FALSE()),0) -> 0 | AI126: =+AG126-AH126 -> 0 | AM126: =IFERROR(VLOOKUP("23_"&A126,SyS!$B:$P,10,FALSE()),0) -> 0 | AN126: =IFERROR(VLOOKUP("23_"&A126,SyS!$B:$P,12,FALSE()),0) -> 0 | AO126: =+AM126-AN126 -> 0 | BK126: =IFERROR(VLOOKUP("29_"&A126,SyS!$B:$P,10,FALSE()),0) -> 0 | BL126: =IFERROR(VLOOKUP("29_"&A126,SyS!$B:$P,12,FALSE()),0) -> 0 | BM126: =+BK126-BL126 -> 0 | BN126: =IFERROR(VLOOKUP("30_"&A126,SyS!$B:$P,10,FALSE()),0) -> 0 | BO126: =IFERROR(VLOOKUP("30_"&A126,SyS!$B:$P,12,FALSE()),0) -> 0 | BP126: =+BN126-BO126 -> 0 | BQ126: =+E126+H126+K126+Q126+T126+W126+Z126+AC126+AF126+AI126+AL126+AO126+AR126+AU126+AX126+BA126+BD126+BG126+BJ126+BM126+BP126 -> 0
A127: 421470000 | B127: Análisis Muestras I - R. Ambiental Catamarca | C127: =IFERROR(VLOOKUP("1_"&A127,SyS!$B:$P,10,FALSE()),0) -> 0 | D127: =IFERROR(VLOOKUP("1_"&A127,SyS!$B:$P,12,FALSE()),0) -> 0 | E127: =+C127-D127 -> 0 | F127: =IFERROR(VLOOKUP("2_"&A127,SyS!$B:$P,10,FALSE()),0) -> 0 | G127: =IFERROR(VLOOKUP("2_"&A127,SyS!$B:$P,12,FALSE()),0) -> 0 | H127: =+F127-G127 -> 0 | O127: =IFERROR(VLOOKUP("14_"&A127,SyS!$B:$P,10,FALSE()),0) -> 0 | P127: =IFERROR(VLOOKUP("14_"&A127,SyS!$B:$P,12,FALSE()),0) -> 0 | Q127: =+O127-P127 -> 0 | R127: =IFERROR(VLOOKUP("15_"&A127,SyS!$B:$P,10,FALSE()),0) -> 0 | S127: =IFERROR(VLOOKUP("15_"&A127,SyS!$B:$P,12,FALSE()),0) -> 0 | T127: =+R127-S127 -> 0 | U127: =IFERROR(VLOOKUP("16_"&A127,SyS!$B:$P,10,FALSE()),0) -> 0 | V127: =IFERROR(VLOOKUP("16_"&A127,SyS!$B:$P,12,FALSE()),0) -> 0 | W127: =+U127-V127 -> 0 | X127: =IFERROR(VLOOKUP("13_"&A127,SyS!$B:$P,10,FALSE()),0) -> 0 | Y127: =IFERROR(VLOOKUP("13_"&A127,SyS!$B:$P,12,FALSE()),0) -> 0 | Z127: =+X127-Y127 -> 0 | AA127: =IFERROR(VLOOKUP("17_"&A127,SyS!$B:$P,10,FALSE()),0) -> 0 | AB127: =IFERROR(VLOOKUP("17_"&A127,SyS!$B:$P,12,FALSE()),0) -> 0 | AC127: =+AA127-AB127 -> 0 | AG127: =IFERROR(VLOOKUP("19_"&A127,SyS!$B:$P,10,FALSE()),0) -> 0 | AH127: =IFERROR(VLOOKUP("19_"&A127,SyS!$B:$P,12,FALSE()),0) -> 0 | AI127: =+AG127-AH127 -> 0 | AM127: =IFERROR(VLOOKUP("23_"&A127,SyS!$B:$P,10,FALSE()),0) -> 0 | AN127: =IFERROR(VLOOKUP("23_"&A127,SyS!$B:$P,12,FALSE()),0) -> 0 | AO127: =+AM127-AN127 -> 0 | BK127: =IFERROR(VLOOKUP("29_"&A127,SyS!$B:$P,10,FALSE()),0) -> 0 | BL127: =IFERROR(VLOOKUP("29_"&A127,SyS!$B:$P,12,FALSE()),0) -> 0 | BM127: =+BK127-BL127 -> 0 | BN127: =IFERROR(VLOOKUP("30_"&A127,SyS!$B:$P,10,FALSE()),0) -> 0 | BO127: =IFERROR(VLOOKUP("30_"&A127,SyS!$B:$P,12,FALSE()),0) -> 0 | BP127: =+BN127-BO127 -> 0 | BQ127: =+E127+H127+K127+Q127+T127+W127+Z127+AC127+AF127+AI127+AL127+AO127+AR127+AU127+AX127+BA127+BD127+BG127+BJ127+BM127+BP127 -> 0
A128: 422090000 | B128: Gs en personal R- Ambiental | C128: =IFERROR(VLOOKUP("1_"&A128,SyS!$B:$P,10,FALSE()),0) -> 0 | D128: =IFERROR(VLOOKUP("1_"&A128,SyS!$B:$P,12,FALSE()),0) -> 0 | E128: =+C128-D128 -> 0 | F128: =IFERROR(VLOOKUP("2_"&A128,SyS!$B:$P,10,FALSE()),0) -> 0 | G128: =IFERROR(VLOOKUP("2_"&A128,SyS!$B:$P,12,FALSE()),0) -> 0 | H128: =+F128-G128 -> 0 | O128: =IFERROR(VLOOKUP("14_"&A128,SyS!$B:$P,10,FALSE()),0) -> 0 | P128: =IFERROR(VLOOKUP("14_"&A128,SyS!$B:$P,12,FALSE()),0) -> 0 | Q128: =+O128-P128 -> 0 | R128: =IFERROR(VLOOKUP("15_"&A128,SyS!$B:$P,10,FALSE()),0) -> 0 | S128: =IFERROR(VLOOKUP("15_"&A128,SyS!$B:$P,12,FALSE()),0) -> 0 | T128: =+R128-S128 -> 0 | U128: =IFERROR(VLOOKUP("16_"&A128,SyS!$B:$P,10,FALSE()),0) -> 0 | V128: =IFERROR(VLOOKUP("16_"&A128,SyS!$B:$P,12,FALSE()),0) -> 0 | W128: =+U128-V128 -> 0 | X128: =IFERROR(VLOOKUP("13_"&A128,SyS!$B:$P,10,FALSE()),0) -> 0 | Y128: =IFERROR(VLOOKUP("13_"&A128,SyS!$B:$P,12,FALSE()),0) -> 0 | Z128: =+X128-Y128 -> 0 | AA128: =IFERROR(VLOOKUP("17_"&A128,SyS!$B:$P,10,FALSE()),0) -> 0 | AB128: =IFERROR(VLOOKUP("17_"&A128,SyS!$B:$P,12,FALSE()),0) -> 0 | AC128: =+AA128-AB128 -> 0 | AG128: =IFERROR(VLOOKUP("19_"&A128,SyS!$B:$P,10,FALSE()),0) -> 0 | AH128: =IFERROR(VLOOKUP("19_"&A128,SyS!$B:$P,12,FALSE()),0) -> 0 | AI128: =+AG128-AH128 -> 0 | AM128: =IFERROR(VLOOKUP("23_"&A128,SyS!$B:$P,10,FALSE()),0) -> 0 | AN128: =IFERROR(VLOOKUP("23_"&A128,SyS!$B:$P,12,FALSE()),0) -> 0 | AO128: =+AM128-AN128 -> 0 | BK128: =IFERROR(VLOOKUP("29_"&A128,SyS!$B:$P,10,FALSE()),0) -> 0 | BL128: =IFERROR(VLOOKUP("29_"&A128,SyS!$B:$P,12,FALSE()),0) -> 0 | BM128: =+BK128-BL128 -> 0 | BN128: =IFERROR(VLOOKUP("30_"&A128,SyS!$B:$P,10,FALSE()),0) -> 0 | BO128: =IFERROR(VLOOKUP("30_"&A128,SyS!$B:$P,12,FALSE()),0) -> 0 | BP128: =+BN128-BO128 -> 0 | BQ128: =+E128+H128+K128+Q128+T128+W128+Z128+AC128+AF128+AI128+AL128+AO128+AR128+AU128+AX128+BA128+BD128+BG128+BJ128+BM128+BP128 -> 0
A129: 422240000 | B129: Honorarios profesionales - Remediación ambiental | C129: =IFERROR(VLOOKUP("1_"&A129,SyS!$B:$P,10,FALSE()),0) -> 0 | D129: =IFERROR(VLOOKUP("1_"&A129,SyS!$B:$P,12,FALSE()),0) -> 0 | E129: =+C129-D129 -> 0 | F129: =IFERROR(VLOOKUP("2_"&A129,SyS!$B:$P,10,FALSE()),0) -> 0 | G129: =IFERROR(VLOOKUP("2_"&A129,SyS!$B:$P,12,FALSE()),0) -> 0 | H129: =+F129-G129 -> 0 | O129: =IFERROR(VLOOKUP("14_"&A129,SyS!$B:$P,10,FALSE()),0) -> 0 | P129: =IFERROR(VLOOKUP("14_"&A129,SyS!$B:$P,12,FALSE()),0) -> 0 | Q129: =+O129-P129 -> 0 | R129: =IFERROR(VLOOKUP("15_"&A129,SyS!$B:$P,10,FALSE()),0) -> 0 | S129: =IFERROR(VLOOKUP("15_"&A129,SyS!$B:$P,12,FALSE()),0) -> 0 | T129: =+R129-S129 -> 0 | U129: =IFERROR(VLOOKUP("16_"&A129,SyS!$B:$P,10,FALSE()),0) -> 0 | V129: =IFERROR(VLOOKUP("16_"&A129,SyS!$B:$P,12,FALSE()),0) -> 0 | W129: =+U129-V129 -> 0 | X129: =IFERROR(VLOOKUP("13_"&A129,SyS!$B:$P,10,FALSE()),0) -> 0 | Y129: =IFERROR(VLOOKUP("13_"&A129,SyS!$B:$P,12,FALSE()),0) -> 0 | Z129: =+X129-Y129 -> 0 | AA129: =IFERROR(VLOOKUP("17_"&A129,SyS!$B:$P,10,FALSE()),0) -> 0 | AB129: =IFERROR(VLOOKUP("17_"&A129,SyS!$B:$P,12,FALSE()),0) -> 0 | AC129: =+AA129-AB129 -> 0 | AG129: =IFERROR(VLOOKUP("19_"&A129,SyS!$B:$P,10,FALSE()),0) -> 0 | AH129: =IFERROR(VLOOKUP("19_"&A129,SyS!$B:$P,12,FALSE()),0) -> 0 | AI129: =+AG129-AH129 -> 0 | AM129: =IFERROR(VLOOKUP("23_"&A129,SyS!$B:$P,10,FALSE()),0) -> 0 | AN129: =IFERROR(VLOOKUP("23_"&A129,SyS!$B:$P,12,FALSE()),0) -> 0 | AO129: =+AM129-AN129 -> 0 | BK129: =IFERROR(VLOOKUP("29_"&A129,SyS!$B:$P,10,FALSE()),0) -> 0 | BL129: =IFERROR(VLOOKUP("29_"&A129,SyS!$B:$P,12,FALSE()),0) -> 0 | BM129: =+BK129-BL129 -> 0 | BN129: =IFERROR(VLOOKUP("30_"&A129,SyS!$B:$P,10,FALSE()),0) -> 0 | BO129: =IFERROR(VLOOKUP("30_"&A129,SyS!$B:$P,12,FALSE()),0) -> 0 | BP129: =+BN129-BO129 -> 0 | BQ129: =+E129+H129+K129+Q129+T129+W129+Z129+AC129+AF129+AI129+AL129+AO129+AR129+AU129+AX129+BA129+BD129+BG129+BJ129+BM129+BP129 -> 0
B130: ADMINISTRACION GENERAL | C130: =IFERROR(VLOOKUP("1_"&A130,SyS!$B:$P,10,FALSE()),0) -> 0 | D130: =IFERROR(VLOOKUP("1_"&A130,SyS!$B:$P,12,FALSE()),0) -> 0 | E130: =+C130-D130 -> 0
A131: 425110000 | B131: REFRIGERIOS ADM. GRAL. | C131: =IFERROR(VLOOKUP("1_"&A131,SyS!$B:$P,10,FALSE()),0) -> 0 | D131: =IFERROR(VLOOKUP("1_"&A131,SyS!$B:$P,12,FALSE()),0) -> 0 | E131: =+C131-D131 -> 0 | F131: =IFERROR(VLOOKUP("2_"&A131,SyS!$B:$P,10,FALSE()),0) -> 634.65 | G131: =IFERROR(VLOOKUP("2_"&A131,SyS!$B:$P,12,FALSE()),0) -> 0 | H131: =+F131-G131 -> 634.65 | O131: =IFERROR(VLOOKUP("14_"&A131,SyS!$B:$P,10,FALSE()),0) -> 0 | P131: =IFERROR(VLOOKUP("14_"&A131,SyS!$B:$P,12,FALSE()),0) -> 0 | Q131: =+O131-P131 -> 0 | R131: =IFERROR(VLOOKUP("15_"&A131,SyS!$B:$P,10,FALSE()),0) -> 0 | S131: =IFERROR(VLOOKUP("15_"&A131,SyS!$B:$P,12,FALSE()),0) -> 0 | T131: =+R131-S131 -> 0 | U131: =IFERROR(VLOOKUP("16_"&A131,SyS!$B:$P,10,FALSE()),0) -> 0 | V131: =IFERROR(VLOOKUP("16_"&A131,SyS!$B:$P,12,FALSE()),0) -> 0 | W131: =+U131-V131 -> 0 | X131: =IFERROR(VLOOKUP("13_"&A131,SyS!$B:$P,10,FALSE()),0) -> 0 | Y131: =IFERROR(VLOOKUP("13_"&A131,SyS!$B:$P,12,FALSE()),0) -> 0 | Z131: =+X131-Y131 -> 0 | AA131: =IFERROR(VLOOKUP("17_"&A131,SyS!$B:$P,10,FALSE()),0) -> 0 | AB131: =IFERROR(VLOOKUP("17_"&A131,SyS!$B:$P,12,FALSE()),0) -> 0 | AC131: =+AA131-AB131 -> 0 | AG131: =IFERROR(VLOOKUP("19_"&A131,SyS!$B:$P,10,FALSE()),0) -> 0 | AH131: =IFERROR(VLOOKUP("19_"&A131,SyS!$B:$P,12,FALSE()),0) -> 0 | AI131: =+AG131-AH131 -> 0 | AM131: =IFERROR(VLOOKUP("23_"&A131,SyS!$B:$P,10,FALSE()),0) -> 0 | AN131: =IFERROR(VLOOKUP("23_"&A131,SyS!$B:$P,12,FALSE()),0) -> 0 | AO131: =+AM131-AN131 -> 0 | BK131: =IFERROR(VLOOKUP("29_"&A131,SyS!$B:$P,10,FALSE()),0) -> 0 | BL131: =IFERROR(VLOOKUP("29_"&A131,SyS!$B:$P,12,FALSE()),0) -> 0 | BM131: =+BK131-BL131 -> 0 | BN131: =IFERROR(VLOOKUP("30_"&A131,SyS!$B:$P,10,FALSE()),0) -> 0 | BO131: =IFERROR(VLOOKUP("30_"&A131,SyS!$B:$P,12,FALSE()),0) -> 0 | BP131: =+BN131-BO131 -> 0 | BQ131: =+E131+H131+K131+Q131+T131+W131+Z131+AC131+AF131+AI131+AL131+AO131+AR131+AU131+AX131+BA131+BD131+BG131+BJ131+BM131+BP131 -> 634.65
A132: 425120000 | B132: MOVILIDAD Y VIATICOS ADM GENERAL | C132: =IFERROR(VLOOKUP("1_"&A132,SyS!$B:$P,10,FALSE()),0) -> 0 | D132: =IFERROR(VLOOKUP("1_"&A132,SyS!$B:$P,12,FALSE()),0) -> 0 | E132: =+C132-D132 -> 0 | F132: =IFERROR(VLOOKUP("2_"&A132,SyS!$B:$P,10,FALSE()),0) -> 123.47 | G132: =IFERROR(VLOOKUP("2_"&A132,SyS!$B:$P,12,FALSE()),0) -> 0 | H132: =+F132-G132 -> 123.47 | O132: =IFERROR(VLOOKUP("14_"&A132,SyS!$B:$P,10,FALSE()),0) -> 0 | P132: =IFERROR(VLOOKUP("14_"&A132,SyS!$B:$P,12,FALSE()),0) -> 0 | Q132: =+O132-P132 -> 0 | R132: =IFERROR(VLOOKUP("15_"&A132,SyS!$B:$P,10,FALSE()),0) -> 0 | S132: =IFERROR(VLOOKUP("15_"&A132,SyS!$B:$P,12,FALSE()),0) -> 0 | T132: =+R132-S132 -> 0 | U132: =IFERROR(VLOOKUP("16_"&A132,SyS!$B:$P,10,FALSE()),0) -> 0 | V132: =IFERROR(VLOOKUP("16_"&A132,SyS!$B:$P,12,FALSE()),0) -> 0 | W132: =+U132-V132 -> 0 | X132: =IFERROR(VLOOKUP("13_"&A132,SyS!$B:$P,10,FALSE()),0) -> 0 | Y132: =IFERROR(VLOOKUP("13_"&A132,SyS!$B:$P,12,FALSE()),0) -> 0 | Z132: =+X132-Y132 -> 0 | AA132: =IFERROR(VLOOKUP("17_"&A132,SyS!$B:$P,10,FALSE()),0) -> 0 | AB132: =IFERROR(VLOOKUP("17_"&A132,SyS!$B:$P,12,FALSE()),0) -> 0 | AC132: =+AA132-AB132 -> 0 | AG132: =IFERROR(VLOOKUP("19_"&A132,SyS!$B:$P,10,FALSE()),0) -> 0 | AH132: =IFERROR(VLOOKUP("19_"&A132,SyS!$B:$P,12,FALSE()),0) -> 0 | AI132: =+AG132-AH132 -> 0 | AM132: =IFERROR(VLOOKUP("23_"&A132,SyS!$B:$P,10,FALSE()),0) -> 0 | AN132: =IFERROR(VLOOKUP("23_"&A132,SyS!$B:$P,12,FALSE()),0) -> 0 | AO132: =+AM132-AN132 -> 0 | BK132: =IFERROR(VLOOKUP("29_"&A132,SyS!$B:$P,10,FALSE()),0) -> 0 | BL132: =IFERROR(VLOOKUP("29_"&A132,SyS!$B:$P,12,FALSE()),0) -> 0 | BM132: =+BK132-BL132 -> 0 | BN132: =IFERROR(VLOOKUP("30_"&A132,SyS!$B:$P,10,FALSE()),0) -> 0 | BO132: =IFERROR(VLOOKUP("30_"&A132,SyS!$B:$P,12,FALSE()),0) -> 0 | BP132: =+BN132-BO132 -> 0 | BQ132: =+E132+H132+K132+Q132+T132+W132+Z132+AC132+AF132+AI132+AL132+AO132+AR132+AU132+AX132+BA132+BD132+BG132+BJ132+BM132+BP132 -> 123.47
A133: 425130000 | B133: EXPENSAS DEPTO GEOLOGOS ADM GRAL | C133: =IFERROR(VLOOKUP("1_"&A133,SyS!$B:$P,10,FALSE()),0) -> 0 | D133: =IFERROR(VLOOKUP("1_"&A133,SyS!$B:$P,12,FALSE()),0) -> 0 | E133: =+C133-D133 -> 0 | F133: =IFERROR(VLOOKUP("2_"&A133,SyS!$B:$P,10,FALSE()),0) -> 0 | G133: =IFERROR(VLOOKUP("2_"&A133,SyS!$B:$P,12,FALSE()),0) -> 0 | H133: =+F133-G133 -> 0 | O133: =IFERROR(VLOOKUP("14_"&A133,SyS!$B:$P,10,FALSE()),0) -> 0 | P133: =IFERROR(VLOOKUP("14_"&A133,SyS!$B:$P,12,FALSE()),0) -> 0 | Q133: =+O133-P133 -> 0 | R133: =IFERROR(VLOOKUP("15_"&A133,SyS!$B:$P,10,FALSE()),0) -> 0 | S133: =IFERROR(VLOOKUP("15_"&A133,SyS!$B:$P,12,FALSE()),0) -> 0 | T133: =+R133-S133 -> 0 | U133: =IFERROR(VLOOKUP("16_"&A133,SyS!$B:$P,10,FALSE()),0) -> 0 | V133: =IFERROR(VLOOKUP("16_"&A133,SyS!$B:$P,12,FALSE()),0) -> 0 | W133: =+U133-V133 -> 0 | X133: =IFERROR(VLOOKUP("13_"&A133,SyS!$B:$P,10,FALSE()),0) -> 0 | Y133: =IFERROR(VLOOKUP("13_"&A133,SyS!$B:$P,12,FALSE()),0) -> 0 | Z133: =+X133-Y133 -> 0 | AA133: =IFERROR(VLOOKUP("17_"&A133,SyS!$B:$P,10,FALSE()),0) -> 0 | AB133: =IFERROR(VLOOKUP("17_"&A133,SyS!$B:$P,12,FALSE()),0) -> 0 | AC133: =+AA133-AB133 -> 0 | AG133: =IFERROR(VLOOKUP("19_"&A133,SyS!$B:$P,10,FALSE()),0) -> 0 | AH133: =IFERROR(VLOOKUP("19_"&A133,SyS!$B:$P,12,FALSE()),0) -> 0 | AI133: =+AG133-AH133 -> 0 | AM133: =IFERROR(VLOOKUP("23_"&A133,SyS!$B:$P,10,FALSE()),0) -> 0 | AN133: =IFERROR(VLOOKUP("23_"&A133,SyS!$B:$P,12,FALSE()),0) -> 0 | AO133: =+AM133-AN133 -> 0 | BK133: =IFERROR(VLOOKUP("29_"&A133,SyS!$B:$P,10,FALSE()),0) -> 0 | BL133: =IFERROR(VLOOKUP("29_"&A133,SyS!$B:$P,12,FALSE()),0) -> 0 | BM133: =+BK133-BL133 -> 0 | BN133: =IFERROR(VLOOKUP("30_"&A133,SyS!$B:$P,10,FALSE()),0) -> 0 | BO133: =IFERROR(VLOOKUP("30_"&A133,SyS!$B:$P,12,FALSE()),0) -> 0 | BP133: =+BN133-BO133 -> 0 | BQ133: =+E133+H133+K133+Q133+T133+W133+Z133+AC133+AF133+AI133+AL133+AO133+AR133+AU133+AX133+BA133+BD133+BG133+BJ133+BM133+BP133 -> 0
A134: 425140000 | B134: INTERESES RESARCITORIOS ADM. GRAL. | C134: =IFERROR(VLOOKUP("1_"&A134,SyS!$B:$P,10,FALSE()),0) -> 0 | D134: =IFERROR(VLOOKUP("1_"&A134,SyS!$B:$P,12,FALSE()),0) -> 0 | E134: =+C134-D134 -> 0 | F134: =IFERROR(VLOOKUP("2_"&A134,SyS!$B:$P,10,FALSE()),0) -> 0 | G134: =IFERROR(VLOOKUP("2_"&A134,SyS!$B:$P,12,FALSE()),0) -> 0 | H134: =+F134-G134 -> 0 | O134: =IFERROR(VLOOKUP("14_"&A134,SyS!$B:$P,10,FALSE()),0) -> 0 | P134: =IFERROR(VLOOKUP("14_"&A134,SyS!$B:$P,12,FALSE()),0) -> 0 | Q134: =+O134-P134 -> 0 | R134: =IFERROR(VLOOKUP("15_"&A134,SyS!$B:$P,10,FALSE()),0) -> 0 | S134: =IFERROR(VLOOKUP("15_"&A134,SyS!$B:$P,12,FALSE()),0) -> 0 | T134: =+R134-S134 -> 0 | U134: =IFERROR(VLOOKUP("16_"&A134,SyS!$B:$P,10,FALSE()),0) -> 0 | V134: =IFERROR(VLOOKUP("16_"&A134,SyS!$B:$P,12,FALSE()),0) -> 0 | W134: =+U134-V134 -> 0 | X134: =IFERROR(VLOOKUP("13_"&A134,SyS!$B:$P,10,FALSE()),0) -> 0 | Y134: =IFERROR(VLOOKUP("13_"&A134,SyS!$B:$P,12,FALSE()),0) -> 0 | Z134: =+X134-Y134 -> 0 | AA134: =IFERROR(VLOOKUP("17_"&A134,SyS!$B:$P,10,FALSE()),0) -> 0 | AB134: =IFERROR(VLOOKUP("17_"&A134,SyS!$B:$P,12,FALSE()),0) -> 0 | AC134: =+AA134-AB134 -> 0 | AG134: =IFERROR(VLOOKUP("19_"&A134,SyS!$B:$P,10,FALSE()),0) -> 0 | AH134: =IFERROR(VLOOKUP("19_"&A134,SyS!$B:$P,12,FALSE()),0) -> 0 | AI134: =+AG134-AH134 -> 0 | AM134: =IFERROR(VLOOKUP("23_"&A134,SyS!$B:$P,10,FALSE()),0) -> 0 | AN134: =IFERROR(VLOOKUP("23_"&A134,SyS!$B:$P,12,FALSE()),0) -> 0 | AO134: =+AM134-AN134 -> 0 | BK134: =IFERROR(VLOOKUP("29_"&A134,SyS!$B:$P,10,FALSE()),0) -> 0 | BL134: =IFERROR(VLOOKUP("29_"&A134,SyS!$B:$P,12,FALSE()),0) -> 0 | BM134: =+BK134-BL134 -> 0 | BN134: =IFERROR(VLOOKUP("30_"&A134,SyS!$B:$P,10,FALSE()),0) -> 0 | BO134: =IFERROR(VLOOKUP("30_"&A134,SyS!$B:$P,12,FALSE()),0) -> 0 | BP134: =+BN134-BO134 -> 0 | BQ134: =+E134+H134+K134+Q134+T134+W134+Z134+AC134+AF134+AI134+AL134+AO134+AR134+AU134+AX134+BA134+BD134+BG134+BJ134+BM134+BP134 -> 0
A135: 425150000 | B135: ALQUILER INMUEBLE ADM. GRAL. | C135: =IFERROR(VLOOKUP("1_"&A135,SyS!$B:$P,10,FALSE()),0) -> 0 | D135: =IFERROR(VLOOKUP("1_"&A135,SyS!$B:$P,12,FALSE()),0) -> 0 | E135: =+C135-D135 -> 0 | F135: =IFERROR(VLOOKUP("2_"&A135,SyS!$B:$P,10,FALSE()),0) -> 1181.74 | G135: =IFERROR(VLOOKUP("2_"&A135,SyS!$B:$P,12,FALSE()),0) -> 0 | H135: =+F135-G135 -> 1181.74 | O135: =IFERROR(VLOOKUP("14_"&A135,SyS!$B:$P,10,FALSE()),0) -> 0 | P135: =IFERROR(VLOOKUP("14_"&A135,SyS!$B:$P,12,FALSE()),0) -> 0 | Q135: =+O135-P135 -> 0 | R135: =IFERROR(VLOOKUP("15_"&A135,SyS!$B:$P,10,FALSE()),0) -> 1235.4 | S135: =IFERROR(VLOOKUP("15_"&A135,SyS!$B:$P,12,FALSE()),0) -> 0 | T135: =+R135-S135 -> 1235.4 | U135: =IFERROR(VLOOKUP("16_"&A135,SyS!$B:$P,10,FALSE()),0) -> 0 | V135: =IFERROR(VLOOKUP("16_"&A135,SyS!$B:$P,12,FALSE()),0) -> 0 | W135: =+U135-V135 -> 0 | X135: =IFERROR(VLOOKUP("13_"&A135,SyS!$B:$P,10,FALSE()),0) -> 0 | Y135: =IFERROR(VLOOKUP("13_"&A135,SyS!$B:$P,12,FALSE()),0) -> 0 | Z135: =+X135-Y135 -> 0 | AA135: =IFERROR(VLOOKUP("17_"&A135,SyS!$B:$P,10,FALSE()),0) -> 0 | AB135: =IFERROR(VLOOKUP("17_"&A135,SyS!$B:$P,12,FALSE()),0) -> 0 | AC135: =+AA135-AB135 -> 0 | AG135: =IFERROR(VLOOKUP("19_"&A135,SyS!$B:$P,10,FALSE()),0) -> 0 | AH135: =IFERROR(VLOOKUP("19_"&A135,SyS!$B:$P,12,FALSE()),0) -> 0 | AI135: =+AG135-AH135 -> 0 | AM135: =IFERROR(VLOOKUP("23_"&A135,SyS!$B:$P,10,FALSE()),0) -> 0 | AN135: =IFERROR(VLOOKUP("23_"&A135,SyS!$B:$P,12,FALSE()),0) -> 0 | AO135: =+AM135-AN135 -> 0 | BK135: =IFERROR(VLOOKUP("29_"&A135,SyS!$B:$P,10,FALSE()),0) -> 0 | BL135: =IFERROR(VLOOKUP("29_"&A135,SyS!$B:$P,12,FALSE()),0) -> 0 | BM135: =+BK135-BL135 -> 0 | BN135: =IFERROR(VLOOKUP("30_"&A135,SyS!$B:$P,10,FALSE()),0) -> 0 | BO135: =IFERROR(VLOOKUP("30_"&A135,SyS!$B:$P,12,FALSE()),0) -> 0 | BP135: =+BN135-BO135 -> 0 | BQ135: =+E135+H135+K135+Q135+T135+W135+Z135+AC135+AF135+AI135+AL135+AO135+AR135+AU135+AX135+BA135+BD135+BG135+BJ135+BM135+BP135 -> 2417.14
A136: 425160000 | B136: CUOTA SOCIETARIA MINERA ADM. GRAL. | C136: =IFERROR(VLOOKUP("1_"&A136,SyS!$B:$P,10,FALSE()),0) -> 0 | D136: =IFERROR(VLOOKUP("1_"&A136,SyS!$B:$P,12,FALSE()),0) -> 0 | E136: =+C136-D136 -> 0 | F136: =IFERROR(VLOOKUP("2_"&A136,SyS!$B:$P,10,FALSE()),0) -> 0 | G136: =IFERROR(VLOOKUP("2_"&A136,SyS!$B:$P,12,FALSE()),0) -> 0 | H136: =+F136-G136 -> 0 | O136: =IFERROR(VLOOKUP("14_"&A136,SyS!$B:$P,10,FALSE()),0) -> 0 | P136: =IFERROR(VLOOKUP("14_"&A136,SyS!$B:$P,12,FALSE()),0) -> 0 | Q136: =+O136-P136 -> 0 | R136: =IFERROR(VLOOKUP("15_"&A136,SyS!$B:$P,10,FALSE()),0) -> 0 | S136: =IFERROR(VLOOKUP("15_"&A136,SyS!$B:$P,12,FALSE()),0) -> 0 | T136: =+R136-S136 -> 0 | U136: =IFERROR(VLOOKUP("16_"&A136,SyS!$B:$P,10,FALSE()),0) -> 0 | V136: =IFERROR(VLOOKUP("16_"&A136,SyS!$B:$P,12,FALSE()),0) -> 0 | W136: =+U136-V136 -> 0 | X136: =IFERROR(VLOOKUP("13_"&A136,SyS!$B:$P,10,FALSE()),0) -> 0 | Y136: =IFERROR(VLOOKUP("13_"&A136,SyS!$B:$P,12,FALSE()),0) -> 0 | Z136: =+X136-Y136 -> 0 | AA136: =IFERROR(VLOOKUP("17_"&A136,SyS!$B:$P,10,FALSE()),0) -> 0 | AB136: =IFERROR(VLOOKUP("17_"&A136,SyS!$B:$P,12,FALSE()),0) -> 0 | AC136: =+AA136-AB136 -> 0 | AG136: =IFERROR(VLOOKUP("19_"&A136,SyS!$B:$P,10,FALSE()),0) -> 0 | AH136: =IFERROR(VLOOKUP("19_"&A136,SyS!$B:$P,12,FALSE()),0) -> 0 | AI136: =+AG136-AH136 -> 0 | AM136: =IFERROR(VLOOKUP("23_"&A136,SyS!$B:$P,10,FALSE()),0) -> 0 | AN136: =IFERROR(VLOOKUP("23_"&A136,SyS!$B:$P,12,FALSE()),0) -> 0 | AO136: =+AM136-AN136 -> 0 | BK136: =IFERROR(VLOOKUP("29_"&A136,SyS!$B:$P,10,FALSE()),0) -> 0 | BL136: =IFERROR(VLOOKUP("29_"&A136,SyS!$B:$P,12,FALSE()),0) -> 0 | BM136: =+BK136-BL136 -> 0 | BN136: =IFERROR(VLOOKUP("30_"&A136,SyS!$B:$P,10,FALSE()),0) -> 0 | BO136: =IFERROR(VLOOKUP("30_"&A136,SyS!$B:$P,12,FALSE()),0) -> 0 | BP136: =+BN136-BO136 -> 0 | BQ136: =+E136+H136+K136+Q136+T136+W136+Z136+AC136+AF136+AI136+AL136+AO136+AR136+AU136+AX136+BA136+BD136+BG136+BJ136+BM136+BP136 -> 0
A137: 425170000 | B137: MENSAJERIA ADM. GRAL. | C137: =IFERROR(VLOOKUP("1_"&A137,SyS!$B:$P,10,FALSE()),0) -> 0 | D137: =IFERROR(VLOOKUP("1_"&A137,SyS!$B:$P,12,FALSE()),0) -> 0 | E137: =+C137-D137 -> 0 | F137: =IFERROR(VLOOKUP("2_"&A137,SyS!$B:$P,10,FALSE()),0) -> 0 | G137: =IFERROR(VLOOKUP("2_"&A137,SyS!$B:$P,12,FALSE()),0) -> 0 | H137: =+F137-G137 -> 0 | O137: =IFERROR(VLOOKUP("14_"&A137,SyS!$B:$P,10,FALSE()),0) -> 0 | P137: =IFERROR(VLOOKUP("14_"&A137,SyS!$B:$P,12,FALSE()),0) -> 0 | Q137: =+O137-P137 -> 0 | R137: =IFERROR(VLOOKUP("15_"&A137,SyS!$B:$P,10,FALSE()),0) -> 0 | S137: =IFERROR(VLOOKUP("15_"&A137,SyS!$B:$P,12,FALSE()),0) -> 0 | T137: =+R137-S137 -> 0 | U137: =IFERROR(VLOOKUP("16_"&A137,SyS!$B:$P,10,FALSE()),0) -> 0 | V137: =IFERROR(VLOOKUP("16_"&A137,SyS!$B:$P,12,FALSE()),0) -> 0 | W137: =+U137-V137 -> 0 | X137: =IFERROR(VLOOKUP("13_"&A137,SyS!$B:$P,10,FALSE()),0) -> 0 | Y137: =IFERROR(VLOOKUP("13_"&A137,SyS!$B:$P,12,FALSE()),0) -> 0 | Z137: =+X137-Y137 -> 0 | AA137: =IFERROR(VLOOKUP("17_"&A137,SyS!$B:$P,10,FALSE()),0) -> 0 | AB137: =IFERROR(VLOOKUP("17_"&A137,SyS!$B:$P,12,FALSE()),0) -> 0 | AC137: =+AA137-AB137 -> 0 | AG137: =IFERROR(VLOOKUP("19_"&A137,SyS!$B:$P,10,FALSE()),0) -> 0 | AH137: =IFERROR(VLOOKUP("19_"&A137,SyS!$B:$P,12,FALSE()),0) -> 0 | AI137: =+AG137-AH137 -> 0 | AM137: =IFERROR(VLOOKUP("23_"&A137,SyS!$B:$P,10,FALSE()),0) -> 0 | AN137: =IFERROR(VLOOKUP("23_"&A137,SyS!$B:$P,12,FALSE()),0) -> 0 | AO137: =+AM137-AN137 -> 0 | BK137: =IFERROR(VLOOKUP("29_"&A137,SyS!$B:$P,10,FALSE()),0) -> 0 | BL137: =IFERROR(VLOOKUP("29_"&A137,SyS!$B:$P,12,FALSE()),0) -> 0 | BM137: =+BK137-BL137 -> 0 | BN137: =IFERROR(VLOOKUP("30_"&A137,SyS!$B:$P,10,FALSE()),0) -> 0 | BO137: =IFERROR(VLOOKUP("30_"&A137,SyS!$B:$P,12,FALSE()),0) -> 0 | BP137: =+BN137-BO137 -> 0 | BQ137: =+E137+H137+K137+Q137+T137+W137+Z137+AC137+AF137+AI137+AL137+AO137+AR137+AU137+AX137+BA137+BD137+BG137+BJ137+BM137+BP137 -> 0
A138: 425180000 | B138: COMUNICACIONES ADM. GRAL. | C138: =IFERROR(VLOOKUP("1_"&A138,SyS!$B:$P,10,FALSE()),0) -> 0 | D138: =IFERROR(VLOOKUP("1_"&A138,SyS!$B:$P,12,FALSE()),0) -> 0 | E138: =+C138-D138 -> 0 | F138: =IFERROR(VLOOKUP("2_"&A138,SyS!$B:$P,10,FALSE()),0) -> 0 | G138: =IFERROR(VLOOKUP("2_"&A138,SyS!$B:$P,12,FALSE()),0) -> 0 | H138: =+F138-G138 -> 0 | O138: =IFERROR(VLOOKUP("14_"&A138,SyS!$B:$P,10,FALSE()),0) -> 0 | P138: =IFERROR(VLOOKUP("14_"&A138,SyS!$B:$P,12,FALSE()),0) -> 0 | Q138: =+O138-P138 -> 0 | R138: =IFERROR(VLOOKUP("15_"&A138,SyS!$B:$P,10,FALSE()),0) -> 0 | S138: =IFERROR(VLOOKUP("15_"&A138,SyS!$B:$P,12,FALSE()),0) -> 0 | T138: =+R138-S138 -> 0 | U138: =IFERROR(VLOOKUP("16_"&A138,SyS!$B:$P,10,FALSE()),0) -> 0 | V138: =IFERROR(VLOOKUP("16_"&A138,SyS!$B:$P,12,FALSE()),0) -> 0 | W138: =+U138-V138 -> 0 | X138: =IFERROR(VLOOKUP("13_"&A138,SyS!$B:$P,10,FALSE()),0) -> 0 | Y138: =IFERROR(VLOOKUP("13_"&A138,SyS!$B:$P,12,FALSE()),0) -> 0 | Z138: =+X138-Y138 -> 0 | AA138: =IFERROR(VLOOKUP("17_"&A138,SyS!$B:$P,10,FALSE()),0) -> 0 | AB138: =IFERROR(VLOOKUP("17_"&A138,SyS!$B:$P,12,FALSE()),0) -> 0 | AC138: =+AA138-AB138 -> 0 | AG138: =IFERROR(VLOOKUP("19_"&A138,SyS!$B:$P,10,FALSE()),0) -> 0 | AH138: =IFERROR(VLOOKUP("19_"&A138,SyS!$B:$P,12,FALSE()),0) -> 0 | AI138: =+AG138-AH138 -> 0 | AM138: =IFERROR(VLOOKUP("23_"&A138,SyS!$B:$P,10,FALSE()),0) -> 0 | AN138: =IFERROR(VLOOKUP("23_"&A138,SyS!$B:$P,12,FALSE()),0) -> 0 | AO138: =+AM138-AN138 -> 0 | BK138: =IFERROR(VLOOKUP("29_"&A138,SyS!$B:$P,10,FALSE()),0) -> 0 | BL138: =IFERROR(VLOOKUP("29_"&A138,SyS!$B:$P,12,FALSE()),0) -> 0 | BM138: =+BK138-BL138 -> 0 | BN138: =IFERROR(VLOOKUP("30_"&A138,SyS!$B:$P,10,FALSE()),0) -> 0 | BO138: =IFERROR(VLOOKUP("30_"&A138,SyS!$B:$P,12,FALSE()),0) -> 0 | BP138: =+BN138-BO138 -> 0 | BQ138: =+E138+H138+K138+Q138+T138+W138+Z138+AC138+AF138+AI138+AL138+AO138+AR138+AU138+AX138+BA138+BD138+BG138+BJ138+BM138+BP138 -> 0
A139: 433050000 | B139: Comunicaciones Adm. Gral USD | C139: =IFERROR(VLOOKUP("1_"&A139,SyS!$B:$P,10,FALSE()),0) -> 0 | D139: =IFERROR(VLOOKUP("1_"&A139,SyS!$B:$P,12,FALSE()),0) -> 0 | E139: =+C139-D139 -> 0 | F139: =IFERROR(VLOOKUP("2_"&A139,SyS!$B:$P,10,FALSE()),0) -> 0 | G139: =IFERROR(VLOOKUP("2_"&A139,SyS!$B:$P,12,FALSE()),0) -> 0 | H139: =+F139-G139 -> 0 | O139: =IFERROR(VLOOKUP("14_"&A139,SyS!$B:$P,10,FALSE()),0) -> 0 | P139: =IFERROR(VLOOKUP("14_"&A139,SyS!$B:$P,12,FALSE()),0) -> 0 | Q139: =+O139-P139 -> 0 | R139: =IFERROR(VLOOKUP("15_"&A139,SyS!$B:$P,10,FALSE()),0) -> 0 | S139: =IFERROR(VLOOKUP("15_"&A139,SyS!$B:$P,12,FALSE()),0) -> 0 | T139: =+R139-S139 -> 0 | U139: =IFERROR(VLOOKUP("16_"&A139,SyS!$B:$P,10,FALSE()),0) -> 0 | V139: =IFERROR(VLOOKUP("16_"&A139,SyS!$B:$P,12,FALSE()),0) -> 0 | W139: =+U139-V139 -> 0 | X139: =IFERROR(VLOOKUP("13_"&A139,SyS!$B:$P,10,FALSE()),0) -> 0 | Y139: =IFERROR(VLOOKUP("13_"&A139,SyS!$B:$P,12,FALSE()),0) -> 0 | Z139: =+X139-Y139 -> 0 | AA139: =IFERROR(VLOOKUP("17_"&A139,SyS!$B:$P,10,FALSE()),0) -> 0 | AB139: =IFERROR(VLOOKUP("17_"&A139,SyS!$B:$P,12,FALSE()),0) -> 0 | AC139: =+AA139-AB139 -> 0 | AG139: =IFERROR(VLOOKUP("19_"&A139,SyS!$B:$P,10,FALSE()),0) -> 0 | AH139: =IFERROR(VLOOKUP("19_"&A139,SyS!$B:$P,12,FALSE()),0) -> 0 | AI139: =+AG139-AH139 -> 0 | AM139: =IFERROR(VLOOKUP("23_"&A139,SyS!$B:$P,10,FALSE()),0) -> 0 | AN139: =IFERROR(VLOOKUP("23_"&A139,SyS!$B:$P,12,FALSE()),0) -> 0 | AO139: =+AM139-AN139 -> 0 | BK139: =IFERROR(VLOOKUP("29_"&A139,SyS!$B:$P,10,FALSE()),0) -> 0 | BL139: =IFERROR(VLOOKUP("29_"&A139,SyS!$B:$P,12,FALSE()),0) -> 0 | BM139: =+BK139-BL139 -> 0 | BN139: =IFERROR(VLOOKUP("30_"&A139,SyS!$B:$P,10,FALSE()),0) -> 0 | BO139: =IFERROR(VLOOKUP("30_"&A139,SyS!$B:$P,12,FALSE()),0) -> 0 | BP139: =+BN139-BO139 -> 0 | BQ139: =+E139+H139+K139+Q139+T139+W139+Z139+AC139+AF139+AI139+AL139+AO139+AR139+AU139+AX139+BA139+BD139+BG139+BJ139+BM139+BP139 -> 0
A140: 425190000 | B140: HONORARIOS PROFESIONALES ADM. GRAL | C140: =IFERROR(VLOOKUP("1_"&A140,SyS!$B:$P,10,FALSE()),0) -> 6000 | D140: =IFERROR(VLOOKUP("1_"&A140,SyS!$B:$P,12,FALSE()),0) -> 0 | E140: =+C140-D140 -> 6000 | F140: =IFERROR(VLOOKUP("2_"&A140,SyS!$B:$P,10,FALSE()),0) -> 0 | G140: =IFERROR(VLOOKUP("2_"&A140,SyS!$B:$P,12,FALSE()),0) -> 0 | H140: =+F140-G140 -> 0 | O140: =IFERROR(VLOOKUP("14_"&A140,SyS!$B:$P,10,FALSE()),0) -> 0 | P140: =IFERROR(VLOOKUP("14_"&A140,SyS!$B:$P,12,FALSE()),0) -> 0 | Q140: =+O140-P140 -> 0 | R140: =IFERROR(VLOOKUP("15_"&A140,SyS!$B:$P,10,FALSE()),0) -> 0 | S140: =IFERROR(VLOOKUP("15_"&A140,SyS!$B:$P,12,FALSE()),0) -> 0 | T140: =+R140-S140 -> 0 | U140: =IFERROR(VLOOKUP("16_"&A140,SyS!$B:$P,10,FALSE()),0) -> 0 | V140: =IFERROR(VLOOKUP("16_"&A140,SyS!$B:$P,12,FALSE()),0) -> 0 | W140: =+U140-V140 -> 0 | X140: =IFERROR(VLOOKUP("13_"&A140,SyS!$B:$P,10,FALSE()),0) -> 0 | Y140: =IFERROR(VLOOKUP("13_"&A140,SyS!$B:$P,12,FALSE()),0) -> 0 | Z140: =+X140-Y140 -> 0 | AA140: =IFERROR(VLOOKUP("17_"&A140,SyS!$B:$P,10,FALSE()),0) -> 0 | AB140: =IFERROR(VLOOKUP("17_"&A140,SyS!$B:$P,12,FALSE()),0) -> 0 | AC140: =+AA140-AB140 -> 0 | AG140: =IFERROR(VLOOKUP("19_"&A140,SyS!$B:$P,10,FALSE()),0) -> 0 | AH140: =IFERROR(VLOOKUP("19_"&A140,SyS!$B:$P,12,FALSE()),0) -> 0 | AI140: =+AG140-AH140 -> 0 | AM140: =IFERROR(VLOOKUP("23_"&A140,SyS!$B:$P,10,FALSE()),0) -> 0 | AN140: =IFERROR(VLOOKUP("23_"&A140,SyS!$B:$P,12,FALSE()),0) -> 0 | AO140: =+AM140-AN140 -> 0 | BK140: =IFERROR(VLOOKUP("29_"&A140,SyS!$B:$P,10,FALSE()),0) -> 0 | BL140: =IFERROR(VLOOKUP("29_"&A140,SyS!$B:$P,12,FALSE()),0) -> 0 | BM140: =+BK140-BL140 -> 0 | BN140: =IFERROR(VLOOKUP("30_"&A140,SyS!$B:$P,10,FALSE()),0) -> 0 | BO140: =IFERROR(VLOOKUP("30_"&A140,SyS!$B:$P,12,FALSE()),0) -> 0 | BP140: =+BN140-BO140 -> 0 | BQ140: =+E140+H140+K140+Q140+T140+W140+Z140+AC140+AF140+AI140+AL140+AO140+AR140+AU140+AX140+BA140+BD140+BG140+BJ140+BM140+BP140 -> 6000
A141: 433030000 | B141: Honorarios Profesionales Adm. Gral. USD | C141: =IFERROR(VLOOKUP("1_"&A141,SyS!$B:$P,10,FALSE()),0) -> 0 | D141: =IFERROR(VLOOKUP("1_"&A141,SyS!$B:$P,12,FALSE()),0) -> 0 | E141: =+C141-D141 -> 0 | F141: =IFERROR(VLOOKUP("2_"&A141,SyS!$B:$P,10,FALSE()),0) -> 0 | G141: =IFERROR(VLOOKUP("2_"&A141,SyS!$B:$P,12,FALSE()),0) -> 0 | H141: =+F141-G141 -> 0 | O141: =IFERROR(VLOOKUP("14_"&A141,SyS!$B:$P,10,FALSE()),0) -> 0 | P141: =IFERROR(VLOOKUP("14_"&A141,SyS!$B:$P,12,FALSE()),0) -> 0 | Q141: =+O141-P141 -> 0 | R141: =IFERROR(VLOOKUP("15_"&A141,SyS!$B:$P,10,FALSE()),0) -> 0 | S141: =IFERROR(VLOOKUP("15_"&A141,SyS!$B:$P,12,FALSE()),0) -> 0 | T141: =+R141-S141 -> 0 | U141: =IFERROR(VLOOKUP("16_"&A141,SyS!$B:$P,10,FALSE()),0) -> 0 | V141: =IFERROR(VLOOKUP("16_"&A141,SyS!$B:$P,12,FALSE()),0) -> 0 | W141: =+U141-V141 -> 0 | X141: =IFERROR(VLOOKUP("13_"&A141,SyS!$B:$P,10,FALSE()),0) -> 0 | Y141: =IFERROR(VLOOKUP("13_"&A141,SyS!$B:$P,12,FALSE()),0) -> 0 | Z141: =+X141-Y141 -> 0 | AA141: =IFERROR(VLOOKUP("17_"&A141,SyS!$B:$P,10,FALSE()),0) -> 0 | AB141: =IFERROR(VLOOKUP("17_"&A141,SyS!$B:$P,12,FALSE()),0) -> 0 | AC141: =+AA141-AB141 -> 0 | AG141: =IFERROR(VLOOKUP("19_"&A141,SyS!$B:$P,10,FALSE()),0) -> 0 | AH141: =IFERROR(VLOOKUP("19_"&A141,SyS!$B:$P,12,FALSE()),0) -> 0 | AI141: =+AG141-AH141 -> 0 | AM141: =IFERROR(VLOOKUP("23_"&A141,SyS!$B:$P,10,FALSE()),0) -> 0 | AN141: =IFERROR(VLOOKUP("23_"&A141,SyS!$B:$P,12,FALSE()),0) -> 0 | AO141: =+AM141-AN141 -> 0 | BK141: =IFERROR(VLOOKUP("29_"&A141,SyS!$B:$P,10,FALSE()),0) -> 0 | BL141: =IFERROR(VLOOKUP("29_"&A141,SyS!$B:$P,12,FALSE()),0) -> 0 | BM141: =+BK141-BL141 -> 0 | BN141: =IFERROR(VLOOKUP("30_"&A141,SyS!$B:$P,10,FALSE()),0) -> 0 | BO141: =IFERROR(VLOOKUP("30_"&A141,SyS!$B:$P,12,FALSE()),0) -> 0 | BP141: =+BN141-BO141 -> 0 | BQ141: =+E141+H141+K141+Q141+T141+W141+Z141+AC141+AF141+AI141+AL141+AO141+AR141+AU141+AX141+BA141+BD141+BG141+BJ141+BM141+BP141 -> 0
A142: 425200000 | B142: COMBUSTIBLE ADM. GRAL. | C142: =IFERROR(VLOOKUP("1_"&A142,SyS!$B:$P,10,FALSE()),0) -> 0 | D142: =IFERROR(VLOOKUP("1_"&A142,SyS!$B:$P,12,FALSE()),0) -> 0 | E142: =+C142-D142 -> 0 | F142: =IFERROR(VLOOKUP("2_"&A142,SyS!$B:$P,10,FALSE()),0) -> 142.21 | G142: =IFERROR(VLOOKUP("2_"&A142,SyS!$B:$P,12,FALSE()),0) -> 0 | H142: =+F142-G142 -> 142.21 | O142: =IFERROR(VLOOKUP("14_"&A142,SyS!$B:$P,10,FALSE()),0) -> 0 | P142: =IFERROR(VLOOKUP("14_"&A142,SyS!$B:$P,12,FALSE()),0) -> 0 | Q142: =+O142-P142 -> 0 | R142: =IFERROR(VLOOKUP("15_"&A142,SyS!$B:$P,10,FALSE()),0) -> 0 | S142: =IFERROR(VLOOKUP("15_"&A142,SyS!$B:$P,12,FALSE()),0) -> 0 | T142: =+R142-S142 -> 0 | U142: =IFERROR(VLOOKUP("16_"&A142,SyS!$B:$P,10,FALSE()),0) -> 0 | V142: =IFERROR(VLOOKUP("16_"&A142,SyS!$B:$P,12,FALSE()),0) -> 0 | W142: =+U142-V142 -> 0 | X142: =IFERROR(VLOOKUP("13_"&A142,SyS!$B:$P,10,FALSE()),0) -> 0 | Y142: =IFERROR(VLOOKUP("13_"&A142,SyS!$B:$P,12,FALSE()),0) -> 0 | Z142: =+X142-Y142 -> 0 | AA142: =IFERROR(VLOOKUP("17_"&A142,SyS!$B:$P,10,FALSE()),0) -> 0 | AB142: =IFERROR(VLOOKUP("17_"&A142,SyS!$B:$P,12,FALSE()),0) -> 0 | AC142: =+AA142-AB142 -> 0 | AG142: =IFERROR(VLOOKUP("19_"&A142,SyS!$B:$P,10,FALSE()),0) -> 0 | AH142: =IFERROR(VLOOKUP("19_"&A142,SyS!$B:$P,12,FALSE()),0) -> 0 | AI142: =+AG142-AH142 -> 0 | AM142: =IFERROR(VLOOKUP("23_"&A142,SyS!$B:$P,10,FALSE()),0) -> 0 | AN142: =IFERROR(VLOOKUP("23_"&A142,SyS!$B:$P,12,FALSE()),0) -> 0 | AO142: =+AM142-AN142 -> 0 | BK142: =IFERROR(VLOOKUP("29_"&A142,SyS!$B:$P,10,FALSE()),0) -> 0 | BL142: =IFERROR(VLOOKUP("29_"&A142,SyS!$B:$P,12,FALSE()),0) -> 0 | BM142: =+BK142-BL142 -> 0 | BN142: =IFERROR(VLOOKUP("30_"&A142,SyS!$B:$P,10,FALSE()),0) -> 0 | BO142: =IFERROR(VLOOKUP("30_"&A142,SyS!$B:$P,12,FALSE()),0) -> 0 | BP142: =+BN142-BO142 -> 0 | BQ142: =+E142+H142+K142+Q142+T142+W142+Z142+AC142+AF142+AI142+AL142+AO142+AR142+AU142+AX142+BA142+BD142+BG142+BJ142+BM142+BP142 -> 142.21
A143: 425210000 | B143: GST. DE CAPACITACIÓN ADM. GRAL | C143: =IFERROR(VLOOKUP("1_"&A143,SyS!$B:$P,10,FALSE()),0) -> 0 | D143: =IFERROR(VLOOKUP("1_"&A143,SyS!$B:$P,12,FALSE()),0) -> 0 | E143: =+C143-D143 -> 0 | F143: =IFERROR(VLOOKUP("2_"&A143,SyS!$B:$P,10,FALSE()),0) -> 0 | G143: =IFERROR(VLOOKUP("2_"&A143,SyS!$B:$P,12,FALSE()),0) -> 0 | H143: =+F143-G143 -> 0 | O143: =IFERROR(VLOOKUP("14_"&A143,SyS!$B:$P,10,FALSE()),0) -> 0 | P143: =IFERROR(VLOOKUP("14_"&A143,SyS!$B:$P,12,FALSE()),0) -> 0 | Q143: =+O143-P143 -> 0 | R143: =IFERROR(VLOOKUP("15_"&A143,SyS!$B:$P,10,FALSE()),0) -> 0 | S143: =IFERROR(VLOOKUP("15_"&A143,SyS!$B:$P,12,FALSE()),0) -> 0 | T143: =+R143-S143 -> 0 | U143: =IFERROR(VLOOKUP("16_"&A143,SyS!$B:$P,10,FALSE()),0) -> 0 | V143: =IFERROR(VLOOKUP("16_"&A143,SyS!$B:$P,12,FALSE()),0) -> 0 | W143: =+U143-V143 -> 0 | X143: =IFERROR(VLOOKUP("13_"&A143,SyS!$B:$P,10,FALSE()),0) -> 0 | Y143: =IFERROR(VLOOKUP("13_"&A143,SyS!$B:$P,12,FALSE()),0) -> 0 | Z143: =+X143-Y143 -> 0 | AA143: =IFERROR(VLOOKUP("17_"&A143,SyS!$B:$P,10,FALSE()),0) -> 0 | AB143: =IFERROR(VLOOKUP("17_"&A143,SyS!$B:$P,12,FALSE()),0) -> 0 | AC143: =+AA143-AB143 -> 0 | AG143: =IFERROR(VLOOKUP("19_"&A143,SyS!$B:$P,10,FALSE()),0) -> 0 | AH143: =IFERROR(VLOOKUP("19_"&A143,SyS!$B:$P,12,FALSE()),0) -> 0 | AI143: =+AG143-AH143 -> 0 | AM143: =IFERROR(VLOOKUP("23_"&A143,SyS!$B:$P,10,FALSE()),0) -> 0 | AN143: =IFERROR(VLOOKUP("23_"&A143,SyS!$B:$P,12,FALSE()),0) -> 0 | AO143: =+AM143-AN143 -> 0 | BK143: =IFERROR(VLOOKUP("29_"&A143,SyS!$B:$P,10,FALSE()),0) -> 0 | BL143: =IFERROR(VLOOKUP("29_"&A143,SyS!$B:$P,12,FALSE()),0) -> 0 | BM143: =+BK143-BL143 -> 0 | BN143: =IFERROR(VLOOKUP("30_"&A143,SyS!$B:$P,10,FALSE()),0) -> 0 | BO143: =IFERROR(VLOOKUP("30_"&A143,SyS!$B:$P,12,FALSE()),0) -> 0 | BP143: =+BN143-BO143 -> 0 | BQ143: =+E143+H143+K143+Q143+T143+W143+Z143+AC143+AF143+AI143+AL143+AO143+AR143+AU143+AX143+BA143+BD143+BG143+BJ143+BM143+BP143 -> 0
A144: 433110000 | B144: Gastos bancarios Adm general (u$s) | C144: =IFERROR(VLOOKUP("1_"&A144,SyS!$B:$P,10,FALSE()),0) -> 18 | D144: =IFERROR(VLOOKUP("1_"&A144,SyS!$B:$P,12,FALSE()),0) -> 0 | E144: =+C144-D144 -> 18 | F144: =IFERROR(VLOOKUP("2_"&A144,SyS!$B:$P,10,FALSE()),0) -> 0 | G144: =IFERROR(VLOOKUP("2_"&A144,SyS!$B:$P,12,FALSE()),0) -> 0 | H144: =+F144-G144 -> 0 | O144: =IFERROR(VLOOKUP("14_"&A144,SyS!$B:$P,10,FALSE()),0) -> 0 | P144: =IFERROR(VLOOKUP("14_"&A144,SyS!$B:$P,12,FALSE()),0) -> 0 | Q144: =+O144-P144 -> 0 | R144: =IFERROR(VLOOKUP("15_"&A144,SyS!$B:$P,10,FALSE()),0) -> 0 | S144: =IFERROR(VLOOKUP("15_"&A144,SyS!$B:$P,12,FALSE()),0) -> 0 | T144: =+R144-S144 -> 0 | U144: =IFERROR(VLOOKUP("16_"&A144,SyS!$B:$P,10,FALSE()),0) -> 0 | V144: =IFERROR(VLOOKUP("16_"&A144,SyS!$B:$P,12,FALSE()),0) -> 0 | X144: =IFERROR(VLOOKUP("13_"&A144,SyS!$B:$P,10,FALSE()),0) -> 0 | Y144: =IFERROR(VLOOKUP("13_"&A144,SyS!$B:$P,12,FALSE()),0) -> 0 | Z144: =+X144-Y144 -> 0 | AA144: =IFERROR(VLOOKUP("17_"&A144,SyS!$B:$P,10,FALSE()),0) -> 0 | AB144: =IFERROR(VLOOKUP("17_"&A144,SyS!$B:$P,12,FALSE()),0) -> 0 | AC144: =+AA144-AB144 -> 0 | AG144: =IFERROR(VLOOKUP("19_"&A144,SyS!$B:$P,10,FALSE()),0) -> 0 | AH144: =IFERROR(VLOOKUP("19_"&A144,SyS!$B:$P,12,FALSE()),0) -> 0 | AI144: =+AG144-AH144 -> 0 | AM144: =IFERROR(VLOOKUP("23_"&A144,SyS!$B:$P,10,FALSE()),0) -> 0 | AN144: =IFERROR(VLOOKUP("23_"&A144,SyS!$B:$P,12,FALSE()),0) -> 0 | AO144: =+AM144-AN144 -> 0 | BK144: =IFERROR(VLOOKUP("29_"&A144,SyS!$B:$P,10,FALSE()),0) -> 0 | BL144: =IFERROR(VLOOKUP("29_"&A144,SyS!$B:$P,12,FALSE()),0) -> 0 | BM144: =+BK144-BL144 -> 0 | BN144: =IFERROR(VLOOKUP("30_"&A144,SyS!$B:$P,10,FALSE()),0) -> 0 | BO144: =IFERROR(VLOOKUP("30_"&A144,SyS!$B:$P,12,FALSE()),0) -> 0 | BP144: =+BN144-BO144 -> 0 | BQ144: =+E144+H144+K144+Q144+T144+W144+Z144+AC144+AF144+AI144+AL144+AO144+AR144+AU144+AX144+BA144+BD144+BG144+BJ144+BM144+BP144 -> 18
A145: 425220000 | B145: GASTOS Y COMISIONES BANCARIAS ADM. GRAL. | C145: =IFERROR(VLOOKUP("1_"&A145,SyS!$B:$P,10,FALSE()),0) -> 176.08 | D145: =IFERROR(VLOOKUP("1_"&A145,SyS!$B:$P,12,FALSE()),0) -> 0 | E145: =+C145-D145 -> 176.08 | F145: =IFERROR(VLOOKUP("2_"&A145,SyS!$B:$P,10,FALSE()),0) -> 0 | G145: =IFERROR(VLOOKUP("2_"&A145,SyS!$B:$P,12,FALSE()),0) -> 0 | H145: =+F145-G145 -> 0 | O145: =IFERROR(VLOOKUP("14_"&A145,SyS!$B:$P,10,FALSE()),0) -> 0 | P145: =IFERROR(VLOOKUP("14_"&A145,SyS!$B:$P,12,FALSE()),0) -> 0 | Q145: =+O145-P145 -> 0 | R145: =IFERROR(VLOOKUP("15_"&A145,SyS!$B:$P,10,FALSE()),0) -> 0 | S145: =IFERROR(VLOOKUP("15_"&A145,SyS!$B:$P,12,FALSE()),0) -> 0 | T145: =+R145-S145 -> 0 | U145: =IFERROR(VLOOKUP("16_"&A145,SyS!$B:$P,10,FALSE()),0) -> 0 | V145: =IFERROR(VLOOKUP("16_"&A145,SyS!$B:$P,12,FALSE()),0) -> 0 | W145: =+U145-V145 -> 0 | X145: =IFERROR(VLOOKUP("13_"&A145,SyS!$B:$P,10,FALSE()),0) -> 0 | Y145: =IFERROR(VLOOKUP("13_"&A145,SyS!$B:$P,12,FALSE()),0) -> 0 | Z145: =+X145-Y145 -> 0 | AA145: =IFERROR(VLOOKUP("17_"&A145,SyS!$B:$P,10,FALSE()),0) -> 0 | AB145: =IFERROR(VLOOKUP("17_"&A145,SyS!$B:$P,12,FALSE()),0) -> 0 | AC145: =+AA145-AB145 -> 0 | AG145: =IFERROR(VLOOKUP("19_"&A145,SyS!$B:$P,10,FALSE()),0) -> 0 | AH145: =IFERROR(VLOOKUP("19_"&A145,SyS!$B:$P,12,FALSE()),0) -> 0 | AI145: =+AG145-AH145 -> 0 | AM145: =IFERROR(VLOOKUP("23_"&A145,SyS!$B:$P,10,FALSE()),0) -> 0 | AN145: =IFERROR(VLOOKUP("23_"&A145,SyS!$B:$P,12,FALSE()),0) -> 0 | AO145: =+AM145-AN145 -> 0 | BK145: =IFERROR(VLOOKUP("29_"&A145,SyS!$B:$P,10,FALSE()),0) -> 0 | BL145: =IFERROR(VLOOKUP("29_"&A145,SyS!$B:$P,12,FALSE()),0) -> 0 | BM145: =+BK145-BL145 -> 0 | BN145: =IFERROR(VLOOKUP("30_"&A145,SyS!$B:$P,10,FALSE()),0) -> 0 | BO145: =IFERROR(VLOOKUP("30_"&A145,SyS!$B:$P,12,FALSE()),0) -> 0 | BP145: =+BN145-BO145 -> 0 | BQ145: =+E145+H145+K145+Q145+T145+W145+Z145+AC145+AF145+AI145+AL145+AO145+AR145+AU145+AX145+BA145+BD145+BG145+BJ145+BM145+BP145 -> 176.08
A146: 423010000 | B146: Gastos y comisiones bancarias | C146: =IFERROR(VLOOKUP("1_"&A146,SyS!$B:$P,10,FALSE()),0) -> 0 | D146: =IFERROR(VLOOKUP("1_"&A146,SyS!$B:$P,12,FALSE()),0) -> 0 | E146: =+C146-D146 -> 0 | F146: =IFERROR(VLOOKUP("2_"&A146,SyS!$B:$P,10,FALSE()),0) -> 0 | G146: =IFERROR(VLOOKUP("2_"&A146,SyS!$B:$P,12,FALSE()),0) -> 0 | H146: =+F146-G146 -> 0 | O146: =IFERROR(VLOOKUP("14_"&A146,SyS!$B:$P,10,FALSE()),0) -> 0 | P146: =IFERROR(VLOOKUP("14_"&A146,SyS!$B:$P,12,FALSE()),0) -> 0 | Q146: =+O146-P146 -> 0 | R146: =IFERROR(VLOOKUP("15_"&A146,SyS!$B:$P,10,FALSE()),0) -> 0 | S146: =IFERROR(VLOOKUP("15_"&A146,SyS!$B:$P,12,FALSE()),0) -> 0 | T146: =+R146-S146 -> 0 | U146: =IFERROR(VLOOKUP("16_"&A146,SyS!$B:$P,10,FALSE()),0) -> 0 | V146: =IFERROR(VLOOKUP("16_"&A146,SyS!$B:$P,12,FALSE()),0) -> 0 | W146: =+U146-V146 -> 0 | X146: =IFERROR(VLOOKUP("13_"&A146,SyS!$B:$P,10,FALSE()),0) -> 0 | Y146: =IFERROR(VLOOKUP("13_"&A146,SyS!$B:$P,12,FALSE()),0) -> 0 | Z146: =+X146-Y146 -> 0 | AA146: =IFERROR(VLOOKUP("17_"&A146,SyS!$B:$P,10,FALSE()),0) -> 0 | AB146: =IFERROR(VLOOKUP("17_"&A146,SyS!$B:$P,12,FALSE()),0) -> 0 | AC146: =+AA146-AB146 -> 0 | AG146: =IFERROR(VLOOKUP("19_"&A146,SyS!$B:$P,10,FALSE()),0) -> 0 | AH146: =IFERROR(VLOOKUP("19_"&A146,SyS!$B:$P,12,FALSE()),0) -> 0 | AI146: =+AG146-AH146 -> 0 | AM146: =IFERROR(VLOOKUP("23_"&A146,SyS!$B:$P,10,FALSE()),0) -> 0 | AN146: =IFERROR(VLOOKUP("23_"&A146,SyS!$B:$P,12,FALSE()),0) -> 0 | AO146: =+AM146-AN146 -> 0 | BK146: =IFERROR(VLOOKUP("29_"&A146,SyS!$B:$P,10,FALSE()),0) -> 0 | BL146: =IFERROR(VLOOKUP("29_"&A146,SyS!$B:$P,12,FALSE()),0) -> 0 | BM146: =+BK146-BL146 -> 0 | BN146: =IFERROR(VLOOKUP("30_"&A146,SyS!$B:$P,10,FALSE()),0) -> 0 | BO146: =IFERROR(VLOOKUP("30_"&A146,SyS!$B:$P,12,FALSE()),0) -> 0 | BP146: =+BN146-BO146 -> 0 | BQ146: =+E146+H146+K146+Q146+T146+W146+Z146+AC146+AF146+AI146+AL146+AO146+AR146+AU146+AX146+BA146+BD146+BG146+BJ146+BM146+BP146 -> 0
A147: 425230000 | B147: IMP.A LOS DÉBITOS Y CRÉDITOS BANCARIOS ADM. GRAL. | C147: =IFERROR(VLOOKUP("1_"&A147,SyS!$B:$P,10,FALSE()),0) -> 427.8 | D147: =IFERROR(VLOOKUP("1_"&A147,SyS!$B:$P,12,FALSE()),0) -> 0 | E147: =+C147-D147 -> 427.8 | F147: =IFERROR(VLOOKUP("2_"&A147,SyS!$B:$P,10,FALSE()),0) -> 3.38 | G147: =IFERROR(VLOOKUP("2_"&A147,SyS!$B:$P,12,FALSE()),0) -> 0 | H147: =+F147-G147 -> 3.38 | O147: =IFERROR(VLOOKUP("14_"&A147,SyS!$B:$P,10,FALSE()),0) -> 0 | P147: =IFERROR(VLOOKUP("14_"&A147,SyS!$B:$P,12,FALSE()),0) -> 0 | Q147: =+O147-P147 -> 0 | R147: =IFERROR(VLOOKUP("15_"&A147,SyS!$B:$P,10,FALSE()),0) -> 0 | S147: =IFERROR(VLOOKUP("15_"&A147,SyS!$B:$P,12,FALSE()),0) -> 0 | T147: =+R147-S147 -> 0 | U147: =IFERROR(VLOOKUP("16_"&A147,SyS!$B:$P,10,FALSE()),0) -> 0 | V147: =IFERROR(VLOOKUP("16_"&A147,SyS!$B:$P,12,FALSE()),0) -> 0 | W147: =+U147-V147 -> 0 | X147: =IFERROR(VLOOKUP("13_"&A147,SyS!$B:$P,10,FALSE()),0) -> 0 | Y147: =IFERROR(VLOOKUP("13_"&A147,SyS!$B:$P,12,FALSE()),0) -> 0 | Z147: =+X147-Y147 -> 0 | AA147: =IFERROR(VLOOKUP("17_"&A147,SyS!$B:$P,10,FALSE()),0) -> 0 | AB147: =IFERROR(VLOOKUP("17_"&A147,SyS!$B:$P,12,FALSE()),0) -> 0 | AC147: =+AA147-AB147 -> 0 | AG147: =IFERROR(VLOOKUP("19_"&A147,SyS!$B:$P,10,FALSE()),0) -> 0 | AH147: =IFERROR(VLOOKUP("19_"&A147,SyS!$B:$P,12,FALSE()),0) -> 0 | AI147: =+AG147-AH147 -> 0 | AM147: =IFERROR(VLOOKUP("23_"&A147,SyS!$B:$P,10,FALSE()),0) -> 0 | AN147: =IFERROR(VLOOKUP("23_"&A147,SyS!$B:$P,12,FALSE()),0) -> 0 | AO147: =+AM147-AN147 -> 0 | BK147: =IFERROR(VLOOKUP("29_"&A147,SyS!$B:$P,10,FALSE()),0) -> 0 | BL147: =IFERROR(VLOOKUP("29_"&A147,SyS!$B:$P,12,FALSE()),0) -> 0 | BM147: =+BK147-BL147 -> 0 | BN147: =IFERROR(VLOOKUP("30_"&A147,SyS!$B:$P,10,FALSE()),0) -> 0 | BO147: =IFERROR(VLOOKUP("30_"&A147,SyS!$B:$P,12,FALSE()),0) -> 0 | BP147: =+BN147-BO147 -> 0 | BQ147: =+E147+H147+K147+Q147+T147+W147+Z147+AC147+AF147+AI147+AL147+AO147+AR147+AU147+AX147+BA147+BD147+BG147+BJ147+BM147+BP147 -> 431.18
A148: 425240000 | B148: SEGUROS ADM. GRAL. | C148: =IFERROR(VLOOKUP("1_"&A148,SyS!$B:$P,10,FALSE()),0) -> 0 | D148: =IFERROR(VLOOKUP("1_"&A148,SyS!$B:$P,12,FALSE()),0) -> 0 | E148: =+C148-D148 -> 0 | F148: =IFERROR(VLOOKUP("2_"&A148,SyS!$B:$P,10,FALSE()),0) -> 0 | G148: =IFERROR(VLOOKUP("2_"&A148,SyS!$B:$P,12,FALSE()),0) -> 0 | H148: =+F148-G148 -> 0 | O148: =IFERROR(VLOOKUP("14_"&A148,SyS!$B:$P,10,FALSE()),0) -> 0 | P148: =IFERROR(VLOOKUP("14_"&A148,SyS!$B:$P,12,FALSE()),0) -> 0 | Q148: =+O148-P148 -> 0 | R148: =IFERROR(VLOOKUP("15_"&A148,SyS!$B:$P,10,FALSE()),0) -> 0 | S148: =IFERROR(VLOOKUP("15_"&A148,SyS!$B:$P,12,FALSE()),0) -> 0 | T148: =+R148-S148 -> 0 | U148: =IFERROR(VLOOKUP("16_"&A148,SyS!$B:$P,10,FALSE()),0) -> 0 | V148: =IFERROR(VLOOKUP("16_"&A148,SyS!$B:$P,12,FALSE()),0) -> 0 | W148: =+U148-V148 -> 0 | X148: =IFERROR(VLOOKUP("13_"&A148,SyS!$B:$P,10,FALSE()),0) -> 0 | Y148: =IFERROR(VLOOKUP("13_"&A148,SyS!$B:$P,12,FALSE()),0) -> 0 | Z148: =+X148-Y148 -> 0 | AA148: =IFERROR(VLOOKUP("17_"&A148,SyS!$B:$P,10,FALSE()),0) -> 0 | AB148: =IFERROR(VLOOKUP("17_"&A148,SyS!$B:$P,12,FALSE()),0) -> 0 | AC148: =+AA148-AB148 -> 0 | AG148: =IFERROR(VLOOKUP("19_"&A148,SyS!$B:$P,10,FALSE()),0) -> 0 | AH148: =IFERROR(VLOOKUP("19_"&A148,SyS!$B:$P,12,FALSE()),0) -> 0 | AI148: =+AG148-AH148 -> 0 | AM148: =IFERROR(VLOOKUP("23_"&A148,SyS!$B:$P,10,FALSE()),0) -> 0 | AN148: =IFERROR(VLOOKUP("23_"&A148,SyS!$B:$P,12,FALSE()),0) -> 0 | AO148: =+AM148-AN148 -> 0 | BK148: =IFERROR(VLOOKUP("29_"&A148,SyS!$B:$P,10,FALSE()),0) -> 0 | BL148: =IFERROR(VLOOKUP("29_"&A148,SyS!$B:$P,12,FALSE()),0) -> 0 | BM148: =+BK148-BL148 -> 0 | BN148: =IFERROR(VLOOKUP("30_"&A148,SyS!$B:$P,10,FALSE()),0) -> 0 | BO148: =IFERROR(VLOOKUP("30_"&A148,SyS!$B:$P,12,FALSE()),0) -> 0 | BP148: =+BN148-BO148 -> 0 | BQ148: =+E148+H148+K148+Q148+T148+W148+Z148+AC148+AF148+AI148+AL148+AO148+AR148+AU148+AX148+BA148+BD148+BG148+BJ148+BM148+BP148 -> 0
A149: 425250000 | B149: AMORTIZACIONES ADM. GRAL. | C149: =IFERROR(VLOOKUP("1_"&A149,SyS!$B:$P,10,FALSE()),0) -> 3918.01 | D149: =IFERROR(VLOOKUP("1_"&A149,SyS!$B:$P,12,FALSE()),0) -> 0 | E149: =+C149-D149 -> 3918.01 | F149: =IFERROR(VLOOKUP("2_"&A149,SyS!$B:$P,10,FALSE()),0) -> 0 | G149: =IFERROR(VLOOKUP("2_"&A149,SyS!$B:$P,12,FALSE()),0) -> 0 | H149: =+F149-G149 -> 0 | O149: =IFERROR(VLOOKUP("14_"&A149,SyS!$B:$P,10,FALSE()),0) -> 0 | P149: =IFERROR(VLOOKUP("14_"&A149,SyS!$B:$P,12,FALSE()),0) -> 0 | Q149: =+O149-P149 -> 0 | R149: =IFERROR(VLOOKUP("15_"&A149,SyS!$B:$P,10,FALSE()),0) -> 0 | S149: =IFERROR(VLOOKUP("15_"&A149,SyS!$B:$P,12,FALSE()),0) -> 0 | T149: =+R149-S149 -> 0 | U149: =IFERROR(VLOOKUP("16_"&A149,SyS!$B:$P,10,FALSE()),0) -> 0 | V149: =IFERROR(VLOOKUP("16_"&A149,SyS!$B:$P,12,FALSE()),0) -> 0 | W149: =+U149-V149 -> 0 | X149: =IFERROR(VLOOKUP("13_"&A149,SyS!$B:$P,10,FALSE()),0) -> 0 | Y149: =IFERROR(VLOOKUP("13_"&A149,SyS!$B:$P,12,FALSE()),0) -> 0 | Z149: =+X149-Y149 -> 0 | AA149: =IFERROR(VLOOKUP("17_"&A149,SyS!$B:$P,10,FALSE()),0) -> 0 | AB149: =IFERROR(VLOOKUP("17_"&A149,SyS!$B:$P,12,FALSE()),0) -> 0 | AC149: =+AA149-AB149 -> 0 | AG149: =IFERROR(VLOOKUP("19_"&A149,SyS!$B:$P,10,FALSE()),0) -> 0 | AH149: =IFERROR(VLOOKUP("19_"&A149,SyS!$B:$P,12,FALSE()),0) -> 0 | AI149: =+AG149-AH149 -> 0 | AM149: =IFERROR(VLOOKUP("23_"&A149,SyS!$B:$P,10,FALSE()),0) -> 0 | AN149: =IFERROR(VLOOKUP("23_"&A149,SyS!$B:$P,12,FALSE()),0) -> 0 | AO149: =+AM149-AN149 -> 0 | BK149: =IFERROR(VLOOKUP("29_"&A149,SyS!$B:$P,10,FALSE()),0) -> 0 | BL149: =IFERROR(VLOOKUP("29_"&A149,SyS!$B:$P,12,FALSE()),0) -> 0 | BM149: =+BK149-BL149 -> 0 | BN149: =IFERROR(VLOOKUP("30_"&A149,SyS!$B:$P,10,FALSE()),0) -> 0 | BO149: =IFERROR(VLOOKUP("30_"&A149,SyS!$B:$P,12,FALSE()),0) -> 0 | BP149: =+BN149-BO149 -> 0 | BQ149: =+E149+H149+K149+Q149+T149+W149+Z149+AC149+AF149+AI149+AL149+AO149+AR149+AU149+AX149+BA149+BD149+BG149+BJ149+BM149+BP149 -> 3918.01
A150: 425300000 | B150: GASTOS VARIOS OFICINA ADM. GRAL | C150: =IFERROR(VLOOKUP("1_"&A150,SyS!$B:$P,10,FALSE()),0) -> 0 | D150: =IFERROR(VLOOKUP("1_"&A150,SyS!$B:$P,12,FALSE()),0) -> 0 | E150: =+C150-D150 -> 0 | F150: =IFERROR(VLOOKUP("2_"&A150,SyS!$B:$P,10,FALSE()),0) -> 130.94 | G150: =IFERROR(VLOOKUP("2_"&A150,SyS!$B:$P,12,FALSE()),0) -> 0 | H150: =+F150-G150 -> 130.94 | O150: =IFERROR(VLOOKUP("14_"&A150,SyS!$B:$P,10,FALSE()),0) -> 0 | P150: =IFERROR(VLOOKUP("14_"&A150,SyS!$B:$P,12,FALSE()),0) -> 0 | Q150: =+O150-P150 -> 0 | R150: =IFERROR(VLOOKUP("15_"&A150,SyS!$B:$P,10,FALSE()),0) -> 0 | S150: =IFERROR(VLOOKUP("15_"&A150,SyS!$B:$P,12,FALSE()),0) -> 0 | T150: =+R150-S150 -> 0 | U150: =IFERROR(VLOOKUP("16_"&A150,SyS!$B:$P,10,FALSE()),0) -> 0 | V150: =IFERROR(VLOOKUP("16_"&A150,SyS!$B:$P,12,FALSE()),0) -> 0 | W150: =+U150-V150 -> 0 | X150: =IFERROR(VLOOKUP("13_"&A150,SyS!$B:$P,10,FALSE()),0) -> 0 | Y150: =IFERROR(VLOOKUP("13_"&A150,SyS!$B:$P,12,FALSE()),0) -> 0 | Z150: =+X150-Y150 -> 0 | AA150: =IFERROR(VLOOKUP("17_"&A150,SyS!$B:$P,10,FALSE()),0) -> 0 | AB150: =IFERROR(VLOOKUP("17_"&A150,SyS!$B:$P,12,FALSE()),0) -> 0 | AC150: =+AA150-AB150 -> 0 | AG150: =IFERROR(VLOOKUP("19_"&A150,SyS!$B:$P,10,FALSE()),0) -> 0 | AH150: =IFERROR(VLOOKUP("19_"&A150,SyS!$B:$P,12,FALSE()),0) -> 0 | AI150: =+AG150-AH150 -> 0 | AM150: =IFERROR(VLOOKUP("23_"&A150,SyS!$B:$P,10,FALSE()),0) -> 0 | AN150: =IFERROR(VLOOKUP("23_"&A150,SyS!$B:$P,12,FALSE()),0) -> 0 | AO150: =+AM150-AN150 -> 0 | BK150: =IFERROR(VLOOKUP("29_"&A150,SyS!$B:$P,10,FALSE()),0) -> 0 | BL150: =IFERROR(VLOOKUP("29_"&A150,SyS!$B:$P,12,FALSE()),0) -> 0 | BM150: =+BK150-BL150 -> 0 | BN150: =IFERROR(VLOOKUP("30_"&A150,SyS!$B:$P,10,FALSE()),0) -> 0 | BO150: =IFERROR(VLOOKUP("30_"&A150,SyS!$B:$P,12,FALSE()),0) -> 0 | BP150: =+BN150-BO150 -> 0 | BQ150: =+E150+H150+K150+Q150+T150+W150+Z150+AC150+AF150+AI150+AL150+AO150+AR150+AU150+AX150+BA150+BD150+BG150+BJ150+BM150+BP150 -> 130.94
A151: 433080000 | B151: Gastos Varios de Adm Gral USD | C151: =IFERROR(VLOOKUP("1_"&A151,SyS!$B:$P,10,FALSE()),0) -> 0 | D151: =IFERROR(VLOOKUP("1_"&A151,SyS!$B:$P,12,FALSE()),0) -> 0 | E151: =+C151-D151 -> 0 | F151: =IFERROR(VLOOKUP("2_"&A151,SyS!$B:$P,10,FALSE()),0) -> 0 | G151: =IFERROR(VLOOKUP("2_"&A151,SyS!$B:$P,12,FALSE()),0) -> 0 | H151: =+F151-G151 -> 0 | O151: =IFERROR(VLOOKUP("14_"&A151,SyS!$B:$P,10,FALSE()),0) -> 0 | P151: =IFERROR(VLOOKUP("14_"&A151,SyS!$B:$P,12,FALSE()),0) -> 0 | Q151: =+O151-P151 -> 0 | R151: =IFERROR(VLOOKUP("15_"&A151,SyS!$B:$P,10,FALSE()),0) -> 0 | S151: =IFERROR(VLOOKUP("15_"&A151,SyS!$B:$P,12,FALSE()),0) -> 0 | T151: =+R151-S151 -> 0 | U151: =IFERROR(VLOOKUP("16_"&A151,SyS!$B:$P,10,FALSE()),0) -> 0 | V151: =IFERROR(VLOOKUP("16_"&A151,SyS!$B:$P,12,FALSE()),0) -> 0 | W151: =+U151-V151 -> 0 | X151: =IFERROR(VLOOKUP("13_"&A151,SyS!$B:$P,10,FALSE()),0) -> 0 | Y151: =IFERROR(VLOOKUP("13_"&A151,SyS!$B:$P,12,FALSE()),0) -> 0 | Z151: =+X151-Y151 -> 0 | AA151: =IFERROR(VLOOKUP("17_"&A151,SyS!$B:$P,10,FALSE()),0) -> 0 | AB151: =IFERROR(VLOOKUP("17_"&A151,SyS!$B:$P,12,FALSE()),0) -> 0 | AC151: =+AA151-AB151 -> 0 | AG151: =IFERROR(VLOOKUP("19_"&A151,SyS!$B:$P,10,FALSE()),0) -> 0 | AH151: =IFERROR(VLOOKUP("19_"&A151,SyS!$B:$P,12,FALSE()),0) -> 0 | AI151: =+AG151-AH151 -> 0 | AM151: =IFERROR(VLOOKUP("23_"&A151,SyS!$B:$P,10,FALSE()),0) -> 0 | AN151: =IFERROR(VLOOKUP("23_"&A151,SyS!$B:$P,12,FALSE()),0) -> 0 | AO151: =+AM151-AN151 -> 0 | BK151: =IFERROR(VLOOKUP("29_"&A151,SyS!$B:$P,10,FALSE()),0) -> 0 | BL151: =IFERROR(VLOOKUP("29_"&A151,SyS!$B:$P,12,FALSE()),0) -> 0 | BM151: =+BK151-BL151 -> 0 | BN151: =IFERROR(VLOOKUP("30_"&A151,SyS!$B:$P,10,FALSE()),0) -> 0 | BO151: =IFERROR(VLOOKUP("30_"&A151,SyS!$B:$P,12,FALSE()),0) -> 0 | BP151: =+BN151-BO151 -> 0 | BQ151: =+E151+H151+K151+Q151+T151+W151+Z151+AC151+AF151+AI151+AL151+AO151+AR151+AU151+AX151+BA151+BD151+BG151+BJ151+BM151+BP151 -> 0
A152: 425400000 | B152: SERVICIOS INFORMÁTICOS ADM GRAL | C152: =IFERROR(VLOOKUP("1_"&A152,SyS!$B:$P,10,FALSE()),0) -> 0 | D152: =IFERROR(VLOOKUP("1_"&A152,SyS!$B:$P,12,FALSE()),0) -> 0 | E152: =+C152-D152 -> 0 | F152: =IFERROR(VLOOKUP("2_"&A152,SyS!$B:$P,10,FALSE()),0) -> 0 | G152: =IFERROR(VLOOKUP("2_"&A152,SyS!$B:$P,12,FALSE()),0) -> 0 | H152: =+F152-G152 -> 0 | O152: =IFERROR(VLOOKUP("14_"&A152,SyS!$B:$P,10,FALSE()),0) -> 0 | P152: =IFERROR(VLOOKUP("14_"&A152,SyS!$B:$P,12,FALSE()),0) -> 0 | Q152: =+O152-P152 -> 0 | R152: =IFERROR(VLOOKUP("15_"&A152,SyS!$B:$P,10,FALSE()),0) -> 0 | S152: =IFERROR(VLOOKUP("15_"&A152,SyS!$B:$P,12,FALSE()),0) -> 0 | T152: =+R152-S152 -> 0 | U152: =IFERROR(VLOOKUP("16_"&A152,SyS!$B:$P,10,FALSE()),0) -> 0 | V152: =IFERROR(VLOOKUP("16_"&A152,SyS!$B:$P,12,FALSE()),0) -> 0 | W152: =+U152-V152 -> 0 | X152: =IFERROR(VLOOKUP("13_"&A152,SyS!$B:$P,10,FALSE()),0) -> 0 | Y152: =IFERROR(VLOOKUP("13_"&A152,SyS!$B:$P,12,FALSE()),0) -> 0 | Z152: =+X152-Y152 -> 0 | AA152: =IFERROR(VLOOKUP("17_"&A152,SyS!$B:$P,10,FALSE()),0) -> 0 | AB152: =IFERROR(VLOOKUP("17_"&A152,SyS!$B:$P,12,FALSE()),0) -> 0 | AC152: =+AA152-AB152 -> 0 | AG152: =IFERROR(VLOOKUP("19_"&A152,SyS!$B:$P,10,FALSE()),0) -> 0 | AH152: =IFERROR(VLOOKUP("19_"&A152,SyS!$B:$P,12,FALSE()),0) -> 0 | AI152: =+AG152-AH152 -> 0 | AM152: =IFERROR(VLOOKUP("23_"&A152,SyS!$B:$P,10,FALSE()),0) -> 0 | AN152: =IFERROR(VLOOKUP("23_"&A152,SyS!$B:$P,12,FALSE()),0) -> 0 | AO152: =+AM152-AN152 -> 0 | BK152: =IFERROR(VLOOKUP("29_"&A152,SyS!$B:$P,10,FALSE()),0) -> 0 | BL152: =IFERROR(VLOOKUP("29_"&A152,SyS!$B:$P,12,FALSE()),0) -> 0 | BM152: =+BK152-BL152 -> 0 | BN152: =IFERROR(VLOOKUP("30_"&A152,SyS!$B:$P,10,FALSE()),0) -> 0 | BO152: =IFERROR(VLOOKUP("30_"&A152,SyS!$B:$P,12,FALSE()),0) -> 0 | BP152: =+BN152-BO152 -> 0 | BQ152: =+E152+H152+K152+Q152+T152+W152+Z152+AC152+AF152+AI152+AL152+AO152+AR152+AU152+AX152+BA152+BD152+BG152+BJ152+BM152+BP152 -> 0
A153: 425500000 | B153: SERVICIOS PUBLICOS ADM GRAL | C153: =IFERROR(VLOOKUP("1_"&A153,SyS!$B:$P,10,FALSE()),0) -> 0 | D153: =IFERROR(VLOOKUP("1_"&A153,SyS!$B:$P,12,FALSE()),0) -> 0 | E153: =+C153-D153 -> 0 | F153: =IFERROR(VLOOKUP("2_"&A153,SyS!$B:$P,10,FALSE()),0) -> 0 | G153: =IFERROR(VLOOKUP("2_"&A153,SyS!$B:$P,12,FALSE()),0) -> 0 | H153: =+F153-G153 -> 0 | O153: =IFERROR(VLOOKUP("14_"&A153,SyS!$B:$P,10,FALSE()),0) -> 0 | P153: =IFERROR(VLOOKUP("14_"&A153,SyS!$B:$P,12,FALSE()),0) -> 0 | Q153: =+O153-P153 -> 0 | R153: =IFERROR(VLOOKUP("15_"&A153,SyS!$B:$P,10,FALSE()),0) -> 0 | S153: =IFERROR(VLOOKUP("15_"&A153,SyS!$B:$P,12,FALSE()),0) -> 0 | T153: =+R153-S153 -> 0 | U153: =IFERROR(VLOOKUP("16_"&A153,SyS!$B:$P,10,FALSE()),0) -> 0 | V153: =IFERROR(VLOOKUP("16_"&A153,SyS!$B:$P,12,FALSE()),0) -> 0 | W153: =+U153-V153 -> 0 | X153: =IFERROR(VLOOKUP("13_"&A153,SyS!$B:$P,10,FALSE()),0) -> 0 | Y153: =IFERROR(VLOOKUP("13_"&A153,SyS!$B:$P,12,FALSE()),0) -> 0 | Z153: =+X153-Y153 -> 0 | AA153: =IFERROR(VLOOKUP("17_"&A153,SyS!$B:$P,10,FALSE()),0) -> 0 | AB153: =IFERROR(VLOOKUP("17_"&A153,SyS!$B:$P,12,FALSE()),0) -> 0 | AC153: =+AA153-AB153 -> 0 | AG153: =IFERROR(VLOOKUP("19_"&A153,SyS!$B:$P,10,FALSE()),0) -> 0 | AH153: =IFERROR(VLOOKUP("19_"&A153,SyS!$B:$P,12,FALSE()),0) -> 0 | AI153: =+AG153-AH153 -> 0 | AM153: =IFERROR(VLOOKUP("23_"&A153,SyS!$B:$P,10,FALSE()),0) -> 0 | AN153: =IFERROR(VLOOKUP("23_"&A153,SyS!$B:$P,12,FALSE()),0) -> 0 | AO153: =+AM153-AN153 -> 0 | BK153: =IFERROR(VLOOKUP("29_"&A153,SyS!$B:$P,10,FALSE()),0) -> 0 | BL153: =IFERROR(VLOOKUP("29_"&A153,SyS!$B:$P,12,FALSE()),0) -> 0 | BM153: =+BK153-BL153 -> 0 | BN153: =IFERROR(VLOOKUP("30_"&A153,SyS!$B:$P,10,FALSE()),0) -> 0 | BO153: =IFERROR(VLOOKUP("30_"&A153,SyS!$B:$P,12,FALSE()),0) -> 0 | BP153: =+BN153-BO153 -> 0 | BQ153: =+E153+H153+K153+Q153+T153+W153+Z153+AC153+AF153+AI153+AL153+AO153+AR153+AU153+AX153+BA153+BD153+BG153+BJ153+BM153+BP153 -> 0
A154: 425600000 | B154: GST. MANTENIMIENTO ADM GRAL. | C154: =IFERROR(VLOOKUP("1_"&A154,SyS!$B:$P,10,FALSE()),0) -> 0 | D154: =IFERROR(VLOOKUP("1_"&A154,SyS!$B:$P,12,FALSE()),0) -> 0 | E154: =+C154-D154 -> 0 | F154: =IFERROR(VLOOKUP("2_"&A154,SyS!$B:$P,10,FALSE()),0) -> 0 | G154: =IFERROR(VLOOKUP("2_"&A154,SyS!$B:$P,12,FALSE()),0) -> 0 | H154: =+F154-G154 -> 0 | O154: =IFERROR(VLOOKUP("14_"&A154,SyS!$B:$P,10,FALSE()),0) -> 0 | P154: =IFERROR(VLOOKUP("14_"&A154,SyS!$B:$P,12,FALSE()),0) -> 0 | Q154: =+O154-P154 -> 0 | R154: =IFERROR(VLOOKUP("15_"&A154,SyS!$B:$P,10,FALSE()),0) -> 0 | S154: =IFERROR(VLOOKUP("15_"&A154,SyS!$B:$P,12,FALSE()),0) -> 0 | T154: =+R154-S154 -> 0 | U154: =IFERROR(VLOOKUP("16_"&A154,SyS!$B:$P,10,FALSE()),0) -> 0 | V154: =IFERROR(VLOOKUP("16_"&A154,SyS!$B:$P,12,FALSE()),0) -> 0 | W154: =+U154-V154 -> 0 | X154: =IFERROR(VLOOKUP("13_"&A154,SyS!$B:$P,10,FALSE()),0) -> 0 | Y154: =IFERROR(VLOOKUP("13_"&A154,SyS!$B:$P,12,FALSE()),0) -> 0 | Z154: =+X154-Y154 -> 0 | AA154: =IFERROR(VLOOKUP("17_"&A154,SyS!$B:$P,10,FALSE()),0) -> 0 | AB154: =IFERROR(VLOOKUP("17_"&A154,SyS!$B:$P,12,FALSE()),0) -> 0 | AC154: =+AA154-AB154 -> 0 | AG154: =IFERROR(VLOOKUP("19_"&A154,SyS!$B:$P,10,FALSE()),0) -> 0 | AH154: =IFERROR(VLOOKUP("19_"&A154,SyS!$B:$P,12,FALSE()),0) -> 0 | AI154: =+AG154-AH154 -> 0 | AM154: =IFERROR(VLOOKUP("23_"&A154,SyS!$B:$P,10,FALSE()),0) -> 0 | AN154: =IFERROR(VLOOKUP("23_"&A154,SyS!$B:$P,12,FALSE()),0) -> 0 | AO154: =+AM154-AN154 -> 0 | BK154: =IFERROR(VLOOKUP("29_"&A154,SyS!$B:$P,10,FALSE()),0) -> 0 | BL154: =IFERROR(VLOOKUP("29_"&A154,SyS!$B:$P,12,FALSE()),0) -> 0 | BM154: =+BK154-BL154 -> 0 | BN154: =IFERROR(VLOOKUP("30_"&A154,SyS!$B:$P,10,FALSE()),0) -> 0 | BO154: =IFERROR(VLOOKUP("30_"&A154,SyS!$B:$P,12,FALSE()),0) -> 0 | BP154: =+BN154-BO154 -> 0 | BQ154: =+E154+H154+K154+Q154+T154+W154+Z154+AC154+AF154+AI154+AL154+AO154+AR154+AU154+AX154+BA154+BD154+BG154+BJ154+BM154+BP154 -> 0
A155: 425820000 | B155: TASAS RETRIBUTIVAS MINERÍA ADM GRAL. | C155: =IFERROR(VLOOKUP("1_"&A155,SyS!$B:$P,10,FALSE()),0) -> 0 | D155: =IFERROR(VLOOKUP("1_"&A155,SyS!$B:$P,12,FALSE()),0) -> 0 | E155: =+C155-D155 -> 0 | F155: =IFERROR(VLOOKUP("2_"&A155,SyS!$B:$P,10,FALSE()),0) -> 0 | G155: =IFERROR(VLOOKUP("2_"&A155,SyS!$B:$P,12,FALSE()),0) -> 0 | H155: =+F155-G155 -> 0 | O155: =IFERROR(VLOOKUP("14_"&A155,SyS!$B:$P,10,FALSE()),0) -> 0 | P155: =IFERROR(VLOOKUP("14_"&A155,SyS!$B:$P,12,FALSE()),0) -> 0 | Q155: =+O155-P155 -> 0 | R155: =IFERROR(VLOOKUP("15_"&A155,SyS!$B:$P,10,FALSE()),0) -> 0 | S155: =IFERROR(VLOOKUP("15_"&A155,SyS!$B:$P,12,FALSE()),0) -> 0 | T155: =+R155-S155 -> 0 | U155: =IFERROR(VLOOKUP("16_"&A155,SyS!$B:$P,10,FALSE()),0) -> 0 | V155: =IFERROR(VLOOKUP("16_"&A155,SyS!$B:$P,12,FALSE()),0) -> 0 | W155: =+U155-V155 -> 0 | X155: =IFERROR(VLOOKUP("13_"&A155,SyS!$B:$P,10,FALSE()),0) -> 0 | Y155: =IFERROR(VLOOKUP("13_"&A155,SyS!$B:$P,12,FALSE()),0) -> 0 | Z155: =+X155-Y155 -> 0 | AA155: =IFERROR(VLOOKUP("17_"&A155,SyS!$B:$P,10,FALSE()),0) -> 0 | AB155: =IFERROR(VLOOKUP("17_"&A155,SyS!$B:$P,12,FALSE()),0) -> 0 | AC155: =+AA155-AB155 -> 0 | AG155: =IFERROR(VLOOKUP("19_"&A155,SyS!$B:$P,10,FALSE()),0) -> 0 | AH155: =IFERROR(VLOOKUP("19_"&A155,SyS!$B:$P,12,FALSE()),0) -> 0 | AI155: =+AG155-AH155 -> 0 | AM155: =IFERROR(VLOOKUP("23_"&A155,SyS!$B:$P,10,FALSE()),0) -> 0 | AN155: =IFERROR(VLOOKUP("23_"&A155,SyS!$B:$P,12,FALSE()),0) -> 0 | AO155: =+AM155-AN155 -> 0 | BK155: =IFERROR(VLOOKUP("29_"&A155,SyS!$B:$P,10,FALSE()),0) -> 0 | BL155: =IFERROR(VLOOKUP("29_"&A155,SyS!$B:$P,12,FALSE()),0) -> 0 | BM155: =+BK155-BL155 -> 0 | BN155: =IFERROR(VLOOKUP("30_"&A155,SyS!$B:$P,10,FALSE()),0) -> 0 | BO155: =IFERROR(VLOOKUP("30_"&A155,SyS!$B:$P,12,FALSE()),0) -> 0 | BP155: =+BN155-BO155 -> 0 | BQ155: =+E155+H155+K155+Q155+T155+W155+Z155+AC155+AF155+AI155+AL155+AO155+AR155+AU155+AX155+BA155+BD155+BG155+BJ155+BM155+BP155 -> 0
A156: 425840000 | B156: Servicios Notariales Administracion Gral. | C156: =IFERROR(VLOOKUP("1_"&A156,SyS!$B:$P,10,FALSE()),0) -> 0 | D156: =IFERROR(VLOOKUP("1_"&A156,SyS!$B:$P,12,FALSE()),0) -> 0 | E156: =+C156-D156 -> 0 | F156: =IFERROR(VLOOKUP("2_"&A156,SyS!$B:$P,10,FALSE()),0) -> 0 | G156: =IFERROR(VLOOKUP("2_"&A156,SyS!$B:$P,12,FALSE()),0) -> 0 | H156: =+F156-G156 -> 0 | O156: =IFERROR(VLOOKUP("14_"&A156,SyS!$B:$P,10,FALSE()),0) -> 0 | P156: =IFERROR(VLOOKUP("14_"&A156,SyS!$B:$P,12,FALSE()),0) -> 0 | Q156: =+O156-P156 -> 0 | R156: =IFERROR(VLOOKUP("15_"&A156,SyS!$B:$P,10,FALSE()),0) -> 0 | S156: =IFERROR(VLOOKUP("15_"&A156,SyS!$B:$P,12,FALSE()),0) -> 0 | T156: =+R156-S156 -> 0 | U156: =IFERROR(VLOOKUP("16_"&A156,SyS!$B:$P,10,FALSE()),0) -> 0 | V156: =IFERROR(VLOOKUP("16_"&A156,SyS!$B:$P,12,FALSE()),0) -> 0 | W156: =+U156-V156 -> 0 | X156: =IFERROR(VLOOKUP("13_"&A156,SyS!$B:$P,10,FALSE()),0) -> 0 | Y156: =IFERROR(VLOOKUP("13_"&A156,SyS!$B:$P,12,FALSE()),0) -> 0 | Z156: =+X156-Y156 -> 0 | AA156: =IFERROR(VLOOKUP("17_"&A156,SyS!$B:$P,10,FALSE()),0) -> 0 | AB156: =IFERROR(VLOOKUP("17_"&A156,SyS!$B:$P,12,FALSE()),0) -> 0 | AC156: =+AA156-AB156 -> 0 | AG156: =IFERROR(VLOOKUP("19_"&A156,SyS!$B:$P,10,FALSE()),0) -> 0 | AH156: =IFERROR(VLOOKUP("19_"&A156,SyS!$B:$P,12,FALSE()),0) -> 0 | AI156: =+AG156-AH156 -> 0 | AM156: =IFERROR(VLOOKUP("23_"&A156,SyS!$B:$P,10,FALSE()),0) -> 0 | AN156: =IFERROR(VLOOKUP("23_"&A156,SyS!$B:$P,12,FALSE()),0) -> 0 | AO156: =+AM156-AN156 -> 0 | BK156: =IFERROR(VLOOKUP("29_"&A156,SyS!$B:$P,10,FALSE()),0) -> 0 | BL156: =IFERROR(VLOOKUP("29_"&A156,SyS!$B:$P,12,FALSE()),0) -> 0 | BM156: =+BK156-BL156 -> 0 | BN156: =IFERROR(VLOOKUP("30_"&A156,SyS!$B:$P,10,FALSE()),0) -> 0 | BO156: =IFERROR(VLOOKUP("30_"&A156,SyS!$B:$P,12,FALSE()),0) -> 0 | BP156: =+BN156-BO156 -> 0 | BQ156: =+E156+H156+K156+Q156+T156+W156+Z156+AC156+AF156+AI156+AL156+AO156+AR156+AU156+AX156+BA156+BD156+BG156+BJ156+BM156+BP156 -> 0
... A208: 421200000 | B208: Intereses resarcitorios Adm Gral Catamarca | C208: =IFERROR(VLOOKUP("1_"&A208,SyS!$B:$P,10,FALSE()),0) -> 0 | D208: =IFERROR(VLOOKUP("1_"&A208,SyS!$B:$P,12,FALSE()),0) -> 0 | E208: =+C208-D208 -> 0 | F208: =IFERROR(VLOOKUP("2_"&A208,SyS!$B:$P,10,FALSE()),0) -> 0 | G208: =IFERROR(VLOOKUP("2_"&A208,SyS!$B:$P,12,FALSE()),0) -> 0 | H208: =+F208-G208 -> 0 | O208: =IFERROR(VLOOKUP("14_"&A208,SyS!$B:$P,10,FALSE()),0) -> 0 | P208: =IFERROR(VLOOKUP("14_"&A208,SyS!$B:$P,12,FALSE()),0) -> 0 | Q208: =+O208-P208 -> 0 | R208: =IFERROR(VLOOKUP("15_"&A208,SyS!$B:$P,10,FALSE()),0) -> 0 | S208: =IFERROR(VLOOKUP("15_"&A208,SyS!$B:$P,12,FALSE()),0) -> 0 | T208: =+R208-S208 -> 0 | U208: =IFERROR(VLOOKUP("16_"&A208,SyS!$B:$P,10,FALSE()),0) -> 0 | V208: =IFERROR(VLOOKUP("16_"&A208,SyS!$B:$P,12,FALSE()),0) -> 0 | W208: =+U208-V208 -> 0 | X208: =IFERROR(VLOOKUP("13_"&A208,SyS!$B:$P,10,FALSE()),0) -> 0 | Y208: =IFERROR(VLOOKUP("13_"&A208,SyS!$B:$P,12,FALSE()),0) -> 0 | Z208: =+X208-Y208 -> 0 | AA208: =IFERROR(VLOOKUP("17_"&A208,SyS!$B:$P,10,FALSE()),0) -> 0 | AB208: =IFERROR(VLOOKUP("17_"&A208,SyS!$B:$P,12,FALSE()),0) -> 0 | AC208: =+AA208-AB208 -> 0 | AG208: =IFERROR(VLOOKUP("19_"&A208,SyS!$B:$P,10,FALSE()),0) -> 0 | AH208: =IFERROR(VLOOKUP("19_"&A208,SyS!$B:$P,12,FALSE()),0) -> 0 | AI208: =+AG208-AH208 -> 0 | AM208: =IFERROR(VLOOKUP("23_"&A208,SyS!$B:$P,10,FALSE()),0) -> 0 | AN208: =IFERROR(VLOOKUP("23_"&A208,SyS!$B:$P,12,FALSE()),0) -> 0 | AO208: =+AM208-AN208 -> 0 | BK208: =IFERROR(VLOOKUP("29_"&A208,SyS!$B:$P,10,FALSE()),0) -> 0 | BL208: =IFERROR(VLOOKUP("29_"&A208,SyS!$B:$P,12,FALSE()),0) -> 0 | BM208: =+BK208-BL208 -> 0 | BN208: =IFERROR(VLOOKUP("30_"&A208,SyS!$B:$P,10,FALSE()),0) -> 0 | BO208: =IFERROR(VLOOKUP("30_"&A208,SyS!$B:$P,12,FALSE()),0) -> 0 | BP208: =+BN208-BO208 -> 0 | BQ208: =+E208+H208+K208+Q208+T208+W208+Z208+AC208+AF208+AI208+AL208+AO208+AR208+AU208+AX208+BA208+BD208+BG208+BJ208+BM208+BP208 -> 0
B209: GASTOS CAMPO
A210: 426110000 | B210: REFRIGERIOS GST. CAMPO | C210: =IFERROR(VLOOKUP("1_"&A210,SyS!$B:$P,10,FALSE()),0) -> 0 | D210: =IFERROR(VLOOKUP("1_"&A210,SyS!$B:$P,12,FALSE()),0) -> 0 | E210: =+C210-D210 -> 0 | F210: =IFERROR(VLOOKUP("2_"&A210,SyS!$B:$P,10,FALSE()),0) -> 705.37 | G210: =IFERROR(VLOOKUP("2_"&A210,SyS!$B:$P,12,FALSE()),0) -> 5.61 | H210: =+F210-G210 -> 699.76 | O210: =IFERROR(VLOOKUP("14_"&A210,SyS!$B:$P,10,FALSE()),0) -> 0 | P210: =IFERROR(VLOOKUP("14_"&A210,SyS!$B:$P,12,FALSE()),0) -> 0 | Q210: =+O210-P210 -> 0 | R210: =IFERROR(VLOOKUP("15_"&A210,SyS!$B:$P,10,FALSE()),0) -> 0 | S210: =IFERROR(VLOOKUP("15_"&A210,SyS!$B:$P,12,FALSE()),0) -> 0 | T210: =+R210-S210 -> 0 | U210: =IFERROR(VLOOKUP("16_"&A210,SyS!$B:$P,10,FALSE()),0) -> 0 | V210: =IFERROR(VLOOKUP("16_"&A210,SyS!$B:$P,12,FALSE()),0) -> 0 | W210: =+U210-V210 -> 0 | X210: =IFERROR(VLOOKUP("13_"&A210,SyS!$B:$P,10,FALSE()),0) -> 0 | Y210: =IFERROR(VLOOKUP("13_"&A210,SyS!$B:$P,12,FALSE()),0) -> 0 | Z210: =+X210-Y210 -> 0 | AA210: =IFERROR(VLOOKUP("17_"&A210,SyS!$B:$P,10,FALSE()),0) -> 1238.03 | AB210: =IFERROR(VLOOKUP("17_"&A210,SyS!$B:$P,12,FALSE()),0) -> 0 | AC210: =+AA210-AB210 -> 1238.03 | AG210: =IFERROR(VLOOKUP("19_"&A210,SyS!$B:$P,10,FALSE()),0) -> 0 | AH210: =IFERROR(VLOOKUP("19_"&A210,SyS!$B:$P,12,FALSE()),0) -> 0 | AI210: =+AG210-AH210 -> 0 | AM210: =IFERROR(VLOOKUP("23_"&A210,SyS!$B:$P,10,FALSE()),0) -> 0 | AN210: =IFERROR(VLOOKUP("23_"&A210,SyS!$B:$P,12,FALSE()),0) -> 0 | AO210: =+AM210-AN210 -> 0 | BK210: =IFERROR(VLOOKUP("29_"&A210,SyS!$B:$P,10,FALSE()),0) -> 0 | BL210: =IFERROR(VLOOKUP("29_"&A210,SyS!$B:$P,12,FALSE()),0) -> 0 | BM210: =+BK210-BL210 -> 0 | BN210: =IFERROR(VLOOKUP("30_"&A210,SyS!$B:$P,10,FALSE()),0) -> 0 | BO210: =IFERROR(VLOOKUP("30_"&A210,SyS!$B:$P,12,FALSE()),0) -> 0 | BP210: =+BN210-BO210 -> 0 | BQ210: =+E210+H210+K210+Q210+T210+W210+Z210+AC210+AF210+AI210+AL210+AO210+AR210+AU210+AX210+BA210+BD210+BG210+BJ210+BM210+BP210 -> 1937.79
A211: 426120000 | B211: MOVILIDAD Y VIATICOS GST. CAMPO | C211: =IFERROR(VLOOKUP("1_"&A211,SyS!$B:$P,10,FALSE()),0) -> 0 | D211: =IFERROR(VLOOKUP("1_"&A211,SyS!$B:$P,12,FALSE()),0) -> 0 | E211: =+C211-D211 -> 0 | F211: =IFERROR(VLOOKUP("2_"&A211,SyS!$B:$P,10,FALSE()),0) -> 6398.37 | G211: =IFERROR(VLOOKUP("2_"&A211,SyS!$B:$P,12,FALSE()),0) -> 0 | H211: =+F211-G211 -> 6398.37 | O211: =IFERROR(VLOOKUP("14_"&A211,SyS!$B:$P,10,FALSE()),0) -> 0 | P211: =IFERROR(VLOOKUP("14_"&A211,SyS!$B:$P,12,FALSE()),0) -> 0 | Q211: =+O211-P211 -> 0 | R211: =IFERROR(VLOOKUP("15_"&A211,SyS!$B:$P,10,FALSE()),0) -> 0 | S211: =IFERROR(VLOOKUP("15_"&A211,SyS!$B:$P,12,FALSE()),0) -> 0 | T211: =+R211-S211 -> 0 | U211: =IFERROR(VLOOKUP("16_"&A211,SyS!$B:$P,10,FALSE()),0) -> 0 | V211: =IFERROR(VLOOKUP("16_"&A211,SyS!$B:$P,12,FALSE()),0) -> 0 | W211: =+U211-V211 -> 0 | X211: =IFERROR(VLOOKUP("13_"&A211,SyS!$B:$P,10,FALSE()),0) -> 0 | Y211: =IFERROR(VLOOKUP("13_"&A211,SyS!$B:$P,12,FALSE()),0) -> 0 | Z211: =+X211-Y211 -> 0 | AA211: =IFERROR(VLOOKUP("17_"&A211,SyS!$B:$P,10,FALSE()),0) -> 110.95 | AB211: =IFERROR(VLOOKUP("17_"&A211,SyS!$B:$P,12,FALSE()),0) -> 0 | AC211: =+AA211-AB211 -> 110.95 | AG211: =IFERROR(VLOOKUP("19_"&A211,SyS!$B:$P,10,FALSE()),0) -> 0 | AH211: =IFERROR(VLOOKUP("19_"&A211,SyS!$B:$P,12,FALSE()),0) -> 0 | AI211: =+AG211-AH211 -> 0 | AM211: =IFERROR(VLOOKUP("23_"&A211,SyS!$B:$P,10,FALSE()),0) -> 0 | AN211: =IFERROR(VLOOKUP("23_"&A211,SyS!$B:$P,12,FALSE()),0) -> 0 | AO211: =+AM211-AN211 -> 0 | BK211: =IFERROR(VLOOKUP("29_"&A211,SyS!$B:$P,10,FALSE()),0) -> 0 | BL211: =IFERROR(VLOOKUP("29_"&A211,SyS!$B:$P,12,FALSE()),0) -> 0 | BM211: =+BK211-BL211 -> 0 | BN211: =IFERROR(VLOOKUP("30_"&A211,SyS!$B:$P,10,FALSE()),0) -> 0 | BO211: =IFERROR(VLOOKUP("30_"&A211,SyS!$B:$P,12,FALSE()),0) -> 0 | BP211: =+BN211-BO211 -> 0 | BQ211: =+E211+H211+K211+Q211+T211+W211+Z211+AC211+AF211+AI211+AL211+AO211+AR211+AU211+AX211+BA211+BD211+BG211+BJ211+BM211+BP211 -> 6509.32
A212: 426140000 | B212: EXPENSAS DEPTO GEOLOGOS GST CAMPO | C212: =IFERROR(VLOOKUP("1_"&A212,SyS!$B:$P,10,FALSE()),0) -> 0 | D212: =IFERROR(VLOOKUP("1_"&A212,SyS!$B:$P,12,FALSE()),0) -> 0 | E212: =+C212-D212 -> 0 | F212: =IFERROR(VLOOKUP("2_"&A212,SyS!$B:$P,10,FALSE()),0) -> 0 | G212: =IFERROR(VLOOKUP("2_"&A212,SyS!$B:$P,12,FALSE()),0) -> 0 | H212: =+F212-G212 -> 0 | O212: =IFERROR(VLOOKUP("14_"&A212,SyS!$B:$P,10,FALSE()),0) -> 0 | P212: =IFERROR(VLOOKUP("14_"&A212,SyS!$B:$P,12,FALSE()),0) -> 0 | Q212: =+O212-P212 -> 0 | R212: =IFERROR(VLOOKUP("15_"&A212,SyS!$B:$P,10,FALSE()),0) -> 0 | S212: =IFERROR(VLOOKUP("15_"&A212,SyS!$B:$P,12,FALSE()),0) -> 0 | T212: =+R212-S212 -> 0 | U212: =IFERROR(VLOOKUP("16_"&A212,SyS!$B:$P,10,FALSE()),0) -> 0 | V212: =IFERROR(VLOOKUP("16_"&A212,SyS!$B:$P,12,FALSE()),0) -> 0 | W212: =+U212-V212 -> 0 | X212: =IFERROR(VLOOKUP("13_"&A212,SyS!$B:$P,10,FALSE()),0) -> 0 | Y212: =IFERROR(VLOOKUP("13_"&A212,SyS!$B:$P,12,FALSE()),0) -> 0 | Z212: =+X212-Y212 -> 0 | AA212: =IFERROR(VLOOKUP("17_"&A212,SyS!$B:$P,10,FALSE()),0) -> 0 | AB212: =IFERROR(VLOOKUP("17_"&A212,SyS!$B:$P,12,FALSE()),0) -> 0 | AC212: =+AA212-AB212 -> 0 | AG212: =IFERROR(VLOOKUP("19_"&A212,SyS!$B:$P,10,FALSE()),0) -> 0 | AH212: =IFERROR(VLOOKUP("19_"&A212,SyS!$B:$P,12,FALSE()),0) -> 0 | AI212: =+AG212-AH212 -> 0 | AM212: =IFERROR(VLOOKUP("23_"&A212,SyS!$B:$P,10,FALSE()),0) -> 0 | AN212: =IFERROR(VLOOKUP("23_"&A212,SyS!$B:$P,12,FALSE()),0) -> 0 | AO212: =+AM212-AN212 -> 0 | BK212: =IFERROR(VLOOKUP("29_"&A212,SyS!$B:$P,10,FALSE()),0) -> 0 | BL212: =IFERROR(VLOOKUP("29_"&A212,SyS!$B:$P,12,FALSE()),0) -> 0 | BM212: =+BK212-BL212 -> 0 | BN212: =IFERROR(VLOOKUP("30_"&A212,SyS!$B:$P,10,FALSE()),0) -> 0 | BO212: =IFERROR(VLOOKUP("30_"&A212,SyS!$B:$P,12,FALSE()),0) -> 0 | BP212: =+BN212-BO212 -> 0 | BQ212: =+E212+H212+K212+Q212+T212+W212+Z212+AC212+AF212+AI212+AL212+AO212+AR212+AU212+AX212+BA212+BD212+BG212+BJ212+BM212+BP212 -> 0
A213: 426150000 | B213: SERVICIOS PUBLICOS GST. CAMPO | C213: =IFERROR(VLOOKUP("1_"&A213,SyS!$B:$P,10,FALSE()),0) -> 0 | D213: =IFERROR(VLOOKUP("1_"&A213,SyS!$B:$P,12,FALSE()),0) -> 0 | E213: =+C213-D213 -> 0 | F213: =IFERROR(VLOOKUP("2_"&A213,SyS!$B:$P,10,FALSE()),0) -> 0 | G213: =IFERROR(VLOOKUP("2_"&A213,SyS!$B:$P,12,FALSE()),0) -> 0 | H213: =+F213-G213 -> 0 | O213: =IFERROR(VLOOKUP("14_"&A213,SyS!$B:$P,10,FALSE()),0) -> 0 | P213: =IFERROR(VLOOKUP("14_"&A213,SyS!$B:$P,12,FALSE()),0) -> 0 | Q213: =+O213-P213 -> 0 | R213: =IFERROR(VLOOKUP("15_"&A213,SyS!$B:$P,10,FALSE()),0) -> 0 | S213: =IFERROR(VLOOKUP("15_"&A213,SyS!$B:$P,12,FALSE()),0) -> 0 | T213: =+R213-S213 -> 0 | U213: =IFERROR(VLOOKUP("16_"&A213,SyS!$B:$P,10,FALSE()),0) -> 0 | V213: =IFERROR(VLOOKUP("16_"&A213,SyS!$B:$P,12,FALSE()),0) -> 0 | W213: =+U213-V213 -> 0 | X213: =IFERROR(VLOOKUP("13_"&A213,SyS!$B:$P,10,FALSE()),0) -> 0 | Y213: =IFERROR(VLOOKUP("13_"&A213,SyS!$B:$P,12,FALSE()),0) -> 0 | Z213: =+X213-Y213 -> 0 | AA213: =IFERROR(VLOOKUP("17_"&A213,SyS!$B:$P,10,FALSE()),0) -> 0 | AB213: =IFERROR(VLOOKUP("17_"&A213,SyS!$B:$P,12,FALSE()),0) -> 0 | AC213: =+AA213-AB213 -> 0 | AG213: =IFERROR(VLOOKUP("19_"&A213,SyS!$B:$P,10,FALSE()),0) -> 0 | AH213: =IFERROR(VLOOKUP("19_"&A213,SyS!$B:$P,12,FALSE()),0) -> 0 | AI213: =+AG213-AH213 -> 0 | AM213: =IFERROR(VLOOKUP("23_"&A213,SyS!$B:$P,10,FALSE()),0) -> 0 | AN213: =IFERROR(VLOOKUP("23_"&A213,SyS!$B:$P,12,FALSE()),0) -> 0 | AO213: =+AM213-AN213 -> 0 | BK213: =IFERROR(VLOOKUP("29_"&A213,SyS!$B:$P,10,FALSE()),0) -> 0 | BL213: =IFERROR(VLOOKUP("29_"&A213,SyS!$B:$P,12,FALSE()),0) -> 0 | BM213: =+BK213-BL213 -> 0 | BN213: =IFERROR(VLOOKUP("30_"&A213,SyS!$B:$P,10,FALSE()),0) -> 0 | BO213: =IFERROR(VLOOKUP("30_"&A213,SyS!$B:$P,12,FALSE()),0) -> 0 | BP213: =+BN213-BO213 -> 0 | BQ213: =+E213+H213+K213+Q213+T213+W213+Z213+AC213+AF213+AI213+AL213+AO213+AR213+AU213+AX213+BA213+BD213+BG213+BJ213+BM213+BP213 -> 0
A214: 433040000 | B214: Servicio de Internet USD | C214: =IFERROR(VLOOKUP("1_"&A214,SyS!$B:$P,10,FALSE()),0) -> 0 | D214: =IFERROR(VLOOKUP("1_"&A214,SyS!$B:$P,12,FALSE()),0) -> 0 | E214: =+C214-D214 -> 0 | F214: =IFERROR(VLOOKUP("2_"&A214,SyS!$B:$P,10,FALSE()),0) -> 0 | G214: =IFERROR(VLOOKUP("2_"&A214,SyS!$B:$P,12,FALSE()),0) -> 0 | H214: =+F214-G214 -> 0 | O214: =IFERROR(VLOOKUP("14_"&A214,SyS!$B:$P,10,FALSE()),0) -> 0 | P214: =IFERROR(VLOOKUP("14_"&A214,SyS!$B:$P,12,FALSE()),0) -> 0 | Q214: =+O214-P214 -> 0 | R214: =IFERROR(VLOOKUP("15_"&A214,SyS!$B:$P,10,FALSE()),0) -> 0 | S214: =IFERROR(VLOOKUP("15_"&A214,SyS!$B:$P,12,FALSE()),0) -> 0 | T214: =+R214-S214 -> 0 | U214: =IFERROR(VLOOKUP("16_"&A214,SyS!$B:$P,10,FALSE()),0) -> 0 | V214: =IFERROR(VLOOKUP("16_"&A214,SyS!$B:$P,12,FALSE()),0) -> 0 | W214: =+U214-V214 -> 0 | X214: =IFERROR(VLOOKUP("13_"&A214,SyS!$B:$P,10,FALSE()),0) -> 0 | Y214: =IFERROR(VLOOKUP("13_"&A214,SyS!$B:$P,12,FALSE()),0) -> 0 | Z214: =+X214-Y214 -> 0 | AA214: =IFERROR(VLOOKUP("17_"&A214,SyS!$B:$P,10,FALSE()),0) -> 0 | AB214: =IFERROR(VLOOKUP("17_"&A214,SyS!$B:$P,12,FALSE()),0) -> 0 | AC214: =+AA214-AB214 -> 0 | AG214: =IFERROR(VLOOKUP("19_"&A214,SyS!$B:$P,10,FALSE()),0) -> 0 | AH214: =IFERROR(VLOOKUP("19_"&A214,SyS!$B:$P,12,FALSE()),0) -> 0 | AI214: =+AG214-AH214 -> 0 | AM214: =IFERROR(VLOOKUP("23_"&A214,SyS!$B:$P,10,FALSE()),0) -> 0 | AN214: =IFERROR(VLOOKUP("23_"&A214,SyS!$B:$P,12,FALSE()),0) -> 0 | AO214: =+AM214-AN214 -> 0 | BK214: =IFERROR(VLOOKUP("29_"&A214,SyS!$B:$P,10,FALSE()),0) -> 0 | BL214: =IFERROR(VLOOKUP("29_"&A214,SyS!$B:$P,12,FALSE()),0) -> 0 | BM214: =+BK214-BL214 -> 0 | BN214: =IFERROR(VLOOKUP("30_"&A214,SyS!$B:$P,10,FALSE()),0) -> 0 | BO214: =IFERROR(VLOOKUP("30_"&A214,SyS!$B:$P,12,FALSE()),0) -> 0 | BP214: =+BN214-BO214 -> 0 | BQ214: =+E214+H214+K214+Q214+T214+W214+Z214+AC214+AF214+AI214+AL214+AO214+AR214+AU214+AX214+BA214+BD214+BG214+BJ214+BM214+BP214 -> 0
A215: 426170000 | B215: ALQUILER COCHERAS GST. CAMPO | C215: =IFERROR(VLOOKUP("1_"&A215,SyS!$B:$P,10,FALSE()),0) -> 0 | D215: =IFERROR(VLOOKUP("1_"&A215,SyS!$B:$P,12,FALSE()),0) -> 0 | E215: =+C215-D215 -> 0 | F215: =IFERROR(VLOOKUP("2_"&A215,SyS!$B:$P,10,FALSE()),0) -> 0 | G215: =IFERROR(VLOOKUP("2_"&A215,SyS!$B:$P,12,FALSE()),0) -> 0 | H215: =+F215-G215 -> 0 | O215: =IFERROR(VLOOKUP("14_"&A215,SyS!$B:$P,10,FALSE()),0) -> 0 | P215: =IFERROR(VLOOKUP("14_"&A215,SyS!$B:$P,12,FALSE()),0) -> 0 | Q215: =+O215-P215 -> 0 | R215: =IFERROR(VLOOKUP("15_"&A215,SyS!$B:$P,10,FALSE()),0) -> 0 | S215: =IFERROR(VLOOKUP("15_"&A215,SyS!$B:$P,12,FALSE()),0) -> 0 | T215: =+R215-S215 -> 0 | U215: =IFERROR(VLOOKUP("16_"&A215,SyS!$B:$P,10,FALSE()),0) -> 0 | V215: =IFERROR(VLOOKUP("16_"&A215,SyS!$B:$P,12,FALSE()),0) -> 0 | W215: =+U215-V215 -> 0 | X215: =IFERROR(VLOOKUP("13_"&A215,SyS!$B:$P,10,FALSE()),0) -> 0 | Y215: =IFERROR(VLOOKUP("13_"&A215,SyS!$B:$P,12,FALSE()),0) -> 0 | Z215: =+X215-Y215 -> 0 | AA215: =IFERROR(VLOOKUP("17_"&A215,SyS!$B:$P,10,FALSE()),0) -> 0 | AB215: =IFERROR(VLOOKUP("17_"&A215,SyS!$B:$P,12,FALSE()),0) -> 0 | AC215: =+AA215-AB215 -> 0 | AG215: =IFERROR(VLOOKUP("19_"&A215,SyS!$B:$P,10,FALSE()),0) -> 0 | AH215: =IFERROR(VLOOKUP("19_"&A215,SyS!$B:$P,12,FALSE()),0) -> 0 | AI215: =+AG215-AH215 -> 0 | AM215: =IFERROR(VLOOKUP("23_"&A215,SyS!$B:$P,10,FALSE()),0) -> 0 | AN215: =IFERROR(VLOOKUP("23_"&A215,SyS!$B:$P,12,FALSE()),0) -> 0 | AO215: =+AM215-AN215 -> 0 | BK215: =IFERROR(VLOOKUP("29_"&A215,SyS!$B:$P,10,FALSE()),0) -> 0 | BL215: =IFERROR(VLOOKUP("29_"&A215,SyS!$B:$P,12,FALSE()),0) -> 0 | BM215: =+BK215-BL215 -> 0 | BN215: =IFERROR(VLOOKUP("30_"&A215,SyS!$B:$P,10,FALSE()),0) -> 0 | BO215: =IFERROR(VLOOKUP("30_"&A215,SyS!$B:$P,12,FALSE()),0) -> 0 | BP215: =+BN215-BO215 -> 0 | BQ215: =+E215+H215+K215+Q215+T215+W215+Z215+AC215+AF215+AI215+AL215+AO215+AR215+AU215+AX215+BA215+BD215+BG215+BJ215+BM215+BP215 -> 0
A216: 426180000 | B216: GST CAMPAMENTO GST CAMPO | C216: =IFERROR(VLOOKUP("1_"&A216,SyS!$B:$P,10,FALSE()),0) -> 0 | D216: =IFERROR(VLOOKUP("1_"&A216,SyS!$B:$P,12,FALSE()),0) -> 0 | E216: =+C216-D216 -> 0 | F216: =IFERROR(VLOOKUP("2_"&A216,SyS!$B:$P,10,FALSE()),0) -> 0 | G216: =IFERROR(VLOOKUP("2_"&A216,SyS!$B:$P,12,FALSE()),0) -> 0 | H216: =+F216-G216 -> 0 | O216: =IFERROR(VLOOKUP("14_"&A216,SyS!$B:$P,10,FALSE()),0) -> 0 | P216: =IFERROR(VLOOKUP("14_"&A216,SyS!$B:$P,12,FALSE()),0) -> 0 | Q216: =+O216-P216 -> 0 | R216: =IFERROR(VLOOKUP("15_"&A216,SyS!$B:$P,10,FALSE()),0) -> 0 | S216: =IFERROR(VLOOKUP("15_"&A216,SyS!$B:$P,12,FALSE()),0) -> 0 | T216: =+R216-S216 -> 0 | U216: =IFERROR(VLOOKUP("16_"&A216,SyS!$B:$P,10,FALSE()),0) -> 0 | V216: =IFERROR(VLOOKUP("16_"&A216,SyS!$B:$P,12,FALSE()),0) -> 0 | W216: =+U216-V216 -> 0 | X216: =IFERROR(VLOOKUP("13_"&A216,SyS!$B:$P,10,FALSE()),0) -> 0 | Y216: =IFERROR(VLOOKUP("13_"&A216,SyS!$B:$P,12,FALSE()),0) -> 0 | Z216: =+X216-Y216 -> 0 | AA216: =IFERROR(VLOOKUP("17_"&A216,SyS!$B:$P,10,FALSE()),0) -> 0 | AB216: =IFERROR(VLOOKUP("17_"&A216,SyS!$B:$P,12,FALSE()),0) -> 0 | AC216: =+AA216-AB216 -> 0 | AG216: =IFERROR(VLOOKUP("19_"&A216,SyS!$B:$P,10,FALSE()),0) -> 0 | AH216: =IFERROR(VLOOKUP("19_"&A216,SyS!$B:$P,12,FALSE()),0) -> 0 | AI216: =+AG216-AH216 -> 0 | AM216: =IFERROR(VLOOKUP("23_"&A216,SyS!$B:$P,10,FALSE()),0) -> 0 | AN216: =IFERROR(VLOOKUP("23_"&A216,SyS!$B:$P,12,FALSE()),0) -> 0 | AO216: =+AM216-AN216 -> 0 | BK216: =IFERROR(VLOOKUP("29_"&A216,SyS!$B:$P,10,FALSE()),0) -> 0 | BL216: =IFERROR(VLOOKUP("29_"&A216,SyS!$B:$P,12,FALSE()),0) -> 0 | BM216: =+BK216-BL216 -> 0 | BN216: =IFERROR(VLOOKUP("30_"&A216,SyS!$B:$P,10,FALSE()),0) -> 0 | BO216: =IFERROR(VLOOKUP("30_"&A216,SyS!$B:$P,12,FALSE()),0) -> 0 | BP216: =+BN216-BO216 -> 0 | BQ216: =+E216+H216+K216+Q216+T216+W216+Z216+AC216+AF216+AI216+AL216+AO216+AR216+AU216+AX216+BA216+BD216+BG216+BJ216+BM216+BP216 -> 0
A217: 426190000 | B217: GST VARIOS OFICINA GST CAMPO | C217: =IFERROR(VLOOKUP("1_"&A217,SyS!$B:$P,10,FALSE()),0) -> 0 | D217: =IFERROR(VLOOKUP("1_"&A217,SyS!$B:$P,12,FALSE()),0) -> 0 | E217: =+C217-D217 -> 0 | F217: =IFERROR(VLOOKUP("2_"&A217,SyS!$B:$P,10,FALSE()),0) -> 0 | G217: =IFERROR(VLOOKUP("2_"&A217,SyS!$B:$P,12,FALSE()),0) -> 0 | H217: =+F217-G217 -> 0 | O217: =IFERROR(VLOOKUP("14_"&A217,SyS!$B:$P,10,FALSE()),0) -> 0 | P217: =IFERROR(VLOOKUP("14_"&A217,SyS!$B:$P,12,FALSE()),0) -> 0 | Q217: =+O217-P217 -> 0 | R217: =IFERROR(VLOOKUP("15_"&A217,SyS!$B:$P,10,FALSE()),0) -> 0 | S217: =IFERROR(VLOOKUP("15_"&A217,SyS!$B:$P,12,FALSE()),0) -> 0 | T217: =+R217-S217 -> 0 | U217: =IFERROR(VLOOKUP("16_"&A217,SyS!$B:$P,10,FALSE()),0) -> 0 | V217: =IFERROR(VLOOKUP("16_"&A217,SyS!$B:$P,12,FALSE()),0) -> 0 | W217: =+U217-V217 -> 0 | X217: =IFERROR(VLOOKUP("13_"&A217,SyS!$B:$P,10,FALSE()),0) -> 0 | Y217: =IFERROR(VLOOKUP("13_"&A217,SyS!$B:$P,12,FALSE()),0) -> 0 | Z217: =+X217-Y217 -> 0 | AA217: =IFERROR(VLOOKUP("17_"&A217,SyS!$B:$P,10,FALSE()),0) -> 0 | AB217: =IFERROR(VLOOKUP("17_"&A217,SyS!$B:$P,12,FALSE()),0) -> 0 | AC217: =+AA217-AB217 -> 0 | AG217: =IFERROR(VLOOKUP("19_"&A217,SyS!$B:$P,10,FALSE()),0) -> 0 | AH217: =IFERROR(VLOOKUP("19_"&A217,SyS!$B:$P,12,FALSE()),0) -> 0 | AI217: =+AG217-AH217 -> 0 | AM217: =IFERROR(VLOOKUP("23_"&A217,SyS!$B:$P,10,FALSE()),0) -> 0 | AN217: =IFERROR(VLOOKUP("23_"&A217,SyS!$B:$P,12,FALSE()),0) -> 0 | AO217: =+AM217-AN217 -> 0 | BK217: =IFERROR(VLOOKUP("29_"&A217,SyS!$B:$P,10,FALSE()),0) -> 0 | BL217: =IFERROR(VLOOKUP("29_"&A217,SyS!$B:$P,12,FALSE()),0) -> 0 | BM217: =+BK217-BL217 -> 0 | BN217: =IFERROR(VLOOKUP("30_"&A217,SyS!$B:$P,10,FALSE()),0) -> 0 | BO217: =IFERROR(VLOOKUP("30_"&A217,SyS!$B:$P,12,FALSE()),0) -> 0 | BP217: =+BN217-BO217 -> 0 | BQ217: =+E217+H217+K217+Q217+T217+W217+Z217+AC217+AF217+AI217+AL217+AO217+AR217+AU217+AX217+BA217+BD217+BG217+BJ217+BM217+BP217 -> 0
A218: 426200000 | B218: COMBUSTIBLE GST CAMPO | C218: =IFERROR(VLOOKUP("1_"&A218,SyS!$B:$P,10,FALSE()),0) -> 0 | D218: =IFERROR(VLOOKUP("1_"&A218,SyS!$B:$P,12,FALSE()),0) -> 0 | E218: =+C218-D218 -> 0 | F218: =IFERROR(VLOOKUP("2_"&A218,SyS!$B:$P,10,FALSE()),0) -> 71.23 | G218: =IFERROR(VLOOKUP("2_"&A218,SyS!$B:$P,12,FALSE()),0) -> 0 | H218: =+F218-G218 -> 71.23 | O218: =IFERROR(VLOOKUP("14_"&A218,SyS!$B:$P,10,FALSE()),0) -> 0 | P218: =IFERROR(VLOOKUP("14_"&A218,SyS!$B:$P,12,FALSE()),0) -> 0 | Q218: =+O218-P218 -> 0 | R218: =IFERROR(VLOOKUP("15_"&A218,SyS!$B:$P,10,FALSE()),0) -> 0 | S218: =IFERROR(VLOOKUP("15_"&A218,SyS!$B:$P,12,FALSE()),0) -> 0 | T218: =+R218-S218 -> 0 | U218: =IFERROR(VLOOKUP("16_"&A218,SyS!$B:$P,10,FALSE()),0) -> 0 | V218: =IFERROR(VLOOKUP("16_"&A218,SyS!$B:$P,12,FALSE()),0) -> 0 | W218: =+U218-V218 -> 0 | X218: =IFERROR(VLOOKUP("13_"&A218,SyS!$B:$P,10,FALSE()),0) -> 0 | Y218: =IFERROR(VLOOKUP("13_"&A218,SyS!$B:$P,12,FALSE()),0) -> 0 | Z218: =+X218-Y218 -> 0 | AA218: =IFERROR(VLOOKUP("17_"&A218,SyS!$B:$P,10,FALSE()),0) -> 657.97 | AB218: =IFERROR(VLOOKUP("17_"&A218,SyS!$B:$P,12,FALSE()),0) -> 0 | AC218: =+AA218-AB218 -> 657.97 | AG218: =IFERROR(VLOOKUP("19_"&A218,SyS!$B:$P,10,FALSE()),0) -> 0 | AH218: =IFERROR(VLOOKUP("19_"&A218,SyS!$B:$P,12,FALSE()),0) -> 0 | AI218: =+AG218-AH218 -> 0 | AM218: =IFERROR(VLOOKUP("23_"&A218,SyS!$B:$P,10,FALSE()),0) -> 0 | AN218: =IFERROR(VLOOKUP("23_"&A218,SyS!$B:$P,12,FALSE()),0) -> 0 | AO218: =+AM218-AN218 -> 0 | BK218: =IFERROR(VLOOKUP("29_"&A218,SyS!$B:$P,10,FALSE()),0) -> 0 | BL218: =IFERROR(VLOOKUP("29_"&A218,SyS!$B:$P,12,FALSE()),0) -> 0 | BM218: =+BK218-BL218 -> 0 | BN218: =IFERROR(VLOOKUP("30_"&A218,SyS!$B:$P,10,FALSE()),0) -> 0 | BO218: =IFERROR(VLOOKUP("30_"&A218,SyS!$B:$P,12,FALSE()),0) -> 0 | BP218: =+BN218-BO218 -> 0 | BQ218: =+E218+H218+K218+Q218+T218+W218+Z218+AC218+AF218+AI218+AL218+AO218+AR218+AU218+AX218+BA218+BD218+BG218+BJ218+BM218+BP218 -> 729.2
A219: 426210000 | B219: SERVICIOS INFORMATICOS GST. CAMPO | C219: =IFERROR(VLOOKUP("1_"&A219,SyS!$B:$P,10,FALSE()),0) -> 0 | D219: =IFERROR(VLOOKUP("1_"&A219,SyS!$B:$P,12,FALSE()),0) -> 0 | E219: =+C219-D219 -> 0 | F219: =IFERROR(VLOOKUP("2_"&A219,SyS!$B:$P,10,FALSE()),0) -> 1767.88 | G219: =IFERROR(VLOOKUP("2_"&A219,SyS!$B:$P,12,FALSE()),0) -> 0 | H219: =+F219-G219 -> 1767.88 | O219: =IFERROR(VLOOKUP("14_"&A219,SyS!$B:$P,10,FALSE()),0) -> 0 | P219: =IFERROR(VLOOKUP("14_"&A219,SyS!$B:$P,12,FALSE()),0) -> 0 | Q219: =+O219-P219 -> 0 | R219: =IFERROR(VLOOKUP("15_"&A219,SyS!$B:$P,10,FALSE()),0) -> 0 | S219: =IFERROR(VLOOKUP("15_"&A219,SyS!$B:$P,12,FALSE()),0) -> 0 | T219: =+R219-S219 -> 0 | U219: =IFERROR(VLOOKUP("16_"&A219,SyS!$B:$P,10,FALSE()),0) -> 0 | V219: =IFERROR(VLOOKUP("16_"&A219,SyS!$B:$P,12,FALSE()),0) -> 0 | W219: =+U219-V219 -> 0 | X219: =IFERROR(VLOOKUP("13_"&A219,SyS!$B:$P,10,FALSE()),0) -> 0 | Y219: =IFERROR(VLOOKUP("13_"&A219,SyS!$B:$P,12,FALSE()),0) -> 0 | Z219: =+X219-Y219 -> 0 | AA219: =IFERROR(VLOOKUP("17_"&A219,SyS!$B:$P,10,FALSE()),0) -> 0 | AB219: =IFERROR(VLOOKUP("17_"&A219,SyS!$B:$P,12,FALSE()),0) -> 0 | AC219: =+AA219-AB219 -> 0 | AG219: =IFERROR(VLOOKUP("19_"&A219,SyS!$B:$P,10,FALSE()),0) -> 0 | AH219: =IFERROR(VLOOKUP("19_"&A219,SyS!$B:$P,12,FALSE()),0) -> 0 | AI219: =+AG219-AH219 -> 0 | AM219: =IFERROR(VLOOKUP("23_"&A219,SyS!$B:$P,10,FALSE()),0) -> 0 | AN219: =IFERROR(VLOOKUP("23_"&A219,SyS!$B:$P,12,FALSE()),0) -> 0 | AO219: =+AM219-AN219 -> 0 | BK219: =IFERROR(VLOOKUP("29_"&A219,SyS!$B:$P,10,FALSE()),0) -> 0 | BL219: =IFERROR(VLOOKUP("29_"&A219,SyS!$B:$P,12,FALSE()),0) -> 0 | BM219: =+BK219-BL219 -> 0 | BN219: =IFERROR(VLOOKUP("30_"&A219,SyS!$B:$P,10,FALSE()),0) -> 0 | BO219: =IFERROR(VLOOKUP("30_"&A219,SyS!$B:$P,12,FALSE()),0) -> 0 | BP219: =+BN219-BO219 -> 0 | BQ219: =+E219+H219+K219+Q219+T219+W219+Z219+AC219+AF219+AI219+AL219+AO219+AR219+AU219+AX219+BA219+BD219+BG219+BJ219+BM219+BP219 -> 1767.88
A220: 426220000 | B220: ALQUILER INMUEBLE GST CAMPO | C220: =IFERROR(VLOOKUP("1_"&A220,SyS!$B:$P,10,FALSE()),0) -> 0 | D220: =IFERROR(VLOOKUP("1_"&A220,SyS!$B:$P,12,FALSE()),0) -> 0 | E220: =+C220-D220 -> 0 | F220: =IFERROR(VLOOKUP("2_"&A220,SyS!$B:$P,10,FALSE()),0) -> 4896.38 | G220: =IFERROR(VLOOKUP("2_"&A220,SyS!$B:$P,12,FALSE()),0) -> 0 | H220: =+F220-G220 -> 4896.38 | O220: =IFERROR(VLOOKUP("14_"&A220,SyS!$B:$P,10,FALSE()),0) -> 0 | P220: =IFERROR(VLOOKUP("14_"&A220,SyS!$B:$P,12,FALSE()),0) -> 0 | Q220: =+O220-P220 -> 0 | R220: =IFERROR(VLOOKUP("15_"&A220,SyS!$B:$P,10,FALSE()),0) -> 0 | S220: =IFERROR(VLOOKUP("15_"&A220,SyS!$B:$P,12,FALSE()),0) -> 0 | T220: =+R220-S220 -> 0 | U220: =IFERROR(VLOOKUP("16_"&A220,SyS!$B:$P,10,FALSE()),0) -> 0 | V220: =IFERROR(VLOOKUP("16_"&A220,SyS!$B:$P,12,FALSE()),0) -> 0 | W220: =+U220-V220 -> 0 | X220: =IFERROR(VLOOKUP("13_"&A220,SyS!$B:$P,10,FALSE()),0) -> 0 | Y220: =IFERROR(VLOOKUP("13_"&A220,SyS!$B:$P,12,FALSE()),0) -> 0 | Z220: =+X220-Y220 -> 0 | AA220: =IFERROR(VLOOKUP("17_"&A220,SyS!$B:$P,10,FALSE()),0) -> 807.88 | AB220: =IFERROR(VLOOKUP("17_"&A220,SyS!$B:$P,12,FALSE()),0) -> 0 | AC220: =+AA220-AB220 -> 807.88 | AG220: =IFERROR(VLOOKUP("19_"&A220,SyS!$B:$P,10,FALSE()),0) -> 0 | AH220: =IFERROR(VLOOKUP("19_"&A220,SyS!$B:$P,12,FALSE()),0) -> 0 | AI220: =+AG220-AH220 -> 0 | AM220: =IFERROR(VLOOKUP("23_"&A220,SyS!$B:$P,10,FALSE()),0) -> 0 | AN220: =IFERROR(VLOOKUP("23_"&A220,SyS!$B:$P,12,FALSE()),0) -> 0 | AO220: =+AM220-AN220 -> 0 | BK220: =IFERROR(VLOOKUP("29_"&A220,SyS!$B:$P,10,FALSE()),0) -> 0 | BL220: =IFERROR(VLOOKUP("29_"&A220,SyS!$B:$P,12,FALSE()),0) -> 0 | BM220: =+BK220-BL220 -> 0 | BN220: =IFERROR(VLOOKUP("30_"&A220,SyS!$B:$P,10,FALSE()),0) -> 0 | BO220: =IFERROR(VLOOKUP("30_"&A220,SyS!$B:$P,12,FALSE()),0) -> 0 | BP220: =+BN220-BO220 -> 0 | BQ220: =+E220+H220+K220+Q220+T220+W220+Z220+AC220+AF220+AI220+AL220+AO220+AR220+AU220+AX220+BA220+BD220+BG220+BJ220+BM220+BP220 -> 5704.26
A221: 426230000 | B221: MENSAJERIA GST CAMPO | C221: =IFERROR(VLOOKUP("1_"&A221,SyS!$B:$P,10,FALSE()),0) -> 0 | D221: =IFERROR(VLOOKUP("1_"&A221,SyS!$B:$P,12,FALSE()),0) -> 0 | E221: =+C221-D221 -> 0 | F221: =IFERROR(VLOOKUP("2_"&A221,SyS!$B:$P,10,FALSE()),0) -> 0 | G221: =IFERROR(VLOOKUP("2_"&A221,SyS!$B:$P,12,FALSE()),0) -> 0 | H221: =+F221-G221 -> 0 | O221: =IFERROR(VLOOKUP("14_"&A221,SyS!$B:$P,10,FALSE()),0) -> 0 | P221: =IFERROR(VLOOKUP("14_"&A221,SyS!$B:$P,12,FALSE()),0) -> 0 | Q221: =+O221-P221 -> 0 | R221: =IFERROR(VLOOKUP("15_"&A221,SyS!$B:$P,10,FALSE()),0) -> 0 | S221: =IFERROR(VLOOKUP("15_"&A221,SyS!$B:$P,12,FALSE()),0) -> 0 | T221: =+R221-S221 -> 0 | U221: =IFERROR(VLOOKUP("16_"&A221,SyS!$B:$P,10,FALSE()),0) -> 0 | V221: =IFERROR(VLOOKUP("16_"&A221,SyS!$B:$P,12,FALSE()),0) -> 0 | W221: =+U221-V221 -> 0 | X221: =IFERROR(VLOOKUP("13_"&A221,SyS!$B:$P,10,FALSE()),0) -> 0 | Y221: =IFERROR(VLOOKUP("13_"&A221,SyS!$B:$P,12,FALSE()),0) -> 0 | Z221: =+X221-Y221 -> 0 | AA221: =IFERROR(VLOOKUP("17_"&A221,SyS!$B:$P,10,FALSE()),0) -> 0 | AB221: =IFERROR(VLOOKUP("17_"&A221,SyS!$B:$P,12,FALSE()),0) -> 0 | AC221: =+AA221-AB221 -> 0 | AG221: =IFERROR(VLOOKUP("19_"&A221,SyS!$B:$P,10,FALSE()),0) -> 0 | AH221: =IFERROR(VLOOKUP("19_"&A221,SyS!$B:$P,12,FALSE()),0) -> 0 | AI221: =+AG221-AH221 -> 0 | AM221: =IFERROR(VLOOKUP("23_"&A221,SyS!$B:$P,10,FALSE()),0) -> 0 | AN221: =IFERROR(VLOOKUP("23_"&A221,SyS!$B:$P,12,FALSE()),0) -> 0 | AO221: =+AM221-AN221 -> 0 | BK221: =IFERROR(VLOOKUP("29_"&A221,SyS!$B:$P,10,FALSE()),0) -> 0 | BL221: =IFERROR(VLOOKUP("29_"&A221,SyS!$B:$P,12,FALSE()),0) -> 0 | BM221: =+BK221-BL221 -> 0 | BN221: =IFERROR(VLOOKUP("30_"&A221,SyS!$B:$P,10,FALSE()),0) -> 0 | BO221: =IFERROR(VLOOKUP("30_"&A221,SyS!$B:$P,12,FALSE()),0) -> 0 | BP221: =+BN221-BO221 -> 0 | BQ221: =+E221+H221+K221+Q221+T221+W221+Z221+AC221+AF221+AI221+AL221+AO221+AR221+AU221+AX221+BA221+BD221+BG221+BJ221+BM221+BP221 -> 0
... A313: 426880000 | B313: Tasas Municipales Gs Campo | C313: =IFERROR(VLOOKUP("1_"&A313,SyS!$B:$P,10,FALSE()),0) -> 0 | D313: =IFERROR(VLOOKUP("1_"&A313,SyS!$B:$P,12,FALSE()),0) -> 0 | E313: =+C313-D313 -> 0 | F313: =IFERROR(VLOOKUP("2_"&A313,SyS!$B:$P,10,FALSE()),0) -> 0 | G313: =IFERROR(VLOOKUP("2_"&A313,SyS!$B:$P,12,FALSE()),0) -> 0 | H313: =+F313-G313 -> 0 | O313: =IFERROR(VLOOKUP("14_"&A313,SyS!$B:$P,10,FALSE()),0) -> 0 | P313: =IFERROR(VLOOKUP("14_"&A313,SyS!$B:$P,12,FALSE()),0) -> 0 | Q313: =+O313-P313 -> 0 | R313: =IFERROR(VLOOKUP("15_"&A313,SyS!$B:$P,10,FALSE()),0) -> 0 | S313: =IFERROR(VLOOKUP("15_"&A313,SyS!$B:$P,12,FALSE()),0) -> 0 | T313: =+R313-S313 -> 0 | U313: =IFERROR(VLOOKUP("16_"&A313,SyS!$B:$P,10,FALSE()),0) -> 0 | V313: =IFERROR(VLOOKUP("16_"&A313,SyS!$B:$P,12,FALSE()),0) -> 0 | W313: =+U313-V313 -> 0 | X313: =IFERROR(VLOOKUP("13_"&A313,SyS!$B:$P,10,FALSE()),0) -> 0 | Y313: =IFERROR(VLOOKUP("13_"&A313,SyS!$B:$P,12,FALSE()),0) -> 0 | Z313: =+X313-Y313 -> 0 | AA313: =IFERROR(VLOOKUP("17_"&A313,SyS!$B:$P,10,FALSE()),0) -> 0 | AB313: =IFERROR(VLOOKUP("17_"&A313,SyS!$B:$P,12,FALSE()),0) -> 0 | AC313: =+AA313-AB313 -> 0 | AG313: =IFERROR(VLOOKUP("19_"&A313,SyS!$B:$P,10,FALSE()),0) -> 0 | AH313: =IFERROR(VLOOKUP("19_"&A313,SyS!$B:$P,12,FALSE()),0) -> 0 | AI313: =+AG313-AH313 -> 0 | AM313: =IFERROR(VLOOKUP("23_"&A313,SyS!$B:$P,10,FALSE()),0) -> 0 | AN313: =IFERROR(VLOOKUP("23_"&A313,SyS!$B:$P,12,FALSE()),0) -> 0 | AO313: =+AM313-AN313 -> 0 | BK313: =IFERROR(VLOOKUP("29_"&A313,SyS!$B:$P,10,FALSE()),0) -> 0 | BL313: =IFERROR(VLOOKUP("29_"&A313,SyS!$B:$P,12,FALSE()),0) -> 0 | BM313: =+BK313-BL313 -> 0 | BN313: =IFERROR(VLOOKUP("30_"&A313,SyS!$B:$P,10,FALSE()),0) -> 0 | BO313: =IFERROR(VLOOKUP("30_"&A313,SyS!$B:$P,12,FALSE()),0) -> 0 | BP313: =+BN313-BO313 -> 0 | BQ313: =+E313+H313+K313+Q313+T313+W313+Z313+AC313+AF313+AI313+AL313+AO313+AR313+AU313+AX313+BA313+BD313+BG313+BJ313+BM313+BP313 -> 0
B314: RELACIONES COMUNITARIAS | AG314: =IFERROR(VLOOKUP("19_"&A314,SyS!$B:$P,10,FALSE()),0) -> 0 | AH314: =IFERROR(VLOOKUP("19_"&A314,SyS!$B:$P,12,FALSE()),0) -> 0 | AI314: =+AG314-AH314 -> 0
A315: 427110000 | B315: MOVILIDAD Y VIATICOS REL. COMUNITARIAS | C315: =IFERROR(VLOOKUP("1_"&A315,SyS!$B:$P,10,FALSE()),0) -> 0 | D315: =IFERROR(VLOOKUP("1_"&A315,SyS!$B:$P,12,FALSE()),0) -> 0 | E315: =+C315-D315 -> 0 | F315: =IFERROR(VLOOKUP("2_"&A315,SyS!$B:$P,10,FALSE()),0) -> 0 | G315: =IFERROR(VLOOKUP("2_"&A315,SyS!$B:$P,12,FALSE()),0) -> 0 | H315: =+F315-G315 -> 0 | O315: =IFERROR(VLOOKUP("14_"&A315,SyS!$B:$P,10,FALSE()),0) -> 0 | P315: =IFERROR(VLOOKUP("14_"&A315,SyS!$B:$P,12,FALSE()),0) -> 0 | Q315: =+O315-P315 -> 0 | R315: =IFERROR(VLOOKUP("15_"&A315,SyS!$B:$P,10,FALSE()),0) -> 0 | S315: =IFERROR(VLOOKUP("15_"&A315,SyS!$B:$P,12,FALSE()),0) -> 0 | T315: =+R315-S315 -> 0 | U315: =IFERROR(VLOOKUP("16_"&A315,SyS!$B:$P,10,FALSE()),0) -> 0 | V315: =IFERROR(VLOOKUP("16_"&A315,SyS!$B:$P,12,FALSE()),0) -> 0 | W315: =+U315-V315 -> 0 | X315: =IFERROR(VLOOKUP("13_"&A315,SyS!$B:$P,10,FALSE()),0) -> 0 | Y315: =IFERROR(VLOOKUP("13_"&A315,SyS!$B:$P,12,FALSE()),0) -> 0 | Z315: =+X315-Y315 -> 0 | AA315: =IFERROR(VLOOKUP("17_"&A315,SyS!$B:$P,10,FALSE()),0) -> 0 | AB315: =IFERROR(VLOOKUP("17_"&A315,SyS!$B:$P,12,FALSE()),0) -> 0 | AC315: =+AA315-AB315 -> 0 | AG315: =IFERROR(VLOOKUP("19_"&A315,SyS!$B:$P,10,FALSE()),0) -> 0 | AH315: =IFERROR(VLOOKUP("19_"&A315,SyS!$B:$P,12,FALSE()),0) -> 0 | AI315: =+AG315-AH315 -> 0 | AM315: =IFERROR(VLOOKUP("23_"&A315,SyS!$B:$P,10,FALSE()),0) -> 0 | AN315: =IFERROR(VLOOKUP("23_"&A315,SyS!$B:$P,12,FALSE()),0) -> 0 | AO315: =+AM315-AN315 -> 0 | BK315: =IFERROR(VLOOKUP("29_"&A315,SyS!$B:$P,10,FALSE()),0) -> 0 | BL315: =IFERROR(VLOOKUP("29_"&A315,SyS!$B:$P,12,FALSE()),0) -> 0 | BM315: =+BK315-BL315 -> 0 | BN315: =IFERROR(VLOOKUP("30_"&A315,SyS!$B:$P,10,FALSE()),0) -> 0 | BO315: =IFERROR(VLOOKUP("30_"&A315,SyS!$B:$P,12,FALSE()),0) -> 0 | BP315: =+BN315-BO315 -> 0 | BQ315: =+E315+H315+K315+Q315+T315+W315+Z315+AC315+AF315+AI315+AL315+AO315+AR315+AU315+AX315+BA315+BD315+BG315+BJ315+BM315+BP315 -> 0
A316: 427120000 | B316: REFRIGERIOS REL. COMUNITARIAS | C316: =IFERROR(VLOOKUP("1_"&A316,SyS!$B:$P,10,FALSE()),0) -> 0 | D316: =IFERROR(VLOOKUP("1_"&A316,SyS!$B:$P,12,FALSE()),0) -> 0 | E316: =+C316-D316 -> 0 | F316: =IFERROR(VLOOKUP("2_"&A316,SyS!$B:$P,10,FALSE()),0) -> 0 | G316: =IFERROR(VLOOKUP("2_"&A316,SyS!$B:$P,12,FALSE()),0) -> 0 | H316: =+F316-G316 -> 0 | O316: =IFERROR(VLOOKUP("14_"&A316,SyS!$B:$P,10,FALSE()),0) -> 0 | P316: =IFERROR(VLOOKUP("14_"&A316,SyS!$B:$P,12,FALSE()),0) -> 0 | Q316: =+O316-P316 -> 0 | R316: =IFERROR(VLOOKUP("15_"&A316,SyS!$B:$P,10,FALSE()),0) -> 0 | S316: =IFERROR(VLOOKUP("15_"&A316,SyS!$B:$P,12,FALSE()),0) -> 0 | T316: =+R316-S316 -> 0 | U316: =IFERROR(VLOOKUP("16_"&A316,SyS!$B:$P,10,FALSE()),0) -> 0 | V316: =IFERROR(VLOOKUP("16_"&A316,SyS!$B:$P,12,FALSE()),0) -> 0 | W316: =+U316-V316 -> 0 | X316: =IFERROR(VLOOKUP("13_"&A316,SyS!$B:$P,10,FALSE()),0) -> 0 | Y316: =IFERROR(VLOOKUP("13_"&A316,SyS!$B:$P,12,FALSE()),0) -> 0 | Z316: =+X316-Y316 -> 0 | AA316: =IFERROR(VLOOKUP("17_"&A316,SyS!$B:$P,10,FALSE()),0) -> 0 | AB316: =IFERROR(VLOOKUP("17_"&A316,SyS!$B:$P,12,FALSE()),0) -> 0 | AC316: =+AA316-AB316 -> 0 | AG316: =IFERROR(VLOOKUP("19_"&A316,SyS!$B:$P,10,FALSE()),0) -> 0 | AH316: =IFERROR(VLOOKUP("19_"&A316,SyS!$B:$P,12,FALSE()),0) -> 0 | AI316: =+AG316-AH316 -> 0 | AM316: =IFERROR(VLOOKUP("23_"&A316,SyS!$B:$P,10,FALSE()),0) -> 0 | AN316: =IFERROR(VLOOKUP("23_"&A316,SyS!$B:$P,12,FALSE()),0) -> 0 | AO316: =+AM316-AN316 -> 0 | BK316: =IFERROR(VLOOKUP("29_"&A316,SyS!$B:$P,10,FALSE()),0) -> 0 | BL316: =IFERROR(VLOOKUP("29_"&A316,SyS!$B:$P,12,FALSE()),0) -> 0 | BM316: =+BK316-BL316 -> 0 | BN316: =IFERROR(VLOOKUP("30_"&A316,SyS!$B:$P,10,FALSE()),0) -> 0 | BO316: =IFERROR(VLOOKUP("30_"&A316,SyS!$B:$P,12,FALSE()),0) -> 0 | BP316: =+BN316-BO316 -> 0 | BQ316: =+E316+H316+K316+Q316+T316+W316+Z316+AC316+AF316+AI316+AL316+AO316+AR316+AU316+AX316+BA316+BD316+BG316+BJ316+BM316+BP316 -> 0
A317: 427140000 | B317: GASTOS DE LIMPIEZA REL. COMUNITARIAS | C317: =IFERROR(VLOOKUP("1_"&A317,SyS!$B:$P,10,FALSE()),0) -> 0 | D317: =IFERROR(VLOOKUP("1_"&A317,SyS!$B:$P,12,FALSE()),0) -> 0 | E317: =+C317-D317 -> 0 | F317: =IFERROR(VLOOKUP("2_"&A317,SyS!$B:$P,10,FALSE()),0) -> 0 | G317: =IFERROR(VLOOKUP("2_"&A317,SyS!$B:$P,12,FALSE()),0) -> 0 | H317: =+F317-G317 -> 0 | O317: =IFERROR(VLOOKUP("14_"&A317,SyS!$B:$P,10,FALSE()),0) -> 0 | P317: =IFERROR(VLOOKUP("14_"&A317,SyS!$B:$P,12,FALSE()),0) -> 0 | Q317: =+O317-P317 -> 0 | R317: =IFERROR(VLOOKUP("15_"&A317,SyS!$B:$P,10,FALSE()),0) -> 0 | S317: =IFERROR(VLOOKUP("15_"&A317,SyS!$B:$P,12,FALSE()),0) -> 0 | T317: =+R317-S317 -> 0 | U317: =IFERROR(VLOOKUP("16_"&A317,SyS!$B:$P,10,FALSE()),0) -> 0 | V317: =IFERROR(VLOOKUP("16_"&A317,SyS!$B:$P,12,FALSE()),0) -> 0 | W317: =+U317-V317 -> 0 | X317: =IFERROR(VLOOKUP("13_"&A317,SyS!$B:$P,10,FALSE()),0) -> 0 | Y317: =IFERROR(VLOOKUP("13_"&A317,SyS!$B:$P,12,FALSE()),0) -> 0 | Z317: =+X317-Y317 -> 0 | AA317: =IFERROR(VLOOKUP("17_"&A317,SyS!$B:$P,10,FALSE()),0) -> 0 | AB317: =IFERROR(VLOOKUP("17_"&A317,SyS!$B:$P,12,FALSE()),0) -> 0 | AC317: =+AA317-AB317 -> 0 | AG317: =IFERROR(VLOOKUP("19_"&A317,SyS!$B:$P,10,FALSE()),0) -> 0 | AH317: =IFERROR(VLOOKUP("19_"&A317,SyS!$B:$P,12,FALSE()),0) -> 0 | AI317: =+AG317-AH317 -> 0 | AM317: =IFERROR(VLOOKUP("23_"&A317,SyS!$B:$P,10,FALSE()),0) -> 0 | AN317: =IFERROR(VLOOKUP("23_"&A317,SyS!$B:$P,12,FALSE()),0) -> 0 | AO317: =+AM317-AN317 -> 0 | BK317: =IFERROR(VLOOKUP("29_"&A317,SyS!$B:$P,10,FALSE()),0) -> 0 | BL317: =IFERROR(VLOOKUP("29_"&A317,SyS!$B:$P,12,FALSE()),0) -> 0 | BM317: =+BK317-BL317 -> 0 | BN317: =IFERROR(VLOOKUP("30_"&A317,SyS!$B:$P,10,FALSE()),0) -> 0 | BO317: =IFERROR(VLOOKUP("30_"&A317,SyS!$B:$P,12,FALSE()),0) -> 0 | BP317: =+BN317-BO317 -> 0 | BQ317: =+E317+H317+K317+Q317+T317+W317+Z317+AC317+AF317+AI317+AL317+AO317+AR317+AU317+AX317+BA317+BD317+BG317+BJ317+BM317+BP317 -> 0
A318: 427150000 | B318: ALQUILER VEHICULOS REL. COMUNITARIAS | C318: =IFERROR(VLOOKUP("1_"&A318,SyS!$B:$P,10,FALSE()),0) -> 0 | D318: =IFERROR(VLOOKUP("1_"&A318,SyS!$B:$P,12,FALSE()),0) -> 0 | E318: =+C318-D318 -> 0 | F318: =IFERROR(VLOOKUP("2_"&A318,SyS!$B:$P,10,FALSE()),0) -> 0 | G318: =IFERROR(VLOOKUP("2_"&A318,SyS!$B:$P,12,FALSE()),0) -> 0 | H318: =+F318-G318 -> 0 | O318: =IFERROR(VLOOKUP("14_"&A318,SyS!$B:$P,10,FALSE()),0) -> 0 | P318: =IFERROR(VLOOKUP("14_"&A318,SyS!$B:$P,12,FALSE()),0) -> 0 | Q318: =+O318-P318 -> 0 | R318: =IFERROR(VLOOKUP("15_"&A318,SyS!$B:$P,10,FALSE()),0) -> 0 | S318: =IFERROR(VLOOKUP("15_"&A318,SyS!$B:$P,12,FALSE()),0) -> 0 | T318: =+R318-S318 -> 0 | U318: =IFERROR(VLOOKUP("16_"&A318,SyS!$B:$P,10,FALSE()),0) -> 0 | V318: =IFERROR(VLOOKUP("16_"&A318,SyS!$B:$P,12,FALSE()),0) -> 0 | W318: =+U318-V318 -> 0 | X318: =IFERROR(VLOOKUP("13_"&A318,SyS!$B:$P,10,FALSE()),0) -> 0 | Y318: =IFERROR(VLOOKUP("13_"&A318,SyS!$B:$P,12,FALSE()),0) -> 0 | Z318: =+X318-Y318 -> 0 | AA318: =IFERROR(VLOOKUP("17_"&A318,SyS!$B:$P,10,FALSE()),0) -> 0 | AB318: =IFERROR(VLOOKUP("17_"&A318,SyS!$B:$P,12,FALSE()),0) -> 0 | AC318: =+AA318-AB318 -> 0 | AG318: =IFERROR(VLOOKUP("19_"&A318,SyS!$B:$P,10,FALSE()),0) -> 0 | AH318: =IFERROR(VLOOKUP("19_"&A318,SyS!$B:$P,12,FALSE()),0) -> 0 | AI318: =+AG318-AH318 -> 0 | AM318: =IFERROR(VLOOKUP("23_"&A318,SyS!$B:$P,10,FALSE()),0) -> 0 | AN318: =IFERROR(VLOOKUP("23_"&A318,SyS!$B:$P,12,FALSE()),0) -> 0 | AO318: =+AM318-AN318 -> 0 | BK318: =IFERROR(VLOOKUP("29_"&A318,SyS!$B:$P,10,FALSE()),0) -> 0 | BL318: =IFERROR(VLOOKUP("29_"&A318,SyS!$B:$P,12,FALSE()),0) -> 0 | BM318: =+BK318-BL318 -> 0 | BN318: =IFERROR(VLOOKUP("30_"&A318,SyS!$B:$P,10,FALSE()),0) -> 0 | BO318: =IFERROR(VLOOKUP("30_"&A318,SyS!$B:$P,12,FALSE()),0) -> 0 | BP318: =+BN318-BO318 -> 0 | BQ318: =+E318+H318+K318+Q318+T318+W318+Z318+AC318+AF318+AI318+AL318+AO318+AR318+AU318+AX318+BA318+BD318+BG318+BJ318+BM318+BP318 -> 0
A319: 427160000 | B319: GASTOS Y COMISIONES BANCARIAS REL. COMUNITARIAS | C319: =IFERROR(VLOOKUP("1_"&A319,SyS!$B:$P,10,FALSE()),0) -> 0 | D319: =IFERROR(VLOOKUP("1_"&A319,SyS!$B:$P,12,FALSE()),0) -> 0 | E319: =+C319-D319 -> 0 | F319: =IFERROR(VLOOKUP("2_"&A319,SyS!$B:$P,10,FALSE()),0) -> 0 | G319: =IFERROR(VLOOKUP("2_"&A319,SyS!$B:$P,12,FALSE()),0) -> 0 | H319: =+F319-G319 -> 0 | O319: =IFERROR(VLOOKUP("14_"&A319,SyS!$B:$P,10,FALSE()),0) -> 0 | P319: =IFERROR(VLOOKUP("14_"&A319,SyS!$B:$P,12,FALSE()),0) -> 0 | Q319: =+O319-P319 -> 0 | R319: =IFERROR(VLOOKUP("15_"&A319,SyS!$B:$P,10,FALSE()),0) -> 0 | S319: =IFERROR(VLOOKUP("15_"&A319,SyS!$B:$P,12,FALSE()),0) -> 0 | T319: =+R319-S319 -> 0 | U319: =IFERROR(VLOOKUP("16_"&A319,SyS!$B:$P,10,FALSE()),0) -> 0 | V319: =IFERROR(VLOOKUP("16_"&A319,SyS!$B:$P,12,FALSE()),0) -> 0 | W319: =+U319-V319 -> 0 | X319: =IFERROR(VLOOKUP("13_"&A319,SyS!$B:$P,10,FALSE()),0) -> 0 | Y319: =IFERROR(VLOOKUP("13_"&A319,SyS!$B:$P,12,FALSE()),0) -> 0 | Z319: =+X319-Y319 -> 0 | AA319: =IFERROR(VLOOKUP("17_"&A319,SyS!$B:$P,10,FALSE()),0) -> 0 | AB319: =IFERROR(VLOOKUP("17_"&A319,SyS!$B:$P,12,FALSE()),0) -> 0 | AC319: =+AA319-AB319 -> 0 | AG319: =IFERROR(VLOOKUP("19_"&A319,SyS!$B:$P,10,FALSE()),0) -> 0 | AH319: =IFERROR(VLOOKUP("19_"&A319,SyS!$B:$P,12,FALSE()),0) -> 0 | AI319: =+AG319-AH319 -> 0 | AM319: =IFERROR(VLOOKUP("23_"&A319,SyS!$B:$P,10,FALSE()),0) -> 0 | AN319: =IFERROR(VLOOKUP("23_"&A319,SyS!$B:$P,12,FALSE()),0) -> 0 | AO319: =+AM319-AN319 -> 0 | BK319: =IFERROR(VLOOKUP("29_"&A319,SyS!$B:$P,10,FALSE()),0) -> 0 | BL319: =IFERROR(VLOOKUP("29_"&A319,SyS!$B:$P,12,FALSE()),0) -> 0 | BM319: =+BK319-BL319 -> 0 | BN319: =IFERROR(VLOOKUP("30_"&A319,SyS!$B:$P,10,FALSE()),0) -> 0 | BO319: =IFERROR(VLOOKUP("30_"&A319,SyS!$B:$P,12,FALSE()),0) -> 0 | BP319: =+BN319-BO319 -> 0 | BQ319: =+E319+H319+K319+Q319+T319+W319+Z319+AC319+AF319+AI319+AL319+AO319+AR319+AU319+AX319+BA319+BD319+BG319+BJ319+BM319+BP319 -> 0
A320: 427170000 | B320: COMBUSTIBLE REL. COMUNITARIAS | C320: =IFERROR(VLOOKUP("1_"&A320,SyS!$B:$P,10,FALSE()),0) -> 0 | D320: =IFERROR(VLOOKUP("1_"&A320,SyS!$B:$P,12,FALSE()),0) -> 0 | E320: =+C320-D320 -> 0 | F320: =IFERROR(VLOOKUP("2_"&A320,SyS!$B:$P,10,FALSE()),0) -> 0 | G320: =IFERROR(VLOOKUP("2_"&A320,SyS!$B:$P,12,FALSE()),0) -> 0 | H320: =+F320-G320 -> 0 | O320: =IFERROR(VLOOKUP("14_"&A320,SyS!$B:$P,10,FALSE()),0) -> 0 | P320: =IFERROR(VLOOKUP("14_"&A320,SyS!$B:$P,12,FALSE()),0) -> 0 | Q320: =+O320-P320 -> 0 | R320: =IFERROR(VLOOKUP("15_"&A320,SyS!$B:$P,10,FALSE()),0) -> 0 | S320: =IFERROR(VLOOKUP("15_"&A320,SyS!$B:$P,12,FALSE()),0) -> 0 | T320: =+R320-S320 -> 0 | U320: =IFERROR(VLOOKUP("16_"&A320,SyS!$B:$P,10,FALSE()),0) -> 0 | V320: =IFERROR(VLOOKUP("16_"&A320,SyS!$B:$P,12,FALSE()),0) -> 0 | W320: =+U320-V320 -> 0 | X320: =IFERROR(VLOOKUP("13_"&A320,SyS!$B:$P,10,FALSE()),0) -> 0 | Y320: =IFERROR(VLOOKUP("13_"&A320,SyS!$B:$P,12,FALSE()),0) -> 0 | Z320: =+X320-Y320 -> 0 | AA320: =IFERROR(VLOOKUP("17_"&A320,SyS!$B:$P,10,FALSE()),0) -> 0 | AB320: =IFERROR(VLOOKUP("17_"&A320,SyS!$B:$P,12,FALSE()),0) -> 0 | AC320: =+AA320-AB320 -> 0 | AG320: =IFERROR(VLOOKUP("19_"&A320,SyS!$B:$P,10,FALSE()),0) -> 0 | AH320: =IFERROR(VLOOKUP("19_"&A320,SyS!$B:$P,12,FALSE()),0) -> 0 | AI320: =+AG320-AH320 -> 0 | AM320: =IFERROR(VLOOKUP("23_"&A320,SyS!$B:$P,10,FALSE()),0) -> 0 | AN320: =IFERROR(VLOOKUP("23_"&A320,SyS!$B:$P,12,FALSE()),0) -> 0 | AO320: =+AM320-AN320 -> 0 | BK320: =IFERROR(VLOOKUP("29_"&A320,SyS!$B:$P,10,FALSE()),0) -> 0 | BL320: =IFERROR(VLOOKUP("29_"&A320,SyS!$B:$P,12,FALSE()),0) -> 0 | BM320: =+BK320-BL320 -> 0 | BN320: =IFERROR(VLOOKUP("30_"&A320,SyS!$B:$P,10,FALSE()),0) -> 0 | BO320: =IFERROR(VLOOKUP("30_"&A320,SyS!$B:$P,12,FALSE()),0) -> 0 | BP320: =+BN320-BO320 -> 0 | BQ320: =+E320+H320+K320+Q320+T320+W320+Z320+AC320+AF320+AI320+AL320+AO320+AR320+AU320+AX320+BA320+BD320+BG320+BJ320+BM320+BP320 -> 0
A321: 427180000 | B321: GST. FERRETERIA REL. COMUNITARIAS | C321: =IFERROR(VLOOKUP("1_"&A321,SyS!$B:$P,10,FALSE()),0) -> 0 | D321: =IFERROR(VLOOKUP("1_"&A321,SyS!$B:$P,12,FALSE()),0) -> 0 | E321: =+C321-D321 -> 0 | F321: =IFERROR(VLOOKUP("2_"&A321,SyS!$B:$P,10,FALSE()),0) -> 0 | G321: =IFERROR(VLOOKUP("2_"&A321,SyS!$B:$P,12,FALSE()),0) -> 0 | H321: =+F321-G321 -> 0 | O321: =IFERROR(VLOOKUP("14_"&A321,SyS!$B:$P,10,FALSE()),0) -> 0 | P321: =IFERROR(VLOOKUP("14_"&A321,SyS!$B:$P,12,FALSE()),0) -> 0 | Q321: =+O321-P321 -> 0 | R321: =IFERROR(VLOOKUP("15_"&A321,SyS!$B:$P,10,FALSE()),0) -> 0 | S321: =IFERROR(VLOOKUP("15_"&A321,SyS!$B:$P,12,FALSE()),0) -> 0 | T321: =+R321-S321 -> 0 | U321: =IFERROR(VLOOKUP("16_"&A321,SyS!$B:$P,10,FALSE()),0) -> 0 | V321: =IFERROR(VLOOKUP("16_"&A321,SyS!$B:$P,12,FALSE()),0) -> 0 | W321: =+U321-V321 -> 0 | X321: =IFERROR(VLOOKUP("13_"&A321,SyS!$B:$P,10,FALSE()),0) -> 0 | Y321: =IFERROR(VLOOKUP("13_"&A321,SyS!$B:$P,12,FALSE()),0) -> 0 | Z321: =+X321-Y321 -> 0 | AA321: =IFERROR(VLOOKUP("17_"&A321,SyS!$B:$P,10,FALSE()),0) -> 0 | AB321: =IFERROR(VLOOKUP("17_"&A321,SyS!$B:$P,12,FALSE()),0) -> 0 | AC321: =+AA321-AB321 -> 0 | AG321: =IFERROR(VLOOKUP("19_"&A321,SyS!$B:$P,10,FALSE()),0) -> 0 | AH321: =IFERROR(VLOOKUP("19_"&A321,SyS!$B:$P,12,FALSE()),0) -> 0 | AI321: =+AG321-AH321 -> 0 | AM321: =IFERROR(VLOOKUP("23_"&A321,SyS!$B:$P,10,FALSE()),0) -> 0 | AN321: =IFERROR(VLOOKUP("23_"&A321,SyS!$B:$P,12,FALSE()),0) -> 0 | AO321: =+AM321-AN321 -> 0 | BK321: =IFERROR(VLOOKUP("29_"&A321,SyS!$B:$P,10,FALSE()),0) -> 0 | BL321: =IFERROR(VLOOKUP("29_"&A321,SyS!$B:$P,12,FALSE()),0) -> 0 | BM321: =+BK321-BL321 -> 0 | BN321: =IFERROR(VLOOKUP("30_"&A321,SyS!$B:$P,10,FALSE()),0) -> 0 | BO321: =IFERROR(VLOOKUP("30_"&A321,SyS!$B:$P,12,FALSE()),0) -> 0 | BP321: =+BN321-BO321 -> 0 | BQ321: =+E321+H321+K321+Q321+T321+W321+Z321+AC321+AF321+AI321+AL321+AO321+AR321+AU321+AX321+BA321+BD321+BG321+BJ321+BM321+BP321 -> 0
A322: 427210000 | B322: CONVENIO DE ACCESO REL. COMUNITARIAS | C322: =IFERROR(VLOOKUP("1_"&A322,SyS!$B:$P,10,FALSE()),0) -> 0 | D322: =IFERROR(VLOOKUP("1_"&A322,SyS!$B:$P,12,FALSE()),0) -> 0 | E322: =+C322-D322 -> 0 | F322: =IFERROR(VLOOKUP("2_"&A322,SyS!$B:$P,10,FALSE()),0) -> 0 | G322: =IFERROR(VLOOKUP("2_"&A322,SyS!$B:$P,12,FALSE()),0) -> 0 | H322: =+F322-G322 -> 0 | O322: =IFERROR(VLOOKUP("14_"&A322,SyS!$B:$P,10,FALSE()),0) -> 0 | P322: =IFERROR(VLOOKUP("14_"&A322,SyS!$B:$P,12,FALSE()),0) -> 0 | Q322: =+O322-P322 -> 0 | R322: =IFERROR(VLOOKUP("15_"&A322,SyS!$B:$P,10,FALSE()),0) -> 0 | S322: =IFERROR(VLOOKUP("15_"&A322,SyS!$B:$P,12,FALSE()),0) -> 0 | T322: =+R322-S322 -> 0 | U322: =IFERROR(VLOOKUP("16_"&A322,SyS!$B:$P,10,FALSE()),0) -> 0 | V322: =IFERROR(VLOOKUP("16_"&A322,SyS!$B:$P,12,FALSE()),0) -> 0 | W322: =+U322-V322 -> 0 | X322: =IFERROR(VLOOKUP("13_"&A322,SyS!$B:$P,10,FALSE()),0) -> 0 | Y322: =IFERROR(VLOOKUP("13_"&A322,SyS!$B:$P,12,FALSE()),0) -> 0 | Z322: =+X322-Y322 -> 0 | AA322: =IFERROR(VLOOKUP("17_"&A322,SyS!$B:$P,10,FALSE()),0) -> 0 | AB322: =IFERROR(VLOOKUP("17_"&A322,SyS!$B:$P,12,FALSE()),0) -> 0 | AC322: =+AA322-AB322 -> 0 | AG322: =IFERROR(VLOOKUP("19_"&A322,SyS!$B:$P,10,FALSE()),0) -> 0 | AH322: =IFERROR(VLOOKUP("19_"&A322,SyS!$B:$P,12,FALSE()),0) -> 0 | AI322: =+AG322-AH322 -> 0 | AM322: =IFERROR(VLOOKUP("23_"&A322,SyS!$B:$P,10,FALSE()),0) -> 0 | AN322: =IFERROR(VLOOKUP("23_"&A322,SyS!$B:$P,12,FALSE()),0) -> 0 | AO322: =+AM322-AN322 -> 0 | BK322: =IFERROR(VLOOKUP("29_"&A322,SyS!$B:$P,10,FALSE()),0) -> 0 | BL322: =IFERROR(VLOOKUP("29_"&A322,SyS!$B:$P,12,FALSE()),0) -> 0 | BM322: =+BK322-BL322 -> 0 | BN322: =IFERROR(VLOOKUP("30_"&A322,SyS!$B:$P,10,FALSE()),0) -> 0 | BO322: =IFERROR(VLOOKUP("30_"&A322,SyS!$B:$P,12,FALSE()),0) -> 0 | BP322: =+BN322-BO322 -> 0 | BQ322: =+E322+H322+K322+Q322+T322+W322+Z322+AC322+AF322+AI322+AL322+AO322+AR322+AU322+AX322+BA322+BD322+BG322+BJ322+BM322+BP322 -> 0
A323: 427220000 | B323: ALQUILERES VARIOS REL. COMUNITARIAS | C323: =IFERROR(VLOOKUP("1_"&A323,SyS!$B:$P,10,FALSE()),0) -> 0 | D323: =IFERROR(VLOOKUP("1_"&A323,SyS!$B:$P,12,FALSE()),0) -> 0 | E323: =+C323-D323 -> 0 | F323: =IFERROR(VLOOKUP("2_"&A323,SyS!$B:$P,10,FALSE()),0) -> 0 | G323: =IFERROR(VLOOKUP("2_"&A323,SyS!$B:$P,12,FALSE()),0) -> 0 | H323: =+F323-G323 -> 0 | O323: =IFERROR(VLOOKUP("14_"&A323,SyS!$B:$P,10,FALSE()),0) -> 0 | P323: =IFERROR(VLOOKUP("14_"&A323,SyS!$B:$P,12,FALSE()),0) -> 0 | Q323: =+O323-P323 -> 0 | R323: =IFERROR(VLOOKUP("15_"&A323,SyS!$B:$P,10,FALSE()),0) -> 0 | S323: =IFERROR(VLOOKUP("15_"&A323,SyS!$B:$P,12,FALSE()),0) -> 0 | T323: =+R323-S323 -> 0 | U323: =IFERROR(VLOOKUP("16_"&A323,SyS!$B:$P,10,FALSE()),0) -> 0 | V323: =IFERROR(VLOOKUP("16_"&A323,SyS!$B:$P,12,FALSE()),0) -> 0 | W323: =+U323-V323 -> 0 | X323: =IFERROR(VLOOKUP("13_"&A323,SyS!$B:$P,10,FALSE()),0) -> 0 | Y323: =IFERROR(VLOOKUP("13_"&A323,SyS!$B:$P,12,FALSE()),0) -> 0 | Z323: =+X323-Y323 -> 0 | AA323: =IFERROR(VLOOKUP("17_"&A323,SyS!$B:$P,10,FALSE()),0) -> 0 | AB323: =IFERROR(VLOOKUP("17_"&A323,SyS!$B:$P,12,FALSE()),0) -> 0 | AC323: =+AA323-AB323 -> 0 | AG323: =IFERROR(VLOOKUP("19_"&A323,SyS!$B:$P,10,FALSE()),0) -> 0 | AH323: =IFERROR(VLOOKUP("19_"&A323,SyS!$B:$P,12,FALSE()),0) -> 0 | AI323: =+AG323-AH323 -> 0 | AM323: =IFERROR(VLOOKUP("23_"&A323,SyS!$B:$P,10,FALSE()),0) -> 0 | AN323: =IFERROR(VLOOKUP("23_"&A323,SyS!$B:$P,12,FALSE()),0) -> 0 | AO323: =+AM323-AN323 -> 0 | BK323: =IFERROR(VLOOKUP("29_"&A323,SyS!$B:$P,10,FALSE()),0) -> 0 | BL323: =IFERROR(VLOOKUP("29_"&A323,SyS!$B:$P,12,FALSE()),0) -> 0 | BM323: =+BK323-BL323 -> 0 | BN323: =IFERROR(VLOOKUP("30_"&A323,SyS!$B:$P,10,FALSE()),0) -> 0 | BO323: =IFERROR(VLOOKUP("30_"&A323,SyS!$B:$P,12,FALSE()),0) -> 0 | BP323: =+BN323-BO323 -> 0 | BQ323: =+E323+H323+K323+Q323+T323+W323+Z323+AC323+AF323+AI323+AL323+AO323+AR323+AU323+AX323+BA323+BD323+BG323+BJ323+BM323+BP323 -> 0
A324: 427230000 | B324: ALOJAMIENTO REL.COMUNITARIAS | C324: =IFERROR(VLOOKUP("1_"&A324,SyS!$B:$P,10,FALSE()),0) -> 0 | D324: =IFERROR(VLOOKUP("1_"&A324,SyS!$B:$P,12,FALSE()),0) -> 0 | E324: =+C324-D324 -> 0 | F324: =IFERROR(VLOOKUP("2_"&A324,SyS!$B:$P,10,FALSE()),0) -> 0 | G324: =IFERROR(VLOOKUP("2_"&A324,SyS!$B:$P,12,FALSE()),0) -> 0 | H324: =+F324-G324 -> 0 | O324: =IFERROR(VLOOKUP("14_"&A324,SyS!$B:$P,10,FALSE()),0) -> 0 | P324: =IFERROR(VLOOKUP("14_"&A324,SyS!$B:$P,12,FALSE()),0) -> 0 | Q324: =+O324-P324 -> 0 | R324: =IFERROR(VLOOKUP("15_"&A324,SyS!$B:$P,10,FALSE()),0) -> 0 | S324: =IFERROR(VLOOKUP("15_"&A324,SyS!$B:$P,12,FALSE()),0) -> 0 | T324: =+R324-S324 -> 0 | U324: =IFERROR(VLOOKUP("16_"&A324,SyS!$B:$P,10,FALSE()),0) -> 0 | V324: =IFERROR(VLOOKUP("16_"&A324,SyS!$B:$P,12,FALSE()),0) -> 0 | W324: =+U324-V324 -> 0 | X324: =IFERROR(VLOOKUP("13_"&A324,SyS!$B:$P,10,FALSE()),0) -> 0 | Y324: =IFERROR(VLOOKUP("13_"&A324,SyS!$B:$P,12,FALSE()),0) -> 0 | Z324: =+X324-Y324 -> 0 | AA324: =IFERROR(VLOOKUP("17_"&A324,SyS!$B:$P,10,FALSE()),0) -> 0 | AB324: =IFERROR(VLOOKUP("17_"&A324,SyS!$B:$P,12,FALSE()),0) -> 0 | AC324: =+AA324-AB324 -> 0 | AG324: =IFERROR(VLOOKUP("19_"&A324,SyS!$B:$P,10,FALSE()),0) -> 0 | AH324: =IFERROR(VLOOKUP("19_"&A324,SyS!$B:$P,12,FALSE()),0) -> 0 | AI324: =+AG324-AH324 -> 0 | AM324: =IFERROR(VLOOKUP("23_"&A324,SyS!$B:$P,10,FALSE()),0) -> 0 | AN324: =IFERROR(VLOOKUP("23_"&A324,SyS!$B:$P,12,FALSE()),0) -> 0 | AO324: =+AM324-AN324 -> 0 | BK324: =IFERROR(VLOOKUP("29_"&A324,SyS!$B:$P,10,FALSE()),0) -> 0 | BL324: =IFERROR(VLOOKUP("29_"&A324,SyS!$B:$P,12,FALSE()),0) -> 0 | BM324: =+BK324-BL324 -> 0 | BN324: =IFERROR(VLOOKUP("30_"&A324,SyS!$B:$P,10,FALSE()),0) -> 0 | BO324: =IFERROR(VLOOKUP("30_"&A324,SyS!$B:$P,12,FALSE()),0) -> 0 | BP324: =+BN324-BO324 -> 0 | BQ324: =+E324+H324+K324+Q324+T324+W324+Z324+AC324+AF324+AI324+AL324+AO324+AR324+AU324+AX324+BA324+BD324+BG324+BJ324+BM324+BP324 -> 0
A325: 427240000 | B325: GASTOS EN PERSONAL REL. COMUNITARIAS | C325: =IFERROR(VLOOKUP("1_"&A325,SyS!$B:$P,10,FALSE()),0) -> 0 | D325: =IFERROR(VLOOKUP("1_"&A325,SyS!$B:$P,12,FALSE()),0) -> 0 | E325: =+C325-D325 -> 0 | F325: =IFERROR(VLOOKUP("2_"&A325,SyS!$B:$P,10,FALSE()),0) -> 0 | G325: =IFERROR(VLOOKUP("2_"&A325,SyS!$B:$P,12,FALSE()),0) -> 0 | H325: =+F325-G325 -> 0 | O325: =IFERROR(VLOOKUP("14_"&A325,SyS!$B:$P,10,FALSE()),0) -> 0 | P325: =IFERROR(VLOOKUP("14_"&A325,SyS!$B:$P,12,FALSE()),0) -> 0 | Q325: =+O325-P325 -> 0 | R325: =IFERROR(VLOOKUP("15_"&A325,SyS!$B:$P,10,FALSE()),0) -> 0 | S325: =IFERROR(VLOOKUP("15_"&A325,SyS!$B:$P,12,FALSE()),0) -> 0 | T325: =+R325-S325 -> 0 | U325: =IFERROR(VLOOKUP("16_"&A325,SyS!$B:$P,10,FALSE()),0) -> 0 | V325: =IFERROR(VLOOKUP("16_"&A325,SyS!$B:$P,12,FALSE()),0) -> 0 | W325: =+U325-V325 -> 0 | X325: =IFERROR(VLOOKUP("13_"&A325,SyS!$B:$P,10,FALSE()),0) -> 0 | Y325: =IFERROR(VLOOKUP("13_"&A325,SyS!$B:$P,12,FALSE()),0) -> 0 | Z325: =+X325-Y325 -> 0 | AA325: =IFERROR(VLOOKUP("17_"&A325,SyS!$B:$P,10,FALSE()),0) -> 0 | AB325: =IFERROR(VLOOKUP("17_"&A325,SyS!$B:$P,12,FALSE()),0) -> 0 | AC325: =+AA325-AB325 -> 0 | AG325: =IFERROR(VLOOKUP("19_"&A325,SyS!$B:$P,10,FALSE()),0) -> 0 | AH325: =IFERROR(VLOOKUP("19_"&A325,SyS!$B:$P,12,FALSE()),0) -> 0 | AI325: =+AG325-AH325 -> 0 | AM325: =IFERROR(VLOOKUP("23_"&A325,SyS!$B:$P,10,FALSE()),0) -> 0 | AN325: =IFERROR(VLOOKUP("23_"&A325,SyS!$B:$P,12,FALSE()),0) -> 0 | AO325: =+AM325-AN325 -> 0 | BK325: =IFERROR(VLOOKUP("29_"&A325,SyS!$B:$P,10,FALSE()),0) -> 0 | BL325: =IFERROR(VLOOKUP("29_"&A325,SyS!$B:$P,12,FALSE()),0) -> 0 | BM325: =+BK325-BL325 -> 0 | BN325: =IFERROR(VLOOKUP("30_"&A325,SyS!$B:$P,10,FALSE()),0) -> 0 | BO325: =IFERROR(VLOOKUP("30_"&A325,SyS!$B:$P,12,FALSE()),0) -> 0 | BP325: =+BN325-BO325 -> 0 | BQ325: =+E325+H325+K325+Q325+T325+W325+Z325+AC325+AF325+AI325+AL325+AO325+AR325+AU325+AX325+BA325+BD325+BG325+BJ325+BM325+BP325 -> 0
A326: 427250000 | B326: PATENTES REL. COMUNITARIAS | C326: =IFERROR(VLOOKUP("1_"&A326,SyS!$B:$P,10,FALSE()),0) -> 0 | D326: =IFERROR(VLOOKUP("1_"&A326,SyS!$B:$P,12,FALSE()),0) -> 0 | E326: =+C326-D326 -> 0 | F326: =IFERROR(VLOOKUP("2_"&A326,SyS!$B:$P,10,FALSE()),0) -> 0 | G326: =IFERROR(VLOOKUP("2_"&A326,SyS!$B:$P,12,FALSE()),0) -> 0 | H326: =+F326-G326 -> 0 | O326: =IFERROR(VLOOKUP("14_"&A326,SyS!$B:$P,10,FALSE()),0) -> 0 | P326: =IFERROR(VLOOKUP("14_"&A326,SyS!$B:$P,12,FALSE()),0) -> 0 | Q326: =+O326-P326 -> 0 | R326: =IFERROR(VLOOKUP("15_"&A326,SyS!$B:$P,10,FALSE()),0) -> 0 | S326: =IFERROR(VLOOKUP("15_"&A326,SyS!$B:$P,12,FALSE()),0) -> 0 | T326: =+R326-S326 -> 0 | U326: =IFERROR(VLOOKUP("16_"&A326,SyS!$B:$P,10,FALSE()),0) -> 0 | V326: =IFERROR(VLOOKUP("16_"&A326,SyS!$B:$P,12,FALSE()),0) -> 0 | W326: =+U326-V326 -> 0 | X326: =IFERROR(VLOOKUP("13_"&A326,SyS!$B:$P,10,FALSE()),0) -> 0 | Y326: =IFERROR(VLOOKUP("13_"&A326,SyS!$B:$P,12,FALSE()),0) -> 0 | Z326: =+X326-Y326 -> 0 | AA326: =IFERROR(VLOOKUP("17_"&A326,SyS!$B:$P,10,FALSE()),0) -> 0 | AB326: =IFERROR(VLOOKUP("17_"&A326,SyS!$B:$P,12,FALSE()),0) -> 0 | AC326: =+AA326-AB326 -> 0 | AG326: =IFERROR(VLOOKUP("19_"&A326,SyS!$B:$P,10,FALSE()),0) -> 0 | AH326: =IFERROR(VLOOKUP("19_"&A326,SyS!$B:$P,12,FALSE()),0) -> 0 | AI326: =+AG326-AH326 -> 0 | AM326: =IFERROR(VLOOKUP("23_"&A326,SyS!$B:$P,10,FALSE()),0) -> 0 | AN326: =IFERROR(VLOOKUP("23_"&A326,SyS!$B:$P,12,FALSE()),0) -> 0 | AO326: =+AM326-AN326 -> 0 | BK326: =IFERROR(VLOOKUP("29_"&A326,SyS!$B:$P,10,FALSE()),0) -> 0 | BL326: =IFERROR(VLOOKUP("29_"&A326,SyS!$B:$P,12,FALSE()),0) -> 0 | BM326: =+BK326-BL326 -> 0 | BN326: =IFERROR(VLOOKUP("30_"&A326,SyS!$B:$P,10,FALSE()),0) -> 0 | BO326: =IFERROR(VLOOKUP("30_"&A326,SyS!$B:$P,12,FALSE()),0) -> 0 | BP326: =+BN326-BO326 -> 0 | BQ326: =+E326+H326+K326+Q326+T326+W326+Z326+AC326+AF326+AI326+AL326+AO326+AR326+AU326+AX326+BA326+BD326+BG326+BJ326+BM326+BP326 -> 0
... A356: 427190000 | B356: Gastos y comisiones bancarias Rel. comunitarias Catamarca | C356: =IFERROR(VLOOKUP("1_"&A356,SyS!$B:$P,10,FALSE()),0) -> 0 | D356: =IFERROR(VLOOKUP("1_"&A356,SyS!$B:$P,12,FALSE()),0) -> 0 | E356: =+C356-D356 -> 0 | F356: =IFERROR(VLOOKUP("2_"&A356,SyS!$B:$P,10,FALSE()),0) -> 0 | G356: =IFERROR(VLOOKUP("2_"&A356,SyS!$B:$P,12,FALSE()),0) -> 0 | H356: =+F356-G356 -> 0 | O356: =IFERROR(VLOOKUP("14_"&A356,SyS!$B:$P,10,FALSE()),0) -> 0 | P356: =IFERROR(VLOOKUP("14_"&A356,SyS!$B:$P,12,FALSE()),0) -> 0 | Q356: =+O356-P356 -> 0 | R356: =IFERROR(VLOOKUP("15_"&A356,SyS!$B:$P,10,FALSE()),0) -> 0 | S356: =IFERROR(VLOOKUP("15_"&A356,SyS!$B:$P,12,FALSE()),0) -> 0 | T356: =+R356-S356 -> 0 | U356: =IFERROR(VLOOKUP("16_"&A356,SyS!$B:$P,10,FALSE()),0) -> 0 | V356: =IFERROR(VLOOKUP("16_"&A356,SyS!$B:$P,12,FALSE()),0) -> 0 | W356: =+U356-V356 -> 0 | X356: =IFERROR(VLOOKUP("13_"&A356,SyS!$B:$P,10,FALSE()),0) -> 0 | Y356: =IFERROR(VLOOKUP("13_"&A356,SyS!$B:$P,12,FALSE()),0) -> 0 | Z356: =+X356-Y356 -> 0 | AA356: =IFERROR(VLOOKUP("17_"&A356,SyS!$B:$P,10,FALSE()),0) -> 0 | AB356: =IFERROR(VLOOKUP("17_"&A356,SyS!$B:$P,12,FALSE()),0) -> 0 | AC356: =+AA356-AB356 -> 0 | AG356: =IFERROR(VLOOKUP("19_"&A356,SyS!$B:$P,10,FALSE()),0) -> 0 | AH356: =IFERROR(VLOOKUP("19_"&A356,SyS!$B:$P,12,FALSE()),0) -> 0 | AI356: =+AG356-AH356 -> 0 | AM356: =IFERROR(VLOOKUP("23_"&A356,SyS!$B:$P,10,FALSE()),0) -> 0 | AN356: =IFERROR(VLOOKUP("23_"&A356,SyS!$B:$P,12,FALSE()),0) -> 0 | AO356: =+AM356-AN356 -> 0 | BK356: =IFERROR(VLOOKUP("29_"&A356,SyS!$B:$P,10,FALSE()),0) -> 0 | BL356: =IFERROR(VLOOKUP("29_"&A356,SyS!$B:$P,12,FALSE()),0) -> 0 | BM356: =+BK356-BL356 -> 0 | BN356: =IFERROR(VLOOKUP("30_"&A356,SyS!$B:$P,10,FALSE()),0) -> 0 | BO356: =IFERROR(VLOOKUP("30_"&A356,SyS!$B:$P,12,FALSE()),0) -> 0 | BP356: =+BN356-BO356 -> 0 | BQ356: =+E356+H356+K356+Q356+T356+W356+Z356+AC356+AF356+AI356+AL356+AO356+AR356+AU356+AX356+BA356+BD356+BG356+BJ356+BM356+BP356 -> 0
B357: MUESTREO GEOFISICO SUPERF. | C357: =IFERROR(VLOOKUP("1_"&A357,SyS!$B:$P,10,FALSE()),0) -> 0 | D357: =IFERROR(VLOOKUP("1_"&A357,SyS!$B:$P,12,FALSE()),0) -> 0 | E357: =+C357-D357 -> 0
A358: 428100000 | B358: GASTOS VARIOS CAMPO MUESTREO GEOF. SUP | C358: =IFERROR(VLOOKUP("1_"&A358,SyS!$B:$P,10,FALSE()),0) -> 0 | D358: =IFERROR(VLOOKUP("1_"&A358,SyS!$B:$P,12,FALSE()),0) -> 0 | E358: =+C358-D358 -> 0 | F358: =IFERROR(VLOOKUP("2_"&A358,SyS!$B:$P,10,FALSE()),0) -> 0 | G358: =IFERROR(VLOOKUP("2_"&A358,SyS!$B:$P,12,FALSE()),0) -> 0 | H358: =+F358-G358 -> 0 | O358: =IFERROR(VLOOKUP("14_"&A358,SyS!$B:$P,10,FALSE()),0) -> 0 | P358: =IFERROR(VLOOKUP("14_"&A358,SyS!$B:$P,12,FALSE()),0) -> 0 | Q358: =+O358-P358 -> 0 | R358: =IFERROR(VLOOKUP("15_"&A358,SyS!$B:$P,10,FALSE()),0) -> 0 | S358: =IFERROR(VLOOKUP("15_"&A358,SyS!$B:$P,12,FALSE()),0) -> 0 | T358: =+R358-S358 -> 0 | U358: =IFERROR(VLOOKUP("16_"&A358,SyS!$B:$P,10,FALSE()),0) -> 0 | V358: =IFERROR(VLOOKUP("16_"&A358,SyS!$B:$P,12,FALSE()),0) -> 0 | W358: =+U358-V358 -> 0 | X358: =IFERROR(VLOOKUP("13_"&A358,SyS!$B:$P,10,FALSE()),0) -> 0 | Y358: =IFERROR(VLOOKUP("13_"&A358,SyS!$B:$P,12,FALSE()),0) -> 0 | Z358: =+X358-Y358 -> 0 | AA358: =IFERROR(VLOOKUP("17_"&A358,SyS!$B:$P,10,FALSE()),0) -> 0 | AB358: =IFERROR(VLOOKUP("17_"&A358,SyS!$B:$P,12,FALSE()),0) -> 0 | AC358: =+AA358-AB358 -> 0 | AG358: =IFERROR(VLOOKUP("19_"&A358,SyS!$B:$P,10,FALSE()),0) -> 0 | AH358: =IFERROR(VLOOKUP("19_"&A358,SyS!$B:$P,12,FALSE()),0) -> 0 | AI358: =+AG358-AH358 -> 0 | AM358: =IFERROR(VLOOKUP("23_"&A358,SyS!$B:$P,10,FALSE()),0) -> 0 | AN358: =IFERROR(VLOOKUP("23_"&A358,SyS!$B:$P,12,FALSE()),0) -> 0 | AO358: =+AM358-AN358 -> 0 | BK358: =IFERROR(VLOOKUP("29_"&A358,SyS!$B:$P,10,FALSE()),0) -> 0 | BL358: =IFERROR(VLOOKUP("29_"&A358,SyS!$B:$P,12,FALSE()),0) -> 0 | BM358: =+BK358-BL358 -> 0 | BN358: =IFERROR(VLOOKUP("30_"&A358,SyS!$B:$P,10,FALSE()),0) -> 0 | BO358: =IFERROR(VLOOKUP("30_"&A358,SyS!$B:$P,12,FALSE()),0) -> 0 | BP358: =+BN358-BO358 -> 0 | BQ358: =+E358+H358+K358+Q358+T358+W358+Z358+AC358+AF358+AI358+AL358+AO358+AR358+AU358+AX358+BA358+BD358+BG358+BJ358+BM358+BP358 -> 0
A359: 428300000 | B359: MENSJAERIA MUESTREO GEOF. SUP. | C359: =IFERROR(VLOOKUP("1_"&A359,SyS!$B:$P,10,FALSE()),0) -> 0 | D359: =IFERROR(VLOOKUP("1_"&A359,SyS!$B:$P,12,FALSE()),0) -> 0 | E359: =+C359-D359 -> 0 | F359: =IFERROR(VLOOKUP("2_"&A359,SyS!$B:$P,10,FALSE()),0) -> 0 | G359: =IFERROR(VLOOKUP("2_"&A359,SyS!$B:$P,12,FALSE()),0) -> 0 | H359: =+F359-G359 -> 0 | O359: =IFERROR(VLOOKUP("14_"&A359,SyS!$B:$P,10,FALSE()),0) -> 0 | P359: =IFERROR(VLOOKUP("14_"&A359,SyS!$B:$P,12,FALSE()),0) -> 0 | Q359: =+O359-P359 -> 0 | R359: =IFERROR(VLOOKUP("15_"&A359,SyS!$B:$P,10,FALSE()),0) -> 0 | S359: =IFERROR(VLOOKUP("15_"&A359,SyS!$B:$P,12,FALSE()),0) -> 0 | T359: =+R359-S359 -> 0 | U359: =IFERROR(VLOOKUP("16_"&A359,SyS!$B:$P,10,FALSE()),0) -> 0 | V359: =IFERROR(VLOOKUP("16_"&A359,SyS!$B:$P,12,FALSE()),0) -> 0 | W359: =+U359-V359 -> 0 | X359: =IFERROR(VLOOKUP("13_"&A359,SyS!$B:$P,10,FALSE()),0) -> 0 | Y359: =IFERROR(VLOOKUP("13_"&A359,SyS!$B:$P,12,FALSE()),0) -> 0 | Z359: =+X359-Y359 -> 0 | AA359: =IFERROR(VLOOKUP("17_"&A359,SyS!$B:$P,10,FALSE()),0) -> 0 | AB359: =IFERROR(VLOOKUP("17_"&A359,SyS!$B:$P,12,FALSE()),0) -> 0 | AC359: =+AA359-AB359 -> 0 | AG359: =IFERROR(VLOOKUP("19_"&A359,SyS!$B:$P,10,FALSE()),0) -> 0 | AH359: =IFERROR(VLOOKUP("19_"&A359,SyS!$B:$P,12,FALSE()),0) -> 0 | AI359: =+AG359-AH359 -> 0 | AM359: =IFERROR(VLOOKUP("23_"&A359,SyS!$B:$P,10,FALSE()),0) -> 0 | AN359: =IFERROR(VLOOKUP("23_"&A359,SyS!$B:$P,12,FALSE()),0) -> 0 | AO359: =+AM359-AN359 -> 0 | BK359: =IFERROR(VLOOKUP("29_"&A359,SyS!$B:$P,10,FALSE()),0) -> 0 | BL359: =IFERROR(VLOOKUP("29_"&A359,SyS!$B:$P,12,FALSE()),0) -> 0 | BM359: =+BK359-BL359 -> 0 | BN359: =IFERROR(VLOOKUP("30_"&A359,SyS!$B:$P,10,FALSE()),0) -> 0 | BO359: =IFERROR(VLOOKUP("30_"&A359,SyS!$B:$P,12,FALSE()),0) -> 0 | BP359: =+BN359-BO359 -> 0 | BQ359: =+E359+H359+K359+Q359+T359+W359+Z359+AC359+AF359+AI359+AL359+AO359+AR359+AU359+AX359+BA359+BD359+BG359+BJ359+BM359+BP359 -> 0
A360: 428200000 | B360: Análisis de Muestras Muestreo Geof. Sup. | C360: =IFERROR(VLOOKUP("1_"&A360,SyS!$B:$P,10,FALSE()),0) -> 0 | D360: =IFERROR(VLOOKUP("1_"&A360,SyS!$B:$P,12,FALSE()),0) -> 0 | E360: =+C360-D360 -> 0 | F360: =IFERROR(VLOOKUP("2_"&A360,SyS!$B:$P,10,FALSE()),0) -> 0 | G360: =IFERROR(VLOOKUP("2_"&A360,SyS!$B:$P,12,FALSE()),0) -> 0 | H360: =+F360-G360 -> 0 | O360: =IFERROR(VLOOKUP("14_"&A360,SyS!$B:$P,10,FALSE()),0) -> 0 | P360: =IFERROR(VLOOKUP("14_"&A360,SyS!$B:$P,12,FALSE()),0) -> 0 | Q360: =+O360-P360 -> 0 | R360: =IFERROR(VLOOKUP("15_"&A360,SyS!$B:$P,10,FALSE()),0) -> 0 | S360: =IFERROR(VLOOKUP("15_"&A360,SyS!$B:$P,12,FALSE()),0) -> 0 | T360: =+R360-S360 -> 0 | U360: =IFERROR(VLOOKUP("16_"&A360,SyS!$B:$P,10,FALSE()),0) -> 0 | V360: =IFERROR(VLOOKUP("16_"&A360,SyS!$B:$P,12,FALSE()),0) -> 0 | W360: =+U360-V360 -> 0 | X360: =IFERROR(VLOOKUP("13_"&A360,SyS!$B:$P,10,FALSE()),0) -> 0 | Y360: =IFERROR(VLOOKUP("13_"&A360,SyS!$B:$P,12,FALSE()),0) -> 0 | Z360: =+X360-Y360 -> 0 | AA360: =IFERROR(VLOOKUP("17_"&A360,SyS!$B:$P,10,FALSE()),0) -> 0 | AB360: =IFERROR(VLOOKUP("17_"&A360,SyS!$B:$P,12,FALSE()),0) -> 0 | AC360: =+AA360-AB360 -> 0 | AG360: =IFERROR(VLOOKUP("19_"&A360,SyS!$B:$P,10,FALSE()),0) -> 0 | AH360: =IFERROR(VLOOKUP("19_"&A360,SyS!$B:$P,12,FALSE()),0) -> 0 | AI360: =+AG360-AH360 -> 0 | AM360: =IFERROR(VLOOKUP("23_"&A360,SyS!$B:$P,10,FALSE()),0) -> 0 | AN360: =IFERROR(VLOOKUP("23_"&A360,SyS!$B:$P,12,FALSE()),0) -> 0 | AO360: =+AM360-AN360 -> 0 | BK360: =IFERROR(VLOOKUP("29_"&A360,SyS!$B:$P,10,FALSE()),0) -> 0 | BL360: =IFERROR(VLOOKUP("29_"&A360,SyS!$B:$P,12,FALSE()),0) -> 0 | BM360: =+BK360-BL360 -> 0 | BN360: =IFERROR(VLOOKUP("30_"&A360,SyS!$B:$P,10,FALSE()),0) -> 0 | BO360: =IFERROR(VLOOKUP("30_"&A360,SyS!$B:$P,12,FALSE()),0) -> 0 | BP360: =+BN360-BO360 -> 0 | BQ360: =+E360+H360+K360+Q360+T360+W360+Z360+AC360+AF360+AI360+AL360+AO360+AR360+AU360+AX360+BA360+BD360+BG360+BJ360+BM360+BP360 -> 0
A361: 421950000 | B361: Mensajeria Muestreo Geof. Sup. Catamarca | C361: =IFERROR(VLOOKUP("1_"&A361,SyS!$B:$P,10,FALSE()),0) -> 0 | D361: =IFERROR(VLOOKUP("1_"&A361,SyS!$B:$P,12,FALSE()),0) -> 0 | E361: =+C361-D361 -> 0 | F361: =IFERROR(VLOOKUP("2_"&A361,SyS!$B:$P,10,FALSE()),0) -> 0 | G361: =IFERROR(VLOOKUP("2_"&A361,SyS!$B:$P,12,FALSE()),0) -> 0 | H361: =+F361-G361 -> 0 | O361: =IFERROR(VLOOKUP("14_"&A361,SyS!$B:$P,10,FALSE()),0) -> 0 | P361: =IFERROR(VLOOKUP("14_"&A361,SyS!$B:$P,12,FALSE()),0) -> 0 | Q361: =+O361-P361 -> 0 | R361: =IFERROR(VLOOKUP("15_"&A361,SyS!$B:$P,10,FALSE()),0) -> 0 | S361: =IFERROR(VLOOKUP("15_"&A361,SyS!$B:$P,12,FALSE()),0) -> 0 | T361: =+R361-S361 -> 0 | U361: =IFERROR(VLOOKUP("16_"&A361,SyS!$B:$P,10,FALSE()),0) -> 0 | V361: =IFERROR(VLOOKUP("16_"&A361,SyS!$B:$P,12,FALSE()),0) -> 0 | W361: =+U361-V361 -> 0 | X361: =IFERROR(VLOOKUP("13_"&A361,SyS!$B:$P,10,FALSE()),0) -> 0 | Y361: =IFERROR(VLOOKUP("13_"&A361,SyS!$B:$P,12,FALSE()),0) -> 0 | Z361: =+X361-Y361 -> 0 | AA361: =IFERROR(VLOOKUP("17_"&A361,SyS!$B:$P,10,FALSE()),0) -> 0 | AB361: =IFERROR(VLOOKUP("17_"&A361,SyS!$B:$P,12,FALSE()),0) -> 0 | AC361: =+AA361-AB361 -> 0 | AG361: =IFERROR(VLOOKUP("19_"&A361,SyS!$B:$P,10,FALSE()),0) -> 0 | AH361: =IFERROR(VLOOKUP("19_"&A361,SyS!$B:$P,12,FALSE()),0) -> 0 | AI361: =+AG361-AH361 -> 0 | AM361: =IFERROR(VLOOKUP("23_"&A361,SyS!$B:$P,10,FALSE()),0) -> 0 | AN361: =IFERROR(VLOOKUP("23_"&A361,SyS!$B:$P,12,FALSE()),0) -> 0 | AO361: =+AM361-AN361 -> 0 | BK361: =IFERROR(VLOOKUP("29_"&A361,SyS!$B:$P,10,FALSE()),0) -> 0 | BL361: =IFERROR(VLOOKUP("29_"&A361,SyS!$B:$P,12,FALSE()),0) -> 0 | BM361: =+BK361-BL361 -> 0 | BN361: =IFERROR(VLOOKUP("30_"&A361,SyS!$B:$P,10,FALSE()),0) -> 0 | BO361: =IFERROR(VLOOKUP("30_"&A361,SyS!$B:$P,12,FALSE()),0) -> 0 | BP361: =+BN361-BO361 -> 0 | BQ361: =+E361+H361+K361+Q361+T361+W361+Z361+AC361+AF361+AI361+AL361+AO361+AR361+AU361+AX361+BA361+BD361+BG361+BJ361+BM361+BP361 -> 0
B362: PERFORACIÓN | C362: =IFERROR(VLOOKUP("1_"&A362,SyS!$B:$P,10,FALSE()),0) -> 0 | D362: =IFERROR(VLOOKUP("1_"&A362,SyS!$B:$P,12,FALSE()),0) -> 0 | E362: =+C362-D362 -> 0
A363: 429100000 | B363: LIBRERÍA Y PAPELERÍA E. PERFORACIÓN | C363: =IFERROR(VLOOKUP("1_"&A363,SyS!$B:$P,10,FALSE()),0) -> 0 | D363: =IFERROR(VLOOKUP("1_"&A363,SyS!$B:$P,12,FALSE()),0) -> 0 | E363: =+C363-D363 -> 0 | F363: =IFERROR(VLOOKUP("2_"&A363,SyS!$B:$P,10,FALSE()),0) -> 0 | G363: =IFERROR(VLOOKUP("2_"&A363,SyS!$B:$P,12,FALSE()),0) -> 0 | H363: =+F363-G363 -> 0 | O363: =IFERROR(VLOOKUP("14_"&A363,SyS!$B:$P,10,FALSE()),0) -> 0 | P363: =IFERROR(VLOOKUP("14_"&A363,SyS!$B:$P,12,FALSE()),0) -> 0 | Q363: =+O363-P363 -> 0 | R363: =IFERROR(VLOOKUP("15_"&A363,SyS!$B:$P,10,FALSE()),0) -> 0 | S363: =IFERROR(VLOOKUP("15_"&A363,SyS!$B:$P,12,FALSE()),0) -> 0 | T363: =+R363-S363 -> 0 | U363: =IFERROR(VLOOKUP("16_"&A363,SyS!$B:$P,10,FALSE()),0) -> 0 | V363: =IFERROR(VLOOKUP("16_"&A363,SyS!$B:$P,12,FALSE()),0) -> 0 | W363: =+U363-V363 -> 0 | X363: =IFERROR(VLOOKUP("13_"&A363,SyS!$B:$P,10,FALSE()),0) -> 0 | Y363: =IFERROR(VLOOKUP("13_"&A363,SyS!$B:$P,12,FALSE()),0) -> 0 | Z363: =+X363-Y363 -> 0 | AA363: =IFERROR(VLOOKUP("17_"&A363,SyS!$B:$P,10,FALSE()),0) -> 0 | AB363: =IFERROR(VLOOKUP("17_"&A363,SyS!$B:$P,12,FALSE()),0) -> 0 | AC363: =+AA363-AB363 -> 0 | AG363: =IFERROR(VLOOKUP("19_"&A363,SyS!$B:$P,10,FALSE()),0) -> 0 | AH363: =IFERROR(VLOOKUP("19_"&A363,SyS!$B:$P,12,FALSE()),0) -> 0 | AI363: =+AG363-AH363 -> 0 | AM363: =IFERROR(VLOOKUP("23_"&A363,SyS!$B:$P,10,FALSE()),0) -> 0 | AN363: =IFERROR(VLOOKUP("23_"&A363,SyS!$B:$P,12,FALSE()),0) -> 0 | AO363: =+AM363-AN363 -> 0 | BK363: =IFERROR(VLOOKUP("29_"&A363,SyS!$B:$P,10,FALSE()),0) -> 0 | BL363: =IFERROR(VLOOKUP("29_"&A363,SyS!$B:$P,12,FALSE()),0) -> 0 | BM363: =+BK363-BL363 -> 0 | BN363: =IFERROR(VLOOKUP("30_"&A363,SyS!$B:$P,10,FALSE()),0) -> 0 | BO363: =IFERROR(VLOOKUP("30_"&A363,SyS!$B:$P,12,FALSE()),0) -> 0 | BP363: =+BN363-BO363 -> 0 | BQ363: =+E363+H363+K363+Q363+T363+W363+Z363+AC363+AF363+AI363+AL363+AO363+AR363+AU363+AX363+BA363+BD363+BG363+BJ363+BM363+BP363 -> 0
A364: 429200000 | B364: GASTOS EN PERSONAL E. PERFORACIÓN | C364: =IFERROR(VLOOKUP("1_"&A364,SyS!$B:$P,10,FALSE()),0) -> 0 | D364: =IFERROR(VLOOKUP("1_"&A364,SyS!$B:$P,12,FALSE()),0) -> 0 | E364: =+C364-D364 -> 0 | F364: =IFERROR(VLOOKUP("2_"&A364,SyS!$B:$P,10,FALSE()),0) -> 0 | G364: =IFERROR(VLOOKUP("2_"&A364,SyS!$B:$P,12,FALSE()),0) -> 0 | H364: =+F364-G364 -> 0 | O364: =IFERROR(VLOOKUP("14_"&A364,SyS!$B:$P,10,FALSE()),0) -> 0 | P364: =IFERROR(VLOOKUP("14_"&A364,SyS!$B:$P,12,FALSE()),0) -> 0 | Q364: =+O364-P364 -> 0 | R364: =IFERROR(VLOOKUP("15_"&A364,SyS!$B:$P,10,FALSE()),0) -> 0 | S364: =IFERROR(VLOOKUP("15_"&A364,SyS!$B:$P,12,FALSE()),0) -> 0 | T364: =+R364-S364 -> 0 | U364: =IFERROR(VLOOKUP("16_"&A364,SyS!$B:$P,10,FALSE()),0) -> 0 | V364: =IFERROR(VLOOKUP("16_"&A364,SyS!$B:$P,12,FALSE()),0) -> 0 | W364: =+U364-V364 -> 0 | X364: =IFERROR(VLOOKUP("13_"&A364,SyS!$B:$P,10,FALSE()),0) -> 0 | Y364: =IFERROR(VLOOKUP("13_"&A364,SyS!$B:$P,12,FALSE()),0) -> 0 | Z364: =+X364-Y364 -> 0 | AA364: =IFERROR(VLOOKUP("17_"&A364,SyS!$B:$P,10,FALSE()),0) -> 0 | AB364: =IFERROR(VLOOKUP("17_"&A364,SyS!$B:$P,12,FALSE()),0) -> 0 | AC364: =+AA364-AB364 -> 0 | AG364: =IFERROR(VLOOKUP("19_"&A364,SyS!$B:$P,10,FALSE()),0) -> 0 | AH364: =IFERROR(VLOOKUP("19_"&A364,SyS!$B:$P,12,FALSE()),0) -> 0 | AI364: =+AG364-AH364 -> 0 | AM364: =IFERROR(VLOOKUP("23_"&A364,SyS!$B:$P,10,FALSE()),0) -> 0 | AN364: =IFERROR(VLOOKUP("23_"&A364,SyS!$B:$P,12,FALSE()),0) -> 0 | AO364: =+AM364-AN364 -> 0 | BK364: =IFERROR(VLOOKUP("29_"&A364,SyS!$B:$P,10,FALSE()),0) -> 0 | BL364: =IFERROR(VLOOKUP("29_"&A364,SyS!$B:$P,12,FALSE()),0) -> 0 | BM364: =+BK364-BL364 -> 0 | BN364: =IFERROR(VLOOKUP("30_"&A364,SyS!$B:$P,10,FALSE()),0) -> 0 | BO364: =IFERROR(VLOOKUP("30_"&A364,SyS!$B:$P,12,FALSE()),0) -> 0 | BP364: =+BN364-BO364 -> 0 | BQ364: =+E364+H364+K364+Q364+T364+W364+Z364+AC364+AF364+AI364+AL364+AO364+AR364+AU364+AX364+BA364+BD364+BG364+BJ364+BM364+BP364 -> 0
A365: 429300000 | B365: SERVICIO DE PERFORACIÓN E. PERFORACIÓN | C365: =IFERROR(VLOOKUP("1_"&A365,SyS!$B:$P,10,FALSE()),0) -> 0 | D365: =IFERROR(VLOOKUP("1_"&A365,SyS!$B:$P,12,FALSE()),0) -> 0 | E365: =+C365-D365 -> 0 | F365: =IFERROR(VLOOKUP("2_"&A365,SyS!$B:$P,10,FALSE()),0) -> 0 | G365: =IFERROR(VLOOKUP("2_"&A365,SyS!$B:$P,12,FALSE()),0) -> 0 | H365: =+F365-G365 -> 0 | O365: =IFERROR(VLOOKUP("14_"&A365,SyS!$B:$P,10,FALSE()),0) -> 0 | P365: =IFERROR(VLOOKUP("14_"&A365,SyS!$B:$P,12,FALSE()),0) -> 0 | Q365: =+O365-P365 -> 0 | R365: =IFERROR(VLOOKUP("15_"&A365,SyS!$B:$P,10,FALSE()),0) -> 0 | S365: =IFERROR(VLOOKUP("15_"&A365,SyS!$B:$P,12,FALSE()),0) -> 0 | T365: =+R365-S365 -> 0 | U365: =IFERROR(VLOOKUP("16_"&A365,SyS!$B:$P,10,FALSE()),0) -> 0 | V365: =IFERROR(VLOOKUP("16_"&A365,SyS!$B:$P,12,FALSE()),0) -> 0 | W365: =+U365-V365 -> 0 | X365: =IFERROR(VLOOKUP("13_"&A365,SyS!$B:$P,10,FALSE()),0) -> 0 | Y365: =IFERROR(VLOOKUP("13_"&A365,SyS!$B:$P,12,FALSE()),0) -> 0 | Z365: =+X365-Y365 -> 0 | AA365: =IFERROR(VLOOKUP("17_"&A365,SyS!$B:$P,10,FALSE()),0) -> 0 | AB365: =IFERROR(VLOOKUP("17_"&A365,SyS!$B:$P,12,FALSE()),0) -> 0 | AC365: =+AA365-AB365 -> 0 | AG365: =IFERROR(VLOOKUP("19_"&A365,SyS!$B:$P,10,FALSE()),0) -> 0 | AH365: =IFERROR(VLOOKUP("19_"&A365,SyS!$B:$P,12,FALSE()),0) -> 0 | AI365: =+AG365-AH365 -> 0 | AM365: =IFERROR(VLOOKUP("23_"&A365,SyS!$B:$P,10,FALSE()),0) -> 0 | AN365: =IFERROR(VLOOKUP("23_"&A365,SyS!$B:$P,12,FALSE()),0) -> 0 | AO365: =+AM365-AN365 -> 0 | BK365: =IFERROR(VLOOKUP("29_"&A365,SyS!$B:$P,10,FALSE()),0) -> 0 | BL365: =IFERROR(VLOOKUP("29_"&A365,SyS!$B:$P,12,FALSE()),0) -> 0 | BM365: =+BK365-BL365 -> 0 | BN365: =IFERROR(VLOOKUP("30_"&A365,SyS!$B:$P,10,FALSE()),0) -> 0 | BO365: =IFERROR(VLOOKUP("30_"&A365,SyS!$B:$P,12,FALSE()),0) -> 0 | BP365: =+BN365-BO365 -> 0 | BQ365: =+E365+H365+K365+Q365+T365+W365+Z365+AC365+AF365+AI365+AL365+AO365+AR365+AU365+AX365+BA365+BD365+BG365+BJ365+BM365+BP365 -> 0
A366: 429400000 | B366: COMUNICACIONES E. PERFORACIÓN | C366: =IFERROR(VLOOKUP("1_"&A366,SyS!$B:$P,10,FALSE()),0) -> 0 | D366: =IFERROR(VLOOKUP("1_"&A366,SyS!$B:$P,12,FALSE()),0) -> 0 | E366: =+C366-D366 -> 0 | F366: =IFERROR(VLOOKUP("2_"&A366,SyS!$B:$P,10,FALSE()),0) -> 0 | G366: =IFERROR(VLOOKUP("2_"&A366,SyS!$B:$P,12,FALSE()),0) -> 0 | H366: =+F366-G366 -> 0 | O366: =IFERROR(VLOOKUP("14_"&A366,SyS!$B:$P,10,FALSE()),0) -> 0 | P366: =IFERROR(VLOOKUP("14_"&A366,SyS!$B:$P,12,FALSE()),0) -> 0 | Q366: =+O366-P366 -> 0 | R366: =IFERROR(VLOOKUP("15_"&A366,SyS!$B:$P,10,FALSE()),0) -> 0 | S366: =IFERROR(VLOOKUP("15_"&A366,SyS!$B:$P,12,FALSE()),0) -> 0 | T366: =+R366-S366 -> 0 | U366: =IFERROR(VLOOKUP("16_"&A366,SyS!$B:$P,10,FALSE()),0) -> 0 | V366: =IFERROR(VLOOKUP("16_"&A366,SyS!$B:$P,12,FALSE()),0) -> 0 | W366: =+U366-V366 -> 0 | X366: =IFERROR(VLOOKUP("13_"&A366,SyS!$B:$P,10,FALSE()),0) -> 0 | Y366: =IFERROR(VLOOKUP("13_"&A366,SyS!$B:$P,12,FALSE()),0) -> 0 | Z366: =+X366-Y366 -> 0 | AA366: =IFERROR(VLOOKUP("17_"&A366,SyS!$B:$P,10,FALSE()),0) -> 0 | AB366: =IFERROR(VLOOKUP("17_"&A366,SyS!$B:$P,12,FALSE()),0) -> 0 | AC366: =+AA366-AB366 -> 0 | AG366: =IFERROR(VLOOKUP("19_"&A366,SyS!$B:$P,10,FALSE()),0) -> 0 | AH366: =IFERROR(VLOOKUP("19_"&A366,SyS!$B:$P,12,FALSE()),0) -> 0 | AI366: =+AG366-AH366 -> 0 | AM366: =IFERROR(VLOOKUP("23_"&A366,SyS!$B:$P,10,FALSE()),0) -> 0 | AN366: =IFERROR(VLOOKUP("23_"&A366,SyS!$B:$P,12,FALSE()),0) -> 0 | AO366: =+AM366-AN366 -> 0 | BK366: =IFERROR(VLOOKUP("29_"&A366,SyS!$B:$P,10,FALSE()),0) -> 0 | BL366: =IFERROR(VLOOKUP("29_"&A366,SyS!$B:$P,12,FALSE()),0) -> 0 | BM366: =+BK366-BL366 -> 0 | BN366: =IFERROR(VLOOKUP("30_"&A366,SyS!$B:$P,10,FALSE()),0) -> 0 | BO366: =IFERROR(VLOOKUP("30_"&A366,SyS!$B:$P,12,FALSE()),0) -> 0 | BP366: =+BN366-BO366 -> 0 | BQ366: =+E366+H366+K366+Q366+T366+W366+Z366+AC366+AF366+AI366+AL366+AO366+AR366+AU366+AX366+BA366+BD366+BG366+BJ366+BM366+BP366 -> 0
A367: 429500000 | B367: REFRIGERIOS E. PERFORCIÓN | C367: =IFERROR(VLOOKUP("1_"&A367,SyS!$B:$P,10,FALSE()),0) -> 0 | D367: =IFERROR(VLOOKUP("1_"&A367,SyS!$B:$P,12,FALSE()),0) -> 0 | E367: =+C367-D367 -> 0 | F367: =IFERROR(VLOOKUP("2_"&A367,SyS!$B:$P,10,FALSE()),0) -> 0 | G367: =IFERROR(VLOOKUP("2_"&A367,SyS!$B:$P,12,FALSE()),0) -> 0 | H367: =+F367-G367 -> 0 | O367: =IFERROR(VLOOKUP("14_"&A367,SyS!$B:$P,10,FALSE()),0) -> 0 | P367: =IFERROR(VLOOKUP("14_"&A367,SyS!$B:$P,12,FALSE()),0) -> 0 | Q367: =+O367-P367 -> 0 | R367: =IFERROR(VLOOKUP("15_"&A367,SyS!$B:$P,10,FALSE()),0) -> 0 | S367: =IFERROR(VLOOKUP("15_"&A367,SyS!$B:$P,12,FALSE()),0) -> 0 | T367: =+R367-S367 -> 0 | U367: =IFERROR(VLOOKUP("16_"&A367,SyS!$B:$P,10,FALSE()),0) -> 0 | V367: =IFERROR(VLOOKUP("16_"&A367,SyS!$B:$P,12,FALSE()),0) -> 0 | W367: =+U367-V367 -> 0 | X367: =IFERROR(VLOOKUP("13_"&A367,SyS!$B:$P,10,FALSE()),0) -> 0 | Y367: =IFERROR(VLOOKUP("13_"&A367,SyS!$B:$P,12,FALSE()),0) -> 0 | Z367: =+X367-Y367 -> 0 | AA367: =IFERROR(VLOOKUP("17_"&A367,SyS!$B:$P,10,FALSE()),0) -> 0 | AB367: =IFERROR(VLOOKUP("17_"&A367,SyS!$B:$P,12,FALSE()),0) -> 0 | AC367: =+AA367-AB367 -> 0 | AG367: =IFERROR(VLOOKUP("19_"&A367,SyS!$B:$P,10,FALSE()),0) -> 0 | AH367: =IFERROR(VLOOKUP("19_"&A367,SyS!$B:$P,12,FALSE()),0) -> 0 | AI367: =+AG367-AH367 -> 0 | AM367: =IFERROR(VLOOKUP("23_"&A367,SyS!$B:$P,10,FALSE()),0) -> 0 | AN367: =IFERROR(VLOOKUP("23_"&A367,SyS!$B:$P,12,FALSE()),0) -> 0 | AO367: =+AM367-AN367 -> 0 | BK367: =IFERROR(VLOOKUP("29_"&A367,SyS!$B:$P,10,FALSE()),0) -> 0 | BL367: =IFERROR(VLOOKUP("29_"&A367,SyS!$B:$P,12,FALSE()),0) -> 0 | BM367: =+BK367-BL367 -> 0 | BN367: =IFERROR(VLOOKUP("30_"&A367,SyS!$B:$P,10,FALSE()),0) -> 0 | BO367: =IFERROR(VLOOKUP("30_"&A367,SyS!$B:$P,12,FALSE()),0) -> 0 | BP367: =+BN367-BO367 -> 0 | BQ367: =+E367+H367+K367+Q367+T367+W367+Z367+AC367+AF367+AI367+AL367+AO367+AR367+AU367+AX367+BA367+BD367+BG367+BJ367+BM367+BP367 -> 0
A368: 429800000 | B368: COMBUSTIBLE E PERFORACION | C368: =IFERROR(VLOOKUP("1_"&A368,SyS!$B:$P,10,FALSE()),0) -> 0 | D368: =IFERROR(VLOOKUP("1_"&A368,SyS!$B:$P,12,FALSE()),0) -> 0 | E368: =+C368-D368 -> 0 | F368: =IFERROR(VLOOKUP("2_"&A368,SyS!$B:$P,10,FALSE()),0) -> 0 | G368: =IFERROR(VLOOKUP("2_"&A368,SyS!$B:$P,12,FALSE()),0) -> 0 | H368: =+F368-G368 -> 0 | O368: =IFERROR(VLOOKUP("14_"&A368,SyS!$B:$P,10,FALSE()),0) -> 0 | P368: =IFERROR(VLOOKUP("14_"&A368,SyS!$B:$P,12,FALSE()),0) -> 0 | Q368: =+O368-P368 -> 0 | R368: =IFERROR(VLOOKUP("15_"&A368,SyS!$B:$P,10,FALSE()),0) -> 0 | S368: =IFERROR(VLOOKUP("15_"&A368,SyS!$B:$P,12,FALSE()),0) -> 0 | T368: =+R368-S368 -> 0 | U368: =IFERROR(VLOOKUP("16_"&A368,SyS!$B:$P,10,FALSE()),0) -> 0 | V368: =IFERROR(VLOOKUP("16_"&A368,SyS!$B:$P,12,FALSE()),0) -> 0 | W368: =+U368-V368 -> 0 | X368: =IFERROR(VLOOKUP("13_"&A368,SyS!$B:$P,10,FALSE()),0) -> 0 | Y368: =IFERROR(VLOOKUP("13_"&A368,SyS!$B:$P,12,FALSE()),0) -> 0 | Z368: =+X368-Y368 -> 0 | AA368: =IFERROR(VLOOKUP("17_"&A368,SyS!$B:$P,10,FALSE()),0) -> 0 | AB368: =IFERROR(VLOOKUP("17_"&A368,SyS!$B:$P,12,FALSE()),0) -> 0 | AC368: =+AA368-AB368 -> 0 | AG368: =IFERROR(VLOOKUP("19_"&A368,SyS!$B:$P,10,FALSE()),0) -> 0 | AH368: =IFERROR(VLOOKUP("19_"&A368,SyS!$B:$P,12,FALSE()),0) -> 0 | AI368: =+AG368-AH368 -> 0 | AM368: =IFERROR(VLOOKUP("23_"&A368,SyS!$B:$P,10,FALSE()),0) -> 0 | AN368: =IFERROR(VLOOKUP("23_"&A368,SyS!$B:$P,12,FALSE()),0) -> 0 | AO368: =+AM368-AN368 -> 0 | BK368: =IFERROR(VLOOKUP("29_"&A368,SyS!$B:$P,10,FALSE()),0) -> 0 | BL368: =IFERROR(VLOOKUP("29_"&A368,SyS!$B:$P,12,FALSE()),0) -> 0 | BM368: =+BK368-BL368 -> 0 | BN368: =IFERROR(VLOOKUP("30_"&A368,SyS!$B:$P,10,FALSE()),0) -> 0 | BO368: =IFERROR(VLOOKUP("30_"&A368,SyS!$B:$P,12,FALSE()),0) -> 0 | BP368: =+BN368-BO368 -> 0 | BQ368: =+E368+H368+K368+Q368+T368+W368+Z368+AC368+AF368+AI368+AL368+AO368+AR368+AU368+AX368+BA368+BD368+BG368+BJ368+BM368+BP368 -> 0
A369: 429700000 | B369: SEGUROS E PERFORACIÒN | C369: =IFERROR(VLOOKUP("1_"&A369,SyS!$B:$P,10,FALSE()),0) -> 0 | D369: =IFERROR(VLOOKUP("1_"&A369,SyS!$B:$P,12,FALSE()),0) -> 0 | E369: =+C369-D369 -> 0 | F369: =IFERROR(VLOOKUP("2_"&A369,SyS!$B:$P,10,FALSE()),0) -> 0 | G369: =IFERROR(VLOOKUP("2_"&A369,SyS!$B:$P,12,FALSE()),0) -> 0 | H369: =+F369-G369 -> 0 | O369: =IFERROR(VLOOKUP("14_"&A369,SyS!$B:$P,10,FALSE()),0) -> 0 | P369: =IFERROR(VLOOKUP("14_"&A369,SyS!$B:$P,12,FALSE()),0) -> 0 | Q369: =+O369-P369 -> 0 | R369: =IFERROR(VLOOKUP("15_"&A369,SyS!$B:$P,10,FALSE()),0) -> 0 | S369: =IFERROR(VLOOKUP("15_"&A369,SyS!$B:$P,12,FALSE()),0) -> 0 | T369: =+R369-S369 -> 0 | U369: =IFERROR(VLOOKUP("16_"&A369,SyS!$B:$P,10,FALSE()),0) -> 0 | V369: =IFERROR(VLOOKUP("16_"&A369,SyS!$B:$P,12,FALSE()),0) -> 0 | W369: =+U369-V369 -> 0 | X369: =IFERROR(VLOOKUP("13_"&A369,SyS!$B:$P,10,FALSE()),0) -> 0 | Y369: =IFERROR(VLOOKUP("13_"&A369,SyS!$B:$P,12,FALSE()),0) -> 0 | Z369: =+X369-Y369 -> 0 | AA369: =IFERROR(VLOOKUP("17_"&A369,SyS!$B:$P,10,FALSE()),0) -> 0 | AB369: =IFERROR(VLOOKUP("17_"&A369,SyS!$B:$P,12,FALSE()),0) -> 0 | AC369: =+AA369-AB369 -> 0 | AG369: =IFERROR(VLOOKUP("19_"&A369,SyS!$B:$P,10,FALSE()),0) -> 0 | AH369: =IFERROR(VLOOKUP("19_"&A369,SyS!$B:$P,12,FALSE()),0) -> 0 | AI369: =+AG369-AH369 -> 0 | AM369: =IFERROR(VLOOKUP("23_"&A369,SyS!$B:$P,10,FALSE()),0) -> 0 | AN369: =IFERROR(VLOOKUP("23_"&A369,SyS!$B:$P,12,FALSE()),0) -> 0 | AO369: =+AM369-AN369 -> 0 | BK369: =IFERROR(VLOOKUP("29_"&A369,SyS!$B:$P,10,FALSE()),0) -> 0 | BL369: =IFERROR(VLOOKUP("29_"&A369,SyS!$B:$P,12,FALSE()),0) -> 0 | BM369: =+BK369-BL369 -> 0 | BN369: =IFERROR(VLOOKUP("30_"&A369,SyS!$B:$P,10,FALSE()),0) -> 0 | BO369: =IFERROR(VLOOKUP("30_"&A369,SyS!$B:$P,12,FALSE()),0) -> 0 | BP369: =+BN369-BO369 -> 0 | BQ369: =+E369+H369+K369+Q369+T369+W369+Z369+AC369+AF369+AI369+AL369+AO369+AR369+AU369+AX369+BA369+BD369+BG369+BJ369+BM369+BP369 -> 0
A370: 429900000 | B370: Alquiler varios - E. Perforacion | C370: =IFERROR(VLOOKUP("1_"&A370,SyS!$B:$P,10,FALSE()),0) -> 0 | D370: =IFERROR(VLOOKUP("1_"&A370,SyS!$B:$P,12,FALSE()),0) -> 0 | E370: =+C370-D370 -> 0 | F370: =IFERROR(VLOOKUP("2_"&A370,SyS!$B:$P,10,FALSE()),0) -> 0 | G370: =IFERROR(VLOOKUP("2_"&A370,SyS!$B:$P,12,FALSE()),0) -> 0 | H370: =+F370-G370 -> 0 | O370: =IFERROR(VLOOKUP("14_"&A370,SyS!$B:$P,10,FALSE()),0) -> 0 | P370: =IFERROR(VLOOKUP("14_"&A370,SyS!$B:$P,12,FALSE()),0) -> 0 | Q370: =+O370-P370 -> 0 | R370: =IFERROR(VLOOKUP("15_"&A370,SyS!$B:$P,10,FALSE()),0) -> 0 | S370: =IFERROR(VLOOKUP("15_"&A370,SyS!$B:$P,12,FALSE()),0) -> 0 | T370: =+R370-S370 -> 0 | U370: =IFERROR(VLOOKUP("16_"&A370,SyS!$B:$P,10,FALSE()),0) -> 0 | V370: =IFERROR(VLOOKUP("16_"&A370,SyS!$B:$P,12,FALSE()),0) -> 0 | W370: =+U370-V370 -> 0 | X370: =IFERROR(VLOOKUP("13_"&A370,SyS!$B:$P,10,FALSE()),0) -> 0 | Y370: =IFERROR(VLOOKUP("13_"&A370,SyS!$B:$P,12,FALSE()),0) -> 0 | Z370: =+X370-Y370 -> 0 | AA370: =IFERROR(VLOOKUP("17_"&A370,SyS!$B:$P,10,FALSE()),0) -> 0 | AB370: =IFERROR(VLOOKUP("17_"&A370,SyS!$B:$P,12,FALSE()),0) -> 0 | AC370: =+AA370-AB370 -> 0 | AG370: =IFERROR(VLOOKUP("19_"&A370,SyS!$B:$P,10,FALSE()),0) -> 0 | AH370: =IFERROR(VLOOKUP("19_"&A370,SyS!$B:$P,12,FALSE()),0) -> 0 | AI370: =+AG370-AH370 -> 0 | AM370: =IFERROR(VLOOKUP("23_"&A370,SyS!$B:$P,10,FALSE()),0) -> 0 | AN370: =IFERROR(VLOOKUP("23_"&A370,SyS!$B:$P,12,FALSE()),0) -> 0 | AO370: =+AM370-AN370 -> 0 | BK370: =IFERROR(VLOOKUP("29_"&A370,SyS!$B:$P,10,FALSE()),0) -> 0 | BL370: =IFERROR(VLOOKUP("29_"&A370,SyS!$B:$P,12,FALSE()),0) -> 0 | BM370: =+BK370-BL370 -> 0 | BN370: =IFERROR(VLOOKUP("30_"&A370,SyS!$B:$P,10,FALSE()),0) -> 0 | BO370: =IFERROR(VLOOKUP("30_"&A370,SyS!$B:$P,12,FALSE()),0) -> 0 | BP370: =+BN370-BO370 -> 0 | BQ370: =+E370+H370+K370+Q370+T370+W370+Z370+AC370+AF370+AI370+AL370+AO370+AR370+AU370+AX370+BA370+BD370+BG370+BJ370+BM370+BP370 -> 0
A371: 429910000 | B371: Movilidad y Viáticos E Perforacion | C371: =IFERROR(VLOOKUP("1_"&A371,SyS!$B:$P,10,FALSE()),0) -> 0 | D371: =IFERROR(VLOOKUP("1_"&A371,SyS!$B:$P,12,FALSE()),0) -> 0 | E371: =+C371-D371 -> 0 | F371: =IFERROR(VLOOKUP("2_"&A371,SyS!$B:$P,10,FALSE()),0) -> 0 | G371: =IFERROR(VLOOKUP("2_"&A371,SyS!$B:$P,12,FALSE()),0) -> 0 | H371: =+F371-G371 -> 0 | O371: =IFERROR(VLOOKUP("14_"&A371,SyS!$B:$P,10,FALSE()),0) -> 0 | P371: =IFERROR(VLOOKUP("14_"&A371,SyS!$B:$P,12,FALSE()),0) -> 0 | Q371: =+O371-P371 -> 0 | R371: =IFERROR(VLOOKUP("15_"&A371,SyS!$B:$P,10,FALSE()),0) -> 0 | S371: =IFERROR(VLOOKUP("15_"&A371,SyS!$B:$P,12,FALSE()),0) -> 0 | T371: =+R371-S371 -> 0 | U371: =IFERROR(VLOOKUP("16_"&A371,SyS!$B:$P,10,FALSE()),0) -> 0 | V371: =IFERROR(VLOOKUP("16_"&A371,SyS!$B:$P,12,FALSE()),0) -> 0 | W371: =+U371-V371 -> 0 | X371: =IFERROR(VLOOKUP("13_"&A371,SyS!$B:$P,10,FALSE()),0) -> 0 | Y371: =IFERROR(VLOOKUP("13_"&A371,SyS!$B:$P,12,FALSE()),0) -> 0 | Z371: =+X371-Y371 -> 0 | AA371: =IFERROR(VLOOKUP("17_"&A371,SyS!$B:$P,10,FALSE()),0) -> 0 | AB371: =IFERROR(VLOOKUP("17_"&A371,SyS!$B:$P,12,FALSE()),0) -> 0 | AC371: =+AA371-AB371 -> 0 | AG371: =IFERROR(VLOOKUP("19_"&A371,SyS!$B:$P,10,FALSE()),0) -> 0 | AH371: =IFERROR(VLOOKUP("19_"&A371,SyS!$B:$P,12,FALSE()),0) -> 0 | AI371: =+AG371-AH371 -> 0 | AM371: =IFERROR(VLOOKUP("23_"&A371,SyS!$B:$P,10,FALSE()),0) -> 0 | AN371: =IFERROR(VLOOKUP("23_"&A371,SyS!$B:$P,12,FALSE()),0) -> 0 | AO371: =+AM371-AN371 -> 0 | BK371: =IFERROR(VLOOKUP("29_"&A371,SyS!$B:$P,10,FALSE()),0) -> 0 | BL371: =IFERROR(VLOOKUP("29_"&A371,SyS!$B:$P,12,FALSE()),0) -> 0 | BM371: =+BK371-BL371 -> 0 | BN371: =IFERROR(VLOOKUP("30_"&A371,SyS!$B:$P,10,FALSE()),0) -> 0 | BO371: =IFERROR(VLOOKUP("30_"&A371,SyS!$B:$P,12,FALSE()),0) -> 0 | BP371: =+BN371-BO371 -> 0 | BQ371: =+E371+H371+K371+Q371+T371+W371+Z371+AC371+AF371+AI371+AL371+AO371+AR371+AU371+AX371+BA371+BD371+BG371+BJ371+BM371+BP371 -> 0
A372: 429920000 | B372: Alojamiento E- Perforacion | C372: =IFERROR(VLOOKUP("1_"&A372,SyS!$B:$P,10,FALSE()),0) -> 0 | D372: =IFERROR(VLOOKUP("1_"&A372,SyS!$B:$P,12,FALSE()),0) -> 0 | E372: =+C372-D372 -> 0 | F372: =IFERROR(VLOOKUP("2_"&A372,SyS!$B:$P,10,FALSE()),0) -> 0 | G372: =IFERROR(VLOOKUP("2_"&A372,SyS!$B:$P,12,FALSE()),0) -> 0 | H372: =+F372-G372 -> 0 | O372: =IFERROR(VLOOKUP("14_"&A372,SyS!$B:$P,10,FALSE()),0) -> 0 | P372: =IFERROR(VLOOKUP("14_"&A372,SyS!$B:$P,12,FALSE()),0) -> 0 | Q372: =+O372-P372 -> 0 | R372: =IFERROR(VLOOKUP("15_"&A372,SyS!$B:$P,10,FALSE()),0) -> 0 | S372: =IFERROR(VLOOKUP("15_"&A372,SyS!$B:$P,12,FALSE()),0) -> 0 | T372: =+R372-S372 -> 0 | U372: =IFERROR(VLOOKUP("16_"&A372,SyS!$B:$P,10,FALSE()),0) -> 0 | V372: =IFERROR(VLOOKUP("16_"&A372,SyS!$B:$P,12,FALSE()),0) -> 0 | W372: =+U372-V372 -> 0 | X372: =IFERROR(VLOOKUP("13_"&A372,SyS!$B:$P,10,FALSE()),0) -> 0 | Y372: =IFERROR(VLOOKUP("13_"&A372,SyS!$B:$P,12,FALSE()),0) -> 0 | Z372: =+X372-Y372 -> 0 | AA372: =IFERROR(VLOOKUP("17_"&A372,SyS!$B:$P,10,FALSE()),0) -> 0 | AB372: =IFERROR(VLOOKUP("17_"&A372,SyS!$B:$P,12,FALSE()),0) -> 0 | AC372: =+AA372-AB372 -> 0 | AG372: =IFERROR(VLOOKUP("19_"&A372,SyS!$B:$P,10,FALSE()),0) -> 0 | AH372: =IFERROR(VLOOKUP("19_"&A372,SyS!$B:$P,12,FALSE()),0) -> 0 | AI372: =+AG372-AH372 -> 0 | AM372: =IFERROR(VLOOKUP("23_"&A372,SyS!$B:$P,10,FALSE()),0) -> 0 | AN372: =IFERROR(VLOOKUP("23_"&A372,SyS!$B:$P,12,FALSE()),0) -> 0 | AO372: =+AM372-AN372 -> 0 | BK372: =IFERROR(VLOOKUP("29_"&A372,SyS!$B:$P,10,FALSE()),0) -> 0 | BL372: =IFERROR(VLOOKUP("29_"&A372,SyS!$B:$P,12,FALSE()),0) -> 0 | BM372: =+BK372-BL372 -> 0 | BN372: =IFERROR(VLOOKUP("30_"&A372,SyS!$B:$P,10,FALSE()),0) -> 0 | BO372: =IFERROR(VLOOKUP("30_"&A372,SyS!$B:$P,12,FALSE()),0) -> 0 | BP372: =+BN372-BO372 -> 0 | BQ372: =+E372+H372+K372+Q372+T372+W372+Z372+AC372+AF372+AI372+AL372+AO372+AR372+AU372+AX372+BA372+BD372+BG372+BJ372+BM372+BP372 -> 0
A373: 429210000 | B373: Gastos Campamento - E. Perforacion | C373: =IFERROR(VLOOKUP("1_"&A373,SyS!$B:$P,10,FALSE()),0) -> 0 | D373: =IFERROR(VLOOKUP("1_"&A373,SyS!$B:$P,12,FALSE()),0) -> 0 | E373: =+C373-D373 -> 0 | F373: =IFERROR(VLOOKUP("2_"&A373,SyS!$B:$P,10,FALSE()),0) -> 0 | G373: =IFERROR(VLOOKUP("2_"&A373,SyS!$B:$P,12,FALSE()),0) -> 0 | H373: =+F373-G373 -> 0 | O373: =IFERROR(VLOOKUP("14_"&A373,SyS!$B:$P,10,FALSE()),0) -> 0 | P373: =IFERROR(VLOOKUP("14_"&A373,SyS!$B:$P,12,FALSE()),0) -> 0 | Q373: =+O373-P373 -> 0 | R373: =IFERROR(VLOOKUP("15_"&A373,SyS!$B:$P,10,FALSE()),0) -> 0 | S373: =IFERROR(VLOOKUP("15_"&A373,SyS!$B:$P,12,FALSE()),0) -> 0 | T373: =+R373-S373 -> 0 | U373: =IFERROR(VLOOKUP("16_"&A373,SyS!$B:$P,10,FALSE()),0) -> 0 | V373: =IFERROR(VLOOKUP("16_"&A373,SyS!$B:$P,12,FALSE()),0) -> 0 | W373: =+U373-V373 -> 0 | X373: =IFERROR(VLOOKUP("13_"&A373,SyS!$B:$P,10,FALSE()),0) -> 0 | Y373: =IFERROR(VLOOKUP("13_"&A373,SyS!$B:$P,12,FALSE()),0) -> 0 | Z373: =+X373-Y373 -> 0 | AA373: =IFERROR(VLOOKUP("17_"&A373,SyS!$B:$P,10,FALSE()),0) -> 0 | AB373: =IFERROR(VLOOKUP("17_"&A373,SyS!$B:$P,12,FALSE()),0) -> 0 | AC373: =+AA373-AB373 -> 0 | AG373: =IFERROR(VLOOKUP("19_"&A373,SyS!$B:$P,10,FALSE()),0) -> 0 | AH373: =IFERROR(VLOOKUP("19_"&A373,SyS!$B:$P,12,FALSE()),0) -> 0 | AI373: =+AG373-AH373 -> 0 | AM373: =IFERROR(VLOOKUP("23_"&A373,SyS!$B:$P,10,FALSE()),0) -> 0 | AN373: =IFERROR(VLOOKUP("23_"&A373,SyS!$B:$P,12,FALSE()),0) -> 0 | AO373: =+AM373-AN373 -> 0 | BK373: =IFERROR(VLOOKUP("29_"&A373,SyS!$B:$P,10,FALSE()),0) -> 0 | BL373: =IFERROR(VLOOKUP("29_"&A373,SyS!$B:$P,12,FALSE()),0) -> 0 | BM373: =+BK373-BL373 -> 0 | BN373: =IFERROR(VLOOKUP("30_"&A373,SyS!$B:$P,10,FALSE()),0) -> 0 | BO373: =IFERROR(VLOOKUP("30_"&A373,SyS!$B:$P,12,FALSE()),0) -> 0 | BP373: =+BN373-BO373 -> 0 | BQ373: =+E373+H373+K373+Q373+T373+W373+Z373+AC373+AF373+AI373+AL373+AO373+AR373+AU373+AX373+BA373+BD373+BG373+BJ373+BM373+BP373 -> 0
...

Sheet Dist.de gastos
C1: SOUTHERN COPPER CORPORATION - AGENCIA EN ARGENTINA
C3: DOLARES
F4: DISTRIBUCION DE GASTOS DEL PERIODO POR PROYECTO Y NATURALEZA DE GASTO
C6: DESCRIPCION | D6: MOVIMIENTO MES | F6: OFICINA | G6: EXPLORACIÓN | H6: TANQUE | I6: CERRO | J6: CERRO | K6: CENTRO | L6: LOS | M6: LOS | N6: CAÑADON | O6: LONCO VACA | P6: GASTOS | Q6: PROYECTO | R6: PROYECTO | S6: PROYECTO | T6: PROYECTO | U6: LA HOYADA | V6: CATAMARCA | W6: TOTAL | X6: TOTAL | Y6: TOTAL | Z6: TOTAL | AA6: TOTAL | AB6: TOTAL | AC6: TOTAL | AD6: TOTAL | AE6: TOTAL | AF6: TOTAL | AG6: TOTAL | AH6: TOTAL | AI6: TOTAL
A7: CHILE | B7: ELLIPSE | D7: DR | E7: CR | F7: GENERAL | G7: REGIONAL | H7: NEGRO | I7: LA MINA | J7: ABANICO | K7: ESPERANZA | L7: MORTERITOS | M7: MENUCOS | N7: DEL MORO | O7: PELENQUE | P7: GENERALES | Q7: SOL | R7: SHEYLA | S7: SHEYLA I | T7: LAS SANTAS I | W7: DICIEMBRE | X7: NOVIEMBRE | Y7: OCTUBRE | Z7: SEPTIEMBRE | AA7: AGOSTO | AB7: JULIO | AC7: JUNIO | AD7: MAYO | AE7: ABRIL | AF7: MARZO | AG7: FEBRERO | AH7: ENERO | AI7: AÑO
A8: 30-100-01 | B8: 9600000062 | C8: PATENTES | D8: =SUM(F8:V8)+E8 -> 243.71 | F8: =+'Sumas y Saldos'!E38+'Sumas y Saldos'!E254+'Sumas y Saldos'!E308+'Sumas y Saldos'!E326 -> 0 | G8: =+'Sumas y Saldos'!H38+'Sumas y Saldos'!H254+'Sumas y Saldos'!H308+'Sumas y Saldos'!H326 -> 0 | H8: =+'Sumas y Saldos'!K38+'Sumas y Saldos'!K254+'Sumas y Saldos'!K308+'Sumas y Saldos'!K326 -> 0 | I8: =+'Sumas y Saldos'!Q38+'Sumas y Saldos'!Q254+'Sumas y Saldos'!Q308+'Sumas y Saldos'!Q326 -> 0 | J8: =+'Sumas y Saldos'!Z38+'Sumas y Saldos'!Z254+'Sumas y Saldos'!Z308+'Sumas y Saldos'!Z326 -> 0 | K8: =+'Sumas y Saldos'!AC38+'Sumas y Saldos'!AC254+'Sumas y Saldos'!AC308+'Sumas y Saldos'!AC326 -> 243.71 | L8: =+'Sumas y Saldos'!AF38+'Sumas y Saldos'!AF254+'Sumas y Saldos'!AF308+'Sumas y Saldos'!AF326 -> 0 | M8: =+'Sumas y Saldos'!W38+'Sumas y Saldos'!W254+'Sumas y Saldos'!W308+'Sumas y Saldos'!W326 -> 0 | N8: =+'Sumas y Saldos'!T38+'Sumas y Saldos'!T254+'Sumas y Saldos'!T308+'Sumas y Saldos'!T326 -> 0 | O8: =+'Sumas y Saldos'!AI38+'Sumas y Saldos'!AI254+'Sumas y Saldos'!AI308+'Sumas y Saldos'!AI326 -> 0 | P8: =+'Sumas y Saldos'!AO38+'Sumas y Saldos'!AO254+'Sumas y Saldos'!AO308+'Sumas y Saldos'!AO326 -> 0 | Q8: =+'Sumas y Saldos'!AL38+'Sumas y Saldos'!AL254+'Sumas y Saldos'!AL308+'Sumas y Saldos'!AL326 -> 0 | T8: =+'Sumas y Saldos'!BD219 -> 0 | U8: =+'Sumas y Saldos'!BM253+'Sumas y Saldos'!BM306 -> 0 | V8: =+'Sumas y Saldos'!BP253 -> 0 | AD8: 243.71 | AE8: 234.18 | AF8: 240.92 | AG8: 242 | AH8: 499.18 | AI8: =SUM(W8:AH8) -> 1459.99
A9: 30-100-02 | B9: 9600000062 | C9: GASTOS COMPUTACIÓN | D9: =SUM(F9:V9)+E9 -> 1767.88 | E9: =+'Sumas y Saldos'!D35 -> 0 | F9: =+'Sumas y Saldos'!E36+'Sumas y Saldos'!E152+'Sumas y Saldos'!E171+'Sumas y Saldos'!E183+'Sumas y Saldos'!E196+'Sumas y Saldos'!E219+'Sumas y Saldos'!E245+'Sumas y Saldos'!E335 -> 0 | G9: =+'Sumas y Saldos'!H36+'Sumas y Saldos'!H152+'Sumas y Saldos'!H171+'Sumas y Saldos'!H183+'Sumas y Saldos'!H196+'Sumas y Saldos'!H219+'Sumas y Saldos'!H245+'Sumas y Saldos'!H335 -> 1767.88 | H9: =+'Sumas y Saldos'!K36+'Sumas y Saldos'!K152+'Sumas y Saldos'!K171+'Sumas y Saldos'!K183+'Sumas y Saldos'!K196+'Sumas y Saldos'!K219+'Sumas y Saldos'!K245+'Sumas y Saldos'!K335 -> 0 | I9: =+'Sumas y Saldos'!Q36+'Sumas y Saldos'!Q152+'Sumas y Saldos'!Q171+'Sumas y Saldos'!Q183+'Sumas y Saldos'!Q196+'Sumas y Saldos'!Q219+'Sumas y Saldos'!Q245+'Sumas y Saldos'!Q335 -> 0 | J9: =+'Sumas y Saldos'!Z36+'Sumas y Saldos'!Z152+'Sumas y Saldos'!Z171+'Sumas y Saldos'!Z183+'Sumas y Saldos'!Z196+'Sumas y Saldos'!Z219+'Sumas y Saldos'!Z245+'Sumas y Saldos'!Z335 -> 0 | K9: =+'Sumas y Saldos'!AC36+'Sumas y Saldos'!AC152+'Sumas y Saldos'!AC171+'Sumas y Saldos'!AC183+'Sumas y Saldos'!AC196+'Sumas y Saldos'!AC219+'Sumas y Saldos'!AC245+'Sumas y Saldos'!AC335 -> 0 | L9: =+'Sumas y Saldos'!AF36+'Sumas y Saldos'!AF152+'Sumas y Saldos'!AF171+'Sumas y Saldos'!AF183+'Sumas y Saldos'!AF196+'Sumas y Saldos'!AF219+'Sumas y Saldos'!AF245+'Sumas y Saldos'!AF335 -> 0 | M9: =+'Sumas y Saldos'!W36+'Sumas y Saldos'!W152+'Sumas y Saldos'!W171+'Sumas y Saldos'!W183+'Sumas y Saldos'!W196+'Sumas y Saldos'!W219+'Sumas y Saldos'!W245+'Sumas y Saldos'!W335 -> 0 | N9: =+'Sumas y Saldos'!T36+'Sumas y Saldos'!T152+'Sumas y Saldos'!T171+'Sumas y Saldos'!T183+'Sumas y Saldos'!T196+'Sumas y Saldos'!T219+'Sumas y Saldos'!T245+'Sumas y Saldos'!T335 -> 0 | O9: =+'Sumas y Saldos'!AI36+'Sumas y Saldos'!AI152+'Sumas y Saldos'!AI171+'Sumas y Saldos'!AI183+'Sumas y Saldos'!AI196+'Sumas y Saldos'!AI219+'Sumas y Saldos'!AI245+'Sumas y Saldos'!AI335 -> 0 | P9: =+'Sumas y Saldos'!AO36+'Sumas y Saldos'!AO152+'Sumas y Saldos'!AO171+'Sumas y Saldos'!AO183+'Sumas y Saldos'!AO196+'Sumas y Saldos'!AO219+'Sumas y Saldos'!AO245+'Sumas y Saldos'!AO335 -> 0 | Q9: =+'Sumas y Saldos'!AL36+'Sumas y Saldos'!AL152+'Sumas y Saldos'!AL171+'Sumas y Saldos'!AL183+'Sumas y Saldos'!AL196+'Sumas y Saldos'!AL219+'Sumas y Saldos'!AL245+'Sumas y Saldos'!AL335 -> 0 | T9: =+'Sumas y Saldos'!BD220 -> 0 | U9: =+'Sumas y Saldos'!BM332 -> 0 | V9: =+'Sumas y Saldos'!BP183+'Sumas y Saldos'!BP196+'Sumas y Saldos'!BP151 -> 0 | AD9: 1767.88 | AE9: 133.25 | AF9: 286.33 | AG9: 24.29 | AH9: 1249.18 | AI9: =SUM(W9:AH9) -> 3460.93
A10: 30-100-04 | B10: 9600000062 | C10: GASTOS COMUNICACIONES | D10: =SUM(F10:V10)+E10 -> 359.96 | E10: =+'Sumas y Saldos'!S214 -> 0 | F10: =+'Sumas y Saldos'!E77+'Sumas y Saldos'!E78+'Sumas y Saldos'!E138+'Sumas y Saldos'!E139+'Sumas y Saldos'!E182+'Sumas y Saldos'!E198+'Sumas y Saldos'!E205+'Sumas y Saldos'!E214+'Sumas y Saldos'!E275+'Sumas y Saldos'!E311+'Sumas y Saldos'!E327+'Sumas y Saldos'!E346+'Sumas y Saldos'!E366 -> 0 | G10: =+'Sumas y Saldos'!H77+'Sumas y Saldos'!H78+'Sumas y Saldos'!H138+'Sumas y Saldos'!H139+'Sumas y Saldos'!H182+'Sumas y Saldos'!H198+'Sumas y Saldos'!H205+'Sumas y Saldos'!H214+'Sumas y Saldos'!H275+'Sumas y Saldos'!H311+'Sumas y Saldos'!H327+'Sumas y Saldos'!H346+'Sumas y Saldos'!H366 -> 0 | H10: =+'Sumas y Saldos'!K77+'Sumas y Saldos'!K78+'Sumas y Saldos'!K138+'Sumas y Saldos'!K139+'Sumas y Saldos'!K182+'Sumas y Saldos'!K198+'Sumas y Saldos'!K205+'Sumas y Saldos'!K214+'Sumas y Saldos'!K275+'Sumas y Saldos'!K311+'Sumas y Saldos'!K327+'Sumas y Saldos'!K346+'Sumas y Saldos'!K366 -> 0 | I10: =+'Sumas y Saldos'!Q77+'Sumas y Saldos'!Q78+'Sumas y Saldos'!Q138+'Sumas y Saldos'!Q139+'Sumas y Saldos'!Q182+'Sumas y Saldos'!Q198+'Sumas y Saldos'!Q205+'Sumas y Saldos'!Q214+'Sumas y Saldos'!Q275+'Sumas y Saldos'!Q311+'Sumas y Saldos'!Q327+'Sumas y Saldos'!Q346+'Sumas y Saldos'!Q366 -> 0 | J10: =+'Sumas y Saldos'!Z77+'Sumas y Saldos'!Z78+'Sumas y Saldos'!Z138+'Sumas y Saldos'!Z139+'Sumas y Saldos'!Z182+'Sumas y Saldos'!Z198+'Sumas y Saldos'!Z205+'Sumas y Saldos'!Z214+'Sumas y Saldos'!Z275+'Sumas y Saldos'!Z311+'Sumas y Saldos'!Z327+'Sumas y Saldos'!Z346+'Sumas y Saldos'!Z366 -> 0 | K10: =+'Sumas y Saldos'!AC77+'Sumas y Saldos'!AC78+'Sumas y Saldos'!AC138+'Sumas y Saldos'!AC139+'Sumas y Saldos'!AC182+'Sumas y Saldos'!AC198+'Sumas y Saldos'!AC205+'Sumas y Saldos'!AC214+'Sumas y Saldos'!AC275+'Sumas y Saldos'!AC311+'Sumas y Saldos'!AC327+'Sumas y Saldos'!AC346+'Sumas y Saldos'!AC366 -> 359.96 | L10: =+'Sumas y Saldos'!AF77+'Sumas y Saldos'!AF78+'Sumas y Saldos'!AF138+'Sumas y Saldos'!AF139+'Sumas y Saldos'!AF182+'Sumas y Saldos'!AF198+'Sumas y Saldos'!AF205+'Sumas y Saldos'!AF214+'Sumas y Saldos'!AF275+'Sumas y Saldos'!AF311+'Sumas y Saldos'!AF327+'Sumas y Saldos'!AF346+'Sumas y Saldos'!AF366 -> 0 | M10: =+'Sumas y Saldos'!W77+'Sumas y Saldos'!W78+'Sumas y Saldos'!W138+'Sumas y Saldos'!W139+'Sumas y Saldos'!W182+'Sumas y Saldos'!W198+'Sumas y Saldos'!W205+'Sumas y Saldos'!W214+'Sumas y Saldos'!W275+'Sumas y Saldos'!W311+'Sumas y Saldos'!W327+'Sumas y Saldos'!W346+'Sumas y Saldos'!W366 -> 0 | N10: =+'Sumas y Saldos'!T77+'Sumas y Saldos'!T78+'Sumas y Saldos'!T138+'Sumas y Saldos'!T139+'Sumas y Saldos'!T182+'Sumas y Saldos'!T198+'Sumas y Saldos'!T205+'Sumas y Saldos'!T214+'Sumas y Saldos'!T275+'Sumas y Saldos'!T311+'Sumas y Saldos'!T327+'Sumas y Saldos'!T346+'Sumas y Saldos'!T366 -> 0 | O10: =+'Sumas y Saldos'!AI77+'Sumas y Saldos'!AI78+'Sumas y Saldos'!AI138+'Sumas y Saldos'!AI139+'Sumas y Saldos'!AI182+'Sumas y Saldos'!AI198+'Sumas y Saldos'!AI205+'Sumas y Saldos'!AI214+'Sumas y Saldos'!AI275+'Sumas y Saldos'!AI311+'Sumas y Saldos'!AI327+'Sumas y Saldos'!AI346+'Sumas y Saldos'!AI366 -> 0 | P10: =+'Sumas y Saldos'!AO77+'Sumas y Saldos'!AO78+'Sumas y Saldos'!AO138+'Sumas y Saldos'!AO139+'Sumas y Saldos'!AO182+'Sumas y Saldos'!AO198+'Sumas y Saldos'!AO205+'Sumas y Saldos'!AO214+'Sumas y Saldos'!AO275+'Sumas y Saldos'!AO311+'Sumas y Saldos'!AO327+'Sumas y Saldos'!AO346+'Sumas y Saldos'!AO366 -> 0 | Q10: =+'Sumas y Saldos'!AL77+'Sumas y Saldos'!AL78+'Sumas y Saldos'!AL138+'Sumas y Saldos'!AL139+'Sumas y Saldos'!AL182+'Sumas y Saldos'!AL198+'Sumas y Saldos'!AL205+'Sumas y Saldos'!AL214+'Sumas y Saldos'!AL275+'Sumas y Saldos'!AL311+'Sumas y Saldos'!AL327+'Sumas y Saldos'!AL346+'Sumas y Saldos'!AL366 -> 0 | T10: =+'Sumas y Saldos'!BD221 -> 0 | U10: =+'Sumas y Saldos'!BM198+'Sumas y Saldos'!BM273+'Sumas y Saldos'!BM343+'Sumas y Saldos'!BM182 -> 0 | V10: =+'Sumas y Saldos'!BP137+'Sumas y Saldos'!BP182+'Sumas y Saldos'!BP198+'Sumas y Saldos'!BP273+'Sumas y Saldos'!BP77 -> 0 | AD10: 359.96 | AE10: 0 | AF10: 2805.03 | AG10: 1468.51 | AH10: 546.58 | AI10: =SUM(W10:AH10) -> 5180.08
A11: 30-100-05 | B11: 9600000062 | C11: GASTOS EXPLORACION | D11: =SUM(F11:V11)+E11 -> 0 | F11: =+'Sumas y Saldos'!E62+'Sumas y Saldos'!E67+'Sumas y Saldos'!E253 -> 0 | G11: =+'Sumas y Saldos'!H62+'Sumas y Saldos'!H67+'Sumas y Saldos'!H253 -> 0 | H11: =+'Sumas y Saldos'!K62+'Sumas y Saldos'!K67+'Sumas y Saldos'!K253 -> 0 | I11: =+'Sumas y Saldos'!Q62+'Sumas y Saldos'!Q67+'Sumas y Saldos'!Q253 -> 0 | J11: =+'Sumas y Saldos'!Z62+'Sumas y Saldos'!Z67+'Sumas y Saldos'!Z253 -> 0 | K11: =+'Sumas y Saldos'!AC62+'Sumas y Saldos'!AC67+'Sumas y Saldos'!AC253 -> 0 | L11: =+'Sumas y Saldos'!AF62+'Sumas y Saldos'!AF67+'Sumas y Saldos'!AF253 -> 0 | M11: =+'Sumas y Saldos'!W62+'Sumas y Saldos'!W67+'Sumas y Saldos'!W253 -> 0 | N11: =+'Sumas y Saldos'!T62+'Sumas y Saldos'!T67+'Sumas y Saldos'!T253 -> 0 | O11: =+'Sumas y Saldos'!AI62+'Sumas y Saldos'!AI67+'Sumas y Saldos'!AI253 -> 0 | P11: =+'Sumas y Saldos'!AO62+'Sumas y Saldos'!AO67+'Sumas y Saldos'!AO253 -> 0 | Q11: =+'Sumas y Saldos'!AL62+'Sumas y Saldos'!AL67+'Sumas y Saldos'!AL253 -> 0 | T11: =+'Sumas y Saldos'!BD222 -> 0 | U11: =+'Sumas y Saldos'!BM293 -> 0 | V11: =+'Sumas y Saldos'!BP252 -> 0 | AD11: 0 | AE11: 0 | AF11: 2234.96 | AG11: 0 | AH11: 0 | AI11: =SUM(W11:AH11) -> 2234.96
A12: 30-100-06 | B12: 9600000062 | C12: REPARAC.Y MANTENC. | D12: =SUM(F12:V12)+E12 -> 0 | E12: =+'Sumas y Saldos'!S103+'Sumas y Saldos'!Y103+'Sumas y Saldos'!G103 -> 0 | F12: =+'Sumas y Saldos'!E85+'Sumas y Saldos'!E104+'Sumas y Saldos'!E154+'Sumas y Saldos'!E201+'Sumas y Saldos'!E224+'Sumas y Saldos'!E302 -> 0 | G12: =+'Sumas y Saldos'!H85+'Sumas y Saldos'!H104+'Sumas y Saldos'!H154+'Sumas y Saldos'!H201+'Sumas y Saldos'!H224+'Sumas y Saldos'!H302 -> 0 | H12: =+'Sumas y Saldos'!K85+'Sumas y Saldos'!K104+'Sumas y Saldos'!K154+'Sumas y Saldos'!K201+'Sumas y Saldos'!K224+'Sumas y Saldos'!K302 -> 0 | I12: =+'Sumas y Saldos'!Q85+'Sumas y Saldos'!Q104+'Sumas y Saldos'!Q154+'Sumas y Saldos'!Q201+'Sumas y Saldos'!Q224+'Sumas y Saldos'!Q302 -> 0 | J12: =+'Sumas y Saldos'!Z85+'Sumas y Saldos'!Z104+'Sumas y Saldos'!Z154+'Sumas y Saldos'!Z201+'Sumas y Saldos'!Z224+'Sumas y Saldos'!Z302 -> 0 | K12: =+'Sumas y Saldos'!AC85+'Sumas y Saldos'!AC104+'Sumas y Saldos'!AC154+'Sumas y Saldos'!AC201+'Sumas y Saldos'!AC224+'Sumas y Saldos'!AC302 -> 0 | L12: =+'Sumas y Saldos'!AF85+'Sumas y Saldos'!AF104+'Sumas y Saldos'!AF154+'Sumas y Saldos'!AF201+'Sumas y Saldos'!AF224+'Sumas y Saldos'!AF302 -> 0 | M12: =+'Sumas y Saldos'!W85+'Sumas y Saldos'!W104+'Sumas y Saldos'!W154+'Sumas y Saldos'!W201+'Sumas y Saldos'!W224+'Sumas y Saldos'!W302 -> 0 | N12: =+'Sumas y Saldos'!T85+'Sumas y Saldos'!T104+'Sumas y Saldos'!T154+'Sumas y Saldos'!T201+'Sumas y Saldos'!T224+'Sumas y Saldos'!T302 -> 0 | O12: =+'Sumas y Saldos'!AI85+'Sumas y Saldos'!AI104+'Sumas y Saldos'!AI154+'Sumas y Saldos'!AI201+'Sumas y Saldos'!AI224+'Sumas y Saldos'!AI302 -> 0 | P12: =+'Sumas y Saldos'!AO85+'Sumas y Saldos'!AO104+'Sumas y Saldos'!AO154+'Sumas y Saldos'!AO201+'Sumas y Saldos'!AO224+'Sumas y Saldos'!AO302 -> 0 | Q12: =+'Sumas y Saldos'!AL85+'Sumas y Saldos'!AL104+'Sumas y Saldos'!AL154+'Sumas y Saldos'!AL201+'Sumas y Saldos'!AL224+'Sumas y Saldos'!AL302 -> 0 | T12: =+'Sumas y Saldos'!BD223 -> 0 | U12: =+'Sumas y Saldos'!BM300 -> 0 | V12: =+'Sumas y Saldos'!BP156+'Sumas y Saldos'!BP153+'Sumas y Saldos'!BN201 -> 0 | AD12: 0 | AE12: 42.89 | AF12: 171.92 | AG12: 0 | AH12: 9907.11 | AI12: =SUM(W12:AH12) -> 10121.92
A13: 30-100-07 | B13: 9600000062 | C13: HONORARIOS LEGALES | D13: =SUM(F13:V13)+E13 -> 0 | E13: =+'Sumas y Saldos'!AN163 -> 0 | F13: =+'Sumas y Saldos'!E156+'Sumas y Saldos'!E163+'Sumas y Saldos'!E190+'Sumas y Saldos'!E348 -> 0 | G13: =+'Sumas y Saldos'!H156+'Sumas y Saldos'!H163+'Sumas y Saldos'!H190+'Sumas y Saldos'!H348 -> 0 | H13: =+'Sumas y Saldos'!K156+'Sumas y Saldos'!K163+'Sumas y Saldos'!K190+'Sumas y Saldos'!K348 -> 0 | I13: =+'Sumas y Saldos'!Q156+'Sumas y Saldos'!Q163+'Sumas y Saldos'!Q190+'Sumas y Saldos'!Q348 -> 0 | J13: =+'Sumas y Saldos'!Z156+'Sumas y Saldos'!Z163+'Sumas y Saldos'!Z190+'Sumas y Saldos'!Z348 -> 0 | K13: =+'Sumas y Saldos'!AC156+'Sumas y Saldos'!AC163+'Sumas y Saldos'!AC190+'Sumas y Saldos'!AC348 -> 0 | L13: =+'Sumas y Saldos'!AF156+'Sumas y Saldos'!AF163+'Sumas y Saldos'!AF190+'Sumas y Saldos'!AF348 -> 0 | M13: =+'Sumas y Saldos'!W156+'Sumas y Saldos'!W163+'Sumas y Saldos'!W190+'Sumas y Saldos'!W348 -> 0 | N13: =+'Sumas y Saldos'!T156+'Sumas y Saldos'!T163+'Sumas y Saldos'!T190+'Sumas y Saldos'!T348 -> 0 | O13: =+'Sumas y Saldos'!AI156+'Sumas y Saldos'!AI163+'Sumas y Saldos'!AI190+'Sumas y Saldos'!AI348 -> 0 | P13: =+'Sumas y Saldos'!AO156+'Sumas y Saldos'!AO163+'Sumas y Saldos'!AO190+'Sumas y Saldos'!AO348 -> 0 | Q13: =+'Sumas y Saldos'!AL156+'Sumas y Saldos'!AL163+'Sumas y Saldos'!AL190+'Sumas y Saldos'!AL348 -> 0 | T13: =+'Sumas y Saldos'!BD224 -> 0 | U13: =+'Sumas y Saldos'!BM163 -> 0 | AD13: 0 | AE13: 0 | AF13: 0 | AG13: 0 | AH13: 0 | AI13: =SUM(W13:AH13) -> 0
A14: 30-100-08 | B14: 9600000062 | C14: GASTOS EN TRÁMITES | D14: =SUM(F14:V14)+E14 -> 0 | E14: =+'Sumas y Saldos'!G38 -> 0 | F14: =+'Sumas y Saldos'!E39 -> 0 | G14: =+'Sumas y Saldos'!H39 -> 0 | H14: =+'Sumas y Saldos'!K39 -> 0 | I14: =+'Sumas y Saldos'!Q39 -> 0 | J14: =+'Sumas y Saldos'!Z39 -> 0 | K14: =+'Sumas y Saldos'!AC39 -> 0 | L14: =+'Sumas y Saldos'!AF39 -> 0 | M14: =+'Sumas y Saldos'!W39 -> 0 | N14: =+'Sumas y Saldos'!T39 -> 0 | O14: =+'Sumas y Saldos'!AI39 -> 0 | P14: =+'Sumas y Saldos'!AO39 -> 0 | Q14: =+'Sumas y Saldos'!AL39 -> 0 | T14: =+'Sumas y Saldos'!BD225 -> 0 | V14: =+'Sumas y Saldos'!BP221+'Sumas y Saldos'!BP168+'Sumas y Saldos'!BP136 -> 0 | AD14: 0 | AE14: 0 | AF14: 0 | AG14: 0 | AH14: 0 | AI14: =SUM(W14:AH14) -> 0
A15: 30-100-09 | B15: 9600000062 | C15: GASTOS DE CAPACITACION | D15: =SUM(F15:V15)+E15 -> 0 | E15: 0 | F15: =+'Sumas y Saldos'!E81+'Sumas y Saldos'!E143+'Sumas y Saldos'!E252+'Sumas y Saldos'!E300 -> 0 | G15: =+'Sumas y Saldos'!H81+'Sumas y Saldos'!H143+'Sumas y Saldos'!H252+'Sumas y Saldos'!H300 -> 0 | H15: =+'Sumas y Saldos'!K81+'Sumas y Saldos'!K143+'Sumas y Saldos'!K252+'Sumas y Saldos'!K300 -> 0 | I15: =+'Sumas y Saldos'!Q81+'Sumas y Saldos'!Q143+'Sumas y Saldos'!Q252+'Sumas y Saldos'!Q300 -> 0 | J15: =+'Sumas y Saldos'!Z81+'Sumas y Saldos'!Z143+'Sumas y Saldos'!Z252+'Sumas y Saldos'!Z300 -> 0 | K15: =+'Sumas y Saldos'!AC81+'Sumas y Saldos'!AC143+'Sumas y Saldos'!AC252+'Sumas y Saldos'!AC300 -> 0 | L15: =+'Sumas y Saldos'!AF81+'Sumas y Saldos'!AF143+'Sumas y Saldos'!AF252+'Sumas y Saldos'!AF300 -> 0 | M15: =+'Sumas y Saldos'!W81+'Sumas y Saldos'!W143+'Sumas y Saldos'!W252+'Sumas y Saldos'!W300 -> 0 | N15: =+'Sumas y Saldos'!T81+'Sumas y Saldos'!T143+'Sumas y Saldos'!T252+'Sumas y Saldos'!T300 -> 0 | O15: =+'Sumas y Saldos'!AI81+'Sumas y Saldos'!AI143+'Sumas y Saldos'!AI252+'Sumas y Saldos'!AI300 -> 0 | P15: =+'Sumas y Saldos'!AO81+'Sumas y Saldos'!AO143+'Sumas y Saldos'!AO252+'Sumas y Saldos'!AO300 -> 0 | Q15: =+'Sumas y Saldos'!AL81+'Sumas y Saldos'!AL143+'Sumas y Saldos'!AL252+'Sumas y Saldos'!AL300 -> 0 | T15: =+'Sumas y Saldos'!BD226 -> 0 | U15: =+'Sumas y Saldos'!BM298 -> 0 | AD15: 0 | AE15: 0 | AF15: 0 | AG15: 0 | AH15: 0 | AI15: =SUM(W15:AH15) -> 0
C16: FOTOCOPIAS | D16: =SUM(F16:V16)+E16 -> 0 | E16: =+'Sumas y Saldos'!D81 -> 0 | F16: =+'Sumas y Saldos'!E102 -> 0 | G16: =+'Sumas y Saldos'!H102 -> 0 | H16: =+'Sumas y Saldos'!K102 -> 0 | I16: =+'Sumas y Saldos'!Q102 -> 0 | J16: =+'Sumas y Saldos'!Z102 -> 0 | K16: =+'Sumas y Saldos'!AC102 -> 0 | L16: =+'Sumas y Saldos'!AF102 -> 0 | M16: =+'Sumas y Saldos'!W102 -> 0 | N16: =+'Sumas y Saldos'!T102 -> 0 | O16: =+'Sumas y Saldos'!AI102 -> 0 | P16: =+'Sumas y Saldos'!AO102 -> 0 | Q16: =+'Sumas y Saldos'!AL102 -> 0 | T16: =+'Sumas y Saldos'!BD227 -> 0 | AD16: 0 | AE16: 0 | AF16: 0 | AG16: 0 | AH16: 0 | AI16: =SUM(W16:AH16) -> 0
A17: 30-100-12 | B17: 9600000062 | C17: LIBRERIA Y PAPELERIA | D17: =SUM(F17:V17)+E17 -> 21.79 | E17: =+'Sumas y Saldos'!D98+'Sumas y Saldos'!G98 -> 0 | F17: =+'Sumas y Saldos'!E99+'Sumas y Saldos'!E161+'Sumas y Saldos'!E193+'Sumas y Saldos'!E239+'Sumas y Saldos'!E279+'Sumas y Saldos'!E336+'Sumas y Saldos'!E339+'Sumas y Saldos'!E363+'Sumas y Saldos'!E396 -> 0 | G17: =+'Sumas y Saldos'!H99+'Sumas y Saldos'!H161+'Sumas y Saldos'!H193+'Sumas y Saldos'!H239+'Sumas y Saldos'!H279+'Sumas y Saldos'!H336+'Sumas y Saldos'!H339+'Sumas y Saldos'!H363+'Sumas y Saldos'!H396 -> 20.71 | H17: =+'Sumas y Saldos'!K99+'Sumas y Saldos'!K161+'Sumas y Saldos'!K193+'Sumas y Saldos'!K239+'Sumas y Saldos'!K279+'Sumas y Saldos'!K336+'Sumas y Saldos'!K339+'Sumas y Saldos'!K363+'Sumas y Saldos'!K396 -> 0 | I17: =+'Sumas y Saldos'!Q99+'Sumas y Saldos'!Q161+'Sumas y Saldos'!Q193+'Sumas y Saldos'!Q239+'Sumas y Saldos'!Q279+'Sumas y Saldos'!Q336+'Sumas y Saldos'!Q339+'Sumas y Saldos'!Q363+'Sumas y Saldos'!Q396 -> 0 | J17: =+'Sumas y Saldos'!Z99+'Sumas y Saldos'!Z161+'Sumas y Saldos'!Z193+'Sumas y Saldos'!Z239+'Sumas y Saldos'!Z279+'Sumas y Saldos'!Z336+'Sumas y Saldos'!Z339+'Sumas y Saldos'!Z363+'Sumas y Saldos'!Z396 -> 0 | K17: =+'Sumas y Saldos'!AC99+'Sumas y Saldos'!AC161+'Sumas y Saldos'!AC193+'Sumas y Saldos'!AC239+'Sumas y Saldos'!AC279+'Sumas y Saldos'!AC336+'Sumas y Saldos'!AC339+'Sumas y Saldos'!AC363+'Sumas y Saldos'!AC396 -> 1.08 | L17: =+'Sumas y Saldos'!AF99+'Sumas y Saldos'!AF161+'Sumas y Saldos'!AF193+'Sumas y Saldos'!AF239+'Sumas y Saldos'!AF279+'Sumas y Saldos'!AF336+'Sumas y Saldos'!AF339+'Sumas y Saldos'!AF363+'Sumas y Saldos'!AF396 -> 0 | M17: =+'Sumas y Saldos'!W99+'Sumas y Saldos'!W161+'Sumas y Saldos'!W193+'Sumas y Saldos'!W239+'Sumas y Saldos'!W279+'Sumas y Saldos'!W336+'Sumas y Saldos'!W339+'Sumas y Saldos'!W363+'Sumas y Saldos'!W396 -> 0 | N17: =+'Sumas y Saldos'!T99+'Sumas y Saldos'!T161+'Sumas y Saldos'!T193+'Sumas y Saldos'!T239+'Sumas y Saldos'!T279+'Sumas y Saldos'!T336+'Sumas y Saldos'!T339+'Sumas y Saldos'!T363+'Sumas y Saldos'!T396 -> 0 | O17: =+'Sumas y Saldos'!AI99+'Sumas y Saldos'!AI161+'Sumas y Saldos'!AI193+'Sumas y Saldos'!AI239+'Sumas y Saldos'!AI279+'Sumas y Saldos'!AI336+'Sumas y Saldos'!AI339+'Sumas y Saldos'!AI363+'Sumas y Saldos'!AI396 -> 0 | P17: =+'Sumas y Saldos'!AO99+'Sumas y Saldos'!AO161+'Sumas y Saldos'!AO193+'Sumas y Saldos'!AO239+'Sumas y Saldos'!AO279+'Sumas y Saldos'!AO336+'Sumas y Saldos'!AO339+'Sumas y Saldos'!AO363+'Sumas y Saldos'!AO396 -> 0 | Q17: =+'Sumas y Saldos'!AL99+'Sumas y Saldos'!AL161+'Sumas y Saldos'!AL193+'Sumas y Saldos'!AL239+'Sumas y Saldos'!AL279+'Sumas y Saldos'!AL336+'Sumas y Saldos'!AL339+'Sumas y Saldos'!AL363+'Sumas y Saldos'!AL396 -> 0 | R17: =+'Sumas y Saldos'!BE277 -> 0 | T17: =+'Sumas y Saldos'!BD228 -> 0 | U17: =+'Sumas y Saldos'!BM333+'Sumas y Saldos'!BM238+'Sumas y Saldos'!BM277+'Sumas y Saldos'!BM336 -> 0 | V17: =+'Sumas y Saldos'!BP161+'Sumas y Saldos'!BP333+'Sumas y Saldos'!BP193+'Sumas y Saldos'!BN394 -> 0 | AD17: 21.79 | AE17: 270.41 | AF17: 96.91 | AG17: 22.16 | AH17: 0 | AI17: =SUM(W17:AH17) -> 411.27
