Workbook

Sheet Balance
A1: ESTADO DE SITUACION PATRIMONIAL
A2: Al 31 de julio de 2026 - Cifras expresadas en dólares
F5: 46234 | G5: 31.03.04 | L5: =+F5 -> 46203
B6: ACTIVO: | G6: Historico | I6: PASIVO
C7: ACTIVO CORRIENTE | I7: PASIVO CORRIENTE
D8: Caja y Bancos (Nota 4.a) | F8: =+'Activo y Pasivo'!F17 -> 13953.93 | J8: Deudas Comerciales (Nota 4.e) | L8: =+'Activo y Pasivo'!F68 -> 71988.875
D9: Otros Créditos (Nota 4.b) | F9: =+'Activo y Pasivo'!F48 -> 3716769.9 | J9: Cargas Fiscales (Nota 4.f) | L9: =+'Activo y Pasivo'!F81 -> 1368944.1
D10: Otros Activos (Nota 4.c) | F10: =+'Activo y Pasivo'!F52 -> 104684 | J10: Remuneraciones y Cargas Sociales (Nota 4.g) | L10: =+'Activo y Pasivo'!F88 -> 58289.6
C11: Total del Activo corriente | F11: =SUM(F8:F10) -> 3835407.9 | I11: Total del Pasivo Corriente | L11: =SUM(L8:L10) -> 1499222.6
I12: Total del Pasivo | L12: =+L11 -> 1499222.6
D14: Inversiones (Nota 4.d) | F14: =+'Activo y Pasivo'!F58 -> 0
D15: Bienes de Uso (Anexo I) | F15: =+'Anexo I'!K24 -> 72868.68
I16: PATRIMONIO NETO (Según estado respectivo) | L16: =+Pat.Neto!J21 -> 2409053.9
C18: Total del Activo no corriente | F18: =SUM(F14:F17) -> 72868.68
C20: Total del Activo | F20: =+F11+F18 -> 3908276.5 | I20: Total del Pasivo y Patrimonio Neto | L20: =+L12+L16 -> 3908276.5
A22: Las notas y anexos adjuntos forman parte integrante de los estados contables
A23: Informe profesional por separado | L23: =+L20-F20 -> 0.0029113134
D31: Miguel Ángel Alonso | F31: Pedro Nicholson | K31: Alejandro Poletto
D32: Contador Público (U.C.A.) | F32: Síndico | K32: Southern Copper Arg. S.R.L.
D33: C.P.C.E.C.A.B.A. Tº176 Fº03 | K33: Gerente

Sheet Resultados
A1: ESTADO DE RESULTADOS
A2: =+Balance!A2 -> Al 30 de junio de 2026 - Cifras expresadas en dólares
B5: =+Balance!F5 -> 46203 | C5: =+Balance!F5 -> 46203
A8: Ventas y servicios netas | C8: 0
A9: Costo de mercaderías vendidas | C9: 0
A10: Ganancia neta | C10: =+C8-C9 -> 0
A12: Gastos de comercialización (Anexo II) | C12: =+'Anexo II'!G102 -> 0
A13: Gastos de administración (Anexo II) | C13: =-'Anexo II'!F102 -> -530007.27
A14: Gastos de financieros (Anexo II) | C14: =+'Anexo II'!I102 -> 0
A15: Gastos de Exploración | C15: =-'Anexo II'!H102 -> -616736.47
A16: Otros ingresos y egresos | C16: 0
A17: Resultados financieros y por tenencia | C17: =-'Distribución por línea'!C149-'Distribución por línea'!C109 -> -46243.868
A18: Otros ingresos y egresos | C18: =-'Distribución por línea'!C112
A19: Resultados Extraordinarios | C19: =-'Distribución por línea'!C208
A21: Pérdida antes de impuesto a las Ganancias | C21: =+C10+SUM(C12:C20) -> -1192987.6
A23: Impuesto a las Ganancias | C23: 0
A25: Pérdida del ejercicio | C25: =+C21-C23 -> -1192987.6
A30: Las notas y anexos adjuntos forman parte integrante de los estados contables
A31: Informe profesional por separado
A38: =+Balance!D31 -> Miguel Ángel Alonso | C38: =+Balance!F31 -> Pedro Nicholson | E38: =+Balance!K31 -> Alejandro Poletto
A39: =+Balance!D32 -> Contador Público (U.C.A.) | C39: =+Balance!F32 -> Síndico | E39: =+Balance!K32 -> Southern Copper Arg. S.R.L.
A40: =+Balance!D33 -> C.P.C.E.C.A.B.A. Tº176 Fº03 | E40: =+Balance!K33 -> Gerente

Sheet Pat.Neto
A1: ESTADO DE EVOLUCION DEL PATRIMONIO NETO
B2: =+Balance!A2 -> Al 30 de junio de 2026 - Cifras expresadas en dólares
J5: =+Balance!F5 -> 46203
B6: CONCEPTO | C6: Aportes de los propietarios | F6: Ganancias | G6: Reservadas | I6: Resultados | J6: Total del
C7: Capital | D7: Cuotas Pendientes de integracion | E7: Capital | F7: Reserva | G7: Otras | H7: Aportes | I7: no | J7: patrimonio
C8: integrado | E8: suscripto | F8: legal | G8: reservas | H8: Irrevocables | I8: asignados | J8: neto
C10: USD | D10: USD | E10: USD | F10: USD | G10: USD | I10: USD | J10: USD
B12: Saldos al inicio del ejercicio | C12: 51718583 | D12: 0 | E12: 51718583 | F12: 0 | G12: 0 | H12: 0 | I12: -48116541 | J12: =+E12+I12 -> 3497357.5
B13: A.R.E.A. | I13: 0 | J13: =+I13 -> 0
B14: Diferencia Resultados no Asignados | I14: 0 | J14: =+I14 -> 0
C15: =SUM(C12:C12) -> 51613899 | D15: =SUM(D12:D12) -> 0 | E15: =SUM(E12:E12) -> 51613899 | F15: =SUM(F12:F12) -> 0 | G15: =SUM(G12:G12) -> 0 | H15: =SUM(H12:H12) -> 0 | I15: =SUM(I12:I14) -> -48116541 | J15: =+J12+J13+J14 -> 3497357.5
B17: Aumento de capital al 31/07/2026 | C17: 176680 | E17: =+C17 | J17: =+E17
B19: Ganancia (Pérdida) del ejercicio | I19: =+Resultados!C25 -> -1192987.6 | J19: =+I19 -> -1192987.6
B21: Saldos al 31.7.2026 | C21: =+C15+C17 -> 51718583 | D21: =SUM(D15:D19) -> 0 | E21: =SUM(E15:E17) -> 51718583 | F21: =+F15 -> 0 | G21: =+G15 -> 0 | H21: =+H15 -> 0 | I21: =SUM(I15:I19) -> -49309529 | J21: =SUM(J15:J19) -> 2409053.9
B23: Las notas y anexos adjuntos forman parte integrante de los estados contables
B24: Informe profesional por separado
C31: =+Balance!D31 -> Miguel Ángel Alonso | F31: =+Balance!F31 -> Pedro Nicholson | I31: =+Balance!K31 -> Alejandro Poletto
C32: =+Balance!D32 -> Contador Público (U.C.A.) | F32: =+Balance!F32 -> Síndico | I32: =+Balance!K32 -> Southern Copper Arg. S.R.L.
C33: =+Balance!D33 -> C.P.C.E.C.A.B.A. Tº176 Fº03 | I33: =+Balance!K33 -> Gerente

Sheet Activo y Pasivo
B1: NOTA 4: | D1: COMPOSICION DE LOS RUBROS
B2: =+Balance!A2 -> Al 30 de junio de 2026 - Cifras expresadas en dólares
F4: =+Balance!F5 -> 46203
B5: ACTIVO
B6: Activo Corriente
B7: a. | C7: Caja y Bancos
D8: - Caja | F8: =+'Distribución por línea'!C3
D9: - Banco de Crédito - BCP | F9: =+'Distribución por línea'!C4 -> 5746.23
D10: - ICBC c/c | F10: =+'Distribución por línea'!C5 -> 7239.24
D11: - Banco Macro USD | F11: =+'Distribución por línea'!C7 -> 981.5
D12: - Banco Macro Pesos | F12: =+'Distribución por línea'!C6 -> -15.71
D13: - Banco Macro Pesos Cta Especial | F13: =+'Distribución por línea'!C8
D14: - Banco Galicia c/c | F14: =+'Distribución por línea'!C9 -> 2.67
D15: - Fondo fima premiun | F15: =+'Distribución por línea'!C10
D16: - Tarjetas VISA | F16: =+'Distribución por línea'!C11
F17: =SUM(F8:F16) -> 13953.93
B19: b. | C19: Otros Créditos
D20: - Zento S.A. | F20: =+'Distribución por línea'!C30
D21: - Iva crédito fiscal | F21: =+'Distribución por línea'!C12
D22: - Iva saldo a favor | F22: =+'Distribución por línea'!C13 -> 1132355.3
D23: - IIBB saldo a favor | F23: =+'Distribución por línea'!C16 -> 5340.7
D24: - Retenciones y percepciones iva | F24: =+'Distribución por línea'!C14 -> -1.7763568e-15
D25: - Retenciones y percepciones IIBB | F25: =+'Distribución por línea'!C15 -> -8.8817842e-16
D26: - Crédito Imp. L.25413 | F26: =+'Distribución por línea'!C17 -> 35314.56
D27: - Imp. Gcia Mínima Presunta | F27: =+'Distribución por línea'!C18 -> 358.96
D28: - Anticipo Imp. Gcia. Mínima Presunta | F28: =+'Distribución por línea'!C23
D29: - Percepción RG 4815 35% computable | F29: =+'Distribución por línea'!C24 -> 17670.09
D30: - Iva importación de servicios | F30: =+'Distribución por línea'!C25
D31: - Southern Cooper Corporation Cta Part | F31: =+'Distribución por línea'!C26 -> 65129.21
D32: - Cía. Minera Los Tolmos S.A. Cta. Part. | F32: =+'Distribución por línea'!C27 -> 0.62
D33: - Depósito en garantía alquiler | F33: =+'Distribución por línea'!C38 -> 73.46
D34: - Garantia a Cobrar/Recuperar | F34: =+'Distribución por línea'!C36
D35: - Adelanto Wilfredo Loza | F35: =+'Distribución por línea'!C31
D36: - Adelantos de Sueldos | F36: =+'Distribución por línea'!C32
D37: - Anticipos a proveedores | F37: =+'Distribución por línea'!D61+'Distribución por línea'!C35 -> 219.28
D38: - Anticipo Geologos | F38: =+'Distribución por línea'!C33
D39: - Anticipo de Fondos | F39: =+'Distribución por línea'!C34 -> 11810.75
D40: - Seguros a devengar | F40: =+'Distribución por línea'!C28 -> 4529.05
D41: - Cuentas por cobrar a Personal | F41: =+'Distribución por línea'!C29
D42: - Ret/Perc. Ganancias | F42: =+'Distribución por línea'!C19
D43: - Saldo a Favor Gcia Minima Presunta | F43: =+'Distribución por línea'!C20 -> 165.44
D44: - Saldo Favor Ganancias | F44: =+'Distribución por línea'!C21 -> 138.22
D45: - Impuesto Diferido | F45: =+'Distribución por línea'!C22 -> 1214719.3
D46: - Cargos Diferidos Los Menucos | F46: =+'Distribución por línea'!C56 -> 165358.57
D47: - Cargos Diferidos Cañadón del Moro | F47: =+'Distribución por línea'!C57 -> 1063586.4
F48: =SUM(F20:F47) -> 3716769.9
B50: c. | C50: Otros Activos
D51: - Socios | F51: =+'Distribución por línea'!C37 -> 104684
F52: =SUM(F51:F51) -> 104684
B54: Activo No Corriente
B56: d. | C56: Inversiones
D57: - Títulos Públicos | F57: =+'Distribución por línea'!C39
F58: =SUM(F57:F57) -> 0
F61: =+Balance!F5 -> 46203
B63: Pasivo
B64: Pasivo Corriente
B65: d. | C65: Deudas Comerciales
D66: - Proveedores | F66: =-'Distribución por línea'!E61 -> 71988.875
D67: - Cheques emitidos en cartera | F67: =-'Distribución por línea'!C91
F68: =SUM(F66:F67) -> 71988.875
B69: e. | C69: Cargas Fiscales
D70: - Sicore a pagar | F70: =-'Distribución por línea'!C86 -> 134391.6
D71: - Retención SUSS | F71: =-'Distribución por línea'!C96 -> 3.907985e-14
D72: - Imp. Bienes, Acc. y Part. Soc. a pagar | F72: =-'Distribución por línea'!C85
D73: - Imp. Gcia Mínima Presunta a pagar | F73: =-'Distribución por línea'!C90
D74: - Tasa Municipalidad Tolar Grande a pagar | F74: =-'Distribución por línea'!C88
D75: - Tasa Seguridad e Higiene a pagar | F75: =-'Distribución por línea'!C93 -> 13.32
D76: - Patentes a pagar | F76: 0
D77: - Provision de Gastos | F77: =-'Distribución por línea'!C95 -> 0.9
D78: - Previsión AID | F78: =-'Distribución por línea'!C80 -> 1208275.2
D79: - Previsión IGMP | F79: =-'Distribución por línea'!C81 -> 521.21
D80: - Provisión Vacaciones | F80: =-'Distribución por línea'!C82 -> 25741.92
F81: =SUM(F70:F80) -> 1368944.1
B83: f. | C83: Remuneraciones y Cargas Sociales
D84: - Sueldos a pagar | F84: =-'Distribución por línea'!C83 -> 31629.29
D85: - Sicoss a pagar | F85: =-'Distribución por línea'!C87 -> 26660.31
D86: - Embargo de Alimentos | F86: =-'Distribución por línea'!C92
D87: - Retenciones SUSS a pagar | F87: =-'Distribución por línea'!C89
F88: =SUM(F84:F87) -> 58289.6
B91: Las notas y anexos adjuntos forman parte integrante de los estados contables
B92: Informe profesional por separado
C98: =+Balance!D31 -> Miguel Ángel Alonso | E98: =+Balance!F31 -> Pedro Nicholson | G98: =+Balance!K31 -> Alejandro Poletto
C99: =+Balance!D32 -> Contador Público (U.C.A.) | E99: =+Balance!F32 -> Síndico | G99: =+Balance!K32 -> Southern Copper Arg. S.R.L.
C100: =+Balance!D33 -> C.P.C.E.C.A.B.A. Tº176 Fº03 | G100: =+Balance!K33 -> Gerente

Sheet Anexo I
K1: ANEXO I
A4: BIENES DE USO
A5: Correspondiente al ejercicio económico finalizado el 31 de julio de 2026
B8: VALOR DE ORIGEN | F8: DEPRECIACIONES
B9: VALORES AL | E9: VALORES AL | F9: ACUMULADAS | H9: DEL EJERCICIO | J9: ACUMULADAS | K9: NETO
A10: CONCEPTO | B10: COMIENZO DEL | C10: AUMENTOS | D10: DISMINUCIONES | E10: CIERRE DEL | F10: AL INICIO DEL | G10: BAJAS | H10: ALICUOTA | I10: MONTO | J10: AL CIERRE DEL | K10: RESULTANTE
B11: EJERCICIO | E11: EJERCICIO | F11: EJERCICIO | I11: MENSUAL | J11: EJERCICIO | K11: AL 31.07.2026
B12: USD | C12: USD | D12: USD | E12: USD | F12: USD | G12: USD | I12: USD | J12: USD | K12: USD
A15: - Muebles y Utiles | B15: 130976.14 | C15: 0 | D15: 0 | E15: =SUM(B15:D15) -> 130976.14 | F15: 109789.38 | G15: 0 | H15: =10/100 -> 0.1 | I15: =+J15-F15 -> 973.22 | J15: =-'Distribución por línea'!C45 -> 110762.6 | K15: =+E15-J15 -> 20213.54
A16: - Equipamiento Exploración | B16: 127410.39 | C16: 9409.86 | D16: 0 | E16: =SUM(B16:D16) -> 136820.25 | F16: 124747.23 | G16: 0 | H16: =33.3333333333333/100 -> 0.33333333 | I16: =+J16-F16 -> 2368.67 | J16: =-'Distribución por línea'!C53 -> 127115.9 | K16: =+E16-J16 -> 9704.35
A17: - Equipos | B17: 58450.05 | C17: 0 | D17: 0 | E17: =SUM(B17:D17) -> 58450.05 | F17: 55436.52 | G17: 0 | H17: =20/100 -> 0.2 | I17: =+J17-F17 -> 206.07 | J17: =-'Distribución por línea'!C46 -> 55642.59 | K17: =+E17-J17 -> 2807.46
A18: - Herramientas | B18: 33289.65 | C18: 0 | D18: 0 | E18: =SUM(B18:D18) -> 33289.65 | F18: 23082.15 | G18: 0 | H18: 0.1 | I18: =+J18-F18 -> 406.97 | J18: =-'Distribución por línea'!C47 -> 23489.12 | K18: =+E18-J18 -> 9800.53
A19: - Equipos de Computación | B19: 76103.66 | C19: 2268.65 | D19: 0 | E19: =SUM(B19:D19) -> 78372.31 | F19: 65705.95 | G19: 0 | H19: 0.2 | I19: =+J19-F19 -> 1758.74 | J19: =-'Distribución por línea'!C49 -> 67464.69 | K19: =+E19-J19 -> 10907.62
A20: - Software | B20: 133453.72 | C20: 0 | D20: 0 | E20: =SUM(B20:D20) -> 133453.72 | F20: 133453.72 | G20: 0 | H20: 0.2 | I20: =+J20-F20 -> 0 | J20: 133453.72 | K20: =+E20-J20 -> 0
A21: - Rodados | B21: 279626.68 | C21: 0 | D21: 0 | E21: =SUM(B21:D21) -> 279626.68 | F21: 259749.99 | G21: 0 | H21: =20/100 -> 0.2 | I21: =+J21-F21 -> 6369.75 | J21: =-'Distribución por línea'!C51 -> 266119.74 | K21: =+E21-J21 -> 13506.94
A22: - Instalaciones | B22: 11629.81 | C22: 0 | D22: 0 | E22: =SUM(B22:D22) -> 11629.81 | F22: 5406.12 | G22: 0 | H22: 0.1 | I22: =+J22-F22 -> 295.45 | J22: =-'Distribución por línea'!C55 -> 5701.57 | K22: =+E22-J22 -> 5928.24
A24: =+Pat.Neto!B21 -> Saldos al 30.6.2026 | B24: =SUM(B15:B23) -> 850940.1 | C24: =SUM(C15:C23) -> 11678.51 | D24: =SUM(D15:D23) -> 0 | E24: =SUM(E15:E23) -> 862618.61 | F24: =SUM(F15:F23) -> 777371.06 | G24: =SUM(G15:G23) -> 0 | I24: =SUM(I15:I22) -> 12378.87 | J24: =SUM(J15:J23) -> 789749.93 | K24: =SUM(K15:K23) -> 72868.68
A26: Las notas y anexos adjuntos forman parte integrante de los estados contables
A27: Informe profesional por separado
B33: =+Balance!D31 -> Miguel Ángel Alonso | F33: =+Balance!F31 -> Pedro Nicholson | J33: =+Balance!K31 -> Alejandro Poletto
B34: =+Balance!D32 -> Contador Público (U.C.A.) | F34: =+Balance!F32 -> Síndico | J34: =+Balance!K32 -> Southern Copper Arg. S.R.L.
B35: =+Balance!D33 -> C.P.C.E.C.A.B.A. Tº176 Fº03 | J35: =+Balance!K33 -> Gerente

Sheet Anexo II
J1: ANEXO II
A3: Información Requerida por el Art. 64 Inc. b) de la Ley 19.550 | I3: Anexo II
A4: =+Balance!A2 -> Al 30 de junio de 2026 - Cifras expresadas en dólares
E6: TOTALES | F6: GASTOS | G6: GASTOS | H6: GASTOS | I6: GASTOS | J6: TOTALES
B7: CONCEPTOS | E7: AL | F7: DE | G7: DE | H7: DE | J7: AL
E8: =+Balance!F5 -> 46203 | F8: ADMINISTRACION | G8: COMERCIALIZACION | H8: EXPLORACION | I8: FINANCIEROS | J8: 31.03.02
A10: - | B10: ALOJAMIENTO | E10: =SUM(F10:I10) -> 36709.74 | H10: =+'Distribución por línea'!C164 -> 36709.74
A11: - | B11: ALQUILERES (Inmuebles) | E11: =SUM(F11:I11) -> 185113.95 | F11: =+'Distribución por línea'!C175+'Distribución por línea'!C205 -> 185113.95
A12: - | B12: ANALISIS MUESTRAS | E12: =SUM(F12:I12) -> 41896.28 | H12: =+'Distribución por línea'!C176 -> 41896.28
A13: - | B13: ALQUILERES VARIOS | E13: =SUM(F13:I13) -> 0 | H13: =+'Distribución por línea'!C144
A14: - | B14: ALQUILER DE VEHÍCULOS | E14: =SUM(F14:I14) -> 130.73 | H14: =+'Distribución por línea'!C156 -> 130.73
A15: - | B15: ALQUILER DE MAQUINARIA | E15: =SUM(F15:I15) -> 0 | H15: =+'Distribución por línea'!C186
A16: - | B16: ALQUILERES EQ. DE CAMPO | E16: =SUM(F16:I16) -> 21.03 | H16: =+'Distribución por línea'!C123+'Distribución por línea'!C120 -> 21.03
A17: - | B17: ACUERDO DE INVERSIONES | E17: =SUM(F17:I17) -> 0 | H17: =+'Distribución por línea'!C160
A18: - | B18: ADQUISICIÓN INFORMACIÓN GEOLÓGICA | E18: =SUM(F18:I18) -> 0 | H18: =+'Distribución por línea'!C170
A19: - | B19: ADQUISICIÓN INFORMACIÓN GEOFÍSICA | E19: =SUM(F19:I19) -> 0 | H19: =+'Distribución por línea'!C171+'Distribución por línea'!C172
A20: - | B20: DEPRECIACIONES | E20: =SUM(F20:I20) -> 12378.87 | F20: =+'Anexo I'!I24 -> 12378.87
A21: - | B21: CARGAS SOCIALES | E21: =SUM(F21:I21) -> 46687.64 | F21: =+'Distribución por línea'!C117 -> 10000.93 | H21: =+'Distribución por línea'!C192 -> 36686.71
A22: - | B22: CANON | E22: =SUM(F22:I22) -> 34732.29 | H22: =+'Distribución por línea'!C157+'Distribución por línea'!C222+'Distribución por línea'!C223+'Distribución por línea'!C229 -> 34732.29
A23: - | B23: CATERING | E23: =SUM(F23:I23) -> 0 | H23: =+'Distribución por línea'!C187
A24: - | B24: CERTIFICACIONES | E24: =SUM(F24:I24) -> 0 | F24: =+'Distribución por línea'!C127
A25: - | B25: COMBUSTIBLE | E25: =SUM(F25:I25) -> 6051.11 | H25: =+'Distribución por línea'!C169 -> 6051.11
A26: - | B26: COMIDA | E26: =SUM(F26:I26) -> 19390 | H26: =+'Distribución por línea'!C165 -> 19390
A27: - | B27: COMISIONES | E27: =SUM(F27:I27) -> 0
A28: - | B28: COMUNICACIONES | E28: =SUM(F28:I28) -> 5298.39 | F28: =+'Distribución por línea'!C168 -> 5298.39
A29: - | B29: CONTROL ZOOFITOSANITARIA | E29: =SUM(F29:I29) -> 0 | H29: 0
A30: - | B30: CONVENIO DE CESIÓN | E30: =SUM(F30:I30) -> 0 | H30: =+'Distribución por línea'!C159
A31: - | B31: DONACIONES | E31: =SUM(F31:I31) -> 0 | F31: =+'Distribución por línea'!C139
A32: - | B32: DERECHOS DE EXPLORACION | E32: =SUM(F32:I32) -> 0 | H32: =+'Distribución por línea'!C195
A33: - | B33: EXPENSAS | E33: =SUM(F33:I33) -> 0 | F33: =+'Distribución por línea'!C204
A34: - | B34: FERRETERÍA | E34: =SUM(F34:I34) -> 346.02 | F34: =+'Distribución por línea'!C188 -> 346.02
A35: - | B35: GASTOS BANCARIOS | E35: =SUM(F35:I35) -> 6613.93 | F35: =+'Distribución por línea'!C146 -> 6613.93
A36: - | B36: GASTOS VARIOS | E36: =SUM(F36:I36) -> 7585.25 | F36: =+'Distribución por línea'!C131+'Distribución por línea'!C124+'Distribución por línea'!C200 -> 7585.25
A37: - | B37: GASTOS VEHÍCULOS | E37: =SUM(F37:I37) -> 10991.7 | F37: =+'Distribución por línea'!C203 -> 10991.7
A38: - | B38: GASTOS CAMPAMENTO | E38: =SUM(F38:I38) -> 0 | H38: =+'Distribución por línea'!C196
A39: - | B39: GASTOS EN CONSTRUCCIÓN | E39: =SUM(F39:I39) -> 6055.09 | H39: =+'Distribución por línea'!C198 -> 6055.09
A40: - | B40: GASTOS DE COMPUTACIÓN | E40: =SUM(F40:I40) -> 3543.26 | H40: =+'Distribución por línea'!C132 -> 3543.26
A41: - | B41: GASTOS MÉDICOS | E41: =SUM(F41:I41) -> 0 | H41: =+'Distribución por línea'!C138
A42: - | B42: GASTOS CAPACITACIÓN | E42: =SUM(F42:I42) -> 0 | H42: =+'Distribución por línea'!C173
A43: - | B43: GASTOS TOPOGRÁFICOS | E43: =SUM(F43:I43) -> 13.29 | H43: =+'Distribución por línea'!C161 -> 13.29
A44: - | B44: GASTOS LIMPIEZA | E44: =SUM(F44:I44) -> 2811.7 | F44: =+'Distribución por línea'!C121 -> 2811.7
A45: - | B45: GASTOS IMPORTACIÓN | E45: =SUM(F45:I45) -> 0
A46: - | B46: GASTOS DE REPRESENTACIÓN | E46: =SUM(F46:I46) -> 0 | F46: =+'Distribución por línea'!C202
A47: - | B47: GASTOS DE ESPECTROMETRIA | E47: =SUM(F47:I47) -> 0 | H47: =+'Distribución por línea'!C143
A48: - | B48: GASTOS DE PERFORACIÓN | E48: =SUM(F48:I48) -> 165115.85 | H48: =+'Distribución por línea'!C189+'Distribución por línea'!C216 -> 165115.85
A49: - | B49: GRATIFICACIONES | E49: =SUM(F49:I49) -> 0 | F49: =+'Distribución por línea'!C136
A50: - | B50: GS MANTENIMIENTO | E50: =SUM(F50:I50) -> 10257.79 | F50: =+'Distribución por línea'!C199 -> 10257.79
A51: - | B51: GS. MANTENIMIENTO SOFTWARE | E51: =SUM(F51:I51) -> 0 | H51: =+'Distribución por línea'!C135
A52: - | B52: GASTOS EN TRÁMITES | E52: =SUM(F52:I52) -> 6455.22 | F52: =+'Distribución por línea'!C134+'Distribución por línea'!C174+'Distribución por línea'!C180+'Distribución por línea'!C183+'Distribución por línea'!C218 -> 6455.22 | H52: 0
A53: - | B53: GS. EN PERSONAL | E53: =SUM(F53:I53) -> 4667.97 | H53: =+'Distribución por línea'!C155+'Distribución por línea'!C184 -> 4667.97
A54: - | B54: GS. EXPLORACIÓN | E54: =SUM(F54:I54) -> 0 | H54: =+'Distribución por línea'!C158
A55: - | B55: HONORARIOS LEGALES | E55: =SUM(F55:I55) -> 0 | F55: =+'Distribución por línea'!C113
A56: - | B56: HONORARIOS PROFESIONALES | E56: =SUM(F56:I56) -> 119655.77 | F56: =+'Distribución por línea'!C114 -> 119655.77
A57: - | B57: IMP. L. 25413 S/DÉBITOS Y CRÉDITOS | E57: =SUM(F57:I57) -> 15857.28 | F57: =+'Distribución por línea'!C147 -> 15857.28
A58: - | B58: INTERESES Y MULTAS | E58: =SUM(F58:I58) -> 0 | F58: =+'Distribución por línea'!C148+'Distribución por línea'!C151+'Distribución por línea'!C122
A59: - | B59: IMPUESTOS NO COMPUTABLES | E59: =SUM(F59:I59) -> 8215.17 | F59: =+'Distribución por línea'!C152+'Distribución por línea'!C115+'Distribución por línea'!C153+'Distribución por línea'!C220+'Distribución por línea'!C225 -> 8215.17
A60: - | B60: IMPUESTOS | E60: =SUM(F60:I60) -> 0 | F60: =+'Distribución por línea'!C230
A61: - | B61: LIBRERIA Y PAPELERIA | E61: =SUM(F61:I61) -> 547.37 | F61: =+'Distribución por línea'!C193 -> 547.37
A62: - | B62: MATRÍCULAS | E62: =SUM(F62:I62) -> 0 | H62: =+'Distribución por línea'!C154
A63: - | B63: MENSAJERÍA | E63: =SUM(F63:I63) -> 104.17 | F63: =+'Distribución por línea'!C142 -> 104.17
A64: - | B64: MOVILIDAD Y VIATICOS | E64: =SUM(F64:I64) -> 62027.53 | F64: =+'Distribución por línea'!C118+'Distribución por línea'!C182 -> 767.75 | H64: =+'Distribución por línea'!C163 -> 61259.78
A65: - | B65: MATERIALES DE CAMPO | E65: =SUM(F65:I65) -> 71.64 | H65: =+'Distribución por línea'!C140 -> 71.64
A66: - | B66: OBRA SOCIAL | E66: =SUM(F66:I66) -> 0 | F66: =+'Distribución por línea'!C206
A67: - | B67: PEAJES | E67: =SUM(F67:I67) -> 0 | H67: =+'Distribución por línea'!C166
A68: - | B68: PATENTES | E68: =SUM(F68:I68) -> 1487.34 | F68: =+'Distribución por línea'!C133 -> 1487.34
A69: - | B69: PLOTEOS | E69: =SUM(F69:I69) -> 0 | H69: =+'Distribución por línea'!C179
A70: - | B70: INFORMES AMBIENTALES | E70: =SUM(F70:I70) -> 0 | F70: =+'Distribución por línea'!C224 | H70: =+'Distribución por línea'!C181
A71: - | B71: PERDIDA DE MATERIALES | E71: =SUM(F71:I71) -> 0 | H71: =+'Distribución por línea'!C209
A72: - | B72: PUBLICACIONES | E72: =SUM(F72:I72) -> 0 | F72: =+'Distribución por línea'!C137
A73: - | B73: PUBLICIDAD | E73: =SUM(F73:I73) -> 0 | F73: =+'Distribución por línea'!C213
A74: - | B74: SEGURIDAD | E74: =SUM(F74:I74) -> 490.88 | F74: =+'Distribución por línea'!C130 -> 490.88
A75: - | B75: SEGUROS | E75: =SUM(F75:I75) -> 2845.01 | F75: =+'Distribución por línea'!C207 -> 2845.01
A76: - | B76: SELLADOS | E76: =SUM(F76:I76) -> 0 | F76: =+'Distribución por línea'!C129
A77: - | B77: SERVICIOS | E77: =SUM(F77:I77) -> 13077.95 | F77: =+'Distribución por línea'!C194 -> 13077.95
A78: - | B78: SERVICIOS DE CADETERIA | E78: =SUM(F78:I78) -> 0 | F78: =+'Distribución por línea'!C214
A79: - | B79: SERVICIOS DE DIGITALIZACION | E79: =SUM(F79:I79) -> 2925.36 | H79: =+'Distribución por línea'!C212 -> 2925.36
A80: - | B80: SERVICIOS DE GEOFÍSICA | E80: =SUM(F80:I80) -> 0 | H80: =+'Distribución por línea'!C162
A81: - | B81: SERVICIOS DE GEOLOGÍA | E81: =SUM(F81:I81) -> 0 | H81: =+'Distribución por línea'!C210
A82: - | B82: SUELDOS | E82: =SUM(F82:I82) -> 301316.8 | F82: =+'Distribución por línea'!C116 -> 106476.09 | H82: =+'Distribución por línea'!C185 -> 194840.71
A83: - | B83: TASAS | E83: =SUM(F83:I83) -> 2468.76 | H83: =+'Distribución por línea'!C201+'Distribución por línea'!C150+'Distribución por línea'!C125+'Distribución por línea'!C191 -> 2468.76
A84: - | B84: TRASLADOS | E84: =SUM(F84:I84) -> 0 | H84: =+'Distribución por línea'!C167+'Distribución por línea'!C108
A85: - | B85: RECUPERO DE GASTOS | E85: =SUM(F85:I85) -> 0 | F85: =+'Distribución por línea'!C145
A86: - | B86: REPARACIONES | E86: =SUM(F86:I86) -> 0 | F86: =+'Distribución por línea'!C177
A87: - | B87: REGALOS AL PERSONAL | E87: =SUM(F87:I87) -> 0 | F87: =+'Distribución por línea'!C141
A88: - | B88: EVENTOS | E88: =SUM(F88:I88) -> 0 | F88: =+'Distribución por línea'!C119
A89: - | B89: CONSUMOS NO REEMBOLSABLES | E89: =SUM(F89:I89) -> 0 | H89: =+'Distribución por línea'!C190
A90: - | B90: REMEDIACIÓN AMBIENTAL | E90: =SUM(F90:I90) -> 69.84 | F90: =+'Distribución por línea'!C197 -> 69.84
A91: - | B91: SERVICIOS DE INVESTIGACIÓN | E91: =SUM(F91:I91) -> 156.87 | H91: =+'Distribución por línea'!C211 -> 156.87
A92: - | B92: GASTOS DE LICITACIÓN | E92: =SUM(F92:I92) -> 4965.52 | F92: =+'Distribución por línea'!C232 -> 4965.52
A93: - | B93: GASTOS LEGALES | E93: =SUM(F93:I93) -> 0 | F93: =+'Distribución por línea'!C126
A94: - | B94: ANÁLISIS QUIMICOS | E94: =SUM(F94:I94) -> 651.34 | F94: =+'Distribución por línea'!C215 -> 651.34
A95: - | B95: VACACIONES | E95: =SUM(F95:I95) -> -3057.96 | F95: =+'Distribución por línea'!C217 -> -3057.96
A96: - | B96: GASTOS EN CALEFACCIÓN | E96: =SUM(F96:I96) -> 0 | H96: =+'Distribución por línea'!C221
A97: - | B97: SERVICIOS DE MOV DE SUELDOS | E97: =SUM(F97:I97) -> 0 | H97: =+'Distribución por línea'!C219
A98: - | B98: SERVICIOS DE CARTOGRAFIA | E98: =SUM(F98:I98) -> 0 | H98: =+'Distribución por línea'!C226
A99: - | B99: INSUMOS PARA MUESTRAS | E99: =SUM(F99:I99) -> 0 | H99: =+'Distribución por línea'!C227
A100: - | B100: USO EVENTUAL DE AGUA | E100: =SUM(F100:I100) -> 0 | H100: =+'Distribución por línea'!C228
A101: - | B101: INFORMES DE EVALUACIÓN ECONÓMICA | E101: =SUM(F101:I101) -> 0 | H101: =+'Distribución por línea'!C231
B102: =+'Anexo I'!A24 -> Saldos al 30.6.2026 | E102: =SUM(E10:E101) -> 1146743.7 | F102: =SUM(F10:F101) -> 530007.27 | G102: =SUM(G10:G101) -> 0 | H102: =SUM(H10:H101) -> 616736.47 | I102: =SUM(I10:J100) -> 0
A103: Las notas y anexos adjuntos forman parte integrante de los estados contables
...

Sheet Distribución por línea
A1: TxtCapitulo | B1: Texto72 | C1: txtsaldop
A2: ACTIVO
B3: 111010001 - Caja | C3: =IFERROR(VLOOKUP(B3,'Balance de sumas y saldos'!A:D,4,FALSE),) | D3: 2677221.3 | F3: =+E3-D3 -> -2677221.3
B4: 111020003 - Banco de Crédito - BCP | C4: =IFERROR(VLOOKUP(B4,'Balance de sumas y saldos'!A:D,4,FALSE),) -> 5746.23
B5: 111020001 - ICBC S.A. c/c | C5: =IFERROR(VLOOKUP(B5,'Balance de sumas y saldos'!A:D,4,FALSE),) -> 7239.24
B6: 111020005 - Banco Macro Pesos | C6: =IFERROR(VLOOKUP(B6,'Balance de sumas y saldos'!A:D,4,FALSE),) -> -15.71
B7: 111020007 - Banco Macro USD | C7: =IFERROR(VLOOKUP(B7,'Balance de sumas y saldos'!A:D,4,FALSE),) -> 981.5
B8: =+'Balance de sumas y saldos'!A11 -> 111020002 - Banco Macro Cta. Especial en pesos | C8: =IFERROR(VLOOKUP(B8,'Balance de sumas y saldos'!A:D,4,FALSE),)
B9: 111020006 - Banco Galicia c/c | C9: =IFERROR(VLOOKUP(B9,'Balance de sumas y saldos'!A:D,4,FALSE),) -> 2.67
B10: 115010001 - Fondo fima premiun | C10: =IFERROR(VLOOKUP(B10,'Balance de sumas y saldos'!A:D,4,FALSE),)
B11: 11104000 - Tarjetas Coorporativas | C11: =IFERROR(VLOOKUP(B11,'Balance de sumas y saldos'!A:D,4,FALSE),)
B12: 11401001 - Iva crédito fiscal | C12: =IFERROR(VLOOKUP(B12,'Balance de sumas y saldos'!A:D,4,FALSE),)
B13: 114010002 - IVA saldo a favor | C13: =IFERROR(VLOOKUP(B13,'Balance de sumas y saldos'!A:D,4,FALSE),) -> 1132355.3
B14: 11401003 - Retenciones y percepciones iva | C14: =IFERROR(VLOOKUP(B14,'Balance de sumas y saldos'!A:D,4,FALSE),) -> -1.7763568e-15
B15: 11401004 - Retenciones y Percepciones II.BB. | C15: =IFERROR(VLOOKUP(B15,'Balance de sumas y saldos'!A:D,4,FALSE),) -> -8.8817842e-16
B16: 11401005 - Ingresos Brutos saldo a favor | C16: =IFERROR(VLOOKUP(B16,'Balance de sumas y saldos'!A:D,4,FALSE),) -> 5340.7
B17: 11401006 - Crédito Imp. L.25413 | C17: =IFERROR(VLOOKUP(B17,'Balance de sumas y saldos'!A:D,4,FALSE),) -> 35314.56
B18: 11401010 - Imp. Gcia Mínima Presunta | C18: =IFERROR(VLOOKUP(B18,'Balance de sumas y saldos'!A:D,4,FALSE),) -> 358.96
B19: 11401012 - Ret/Perc Ganancias | C19: =IFERROR(VLOOKUP(B19,'Balance de sumas y saldos'!A:D,4,FALSE),)
B20: 11401013 - Saldo a Favor Gcia Minima Presunta | C20: =IFERROR(VLOOKUP(B20,'Balance de sumas y saldos'!A:D,4,FALSE),) -> 165.44
... B39: 12301000 - Titulos Públicos | C39: =IFERROR(VLOOKUP(B39,'Balance de sumas y saldos'!A:D,4,FALSE),)
B40: 12402000 - Muebles y Utiles | C40: =IFERROR(VLOOKUP(B40,'Balance de sumas y saldos'!A:D,4,FALSE),) -> 130976.14 | E40: =SUM(C40:C55) -> 72868.68 | F40: =+'Anexo I'!K24 -> 72868.68
B41: 12403000 - Equipos | C41: =IFERROR(VLOOKUP(B41,'Balance de sumas y saldos'!A:D,4,FALSE),) -> 58450.05 | F41: =+F40-E40 -> -1.1641532e-10
B42: 12404000 - Herramientas | C42: =IFERROR(VLOOKUP(B42,'Balance de sumas y saldos'!A:D,4,FALSE),) -> 33289.65
B43: 12405000 - Equipos de Computación | C43: =IFERROR(VLOOKUP(B43,'Balance de sumas y saldos'!A:D,4,FALSE),) -> 78372.31
B44: 12406000 - Software | C44: =IFERROR(VLOOKUP(B44,'Balance de sumas y saldos'!A:D,4,FALSE),) -> 133453.72
B45: 12407000 - Am. Ac. Muebles y Útiles | C45: =IFERROR(VLOOKUP(B45,'Balance de sumas y saldos'!A:D,4,FALSE),) -> -110762.6 | D45: 110182.16 | E45: =+C45+D45 -> -580.44
B46: 12408000 - Am. Ac. Equipos | C46: =IFERROR(VLOOKUP(B46,'Balance de sumas y saldos'!A:D,4,FALSE),) -> -55642.59 | D46: 55524.69 | E46: =+C46+D46 -> -117.9
B47: 12409000 - Am. Ac. Herramientas | C47: =IFERROR(VLOOKUP(B47,'Balance de sumas y saldos'!A:D,4,FALSE),) -> -23489.12 | D47: 23232.84 | E47: =+C47+D47 -> -256.28
B48: 12411000 - Rodados | C48: =IFERROR(VLOOKUP(B48,'Balance de sumas y saldos'!A:D,4,FALSE),) -> 279626.68
B49: 12412000 - Am. Ac. Eq. de Computación | C49: =IFERROR(VLOOKUP(B49,'Balance de sumas y saldos'!A:D,4,FALSE),) -> -67464.69 | D49: 66359.77 | E49: =+C49+D49 -> -1104.92
B50: 12413000 - Am. Ac. Software | C50: =IFERROR(VLOOKUP(B50,'Balance de sumas y saldos'!A:D,4,FALSE),) -> -133453.72 | D50: 133453.72 | E50: =+C50+D50 -> 0
B51: 12414000 - Am. Ac. Rodados | C51: =IFERROR(VLOOKUP(B51,'Balance de sumas y saldos'!A:D,4,FALSE),) -> -266119.74 | D51: 262141.62 | E51: =+C51+D51 -> -3978.12
B52: 12415000 - Equipamiento Exploración | C52: =IFERROR(VLOOKUP(B52,'Balance de sumas y saldos'!A:D,4,FALSE),) -> 136820.25
B53: 12416000 - Am. Ac. Equipamiento Exploración | C53: =IFERROR(VLOOKUP(B53,'Balance de sumas y saldos'!A:D,4,FALSE),) -> -127115.9 | D53: 125515.34 | E53: =+C53+D53 -> -1600.56
B54: 12417000 - Instalaciones | C54: =IFERROR(VLOOKUP(B54,'Balance de sumas y saldos'!A:D,4,FALSE),) -> 11629.81
B55: 12418000 - Am. Ac. Instalaciones | C55: =IFERROR(VLOOKUP(B55,'Balance de sumas y saldos'!A:D,4,FALSE),) -> -5701.57 | D55: 5524.4 | E55: =+C55+D55 -> -177.17
B56: 125010001 - Cargos Diferidos Los Menucos | C56: =IFERROR(VLOOKUP(B56,'Balance de sumas y saldos'!A:D,4,FALSE),) -> 165358.57 | F56: ACTIVO
B57: 125010002 - Cargos Diferidos Cañadón del Moro | C57: =IFERROR(VLOOKUP(B57,'Balance de sumas y saldos'!A:D,4,FALSE),) -> 1063586.4 | F57: =SUM(C3:C57) -> 3908276.5
A58: PASIVO
E60: PROVEEDORES
B61: 21101000 - Proveedores | C61: =+'Balance de sumas y saldos'!D68 -> -71988.875 | E61: =SUM(C60:C62) -> -71988.875
B80: 211050000 - Previsión AID | C80: =IFERROR(VLOOKUP(B80,'Balance de sumas y saldos'!$A$27:$D$444,4,FALSE),) -> -1208275.2
A81: 211060000 - Previsión IGMP | B81: 211060000 - Previsión IGMP | C81: =IFERROR(VLOOKUP(B81,'Balance de sumas y saldos'!$A$27:$D$444,4,FALSE),) -> -521.21
A82: 212010003 - Provisión Vacaciones | B82: 212010003 - Provisión Vacaciones | C82: =IFERROR(VLOOKUP(B82,'Balance de sumas y saldos'!$A$27:$D$444,4,FALSE),) -> -25741.92
A83: 212010001 - Sueldos a pagar | B83: 21301000 - Sueldos a pagar | C83: =IFERROR(VLOOKUP(B83,'Balance de sumas y saldos'!$A$27:$D$444,4,FALSE),) -> -31629.29
B84: 21401000 - Iva débito fiscal | C84: =IFERROR(VLOOKUP(B84,'Balance de sumas y saldos'!$A$27:$D$444,4,FALSE),)
B85: 21405000 - Imp. Bienes, Acc. y Part. Soc. a pagar | C85: =IFERROR(VLOOKUP(B85,'Balance de sumas y saldos'!$A$27:$D$444,4,FALSE),)
A86: 213010001 - SICORE a pagar | B86: 21406000 - Sicore a pagar | C86: =IFERROR(VLOOKUP(B86,'Balance de sumas y saldos'!$A$27:$D$444,4,FALSE),) -> -134391.6
A87: 212020001 - SICOSS a pagar | B87: 21407000 - Sicoss a pagar | C87: =IFERROR(VLOOKUP(B87,'Balance de sumas y saldos'!$A$27:$D$444,4,FALSE),) -> -26660.31
B88: 213010006 - Tasas Retributivas Mineras | C88: =IFERROR(VLOOKUP(B88,'Balance de sumas y saldos'!$A$27:$D$444,4,FALSE),)
B89: 21409000 - Retenciones SUSS a pagar | C89: =IFERROR(VLOOKUP(B89,'Balance de sumas y saldos'!$A$27:$D$444,4,FALSE),)
B90: 21408000 - Imp. Gcia Mínima Presunta a pagar | C90: =IFERROR(VLOOKUP(B90,'Balance de sumas y saldos'!$A$27:$D$444,4,FALSE),)
B91: 21504000 - Cheques emitidos en cartera | C91: =IFERROR(VLOOKUP(B91,'Balance de sumas y saldos'!$A$27:$D$444,4,FALSE),) | E91: PASIVO
B92: 212010002 - Embargo por Alimentos | C92: =IFERROR(VLOOKUP(B92,'Balance de sumas y saldos'!$A$27:$D$444,4,FALSE),) | E92: =SUM(C60:C95) -> -1499222.6 | F92: =+Balance!L12 -> 1499222.6
B93: 213010007 - Tasa Seguridad e Higiene a pagar | C93: =IFERROR(VLOOKUP(B93,'Balance de sumas y saldos'!$A$27:$D$444,4,FALSE),) -> -13.32 | F93: =+F92+E92 -> 0
B94: 213010008 - Iva importación de servicios a pagar | C94: =IFERROR(VLOOKUP(B94,'Balance de sumas y saldos'!$A$27:$D$444,4,FALSE),)
B95: 211030000 - Provision de Gastos | C95: =IFERROR(VLOOKUP(B95,'Balance de sumas y saldos'!$A$27:$D$444,4,FALSE),) -> -0.9
B96: 212020002 - Retenciones SUSS a pagar | C96: =IFERROR(VLOOKUP(B96,'Balance de sumas y saldos'!$A$27:$D$444,4,FALSE),) -> -3.907985e-14
A100: 311000000 - Capital Suscripto | B100: 31100000 - Capital Suscripto | C100: =IFERROR(VLOOKUP(B100,'Balance de sumas y saldos'!$A$27:$D$444,4,FALSE),) -> -51718583
A101: 321000000 - Resultados No Asignados | B101: 32201000 - Resultados no asignados | C101: =IFERROR(VLOOKUP(B101,'Balance de sumas y saldos'!$A$27:$D$444,4,FALSE),) -> 48116541
B102: 322000000 - AREA | C102: =IFERROR(VLOOKUP(B102,'Balance de sumas y saldos'!$A$27:$D$438,4,FALSE),)
B103: Diferencia Resultados no Asignados | C103: =IFERROR(VLOOKUP(B103,'Balance de sumas y saldos'!$A$27:$D$438,4,FALSE),)
B106: 41210000 - Resultado baja bien de Uso | C106: =IFERROR(VLOOKUP(B106,'Balance de sumas y saldos'!$A$27:$D$450,4,FALSE),)
B107: 41220000 - RECUPERO SINIESTRO | C107: =IFERROR(VLOOKUP(B107,'Balance de sumas y saldos'!$A$27:$D$450,4,FALSE),)
B108: 41230000 - Envío muestras Chile | C108: =IFERROR(VLOOKUP(B108,'Balance de sumas y saldos'!$A$27:$D$450,4,FALSE),)
B109: 41240000 - Resultado Venta Títulos Públicos | C109: =IFERROR(VLOOKUP(B109,'Balance de sumas y saldos'!$A$27:$D$450,4,FALSE),)
B110: 41250000 - Venta de bienes de uso | C110: =IFERROR(VLOOKUP(B110,'Balance de sumas y saldos'!$A$27:$D$450,4,FALSE),)
B111: 412600000 - Recupero de Seguros | C111: =IFERROR(VLOOKUP(B111,'Balance de sumas y saldos'!$A$27:$D$450,4,FALSE),)
B112: 412700000 - Intereses ganados | C112: =IFERROR(VLOOKUP(B112,'Balance de sumas y saldos'!$A$27:$D$450,4,FALSE),)
A113: 42101000 - Honorarios legales | B113: 42101000 - Honorarios legales | C113: =IFERROR(VLOOKUP(B113,'Balance de sumas y saldos'!$A$27:$D$450,4,FALSE),)
B114: 42102000 - Honorarios profesionales | C114: =IFERROR(VLOOKUP(B114,'Balance de sumas y saldos'!$A$27:$D$450,4,FALSE),) -> 119655.77
B115: 42103000 - Iva credito fiscal no computable | C115: =IFERROR(VLOOKUP(B115,'Balance de sumas y saldos'!$A$27:$D$450,4,FALSE),)
B116: 42105000 - Sueldos Adm. | C116: =IFERROR(VLOOKUP(B116,'Balance de sumas y saldos'!$A$27:$D$450,4,FALSE),) -> 106476.09
B117: 42106000 - Cargas sociales | C117: =IFERROR(VLOOKUP(B117,'Balance de sumas y saldos'!$A$27:$D$450,4,FALSE),) -> 10000.93
B118: 42107000 - Movilidad y Viaticos Adm. | C118: =IFERROR(VLOOKUP(B118,'Balance de sumas y saldos'!$A$27:$D$450,4,FALSE),) -> 767.75
B119: 42110000 - Eventos | C119: =IFERROR(VLOOKUP(B119,'Balance de sumas y saldos'!$A$27:$D$450,4,FALSE),)
B120: 42111000 - Alquileres eq. De campo | C120: =IFERROR(VLOOKUP(B120,'Balance de sumas y saldos'!$A$27:$D$450,4,FALSE),) -> 21.03
B121: 42112000 - Gs. Limpieza | C121: =IFERROR(VLOOKUP(B121,'Balance de sumas y saldos'!$A$27:$D$450,4,FALSE),) -> 2811.7
B122: 42115000 - Inspecciones | C122: =IFERROR(VLOOKUP(B122,'Balance de sumas y saldos'!$A$27:$D$450,4,FALSE),)
B123: 42111000 - Alquiler de Eq. De campo | C123: =IFERROR(VLOOKUP(B123,'Balance de sumas y saldos'!$A$27:$D$450,4,FALSE),)
B124: 42114000 - Gastos varios oficina | C124: =IFERROR(VLOOKUP(B124,'Balance de sumas y saldos'!$A$27:$D$450,4,FALSE),) -> 7383.83
B125: 42113000 - Tasas Retributivas Minería | C125: =IFERROR(VLOOKUP(B125,'Balance de sumas y saldos'!$A$27:$D$450,4,FALSE),)
... B127: 42202000 - Certificaciones | C127: =IFERROR(VLOOKUP(B127,'Balance de sumas y saldos'!$A$27:$D$450,4,FALSE),)
B128: 42203000 - Depreciaciones | C128: =IFERROR(VLOOKUP(B128,'Balance de sumas y saldos'!$A$27:$D$450,4,FALSE),) -> 12378.87 | D128: 1.4460966e-10
B129: 42204000 - Sellados | C129: =IFERROR(VLOOKUP(B129,'Balance de sumas y saldos'!$A$27:$D$450,4,FALSE),)
B130: 42207000 - Seguridad | C130: =IFERROR(VLOOKUP(B130,'Balance de sumas y saldos'!$A$27:$D$450,4,FALSE),) -> 490.88
B131: 42208000 - Gastos Varios Campo | C131: =IFERROR(VLOOKUP(B131,'Balance de sumas y saldos'!$A$27:$D$450,4,FALSE),) -> 201.42
B132: 42209000 - Gastos de computacion | C132: =IFERROR(VLOOKUP(B132,'Balance de sumas y saldos'!$A$27:$D$450,4,FALSE),) -> 3543.26
B133: 42211000 - Patentes | C133: =IFERROR(VLOOKUP(B133,'Balance de sumas y saldos'!$A$27:$D$450,4,FALSE),) -> 1487.34
B134: 42213000 - Gastos en tramites | C134: =IFERROR(VLOOKUP(B134,'Balance de sumas y saldos'!$A$27:$D$450,4,FALSE),)
B135: 42215000 - Mantenimiento Software | C135: =IFERROR(VLOOKUP(B135,'Balance de sumas y saldos'!$A$27:$D$450,4,FALSE),)
B136: 42216000 - Gratificaciones | C136: =IFERROR(VLOOKUP(B136,'Balance de sumas y saldos'!$A$27:$D$450,4,FALSE),)
B137: 42217000 - Publicaciones | C137: =IFERROR(VLOOKUP(B137,'Balance de sumas y saldos'!$A$27:$D$450,4,FALSE),)
B138: 42218000 - Gastos Médicos | C138: =IFERROR(VLOOKUP(B138,'Balance de sumas y saldos'!$A$27:$D$450,4,FALSE),)
B139: 42219000 - Donaciones | C139: =IFERROR(VLOOKUP(B139,'Balance de sumas y saldos'!$A$27:$D$450,4,FALSE),)
B140: 42220000 - Materiales de campo | C140: =IFERROR(VLOOKUP(B140,'Balance de sumas y saldos'!$A$27:$D$450,4,FALSE),) -> 71.64
... B232: 426380000 - Gastos de licitación Gst Campo | C232: =IFERROR(VLOOKUP(B232,'Balance de sumas y saldos'!$A$27:$D$450,4,FALSE),) -> 4965.52
C234: =SUM(C2:C232) -> -0.002911316

Sheet Balance de sumas y saldos
A1: SOUTHERN COPPER ARGENTINA S.R.L.
A2: BALANCE DE COMPROBACION - DOLARES
A3: 45016
A4: 1 | B4: 2 | C4: 3 | D4: 4
A5: Cuenta Contable | B5: Subcuenta | C5: Movimiento del Mes Dolares
A6: ACTIVO
A7: 111010001 - Caja | D7: 1014.2
A8: 111020003 - Banco de Crédito - BCP | D8: 5728.23
A9: 111020001 - ICBC S.A. c/c | D9: 8064.94
A10: 111020007 - Banco Macro USD | D10: 83641
A11: 111020002 - Banco Macro Cta. Especial en pesos | D11: 0
A12: 111020005 - Banco Macro Pesos | D12: 10395.91
A13: 111020006 - Banco Galicia c/c | D13: 4.84
A14: 11401001 - Iva crédito fiscal | D14: -4.5474735e-15
A15: 114010002 - IVA saldo a favor | D15: 1131450.4
A16: 11401003 - Retenciones y percepciones iva | D16: 3.5527137e-17
A17: 11401004 - Retenciones y Percepciones II.BB. | D17: 0.78
A18: 11401005 - Ingresos Brutos saldo a favor | D18: 5340.61
... A58: 125010002 - Cargos Diferidos Cañadón del Moro | D58: 1063586.4
D59: 0
D60: 0
D61: 0
D62: 0
D63: 0
D64: 0
D65: 0
D66: 0
A67: PASIVO | D67: 0
A68: 21101000 - Proveedores | D68: -37407.588
A69: 21301000 - Sueldos a pagar | D69: -1.1641532e-12
A70: 212010003 - Provisión Vacaciones | D70: -25781.52
A71: 211050000 - Previsión AID | D71: -1208275.2
A72: 211060000 - Previsión IGMP | D72: -519.11
A73: 21406000 - Sicore a pagar | D73: -136085.37
A74: 21407000 - Sicoss a pagar | D74: -11041.19
A75: 211030000 - Provision de Gastos | D75: -0.9
A76: 213010007 - Tasa Seguridad e Higiene a pagar | D76: -13.27
A77: 213010008 - Iva importación de servicios a pagar | D77: 0
A78: 213010010 - Patentes a pagar | D78: 0
A79: 212020002 - Retenciones SUSS a pagar | D79: -30.97
D80: 0
D81: 0
D82: 0
D83: 0
D84: 0
D85: 0
D86: 0
A87: CAPITAL Y PATRIMONIO | D87: 0
A88: 31100000 - Capital suscripto | D88: -51895263
A89: 32201000 - Resultados no asignados | D89: 48116541
A90: 32203000 - A.R.E.A. | D90: 0
A91: Diferencia Resultados no Asignados | D91: 0
A92: RESULTADOS | D92: 0
A93: 41210000 - Resultado Venta | D93: 0
A94: 41220000 - Recupero Siniestro | D94: 0
A95: 41230000 - Envío muestras Chile | D95: 0
A96: 41240000 - Resultado Venta Títulos Públicos | D96: 0
A97: 41250000 - Venta de bienes de uso | D97: 0
A98: 412600000 - Recupero de Seguros | D98: 0
A99: 412700000 - Intereses ganados | D99: 0
D100: 0
D101: 0 | E101: 425940000 - Honorarios Legales Adm. Gral
D102: 0 | E102: 421430000 - Honorarios legales Adm Catamarca
D103: 0 | E103: 421580000 - Servicio Notarial Rel Comunitaria Catamarca
A104: 42101000 - Honorarios legales | D104: 0 | E104: 425840000 - Servicios Notariales Administracion Gral.
A105: 42102000 - Honorarios profesionales | D105: 126680.36
D106: 0 | E106: 425190000 - Honorarios Profesionales Adm. Gral.
D107: 0 | E107: 433030000 - Honorarios Profesionales Adm. Gral. USD
D108: 0 | E108: 426440000 - Honorarios Profesionales Gs Campo
D109: 0 | E109: 421310000 - Honorarios Profesionales - Adm Catamarca
D110: 0 | E110: 427400000 - Honorarios Profesionales - Rel. Comunitarias
D111: 0 | E111: 421970000 - Honorarios Profesionales Gs Campo Catamarca
D112: 0 | E112: 421590000 - Honorarios profesionales Rel Comunitaria Catamarca
D113: 0 | E113: 422240000 - Honorarios profesionales - Remediación ambiental
D114: 0 | E114: 426630000 - Honorarios profesionales Vigencia y Penalidades
A115: 42103000 - Iva credito fiscal no computable | D115: 0
A116: 42105000 - Sueldos Adm. | D116: 108177.07 | E116: 421050000 - Sueldos Adm.
A117: 42106000 - Cargas sociales | D117: 10501.01 | E117: 421060000 - Cargas sociales Adm.
A118: 42107000 - Movilidad y Viaticos Adm. | D118: 1067.39
D119: 0 | E119: 425120000 - Movilidad y Viáticos Adm. Gral.
D120: 0 | E120: 433120000 - Movilidad y Viáticos Gastos de Campo (u$s)
D121: 0 | E121: 421070000 - Movilidad y viáticos Adm.
D122: 0 | E122: 421440000 - Movilidad y Viáticos Adm Catamarca
A123: 42110000 - Eventos | D123: 0
A124: 42111000 - Alquileres eq. De campo | D124: 21.03 | E124: 426520000 - Alquiler Equipos. Gst de Campo
A125: 42112000 - Gs. Limpieza | D125: 3730.12
D126: 0 | E126: 426130000 - Gastos de Limpieza Gs Campo
D127: 0 | E127: 427140000 - Gastos de limpieza Rel. comunitarias
D128: 0 | E128: 425970000 - Gs Limpieza Adm Gral.
D129: 0 | E129: 421340000 - Gastos de limpieza - Adm Catamarca
D130: 0 | E130: 426810000 - Gastos de limpieza Gts campo Catam
A131: 42114000 - Gastos varios oficina | D131: 7895.89
D132: 0 | E132: 425300000 - Gst Varios Oficina Adm. Gral.
D133: 0 | E133: 433080000 - Gastos Varios de Adm Gral USD
D134: 0 | E134: 427500000 - Gastos de oficina - Relaciones Comun.
D135: 0 | E135: 426190000 - Gst Varios Oficina Gst Campo
D136: 0 | E136: 421140000 - Gastos varios oficina - Adm Catamarca
D137: 0 | E137: 421930000 - Gs Varios Oficina Gs Campo Catamarca
A138: 42113000 - Tasas Retributivas Minería | D138: 0
D139: 0 | E139: 425820000 - Tasas Retributivas Minería Adm Gral.
...
