Workbook

Sheet Balance
A1: ESTADO DE SITUACION PATRIMONIAL
A2: Al 30 de junio 2026 - Cifras expresadas en pesos
F5: 30.06.2026 | G5: 31.03.04 | L5: =+F5 -> 30.06.2026
B6: ACTIVO: | G6: Historico | I6: PASIVO
C7: ACTIVO CORRIENTE | I7: PASIVO CORRIENTE
D8: Caja y Bancos (Nota 4.a) | F8: =+'Activo y Pasivo'!F18 -> 20554136 | G8: =+'Activo y Pasivo'!#REF! -> #REF! | J8: Deudas Comerciales (Nota 4.f) | L8: =+'Activo y Pasivo'!F72 -> 1.0668752e+08
D9: Otros Créditos (Nota 4.c) | F9: =+'Activo y Pasivo'!F51 -> 2.1128735e+09 | J9: Cargas Fiscales (Nota 4.g) | L9: =+'Activo y Pasivo'!F86 -> 2.8366338e+08
D10: Otros Activos (Nota 4.d) | F10: =+'Activo y Pasivo'!F55 -> 0 | J10: Remuneraciones y Cargas Sociales (Nota 4.h) | L10: =+'Activo y Pasivo'!F93 -> 86385185
G11: =SUM(G8:G8) -> #REF!
C12: Total del Activo corriente | F12: =SUM(F8:F10) -> 2.1334276e+09 | I12: Total del Pasivo Corriente | L12: =SUM(L8:L10) -> 4.7673608e+08
I13: Total del Pasivo | L13: =+L12 -> 4.7673608e+08
D15: Inversiones (Nota 4.e) | F15: =+'Activo y Pasivo'!F61 -> 0
D16: Bienes de Uso (Anexo I) | F16: =+'Anexo I'!E24-'Anexo I'!J24 -> 24748089
G17: =+#REF! -> #REF! | I17: PATRIMONIO NETO (Según estado respectivo) | L17: =+Pat.Neto!K27 -> 1.6814396e+09
C19: Total del Activo no corriente | F19: =SUM(F15:F18) -> 24748089 | G19: =SUM(G17:G18) -> #REF!
C21: Total del Activo | F21: =+F12+F19 -> 2.1581757e+09 | G21: =+G11+G19 -> #REF! | I21: Total del Pasivo y Patrimonio Neto | L21: =+L13+L17 -> 2.1581757e+09
A23: Las notas y anexos adjuntos forman parte integrante de los estados contables
A24: Informe profesional por separado
D32: Miguel Ángel Alonso | F32: Pedro Nicholson | K32: Alejandro Poletto
D33: Contador Público (U.C.A.) | F33: Síndico | K33: Southern Copper Arg. S.R.L.
D34: C.P.C.E.C.A.B.A. Tº176 Fº03 | K34: Gerente

Sheet Resultados
A1: ESTADO DE RESULTADOS
A2: =+Balance!A2 -> Al 30 de junio 2026 - Cifras expresadas en pesos
B5: =+Balance!F5 -> 30.06.2026 | C5: =+Balance!F5 -> 30.06.2026
A8: Ventas y servicios netas | C8: 0
A9: Costo de mercaderías vendidas | C9: 0
A10: Ganancia neta | C10: =+C8-C9 -> 0
A12: Gastos de comercialización (Anexo II) | C12: =+'Anexo II'!G103 -> 0
A13: Gastos de administración (Anexo II) | C13: =-'Anexo II'!F103 -> -7.296172e+08
A14: Gastos de financieros (Anexo II) | C14: =-'Anexo II'!I103 -> 0
A15: Gastos de Exploración | C15: =-'Anexo II'!H103 -> -8.8016173e+08
A17: Resultados financieros y por tenencia | C17: =-SALDOS!G280-SALDOS!G149 -> -62810190
A18: Otros ingresos y egresos | C18: =-SALDOS!G150-SALDOS!G151-SALDOS!G152 -> 0
A19: Resultados Extraordinarios | C19: =-SALDOS!G483 -> 0
A22: Ganancia (Pérdida) antes de impuesto a las Ganancias | C22: =+C10+SUM(C12:C19) -> -1.6725891e+09
A24: Impuesto a las Ganancias | C24: 0
A26: Ganancia (Pérdida) del ejercicio | C26: =+C22-C24 -> -1.6725891e+09
A31: Las notas y anexos adjuntos forman parte integrante de los estados contables
A32: Informe profesional por separado
A39: =+Balance!D32 -> Miguel Ángel Alonso | C39: =+Balance!F32 -> Pedro Nicholson | E39: =+Balance!K32 -> Alejandro Poletto
A40: =+Balance!D33 -> Contador Público (U.C.A.) | C40: =+Balance!F33 -> Síndico | E40: =+Balance!K33 -> Southern Copper Arg. S.R.L.
A41: =+Balance!D34 -> C.P.C.E.C.A.B.A. Tº176 Fº03 | E41: =+Balance!K34 -> Gerente

Sheet Pat.Neto
A1: ESTADO DE EVOLUCION DEL PATRIMONIO NETO
B2: =+Balance!A2 -> Al 30 de junio 2026 - Cifras expresadas en pesos
K5: =+Balance!F5 -> 30.06.2026
B6: CONCEPTO | C6: Aportes de los propietarios | G6: Ganancias | H6: Reservadas | J6: Resultados | K6: Total del
C7: Capital | D7: Ajuste de | E7: Cuotas Pendientes de integracion | F7: Capital | G7: Reserva | H7: Otras | I7: Aportes | J7: no | K7: patrimonio
C8: integrado | D8: Capital | F8: suscripto | G8: legal | H8: reservas | I8: Irrevocables | J8: asignados | K8: neto
C10: $ | E10: $ | F10: $ | G10: $ | H10: $ | J10: $ | K10: $
B12: Saldos al inicio del ejercicio | C12: 14700098884 | D12: 8 | E12: 0 | F12: =+C12+D12 -> 14700098892 | G12: 0 | H12: 0 | I12: 0 | J12: =+-SALDOS!G141-SALDOS!G142 -> -1.1494617e+10 | K12: =+J12+F12 -> 3.2054821e+09
B13: Diferencia Resultados no Asignados
C14: =SUM(C12:C12) -> 14700098884 | D14: =SUM(D12:D12) -> 8 | E14: =SUM(E12:E12) -> 0 | F14: =SUM(F12:F12) -> 14700098892 | G14: 0 | H14: 0 | I14: 0 | J14: =SUM(J12:J13) -> -1.1494617e+10 | K14: =+K12 -> 3.2054821e+09
F16: =+C16 -> 0 | K16: =+F16 -> 0
F17: =+C17 -> 0 | K17: =+F17 -> 0
F18: =+C18 -> 0 | K18: =+F18 -> 0
F19: =+C19 -> 0 | K19: =+F19 -> 0
F20: =+C20 -> 0 | K20: =+F20 -> 0
F21: =+C21 -> 0 | K21: =+F21 -> 0
B22: Aumento de capital 16/06/2026 | C22: 148546600 | F22: =+C22 -> 148546600 | K22: =+F22 -> 148546600
K23: =+F23 -> 0
B25: Ganancia (Pérdida) del ejercicio | J25: =+Resultados!C26 -> -1.6725891e+09 | K25: =+J25 -> -1.6725891e+09
B27: Saldos al 30.06.2026 | C27: =SUM(C14:C25) -> 14848645484 | D27: =SUM(D14:D26) -> 8 | E27: =SUM(E14:E25) -> 0 | F27: =SUM(F14:F25) -> 14848645492 | G27: =+G14 -> 0 | H27: =+H14 -> 0 | I27: =+I14 -> 0 | J27: =+J14+J25 -> -1.3167206e+10 | K27: =SUM(K14:K25) -> 1.6814396e+09
B29: Las notas y anexos adjuntos forman parte integrante de los estados contables
B30: Informe profesional por separado
C37: =+Resultados!A39 -> Miguel Ángel Alonso | G37: =+Balance!F32 -> Pedro Nicholson | J37: =+Balance!K32 -> Alejandro Poletto
C38: =+Resultados!A40 -> Contador Público (U.C.A.) | G38: =+Balance!F33 -> Síndico | J38: Southern Copper Arg. S.R.L.
C39: =+Resultados!A41 -> C.P.C.E.C.A.B.A. Tº176 Fº03 | J39: Gerente

Sheet Activo y Pasivo
B1: NOTA 4: | D1: COMPOSICION DE LOS RUBROS
B2: =+Balance!A2 -> Al 30 de junio 2026 - Cifras expresadas en pesos
F4: =+Balance!F5 -> 30.06.2026
B5: ACTIVO
B6: Activo Corriente
B7: a. | C7: Caja y Bancos
D8: - Caja | F8: =+SALDOS!G3 -> 0
D9: - Caja Los Menucos | F9: =+SALDOS!G4 -> 0
D10: - ICBC S.A. c/c | F10: =+SALDOS!G5 -> 10663404
D11: - Banco de Crédito - BCP | F11: =+SALDOS!G11 -> 8464196.8
D12: - Banco Macro USD | F12: =+SALDOS!G6 -> 1445749.5
D13: - Banco Macro Pesos cta especial | F13: =+SALDOS!G7 -> 0
D14: - Banco Macro Pesos | F14: =+SALDOS!G8 -> -23141.31
D15: - Banco Galicia c/c | F15: =+SALDOS!G9 -> 3926.88
D16: - Fondo fima premiun | F16: =+SALDOS!G12 -> 0
D17: - Tarjetas VISA | F17: =+SALDOS!G10 -> 0
F18: =SUM(F8:F17) -> 20554136
B20: c. | C20: Otros Créditos
D21: - Zento S.A. | F21: =+SALDOS!G40 -> 0
D22: - Iva crédito fiscal | F22: =+SALDOS!G14 -> 0
D23: - Iva saldo a favor | F23: =+SALDOS!G15 -> 1.6679594e+09
D24: - IIBB saldo a favor | F24: =+SALDOS!G18 -> 7866857.1
D25: - Retenciones y percepciones iva | F25: =+SALDOS!G16 -> 0
D26: - Retenciones y percepciones IIBB | F26: =+SALDOS!G17 -> 0
D27: - Crédito Imp. L.25413 | F27: =+SALDOS!G19 -> 52018352
D28: - Imp. Gcia. Mínima Presunta | F28: =+SALDOS!G20 -> 528747.09
D29: - Percepcion RG 4815 35% computable Ganancias | F29: =+SALDOS!G25 -> 26028041
D30: - Ret. y Perc. IIBB San Juan | F30: =+SALDOS!G26 -> 0
D31: - Antic. Tributos Aduaneros | F31: =+SALDOS!G27 -> 0
D32: - Iva importación de servicios | F32: =+SALDOS!G28 -> 0
D33: - Southern Cooper Corporation Cta Part | F33: =+SALDOS!G29 -> 95935319
D34: - Cía. Minera Los Tolmos S.A. Cta. Part. | F34: =+SALDOS!G30 -> 908.12
D35: - Southern Cooper Corporation | F35: =+SALDOS!G33 -> 154199532
D36: - Depósito en garantía alquiler | F36: =+SALDOS!G42 -> 108200
D37: - Garantia a Cobrar/Recuperar | F37: =+SALDOS!G41 -> 0
D38: - AdelantoS Wilfredo Loza | F38: =+SALDOS!G34 -> 0
D39: - Adelantos de Sueldos | F39: =+SALDOS!G35 -> 0
D40: - Anticipo Geólogos | F40: =+SALDOS!G36 -> 0
D41: - Anticipo de Fondos | F41: =+SALDOS!G37 -> 17397227
D42: - Anticipos a proveedores | F42: =+SALDOS!G38 -> 323000
D43: - Seguros a devengar | F43: =+SALDOS!G31 -> 6297405.2
D44: - Cuentas por cobrar a Personal | F44: =+SALDOS!G32 -> 0
D45: - Ret/Perc. Ganancias | F45: =+SALDOS!G21 -> 0
D46: - Saldo a Favor Gcia Minima Presunta | F46: =+SALDOS!G22 -> 243686.59
D47: - Saldo Favor Ganancias | F47: =+SALDOS!G23 -> 203599.05
D48: - Impuesto Credito Diferido | F48: =+SALDOS!G24 -> 45551975
D49: - Cargos Diferidos Los Menucos | F49: =+SALDOS!G60 -> 5439067
D50: - Cargos Diferidos Cañadón del Moro | F50: =+SALDOS!G61 -> 32772165
F51: =SUM(F21:F50) -> 2.1128735e+09
B53: d. | C53: Otros Activos
D54: - Socios | F54: =+SALDOS!G39 -> 0
F55: =SUM(F54:F54) -> 0
B57: Activo No Corriente
B59: e. | C59: Inversiones
D60: - Títulos Públicos | F60: =+SALDOS!G43 -> 0
F61: =SUM(F60:F60) -> 0
F63: =+Balance!F5 -> 30.06.2026
B65: Pasivo
B66: Pasivo Corriente
B67: f. | C67: Deudas Comerciales
D68: - Proveedores | F68: =-SALDOS!I116 -> 1.0668752e+08
D69: - Cheques emitidos en cartera | F69: =-SALDOS!G126 -> 0
D70: - Depósito efectivo Bco. Galicia | F70: =-SALDOS!G129 -> 0
D71: - Transferencia a debitar | F71: =-SALDOS!G134 -> 0
F72: =SUM(F68:F71) -> 1.0668752e+08
B73: g. | C73: Cargas Fiscales
D74: - Sicore a pagar | F74: =-SALDOS!G121 -> 1.9916836e+08
D75: - IVA débito fiscal | F75: 0
D76: - Imp. Bienes, Acc. y Part. Soc. a pagar | F76: 0
D77: - Imp. Gcia Mínima Presunta a pagar | F77: =-SALDOS!G124 -> 0
D78: - Tasa Municipalidad a pagar | F78: =-SALDOS!G123-SALDOS!G132 -> 0
D79: - Tasa Seguridad e Higiene a pagar | F79: =-SALDOS!G136 -> 19744
D80: - Retención SUSS | F80: =-SALDOS!G137 -> 0
D81: - Tasas Retributivas Mineras | F81: =-SALDOS!G133 -> 0
D82: - Provision de Gastos | F82: =-SALDOS!G135 -> 1335.23
D83: - Previsión AID | F83: =-SALDOS!G127 -> 45551975
D84: - Previsión IGMP | F84: =-SALDOS!G128 -> 772433.68
D85: - Provisión Vacaciones | F85: =-SALDOS!G131 -> 38149532
F86: =SUM(F74:F85) -> 2.8366338e+08
B88: h. | C88: Remuneraciones y Cargas Sociales
D89: - Sueldos a pagar | F89: =-SALDOS!G120 -> 46874611
D90: - Sicoss a pagar | F90: =-SALDOS!G122 -> 39510574
D91: - Retenciones SUSS a pagar | F91: =-SALDOS!G125 -> 0
D92: - Embargo por alimentos | F92: =-SALDOS!G130 -> 0
F93: =SUM(F89:F92) -> 86385185
B95: Las notas y anexos adjuntos forman parte integrante de los estados contables
B96: Informe profesional por separado
C102: =+Balance!D32 -> Miguel Ángel Alonso | E102: =+Balance!F32 -> Pedro Nicholson | G102: =+Balance!K32 -> Alejandro Poletto
C103: =+Balance!D33 -> Contador Público (U.C.A.) | E103: =+Balance!F33 -> Síndico | G103: =+Balance!K33 -> Southern Copper Arg. S.R.L.
C104: =+Balance!D34 -> C.P.C.E.C.A.B.A. Tº176 Fº03 | G104: =+Balance!K34 -> Gerente

Sheet Anexo I
K1: ANEXO I
A4: BIENES DE USO
A5: Correspondiente al ejercicio económico finalizado el 30 de Junio de 2026
B8: VALOR DE ORIGEN | F8: DEPRECIACIONES
B9: VALORES AL | E9: VALORES AL | F9: ACUMULADAS | H9: DEL EJERCICIO | J9: ACUMULADAS | K9: NETO
A10: CONCEPTO | B10: COMIENZO DEL | C10: AUMENTOS | D10: DISMINUCIONES | E10: CIERRE DEL | F10: AL INICIO DEL | G10: BAJAS | H10: ALICUOTA | I10: MONTO | J10: AL CIERRE DEL | K10: RESULTANTE
B11: EJERCICIO | E11: EJERCICIO | F11: EJERCICIO | I11: DEL EJERCICIO | J11: EJERCICIO | K11: AL 31.5.26
B12: $ | C12: $ | D12: $ | E12: $ | F12: $ | G12: $ | I12: $ | J12: $ | K12: $
A15: - Muebles y Utiles | B15: 7137147.1 | C15: =+E15-B15 -> 0 | D15: 0 | E15: =+SALDOS!G44 -> 7137147.1 | F15: 2874614.2 | G15: 0 | H15: =10/100 -> 0.1 | I15: =+J15-F15+G15 -> 250094.39 | J15: =-SALDOS!G49 -> 3124708.6 | K15: =+E15-J15 -> 4012438.6
A16: - Equipamiento Exploración | B16: 9983623.9 | C16: =+E16-B16 -> 13200827 | D16: 0 | E16: =+SALDOS!G56 -> 23184451 | F16: 8824107.4 | G16: 0 | H16: =33.3333333333333/100 -> 0.33333333 | I16: =+J16-F16+G16 -> 1380460.8 | J16: =-SALDOS!G57 -> 10204568 | K16: =+E16-J16 -> 12979883
A17: - Equipos | B17: 2163642.2 | C17: =+E17-B17 -> 0 | D17: 0 | E17: =+SALDOS!G45 -> 2163642.2 | F17: 1414600.9 | G17: 0 | H17: =20/100 -> 0.2 | I17: =+J17-F17+G17 -> 84405.3 | J17: =-SALDOS!G50 -> 1499006.2 | K17: =+E17-J17 -> 664636.02
A18: - Herramientas | B18: 1676264 | C18: =+E18-B18 -> 0 | D18: 0 | E18: =+SALDOS!G46 -> 1676264 | F18: 711103.11 | G18: 0 | H18: 0.1 | I18: =+J18-F18+G18 -> 65273.46 | J18: =-SALDOS!G51 -> 776376.57 | K18: =+E18-J18 -> 899887.42
A19: - Equipos de Computación | B19: 5362126.4 | C19: =+E19-B19 -> 3100884.5 | D19: 0 | E19: =+SALDOS!G47 -> 8463010.9 | F19: 3956712.1 | G19: 0 | H19: 0.2 | I19: =+J19-F19+G19 -> 479521.93 | J19: =-SALDOS!G53 -> 4436234 | K19: =+E19-J19 -> 4026776.9
A20: - Software | B20: 5117083.3 | C20: =+E20-B20 -> 0 | D20: 0 | E20: =+SALDOS!G48 -> 5117083.3 | F20: 5117083.3 | G20: 0 | H20: 0.2 | I20: =+J20-F20+G20 -> 0 | J20: =-SALDOS!G54 -> 5117083.3 | K20: =+E20-J20 -> 0
A21: - Rodados | B21: 20790195 | C21: =+E21-B21 -> 0 | D21: 0 | E21: =+SALDOS!G52 -> 20790195 | F21: 18441674 | G21: 0 | H21: =20/100 -> 0.2 | I21: =+J21-F21+G21 -> 1164375.5 | J21: =-SALDOS!G55 -> 19606049 | K21: =+E21-J21 -> 1184145.8
A22: - Instalaciones | B22: 1598074.1 | C22: =+E22-B22 -> 0 | D22: 0 | E22: =+SALDOS!G58 -> 1598074.1 | F22: 539130.52 | G22: 0 | H22: 0.1 | I22: =+J22-F22+G22 -> 78622.13 | J22: =-SALDOS!G59 -> 617752.65 | K22: =+E22-J22 -> 980321.44
A24: Total al 30.06.2026 | B24: =SUM(B15:B23) -> 53828156 | C24: =SUM(C15:C23) -> 16301712 | D24: =SUM(D15:D23) -> 0 | E24: =SUM(E15:E23) -> 70129868 | F24: =SUM(F15:F23) -> 41879025 | G24: =SUM(G15:G23) -> 0 | I24: =SUM(I15:I23) -> 3502753.6 | J24: =SUM(J15:J23) -> 45381779 | K24: =SUM(K15:K23) -> 24748089
A26: Las notas y anexos adjuntos forman parte integrante de los estados contables
A27: Informe profesional por separado
B33: =+Balance!D32 -> Miguel Ángel Alonso | F33: =+Balance!F32 -> Pedro Nicholson | J33: =+Balance!K32 -> Alejandro Poletto
B34: =+Balance!D33 -> Contador Público (U.C.A.) | F34: =+Balance!F33 -> Síndico | J34: =+Balance!K33 -> Southern Copper Arg. S.R.L.
B35: =+Balance!D34 -> C.P.C.E.C.A.B.A. Tº176 Fº03 | J35: =+Balance!K34 -> Gerente

Sheet Anexo II
J1: ANEXO II
A3: Información Requerida por el Art. 64 Inc. b) de la Ley 19.550 | I3: Anexo II
A4: =+Balance!A2 -> Al 30 de junio 2026 - Cifras expresadas en pesos
E6: TOTALES | F6: GASTOS | G6: GASTOS | H6: GASTOS | I6: GASTOS | J6: TOTALES
B7: CONCEPTOS | E7: AL | F7: DE | G7: DE | H7: DE | J7: AL
E8: =+Balance!F5 -> 30.06.2026 | F8: ADMINISTRACION | G8: COMERCIALIZACION | H8: EXPLORACION | I8: FINANCIEROS | J8: 31.03.02
A10: - | B10: ALOJAMIENTO | E10: =SUM(F10:I10) -> 51970355 | H10: =+SALDOS!G322 -> 51970355
A11: - | B11: ALQUILERES (Inmuebles) | E11: =SUM(F11:I11) -> 2.6265326e+08 | F11: =+SALDOS!G368 -> 2.6265326e+08
A12: - | B12: ANALISIS MUESTRAS | E12: =SUM(F12:I12) -> 58572858 | H12: =+SALDOS!G374 -> 58572858
A13: - | B13: ALQUILERES VARIOS | E13: =SUM(F13:I13) -> 0 | H13: =+SALDOS!G257 -> 0
A14: - | B14: ALQUILER DE VEHÍCULOS | E14: =SUM(F14:I14) -> 189946.28 | H14: =+SALDOS!G302 -> 189946.28
A15: - | B15: ALQUILER DE MAQUINARIA | E15: =SUM(F15:I15) -> 0 | H15: =+SALDOS!G402 -> 0
A16: - | B16: ALQUILERES EQ. DE CAMPO | E16: =SUM(F16:I16) -> 30000 | H16: =+SALDOS!G187 -> 30000
A17: - | B17: ACUERDO DE INVERSIONES | E17: =SUM(F17:I17) -> 0 | H17: =+SALDOS!G314 -> 0
A18: - | B18: ADQUISICIÓN INFORMACIÓN GEOLÓGICA | E18: =SUM(F18:I18) -> 0 | H18: =+SALDOS!G358+SALDOS!G397 -> 0
A19: - | B19: ADQUISICIÓN INFORMACIÓN GEOFÍSCA | E19: =SUM(F19:I19) -> 0 | H19: =+SALDOS!G361 -> 0
A20: - | B20: DEPRECIACIONES | E20: =SUM(F20:I20) -> 3502753.6 | F20: =+'Anexo I'!I24 -> 3502753.6
A21: - | B21: CARGAS SOCIALES | E21: =SUM(F21:I21) -> 65998057 | F21: =+SALDOS!G170 -> 14081454 | H21: =+SALDOS!G424 -> 51916603
A22: - | B22: CANON | E22: =SUM(F22:I22) -> 48607847 | H22: =+SALDOS!G306+SALDOS!G308+SALDOS!G309+SALDOS!G307 -> 48607847
A23: - | B23: CATERING | E23: =SUM(F23:I23) -> 0
A24: - | B24: CERTIFICACIONES | E24: =SUM(F24:I24) -> 0 | F24: =+SALDOS!G202 -> 0
A25: - | B25: COMBUSTIBLE | E25: =SUM(F25:I25) -> 8616654.6 | H25: =+SALDOS!G351 -> 8616654.6
A26: - | B26: COMIDA | E26: =SUM(F26:I26) -> 27411009 | H26: =+SALDOS!G330 -> 27411009
A27: - | B27: COMISIONES | E27: =SUM(F27:I27) -> 0
A28: - | B28: COMUNICACIONES | E28: =SUM(F28:I28) -> 7955308.8 | F28: =+SALDOS!G342+SALDOS!G495+SALDOS!G496 -> 7955308.8
A29: - | B29: CONTROL ZOOFITOSANITARIA | E29: =SUM(F29:I29) -> 0
A30: - | B30: CONVENIO DE CESIÓN | E30: =SUM(F30:I30) -> 0 | H30: =+SALDOS!G311 -> 0
A31: - | B31: DONACIONES | E31: =SUM(F31:I31) -> 0 | F31: =+SALDOS!G239 -> 0
A32: - | B32: DERECHOS DE EXPLORACION | E32: =SUM(F32:I32) -> 0 | H32: =+SALDOS!G439 -> 0
A33: - | B33: EXPENSAS | E33: =SUM(F33:I33) -> 0 | F33: =+SALDOS!G471 -> 0
A34: - | B34: FERRETERÍA | E34: =SUM(F34:I34) -> 489482.99 | F34: =+SALDOS!G406 -> 489482.99
A35: - | B35: GASTOS BANCARIOS | E35: =SUM(F35:I35) -> 9664883.1 | F35: =+SALDOS!G264 -> 9664883.1
A36: - | B36: GASTOS VARIOS | E36: =SUM(F36:I36) -> 16223059 | F36: =+SALDOS!G188 -> 10335683 | H36: =+SALDOS!G213+SALDOS!G393+SALDOS!G457 -> 5887375.8
A37: - | B37: GASTOS VEHÍCULOS | E37: =SUM(F37:I37) -> 15451044 | F37: =+SALDOS!G462 -> 15451044
A38: - | B38: GASTOS CAMPAMENTO | E38: =SUM(F38:I38) -> 0 | H38: =+SALDOS!G399+SALDOS!G440 -> 0
A39: - | B39: GASTOS EN CONSTRUCCIÓN | E39: =SUM(F39:I39) -> 8441197.3 | H39: =+SALDOS!G448 -> 8441197.3
A40: - | B40: GASTOS DE COMPUTACIÓN | E40: =SUM(F40:I40) -> 5034121.2 | F40: =+SALDOS!G217 -> 5034121.2
A41: - | B41: GASTOS MÉDICOS | E41: =SUM(F41:I41) -> 0 | F41: =+SALDOS!G238 -> 0
A42: - | B42: GASTOS CAPACITACIÓN | E42: =SUM(F42:I42) -> 0 | F42: =+SALDOS!G363 -> 0
A43: - | B43: GASTOS TOPOGRÁFICOS | E43: =SUM(F43:I43) -> 18512.4 | H43: =+SALDOS!G315 -> 18512.4
A44: - | B44: GASTOS IMPORTACIÓN | E44: =SUM(F44:I44) -> 0 | H44: =+SALDOS!G385 -> 0
A45: - | B45: GASTOS LIMPIEZA | E45: =SUM(F45:I45) -> 3938960.9 | F45: =+SALDOS!G179 -> 3938960.9
A46: - | B46: GASTOS DE REPRESENTACIÓN | E46: =SUM(F46:I46) -> 0 | F46: =+SALDOS!G459 -> 0
A47: - | B47: GASTOS DE ESPECTROMETRIA | E47: =SUM(F47:I47) -> 0 | F47: =+SALDOS!G256 -> 0
A48: - | B48: GASTOS DE PERFORACIÓN | E48: =SUM(F48:I48) -> 2.3611567e+08 | H48: =+SALDOS!G413 -> 2.3611567e+08
A49: - | B49: GRATIFICACIONES | E49: =SUM(F49:I49) -> 0 | F49: =+SALDOS!G233 -> 0
A50: - | B50: GS MANTENIMIENTO | E50: =SUM(F50:I50) -> 14667167 | F50: =+SALDOS!G452 -> 14667167
A51: - | B51: GS. MANTENIMIENTO SOFTWARE | E51: =SUM(F51:I51) -> 0 | F51: =+SALDOS!G232 -> 0
A52: - | B52: GASTOS EN TRÁMITES | E52: =SUM(F52:I52) -> 9103800 | F52: =+SALDOS!G186+SALDOS!G230+SALDOS!G367+SALDOS!G386 -> 39000 | H52: =+SALDOS!G390 -> 9064800
A53: - | B53: GS. EN PERSONAL | E53: =SUM(F53:I53) -> 832331.19 | H53: =+SALDOS!G294 -> 832331.19
A54: - | B54: GS. EXPLORACIÓN | E54: =SUM(F54:I54) -> 0 | H54: =+SALDOS!G310 -> 0
A55: - | B55: HONORARIOS PROFESIONALES | E55: =SUM(F55:I55) -> 1.7044177e+08 | F55: =+SALDOS!G159 -> 1.7044177e+08
A56: - | B56: HONORARIOS LEGALES | E56: =SUM(F56:I56) -> 0 | F56: =+SALDOS!G154 -> 0
A57: - | B57: IMP. L. 25413 S/DÉBITOS Y CRÉDITOS | E57: =SUM(F57:I57) -> 22769032 | F57: =+SALDOS!G269 -> 22769032
A58: - | B58: INTERESES Y MULTAS | E58: =SUM(F58:I58) -> 0 | F58: =+SALDOS!G272+SALDOS!G282 -> 0
A59: - | B59: IMPUESTOS NO COMPUTABLE | E59: =SUM(F59:I59) -> 11619113 | F59: =+SALDOS!G168+SALDOS!G283+SALDOS!G284+SALDOS!G493+SALDOS!F498 -> 11619113
A60: - | B60: LIBRERIA Y PAPELERIA | E60: =SUM(F60:I60) -> 768315.33 | F60: =+SALDOS!G425 -> 768315.33
A61: - | B61: MATRÍCULAS | E61: =SUM(F61:I61) -> 0 | H61: =+SALDOS!G293 -> 0
A62: - | B62: MENSAJERÍA | E62: =SUM(F62:I62) -> 149263.11 | F62: =+SALDOS!G246 -> 149263.11
A63: - | B63: MOVILIDAD Y VIATICOS | E63: =SUM(F63:I63) -> 88381242 | F63: =+SALDOS!G171+SALDOS!G338+SALDOS!G389+SALDOS!G339 -> 1068794.4 | H63: =+SALDOS!G318 -> 87312448
A64: - | B64: MATERIALES DE CAMPO | E64: =SUM(F64:I64) -> 101825.6 | H64: =+SALDOS!G243 -> 101825.6
A65: - | B65: OBRA SOCIAL | E65: =SUM(F65:I65) -> 0 | F65: =+SALDOS!G477 -> 0
A66: - | B66: PEAJES | E66: =SUM(F66:I66) -> 0
A67: - | B67: PATENTES | E67: =SUM(F67:I67) -> 2052084.4 | F67: =+SALDOS!G226 -> 2052084.4
A68: - | B68: PLOTEOS | E68: =SUM(F68:I68) -> 0
A69: - | B69: INFORMES AMBIENTALES | E69: =SUM(F69:I69) -> 0 | H69: =+SALDOS!G387 -> 0
A70: - | B70: PERDIDA DE MATERIALES | E70: =SUM(F70:I70) -> 0
A71: - | B71: PUBLICACIONES | E71: =SUM(F71:I71) -> 0 | F71: =+SALDOS!G234 -> 0
A72: - | B72: PUBLICIDAD | E72: =SUM(F72:I72) -> 0 | F72: =+SALDOS!G487 -> 0
A73: - | B73: SEGURIDAD | E73: =SUM(F73:I73) -> 700000 | F73: =+SALDOS!G208 -> 700000
A74: - | B74: SEGUROS | E74: =SUM(F74:I74) -> 4013597 | F74: =+SALDOS!G480 -> 4013597
A75: - | B75: SELLADOS | E75: =SUM(F75:I75) -> 0 | F75: =+SALDOS!G205 -> 0
A76: - | B76: SERVICIOS | E76: =SUM(F76:I76) -> 17921832 | F76: =+SALDOS!G434 -> 17921832
A77: - | B77: SERVICIOS DE CADETERIA | E77: =SUM(F77:I77) -> 0 | F77: =+SALDOS!G488 -> 0
A78: - | B78: SERVICIOS DE GEOFÍSICA | E78: =SUM(F78:I78) -> 0 | H78: =+SALDOS!G317 -> 0
A79: - | B79: SERVICIOS DE GEOLOGÍA | E79: =SUM(F79:I79) -> 0 | H79: =+SALDOS!G485 -> 0
A80: - | B80: SERVICIOS DE DIGITALIZACION | E80: =SUM(F80:I80) -> 4150213.4 | H80: =+SALDOS!G486 -> 4150213.4
A81: - | B81: SUELDOS | E81: =SUM(F81:I81) -> 4.2325566e+08 | F81: =+SALDOS!G169 -> 1.4697471e+08 | H81: =+SALDOS!G401 -> 276280951
A82: - | B82: TASAS | E82: =SUM(F82:I82) -> 3499846.7 | F82: =+SALDOS!G281+SALDOS!G197 -> 0 | H82: =+SALDOS!G416 -> 3499846.7
A83: - | B83: TRASLADOS | E83: =SUM(F83:I83) -> 0 | F83: 0 | H83: =+SALDOS!G148 -> 0
A84: - | B84: RECUPERO GASTOS | E84: =SUM(F84:I84) -> 0 | F84: =+SALDOS!G263 -> 0
A85: - | B85: REPARACIONES | E85: =SUM(F85:I85) -> 0 | F85: =+SALDOS!G384 -> 0
A86: - | B86: REGALOS AL PERSONAL | E86: =SUM(F86:I86) -> 0 | F86: =+SALDOS!G245 -> 0
A87: - | B87: EVENTOS | E87: =SUM(F87:I87) -> 0 | F87: =+SALDOS!G178 -> 0
A88: - | B88: CONSUMOS NO REEMBOLSABLES | E88: =SUM(F88:I88) -> 0 | H88: =+SALDOS!G415 -> 0
A89: - | B89: REMEDIACIÓN AMBIENTAL | E89: =SUM(F89:I89) -> 101483.28 | F89: =+SALDOS!G443 -> 101483.28
A90: - | B90: SERVICIOS DE INVESTIGACION | E90: =SUM(F90:I90) -> 0 | H90: =+SALDOS!G475 -> 0
A91: - | B91: GASTOS LICITACIÓN | E91: =SUM(F91:I91) -> 6840000 | F91: =+SALDOS!G153 -> 6840000
A92: - | B92: HONORARIOS LEGALES | E92: =SUM(F92:I92) -> 0
B93: SERV DE SEGURIDAD E INV DE CAMPO | E93: =SUM(F93:I93) -> 226987 | H93: =+SALDOS!G489 -> 226987
A94: - | B94: ANALISIS GEOQUIMICOS | E94: =SUM(F94:I94) -> 914304.7 | H94: =+SALDOS!G490+SALDOS!G491 -> 914304.7
A95: - | B95: VACACIONES | E95: =SUM(F95:I95) -> -3615904.1 | F95: =+SALDOS!G200 -> -3615904.1
A96: - | B96: GASTOS EN CALEFACCIÓN | E96: =SUM(F96:I96) -> 0 | H96: =+SALDOS!G494 -> 0
A97: - | B97: SERV DE MOVIMIENTOS DE SUELO | E97: =SUM(F97:I97) -> 0 | H97: =+SALDOS!F492 -> 0
A98: - | B98: MONITOREO DE SUELOS | E98: =SUM(F98:I98) -> 0 | H98: =+SALDOS!G497 -> 0
A99: - | B99: SERVICIOS DE CARTOGRAFIA | E99: =SUM(F99:I99) -> 0 | H99: =+SALDOS!G499 -> 0
A100: - | B100: INSUMOS PARA MUESTRAS | E100: =SUM(F100:I100) -> 0 | H100: =+SALDOS!G500 -> 0
A101: - | B101: USO EVENTUAL DE AGUA | E101: =SUM(F101:I101) -> 0 | H101: =+SALDOS!G501 -> 0
A102: - | B102: INFORMES DE EVALUACIÓN ECONÓMICA | E102: =SUM(F102:I102) -> 0 | H102: =+SALDOS!G502 -> 0
B103: =+'Anexo I'!A24 -> Total al 30.06.2026 | E103: =SUM(E10:E102) -> 1.6097789e+09 | F103: =SUM(F10:F102) -> 7.296172e+08 | G103: =SUM(G10:G102) -> 0 | H103: =SUM(H10:H102) -> 8.8016173e+08 | I103: =SUM(I10:I102) -> 0 | J103: =SUM(#REF!) -> #REF!
...

Sheet SALDOS
A1: txtRazonSocial | B1: txtEjercicio | C1: TxtCapitulo | D1: Texto72 | G1: txtsaldop
C2: ACTIVO
C3: 111010001 - Caja | D3: 111010001 - Caja | G3: =IFERROR(VLOOKUP(C3,Hoja1!$A$2:$E$338,5,FALSE),) -> 0
C4: 11101002 - Caja Chica Los Menucos | D4: 11101002 - Caja Chica Los Menucos | G4: =IFERROR(VLOOKUP(C4,Hoja1!$A$2:$E$338,5,FALSE),) -> 0
C5: 111020001 - ICBC S.A. C/C | D5: 111020001 - ICBC S.A. C/C | G5: =IFERROR(VLOOKUP(C5,Hoja1!$A$2:$E$338,5,FALSE),) -> 10663404
C6: 111020007 - Banco Macro (u$s) | D6: 111020007 - Banco Macro USD | G6: =IFERROR(VLOOKUP(C6,Hoja1!$A$2:$E$338,5,FALSE),) -> 1445749.5
C7: 111020002 - Banco Macro Cta. Especial en pesos | D7: 111020002 - Banco Macro Cta. Especial en pesos | G7: =IFERROR(VLOOKUP(C7,Hoja1!$A$2:$E$338,5,FALSE),) -> 0
C8: 111020005 - Banco Macro Pesos | D8: 111020005 - Banco Macro Pesos | G8: =IFERROR(VLOOKUP(C8,Hoja1!$A$2:$E$338,5,FALSE),) -> -23141.31
C9: 111020006 - Banco Galicia c/c | D9: 111020006 - Banco Galicia c/c | G9: =IFERROR(VLOOKUP(C9,Hoja1!$A$2:$E$338,5,FALSE),) -> 3926.88
C10: 111040020 - Tarjeta Corporativa E.Bernuy | D10: 111040020 - Tarjeta Corporativa E.Bernuy | G10: =IFERROR(VLOOKUP(C10,Hoja1!$A$2:$E$338,5,FALSE),) -> 0
C11: 111020003 - Banco de Crédito - BCP | D11: 111020003 - Banco de Crédito - BCP | G11: =IFERROR(VLOOKUP(C11,Hoja1!$A$2:$E$338,5,FALSE),) -> 8464196.8
C12: 115010001 - Fondo fima premiun | D12: 115010001 - Fondo fima premiun | G12: =IFERROR(VLOOKUP(C12,Hoja1!$A$2:$E$338,5,FALSE),) -> 0
G13: =IFERROR(VLOOKUP(C13,Hoja1!$A$2:$E$338,5,FALSE),) -> 0
C14: 114010001 - Iva crédito fiscal | D14: 114010001 - Iva crédito fiscal | G14: =IFERROR(VLOOKUP(C14,Hoja1!$A$2:$E$338,5,FALSE),) -> 0
C15: 114010002 - Iva saldo a favor | D15: 114010002 - Iva saldo a favor | G15: =IFERROR(VLOOKUP(C15,Hoja1!$A$2:$E$338,5,FALSE),) -> 1.6679594e+09
C16: 114010003 - Ret. y Perc. IVA | D16: 114010003 - Retenciones y percepciones iva | G16: =IFERROR(VLOOKUP(C16,Hoja1!$A$2:$E$338,5,FALSE),) -> 0
C17: 114010004 - Ret. y Perc. IIBB | D17: 114010004 - Retenciones y Percepciones II.BB. | G17: =IFERROR(VLOOKUP(C17,Hoja1!$A$2:$E$338,5,FALSE),) -> 0
C18: 114010005 - IIBB saldo a favor | D18: 114010005 - Ingresos Brutos saldo a favor | G18: =IFERROR(VLOOKUP(C18,Hoja1!$A$2:$E$338,5,FALSE),) -> 7866857.1
C19: 114010006 - Crédito Imp. L.25413 | D19: 114010006 - Crédito Imp. L.25413 | G19: =IFERROR(VLOOKUP(C19,Hoja1!$A$2:$E$338,5,FALSE),) -> 52018352
C20: 114010010 - Imp. Gcia. Min. Presunta | D20: 114010010 - Imp. Gcia Mínima Presunta | G20: =IFERROR(VLOOKUP(C20,Hoja1!$A$2:$E$338,5,FALSE),) -> 528747.09
C21: 114010012 - Ret. y Perc. Ganancias | D21: 114010012 - Ret/Perc Ganancias | G21: =IFERROR(VLOOKUP(C21,Hoja1!$A$2:$E$338,5,FALSE),) -> 0
C22: 114010013 - GMP saldo a favor | D22: 11401013 - Saldo a Favor Gcia Minima Presunta | G22: =IFERROR(VLOOKUP(C22,Hoja1!$A$2:$E$338,5,FALSE),) -> 243686.59
C23: 114010014 - Saldos a favor Ganancias | D23: 114010014 - Saldo Favor Ganancias | G23: =IFERROR(VLOOKUP(C23,Hoja1!$A$2:$E$338,5,FALSE),) -> 203599.05
C24: 114010016 - Impuesto Credito Diferido | D24: 114010016 - Impuesto Credito Diferido | G24: =IFERROR(VLOOKUP(C24,Hoja1!$A$2:$E$338,5,FALSE),) -> 45551975
C25: 114010018 - Percepcion RG 4815 35% computable Ganancias | D25: 114010018 - Percepcion RG 4815 35% computable Ganancias | G25: =IFERROR(VLOOKUP(C25,Hoja1!$A$2:$E$338,5,FALSE),) -> 26028041
... C38: 114050004 - Anticipo a Proveedores | D38: 114050004 - Anticipo a Proveedores | G38: =IFERROR(VLOOKUP(C38,Hoja1!$A$2:$E$338,5,FALSE),) -> 323000
G39: =IFERROR(VLOOKUP(C39,Hoja1!$A$2:$E$338,5,FALSE),) -> 0
D40: 114060002 - Zento S.A. | G40: =IFERROR(VLOOKUP(C40,Hoja1!$A$2:$E$338,5,FALSE),) -> 0
C41: 114050007 - Garantia a Cobrar/Recuperar | D41: 114050007 - Garantia a Cobrar/Recuperar | G41: =IFERROR(VLOOKUP(C41,Hoja1!$A$2:$E$338,5,FALSE),) -> 0
C42: 122010000 - Depósito en garantía alquiler | D42: 122010000 - Depósito en garantía alquiler | G42: =IFERROR(VLOOKUP(C42,Hoja1!$A$2:$E$338,5,FALSE),) -> 108200
D43: 12301000 - Titulos Públicos | G43: =IFERROR(VLOOKUP(C43,Hoja1!$A$2:$E$338,5,FALSE),) -> 0
C44: 124010001 - Muebles y Utiles | D44: 124010001 - Muebles y Utiles | G44: =IFERROR(VLOOKUP(C44,Hoja1!$A$2:$E$338,5,FALSE),) -> 7137147.1 | H44: Ok con Anexo I
C45: 124010002 - Equipos | D45: 124010002 - Equipos | G45: =IFERROR(VLOOKUP(C45,Hoja1!$A$2:$E$338,5,FALSE),) -> 2163642.2 | H45: Ok con Anexo I
C46: 124010003 - Herramientas | D46: 124010003 - Herramientas | G46: =IFERROR(VLOOKUP(C46,Hoja1!$A$2:$E$338,5,FALSE),) -> 1676264 | H46: Ok con Anexo I
C47: 124010004 - Equipos de Computaciòn | D47: 124010004 - Equipos de Computaciòn | G47: =IFERROR(VLOOKUP(C47,Hoja1!$A$2:$E$338,5,FALSE),) -> 8463010.9 | H47: Ok con Anexo I
C48: 124010005 - Software | D48: 124010005 - Software | G48: =IFERROR(VLOOKUP(C48,Hoja1!$A$2:$E$338,5,FALSE),) -> 5117083.3 | H48: Ok con Anexo I
C49: 124020001 - Dep. Ac. Muebles y Utiles | D49: 12407000 - Am. Ac. Muebles y Útiles | G49: =IFERROR(VLOOKUP(C49,Hoja1!$A$2:$E$338,5,FALSE),) -> -3124708.6 | H49: Ok con Anexo I | I49: =+'Anexo I'!J15 -> 3124708.6 | J49: =+I49+G49 -> 0
C50: 124020002 - Dep. Ac. Equipos | D50: 12408000 - Am. Ac. Equipos | G50: =IFERROR(VLOOKUP(C50,Hoja1!$A$2:$E$338,5,FALSE),) -> -1499006.2 | H50: Ok con Anexo I | I50: =+'Anexo I'!J17 -> 1499006.2 | J50: =+I50+G50 -> 0
C51: 124020003 - Dep. Ac. Herramientas | D51: 12409000 - Am. Ac. Herramientas | G51: =IFERROR(VLOOKUP(C51,Hoja1!$A$2:$E$338,5,FALSE),) -> -776376.57 | H51: Ok con Anexo I | I51: =+'Anexo I'!J18 -> 776376.57 | J51: =+I51+G51 -> 0
C52: 124010006 - Rodados | D52: 124010006 - Rodados | G52: =IFERROR(VLOOKUP(C52,Hoja1!$A$2:$E$338,5,FALSE),) -> 20790195 | H52: Ok con Anexo I
C53: 124020004 - Dep. Ac. Eq. de Computación | D53: 12412000 - Am. Ac. Eq. de Computación | G53: =IFERROR(VLOOKUP(C53,Hoja1!$A$2:$E$338,5,FALSE),) -> -4436234 | H53: Ok con Anexo I | I53: =+'Anexo I'!J19 -> 4436234 | J53: =+I53+G53 -> 0
C54: 124020005 - Dep. Ac. Software | D54: 12413000 - Am. Ac. Software | G54: =IFERROR(VLOOKUP(C54,Hoja1!$A$2:$E$338,5,FALSE),) -> -5117083.3 | H54: Ok con Anexo I | I54: =+'Anexo I'!J20 -> 5117083.3 | J54: =+I54+G54 -> 0
C55: 124020006 - Dep. Ac. Rodados | D55: 12414000 - Am. Ac. Rodados | G55: =IFERROR(VLOOKUP(C55,Hoja1!$A$2:$E$338,5,FALSE),) -> -19606049 | H55: Ok con Anexo I | I55: =+'Anexo I'!J21 -> 19606049 | J55: =+I55+G55 -> 0
C56: 124010007 - Equipamiento Exploración | D56: 124010007 - Equipamiento Exploración | G56: =IFERROR(VLOOKUP(C56,Hoja1!$A$2:$E$338,5,FALSE),) -> 23184451 | H56: Ok con Anexo I
C57: 124020007 - Dep. Ac. Equipamiento Exploración | D57: 12416000 - Am. Ac. Equipamiento Exploración | G57: =IFERROR(VLOOKUP(C57,Hoja1!$A$2:$E$338,5,FALSE),) -> -10204568 | H57: Ok con Anexo I | I57: =+'Anexo I'!J16 -> 10204568 | J57: =+I57+G57 -> 0
C58: 124010008 - Instalaciones | D58: 124010008 - Instalaciones | G58: =IFERROR(VLOOKUP(C58,Hoja1!$A$2:$E$338,5,FALSE),) -> 1598074.1 | H58: Ok con Anexo I
C59: 124020008 - Dep. Ac. Instalaciones | D59: 12418000 - Am. Ac. Instalaciones | G59: =IFERROR(VLOOKUP(C59,Hoja1!$A$2:$E$338,5,FALSE),) -> -617752.65 | H59: Ok con Anexo I | I59: =+'Anexo I'!J22 -> 617752.65 | J59: =+I59+G59 -> 0
C60: 125010001 - Cargos Diferidos Los Menucos | D60: 125010001 - Cargos Diferidos Los Menucos | G60: =IFERROR(VLOOKUP(C60,Hoja1!$A$2:$E$338,5,FALSE),) -> 5439067
C61: 125010002 - Cargos Diferidos Cañadón del Moro | D61: 125010002 - Cargos Diferidos Cañadón del Moro | G61: =IFERROR(VLOOKUP(C61,Hoja1!$A$2:$E$338,5,FALSE),) -> 32772165 | I61: =SUM(G3:G61) -> 2.1581757e+09 | J61: Total Activo
I62: =+Hoja1!E54-SALDOS!I61 -> 0 | J62: Control
D63: 211010004 - AMX Argentina | G63: 112281.77
D64: 211010005 - Estudio Beccar Varela | G64: -10759320
D65: 211010038 - Nippon Car S.R.L. | G65: -108900
D66: 211010134 - Li Zhi | G66: -37700
D67: 211010209 - IMC S.R.L | G67: -45216.89
D68: 211010258 - Edersa | G68: 379251.49
D69: 211010329 - Servicios Cipolletti S.A. | G69: -50000
D70: 211010402 - Crown Casino S.A. | G70: -20786.65
D71: 211010404 - Camara Argentina de Empresarios Mineros | G71: -3087400
D72: 211010436 - Bien del Sur S.R.L. | G72: -107500
D73: 211010448 - Alex Stewart (Assayers) Argentina S.A. | G73: 602391.95
D74: 211010473 - Construcciones Industriales S.A. | G74: 57904.46
... D114: 211012480 - Ismar SRL | G114: 312023.95
I115: Proveedores
I116: =SUM(G63:G114) -> -1.0668752e+08 | J116: DE ACA VA A LAS NOTAS
C120: 212010001 - Sueldos a pagar | D120: 212010001 - Sueldos a pagar | G120: -46874611
C121: 213010001 - SICORE a pagar | D121: 213010001 - SICORE a pagar | G121: -1.9916836e+08
C122: 212020001 - SICOSS a pagar | D122: 21407000 - Sicoss a pagar | G122: -39510574
D123: 21410000 - Tasa Municipalidad Tolar Grande a pagar | G123: 0
D124: 21408000 - Imp. Gcia Mínima Presunta a pagar | G124: 0
D125: 21409000 - Retenciones SUSS a pagar | G125: 0
D126: 21504000 - Cheques emitidos en cartera | G126: 0 | I126: =SUM(G120:G137) -> -3.7004856e+08
C127: 211050000 - Previsión AID | D127: 211050000 - Previsión AID | G127: -45551975
C128: 211060000 - Previsión IGMP | D128: 211060000 - Previsión IGMP | G128: -772433.68 | I128: =+-476736080.9-I126-I116 -> 0 | J128: DIF
D129: 211070000 - Depósito efectivo Bco. Galicia | G129: 0
D130: 212010002 - Embargo por Alimentos | G130: 0
C131: 212010003 - Provisión Vacaciones | D131: 212010003 - Provisión Vacaciones | G131: -38149532
D132: 213010005 - Tasa Municipal Catamarca a pagar | G132: 0
D133: 213010006 - Tasas Retributivas Mineras | G133: 0
D134: 211080000 - Transferencia a debitar | G134: 0
C135: 211030000 - Provision de Gastos | D135: 211030000 - Provision de Gastos | G135: -1335.23
C136: 213010007 - Tasa Seguridad e Higiene a pagar | D136: 213010007 - Tasa Seguridad e Higiene a pagar | G136: -19744
C137: 213010010 - Patentes a pagar | D137: 212020002 - Retenciones SUSS a pagar | G137: 0
C139: 311000000 - Capital Suscripto | D139: 31100000 - Capital Suscripto | G139: -14848645484
C140: 313000000 - Ajuste de Capital | D140: 313000000 - Ajuste de Capital | G140: -8
C141: 321000000 - Resultados No Asignados | D141: 32201000 - Resultados no asignados | G141: 8.1785086e+08 | I141: =SUM(G139:G142) -> -3.3540287e+09 | J141: Total PN
C142: 323000000 - Resultado del Ejercicio | D142: 323000000 - Resultado del Ejercicio | G142: 1.0676766e+10 | I142: =+Pat.Neto!F27+Pat.Neto!J14 -> 3.3540287e+09 | J142: Pat. Neto
D143: 32203000 - A.R.E.A. | G143: =IFERROR(VLOOKUP(C143,Hoja1!$A$2:$E$338,5,FALSE),) -> 0 | I143: =+I141+I142 -> 0 | J143: dif
D144: Diferencia Resultados no Asignados | G144: =IFERROR(VLOOKUP(C144,Hoja1!$A$2:$E$338,5,FALSE),) -> 0
D146: 41210000 - Resultado baja bien de Uso | G146: =+F146 -> 0
D147: 41220000 - RECUPERO SINIESTRO | G147: =+F147 -> 0
D148: 41230000 - Envío muestras Chile | G148: =+F148 -> 0
D149: 41240000 - Resultado Venta Títulos Públicos | G149: =+F149 -> 0
D150: 412500000 - Venta de bienes de uso | E150: 412500000 - Venta de bienes de uso | G150: =+F150 -> 0
D151: 412600000 - Recupero de Seguros | F151: =IFERROR(VLOOKUP(D151,Hoja1!$A$2:$E$399,5,FALSE),) -> 0 | G151: =+F151 -> 0
D152: 412700000 - Intereses ganados | F152: =IFERROR(VLOOKUP(D152,Hoja1!$A$2:$E$399,5,FALSE),) -> 0 | G152: =+F152 -> 0
D153: 426380000 - Gastos de licitación Gst Campo | F153: =IFERROR(VLOOKUP(D153,Hoja1!$A$2:$E$399,5,FALSE),) -> 6840000 | G153: =+F153 -> 6840000 | H153: Agregada 03-26
D154: 42101000 - Honorarios legales | F154: =IFERROR(VLOOKUP(D154,Hoja1!$A$2:$E$399,5,FALSE),) -> 0 | G154: =SUM(F155:F158) -> 0
E155: 425940000 - Honorarios Legales Adm. Gral | F155: =IFERROR(VLOOKUP(E155,Hoja1!$A$2:$E$399,5,FALSE),) -> 0
E156: 421430000 - Honorarios legales Adm Catamarca | F156: =IFERROR(VLOOKUP(E156,Hoja1!$A$2:$E$399,5,FALSE),) -> 0
...

Sheet Hoja1
A1: ACTIVO | E1: Saldos
A2: 111010001 - Caja | E2: 0
A3: 111020001 - ICBC S.A. c/c | E3: 10663404
A4: 111020002 - Banco Macro Cta. Especial en pesos | E4: 0
A5: 111020003 - Banco de Crédito - BCP | E5: 8464196.8
A6: 111020005 - Banco Macro Pesos | E6: -23141.31
A7: 111020006 - Banco Galicia c/c | E7: 3926.88
A8: 111020007 - Banco Macro (u$s) | E8: 1445749.5
A9: 114010002 - IVA saldo a favor | E9: 1.6679594e+09
A10: 114010003 - Ret. y Perc. IVA | E10: 0
A11: 114010004 - Ret. y Perc. IIBB | E11: 0
A12: 114010005 - IIBB saldo a favor | E12: 7866857.1
A13: 114010006 - Crédito Imp. L.25413 | E13: 52018352
... A46: 125010002 - Cargos Diferidos Cañadón del Moro | E46: 32772165
G47: SALDO SyS | H47: DIF
G52: 2.0039762e+09 | H52: =+G52-E54 -> -1.5419953e+08
E54: =SUM(E2:E53) -> 2.1581757e+09 | F54: =+SUM(SALDOS!G3:G61) -> 2.1581757e+09 | G54: =+E54-F54 -> 0
F55: =+Balance!F21 -> 2.1581757e+09 | G55: =+F55-E54 -> 0
A58: PASIVO | F58: VER - VA EN HOJA SALDOS DIRECTAMENTE
A59: 211010004 - AMX Argentina | E59: 112281.77
A60: 211010038 - Nippon Car S.R.L. | E60: -108900
A61: 211010081 - Polans S.R.L. | E61: 0
A62: 211010134 - Li Zhi | E62: -37700
A63: 211010209 - IMC S.R.L | E63: -45216.89
A64: 211010258 - Edersa | E64: 379251.49
A65: 211010329 - Servicios Cipolletti S.A. | E65: -50000
A66: 211010402 - Crown Casino S.A. | E66: -20786.65
A67: 211010404 - Camara Argentina de Empresarios Mineros | E67: -3087400
A68: 211010436 - Bien del Sur S.R.L. | E68: -107500
A69: 211010448 - Alex Stewart (Assayers) Argentina S.A. | E69: 602391.95
A70: 211010473 - Construcciones Industriales S.A. | E70: 57904.46
... A210: 323000000 - Resultado del Ejercicio | E210: 1.0676766e+10
A213: RESULTADO | E213: Saldos
A214: 421010000 - Refrigerios - Adm Catamarca | E214: 0
A215: 421030000 - IVA crédito fiscal no computable | E215: 11619113
A216: 421050000 - Sueldos Adm. | E216: 1.4697471e+08
A217: 421060000 - Cargas sociales Adm. | E217: 14081454
A218: 421090000 - Seguridad e Higiene Adm Gral Catamarca | E218: 0
A219: 421110000 - Comunicaciones - Adm Catamarca | E219: 0
A220: 421130000 - Ferreteria - Adm Catamarca | E220: 0
A221: 421140000 - Gastos varios oficina - Adm Catamarca | E221: 0
A222: 421210000 - Canon Minero - Vigencia y Penalidades | E222: 48607847
A223: 421440000 - Movilidad y Viáticos Adm Catamarca | E223: 0
A224: 422010000 - Tasas ambientales I- R. Ambiental | E224: 0
A225: 422220000 - Análisis Muestras - R. Ambiental | E225: 0
... A338: 426520000 - Alquiler Equipos. Gst de Campo | E338: 30000
F339: Rdos | G339: Dif
E340: =SUM(E214:E338) -> 1.6725891e+09 | F340: =+Resultados!C26 -> -1.6725891e+09 | G340: =+F340+E340 -> 0
G366: =+SUM(E59:E201) -> -4.7673608e+08 | H366: Pasivo
E367: 1.6725891e+09 | G367: =+SUM(E207:E210) -> -3.3540287e+09 | H367: PN
G368: =+SUM(E214:E338) -> 1.6725891e+09 | H368: Resultados
E369: =+E340-E367 -> 0 | H369: SyS
G371: SyS | H371: Dif
G372: 1.5398099e+09 | H372: =+G372-E340 -> -1.3277919e+08
